{
  "type": "Feature",
  "properties": {
    "gn:admin1_code":"11.0",
    "gn:admin2_code":"52",
    "gn:admin3_code":"5212.0",
    "gn:admin4_code":"521205.0",
    "gn:asciiname":"Bweya",
    "gn:country_code":"RW",
    "gn:dem":1509,
    "gn:feature_class":"P",
    "gn:feature_code":"PPL",
    "gn:name":"Bweya",
    "gn:population":0,
    "gn:timezone":"Africa/Kigali",
    "iso:country":"RW",
    "wof:name":"Bweya",
    "wof:placetype":"locality"
},
  "geometry": {"coordinates":[30.2638,-1.2309],"type":"Point"}
}