{
  "type": "Feature",
  "properties": {
    "gn:admin1_code":"14",
    "gn:admin2_code":"34.0",
    "gn:admin3_code":"3407.0",
    "gn:admin4_code":"340706.0",
    "gn:asciiname":"Buhinga",
    "gn:country_code":"RW",
    "gn:dem":2438,
    "gn:feature_class":"P",
    "gn:feature_code":"PPLL",
    "gn:name":"Buhinga",
    "gn:population":0,
    "gn:timezone":"Africa/Kigali",
    "iso:country":"RW",
    "wof:name":"Buhinga",
    "wof:placetype":"locality"
},
  "geometry": {"coordinates":[29.5365,-1.6114],"type":"Point"}
}