{
  "type": "Feature",
  "properties": {
    "gn:admin1_code":"13",
    "gn:admin2_code":"43.0",
    "gn:admin3_code":"4303.0",
    "gn:admin4_code":"430302.0",
    "gn:asciiname":"Shangaro",
    "gn:country_code":"RW",
    "gn:dem":1869,
    "gn:feature_class":"P",
    "gn:feature_code":"PPLL",
    "gn:name":"Shangaro",
    "gn:population":0,
    "gn:timezone":"Africa/Kigali",
    "iso:country":"RW",
    "name:und_x_variant":[
        "Shangare"
    ],
    "wof:name":"Shangaro",
    "wof:placetype":"locality"
},
  "geometry": {"coordinates":[29.705,-1.5141],"type":"Point"}
}