{
  "type": "Feature",
  "properties": {
    "gn:admin1_code":"11",
    "gn:admin2_code":"57.0",
    "gn:admin3_code":"5708.0",
    "gn:admin4_code":"570805.0",
    "gn:asciiname":"Rugazi",
    "gn:country_code":"RW",
    "gn:dem":1420,
    "gn:feature_class":"P",
    "gn:feature_code":"PPLL",
    "gn:name":"Rugazi",
    "gn:population":0,
    "gn:timezone":"Africa/Kigali",
    "iso:country":"RW",
    "name:und_x_variant":[
        "Rugali"
    ],
    "wof:name":"Rugazi",
    "wof:placetype":"locality"
},
  "geometry": {"coordinates":[30.0761,-2.3562],"type":"Point"}
}