{
  "type": "Feature",
  "properties": {
    "gn:admin1_code":"13",
    "gn:admin2_code":"41.0",
    "gn:admin3_code":"4104.0",
    "gn:admin4_code":"410406.0",
    "gn:asciiname":"Giko",
    "gn:country_code":"RW",
    "gn:dem":2092,
    "gn:feature_class":"P",
    "gn:feature_code":"PPLL",
    "gn:name":"Giko",
    "gn:population":0,
    "gn:timezone":"Africa/Kigali",
    "iso:country":"RW",
    "wof:name":"Giko",
    "wof:placetype":"locality"
},
  "geometry": {"coordinates":[30.0151,-1.6901],"type":"Point"}
}