{
  "type": "Feature",
  "properties": {
    "gn:admin1_code":"11",
    "gn:admin2_code":"57.0",
    "gn:admin3_code":"5702.0",
    "gn:admin4_code":"570203.0",
    "gn:asciiname":"Kirabo",
    "gn:country_code":"RW",
    "gn:dem":1446,
    "gn:feature_class":"P",
    "gn:feature_code":"PPLL",
    "gn:name":"Kirabo",
    "gn:population":0,
    "gn:timezone":"Africa/Kigali",
    "iso:country":"RW",
    "wof:name":"Kirabo",
    "wof:placetype":"locality"
},
  "geometry": {"coordinates":[30.2288,-2.1194],"type":"Point"}
}