{
  "type": "Feature",
  "properties": {
    "gn:admin1_code":"13",
    "gn:admin2_code":"42.0",
    "gn:admin3_code":"4205.0",
    "gn:admin4_code":"420504.0",
    "gn:asciiname":"Teranzara",
    "gn:country_code":"RW",
    "gn:dem":2155,
    "gn:feature_class":"P",
    "gn:feature_code":"PPLL",
    "gn:name":"Teranzara",
    "gn:population":0,
    "gn:timezone":"Africa/Kigali",
    "iso:country":"RW",
    "wof:name":"Teranzara",
    "wof:placetype":"locality"
},
  "geometry": {"coordinates":[29.87352000000001,-1.67067],"type":"Point"}
}