{
  "type": "Feature",
  "properties": {
    "gn:admin1_code":"13",
    "gn:admin2_code":"45.0",
    "gn:admin3_code":"4501.0",
    "gn:admin4_code":"450101.0",
    "gn:asciiname":"Karenge",
    "gn:country_code":"RW",
    "gn:dem":1582,
    "gn:feature_class":"P",
    "gn:feature_code":"PPLL",
    "gn:name":"Karenge",
    "gn:population":0,
    "gn:timezone":"Africa/Kigali",
    "iso:country":"RW",
    "wof:name":"Karenge",
    "wof:placetype":"locality"
},
  "geometry": {"coordinates":[30.2371,-1.7952],"type":"Point"}
}