{
  "type": "Feature",
  "properties": {
    "gn:admin1_code":"11",
    "gn:admin2_code":"54.0",
    "gn:admin3_code":"5406.0",
    "gn:admin4_code":"540603.0",
    "gn:asciiname":"Macuba",
    "gn:country_code":"RW",
    "gn:dem":1392,
    "gn:feature_class":"P",
    "gn:feature_code":"PPLL",
    "gn:name":"Macuba",
    "gn:population":0,
    "gn:timezone":"Africa/Kigali",
    "iso:country":"RW",
    "wof:name":"Macuba",
    "wof:placetype":"locality"
},
  "geometry": {"coordinates":[30.493,-1.7271],"type":"Point"}
}