{
  "type": "Feature",
  "properties": {
    "gn:admin1_code":"13",
    "gn:admin2_code":"42.0",
    "gn:admin3_code":"4209.0",
    "gn:admin4_code":"420903.0",
    "gn:asciiname":"Rurambo",
    "gn:country_code":"RW",
    "gn:dem":1793,
    "gn:feature_class":"P",
    "gn:feature_code":"PPLL",
    "gn:name":"Rurambo",
    "gn:population":0,
    "gn:timezone":"Africa/Kigali",
    "iso:country":"RW",
    "wof:name":"Rurambo",
    "wof:placetype":"locality"
},
  "geometry": {"coordinates":[29.729,-1.5789],"type":"Point"}
}