{
  "type": "Feature",
  "properties": {
    "gn:admin1_code":"15.0",
    "gn:admin2_code":"24",
    "gn:admin3_code":"2406.0",
    "gn:admin4_code":"240601.0",
    "gn:asciiname":"Gatumbazi",
    "gn:country_code":"RW",
    "gn:dem":1759,
    "gn:feature_class":"P",
    "gn:feature_code":"PPLL",
    "gn:name":"Gatumbazi",
    "gn:population":0,
    "gn:timezone":"Africa/Kigali",
    "iso:country":"RW",
    "wof:name":"Gatumbazi",
    "wof:placetype":"locality"
},
  "geometry": {"coordinates":[29.6107,-2.5414],"type":"Point"}
}