{
  "type": "Feature",
  "properties": {
    "gn:admin1_code":"15",
    "gn:admin2_code":"22.0",
    "gn:admin3_code":"2203.0",
    "gn:admin4_code":"220302.0",
    "gn:asciiname":"Bucyo",
    "gn:country_code":"RW",
    "gn:dem":1601,
    "gn:feature_class":"P",
    "gn:feature_code":"PPLL",
    "gn:name":"Bucyo",
    "gn:population":0,
    "gn:timezone":"Africa/Kigali",
    "iso:country":"RW",
    "wof:name":"Bucyo",
    "wof:placetype":"locality"
},
  "geometry": {"coordinates":[29.7911,-2.6763],"type":"Point"}
}