{
  "type": "Feature",
  "properties": {
    "gn:admin1_code":"13",
    "gn:admin2_code":"42.0",
    "gn:admin3_code":"4204.0",
    "gn:admin4_code":"420403.0",
    "gn:asciiname":"Karehe",
    "gn:country_code":"RW",
    "gn:dem":1959,
    "gn:feature_class":"P",
    "gn:feature_code":"PPLL",
    "gn:name":"Karehe",
    "gn:population":0,
    "gn:timezone":"Africa/Kigali",
    "iso:country":"RW",
    "wof:name":"Karehe",
    "wof:placetype":"locality"
},
  "geometry": {"coordinates":[29.7602,-1.6811],"type":"Point"}
}