{
  "type": "Feature",
  "properties": {
    "gn:admin1_code":"11",
    "gn:admin2_code":"57.0",
    "gn:admin3_code":"5704.0",
    "gn:admin4_code":"570401.0",
    "gn:asciiname":"Rususa",
    "gn:country_code":"RW",
    "gn:dem":1377,
    "gn:feature_class":"P",
    "gn:feature_code":"PPLL",
    "gn:name":"Rususa",
    "gn:population":0,
    "gn:timezone":"Africa/Kigali",
    "iso:country":"RW",
    "name:und_x_variant":[
        "Rusasa"
    ],
    "wof:name":"Rususa",
    "wof:placetype":"locality"
},
  "geometry": {"coordinates":[30.0925,-2.254],"type":"Point"}
}