{
  "type": "Feature",
  "properties": {
    "gn:admin1_code":"15.0",
    "gn:admin2_code":"28",
    "gn:admin3_code":"2801.0",
    "gn:admin4_code":"280104.0",
    "gn:asciiname":"Rubona",
    "gn:country_code":"RW",
    "gn:dem":1686,
    "gn:feature_class":"P",
    "gn:feature_code":"PPL",
    "gn:name":"Rubona",
    "gn:population":0,
    "gn:timezone":"Africa/Kigali",
    "iso:country":"RW",
    "wof:name":"Rubona",
    "wof:placetype":"locality"
},
  "geometry": {"coordinates":[29.8893,-1.9955],"type":"Point"}
}