{
  "type": "Feature",
  "properties": {
    "gn:admin1_code":"13.0",
    "gn:admin2_code":"44",
    "gn:admin3_code":"4403.0",
    "gn:admin4_code":"440306.0",
    "gn:asciiname":"Nindo",
    "gn:country_code":"RW",
    "gn:dem":2337,
    "gn:feature_class":"P",
    "gn:feature_code":"PPLL",
    "gn:name":"Nindo",
    "gn:population":0,
    "gn:timezone":"Africa/Kigali",
    "iso:country":"RW",
    "wof:name":"Nindo",
    "wof:placetype":"locality"
},
  "geometry": {"coordinates":[29.7104,-1.3733],"type":"Point"}
}