{
  "type": "Feature",
  "properties": {
    "gn:admin1_code":"15.0",
    "gn:admin2_code":"23",
    "gn:admin3_code":"2303.0",
    "gn:admin4_code":"230304.0",
    "gn:asciiname":"Banga",
    "gn:country_code":"RW",
    "gn:dem":1833,
    "gn:feature_class":"P",
    "gn:feature_code":"PPL",
    "gn:name":"Banga",
    "gn:population":0,
    "gn:timezone":"Africa/Kigali",
    "iso:country":"RW",
    "wof:name":"Banga",
    "wof:placetype":"locality"
},
  "geometry": {"coordinates":[29.6006,-2.6312],"type":"Point"}
}