{
  "type": "Feature",
  "properties": {
    "gn:admin1_code":"14.0",
    "gn:admin2_code":"37",
    "gn:admin3_code":"3709.0",
    "gn:admin4_code":"370903.0",
    "gn:asciiname":"Gisesero",
    "gn:country_code":"RW",
    "gn:dem":1538,
    "gn:feature_class":"P",
    "gn:feature_code":"PPLL",
    "gn:name":"Gisesero",
    "gn:population":0,
    "gn:timezone":"Africa/Kigali",
    "iso:country":"RW",
    "wof:name":"Gisesero",
    "wof:placetype":"locality"
},
  "geometry": {"coordinates":[29.198,-2.2667],"type":"Point"}
}