{
  "type": "Feature",
  "properties": {
    "gn:admin1_code":"15.0",
    "gn:admin2_code":"24",
    "gn:admin3_code":"2413.0",
    "gn:admin4_code":"241305.0",
    "gn:asciiname":"Shunga",
    "gn:country_code":"RW",
    "gn:dem":1700,
    "gn:feature_class":"P",
    "gn:feature_code":"PPLL",
    "gn:name":"Shunga",
    "gn:population":0,
    "gn:timezone":"Africa/Kigali",
    "iso:country":"RW",
    "wof:name":"Shunga",
    "wof:placetype":"locality"
},
  "geometry": {"coordinates":[29.6663,-2.4892],"type":"Point"}
}