{
  "type": "Feature",
  "properties": {
    "gn:admin1_code":"15.0",
    "gn:admin2_code":"24",
    "gn:admin3_code":"2413.0",
    "gn:admin4_code":"241305.0",
    "gn:asciiname":"Shunga",
    "gn:country_code":"RW",
    "gn:dem":1700,
    "gn:feature_class":"P",
    "gn:feature_code":"PPLL",
    "gn:name":"Shunga",
    "gn:population":0,
    "gn:timezone":"Africa/Kigali",
    "iso:country":"RW",
    "name:bel_x_preferred":[
        "\u0421\u044e\u043d\u0433\u0430"
    ],
    "name:cat_x_preferred":[
        "Shunga"
    ],
    "name:ces_x_preferred":[
        "\u0160unga"
    ],
    "name:chv_x_preferred":[
        "\u0421\u044e\u043d\u0433\u0430"
    ],
    "name:cym_x_preferred":[
        "Shunga"
    ],
    "name:deu_x_preferred":[
        "Shunga"
    ],
    "name:ell_x_preferred":[
        "\u03a3\u03bf\u03cd\u03bd\u03b3\u03ba\u03b1"
    ],
    "name:epo_x_preferred":[
        "\u015cungo"
    ],
    "name:fas_x_preferred":[
        "\u0634\u0648\u0646\u06af\u0627"
    ],
    "name:fra_x_preferred":[
        "Shunga"
    ],
    "name:heb_x_preferred":[
        "\u05e9\u05d5\u05e0\u05d2\u05d4"
    ],
    "name:hun_x_preferred":[
        "Sunga"
    ],
    "name:ind_x_preferred":[
        "Shunga"
    ],
    "name:ita_x_preferred":[
        "Shunga"
    ],
    "name:lit_x_preferred":[
        "\u0160iunga"
    ],
    "name:nld_x_preferred":[
        "Shunga"
    ],
    "name:nor_x_preferred":[
        "Shunga"
    ],
    "name:pol_x_preferred":[
        "Shunga"
    ],
    "name:por_x_preferred":[
        "Shunga"
    ],
    "name:rus_x_preferred":[
        "\u0421\u044e\u043d\u0433\u0430"
    ],
    "name:spa_x_preferred":[
        "Shunga"
    ],
    "name:swe_x_preferred":[
        "Shunga"
    ],
    "name:tur_x_preferred":[
        "Shunga"
    ],
    "name:ukr_x_preferred":[
        "\u0421\u044e\u043d\u0491\u0430"
    ],
    "name:vie_x_preferred":[
        "Shunga"
    ],
    "name:zho_x_preferred":[
        "\u6625\u5bab\u56fe"
    ],
    "wof:name":"Shunga",
    "wof:placetype":"locality"
},
  "geometry": {"coordinates":[29.6663,-2.4892],"type":"Point"}
}