{
  "type": "Feature",
  "properties": {
    "gn:admin1_code":"14.0",
    "gn:admin2_code":"36",
    "gn:admin3_code":"3604.0",
    "gn:admin4_code":"360408.0",
    "gn:asciiname":"Kabakobwa",
    "gn:country_code":"RW",
    "gn:dem":1685,
    "gn:feature_class":"P",
    "gn:feature_code":"PPL",
    "gn:name":"Kabakobwa",
    "gn:population":0,
    "gn:timezone":"Africa/Kigali",
    "iso:country":"RW",
    "wof:name":"Kabakobwa",
    "wof:placetype":"locality"
},
  "geometry": {"coordinates":[28.93272,-2.60829],"type":"Point"}
}