{
  "type": "Feature",
  "properties": {
    "gn:admin1_code":"14.0",
    "gn:admin2_code":"32",
    "gn:admin3_code":"3202.0",
    "gn:admin4_code":"320206.0",
    "gn:asciiname":"Kumusenyi",
    "gn:country_code":"RW",
    "gn:dem":1670,
    "gn:feature_class":"P",
    "gn:feature_code":"PPLL",
    "gn:name":"Kumusenyi",
    "gn:population":0,
    "gn:timezone":"Africa/Kigali",
    "iso:country":"RW",
    "wof:name":"Kumusenyi",
    "wof:placetype":"locality"
},
  "geometry": {"coordinates":[29.3696,-1.922],"type":"Point"}
}