{
  "type": "Feature",
  "properties": {
    "gn:admin1_code":"11",
    "gn:admin2_code":"53.0",
    "gn:admin3_code":"5312.0",
    "gn:admin4_code":"531201.0",
    "gn:asciiname":"Bushobora",
    "gn:country_code":"RW",
    "gn:dem":1597,
    "gn:feature_class":"P",
    "gn:feature_code":"PPLL",
    "gn:name":"Bushobora",
    "gn:population":0,
    "gn:timezone":"Africa/Kigali",
    "iso:country":"RW",
    "wof:name":"Bushobora",
    "wof:placetype":"locality"
},
  "geometry": {"coordinates":[30.359,-1.7214],"type":"Point"}
}