{
  "type": "Feature",
  "properties": {
    "gn:admin1_code":"14.0",
    "gn:admin2_code":"37",
    "gn:admin3_code":"3708.0",
    "gn:admin4_code":"370804.0",
    "gn:asciiname":"Kabisheshe",
    "gn:country_code":"RW",
    "gn:dem":1918,
    "gn:feature_class":"P",
    "gn:feature_code":"PPLL",
    "gn:name":"Kabisheshe",
    "gn:population":0,
    "gn:timezone":"Africa/Kigali",
    "iso:country":"RW",
    "wof:name":"Kabisheshe",
    "wof:placetype":"locality"
},
  "geometry": {"coordinates":[29.0072,-2.5086],"type":"Point"}
}