{
  "type": "Feature",
  "properties": {
    "gn:admin1_code":"13.0",
    "gn:admin2_code":"44",
    "gn:admin3_code":"4416.0",
    "gn:admin4_code":"441602.0",
    "gn:asciiname":"Cyeru",
    "gn:country_code":"RW",
    "gn:dem":2119,
    "gn:feature_class":"P",
    "gn:feature_code":"PPL",
    "gn:name":"Cyeru",
    "gn:population":0,
    "gn:timezone":"Africa/Kigali",
    "iso:country":"RW",
    "wof:name":"Cyeru",
    "wof:placetype":"locality"
},
  "geometry": {"coordinates":[29.8305,-1.4888],"type":"Point"}
}