{
  "type": "Feature",
  "properties": {
    "gn:admin1_code":"15.0",
    "gn:admin2_code":"26",
    "gn:admin3_code":"2602.0",
    "gn:admin4_code":"260201.0",
    "gn:asciiname":"Byimana",
    "gn:country_code":"RW",
    "gn:dem":1820,
    "gn:feature_class":"P",
    "gn:feature_code":"PPL",
    "gn:name":"Byimana",
    "gn:population":0,
    "gn:timezone":"Africa/Kigali",
    "iso:country":"RW",
    "name:und_x_variant":[
        "Bimana-Mayebe",
        "Byimana"
    ],
    "wof:name":"Byimana",
    "wof:placetype":"locality"
},
  "geometry": {"coordinates":[29.73608,-2.15124],"type":"Point"}
}