{
  "type": "Feature",
  "properties": {
    "gn:admin1_code":"14.0",
    "gn:admin2_code":"31",
    "gn:admin3_code":"3103.0",
    "gn:admin4_code":"310303.0",
    "gn:asciiname":"Ngoma",
    "gn:country_code":"RW",
    "gn:dem":1647,
    "gn:feature_class":"P",
    "gn:feature_code":"PPL",
    "gn:name":"Ngoma",
    "gn:population":0,
    "gn:timezone":"Africa/Kigali",
    "iso:country":"RW",
    "wof:name":"Ngoma",
    "wof:placetype":"locality"
},
  "geometry": {"coordinates":[29.2777,-2.1566],"type":"Point"}
}