{
  "type": "Feature",
  "properties": {
    "gn:admin1_code":"15.0",
    "gn:admin2_code":"25",
    "gn:admin3_code":"2511.0",
    "gn:admin4_code":"251104.0",
    "gn:asciiname":"Nyaburondwe",
    "gn:country_code":"RW",
    "gn:dem":1775,
    "gn:feature_class":"P",
    "gn:feature_code":"PPLL",
    "gn:name":"Nyaburondwe",
    "gn:population":0,
    "gn:timezone":"Africa/Kigali",
    "iso:country":"RW",
    "wof:name":"Nyaburondwe",
    "wof:placetype":"locality"
},
  "geometry": {"coordinates":[29.5145,-2.2821],"type":"Point"}
}