{
  "type": "Feature",
  "properties": {
    "gn:admin1_code":"11",
    "gn:admin2_code":"53.0",
    "gn:admin3_code":"5312.0",
    "gn:admin4_code":"531204.0",
    "gn:asciiname":"Kababito",
    "gn:country_code":"RW",
    "gn:dem":1648,
    "gn:feature_class":"P",
    "gn:feature_code":"PPL",
    "gn:name":"Kababito",
    "gn:population":0,
    "gn:timezone":"Africa/Kigali",
    "iso:country":"RW",
    "wof:name":"Kababito",
    "wof:placetype":"locality"
},
  "geometry": {"coordinates":[30.3292,-1.7017],"type":"Point"}
}