{
  "type": "Feature",
  "properties": {
    "gn:admin1_code":"13.0",
    "gn:admin2_code":"42",
    "gn:admin3_code":"4218.0",
    "gn:admin4_code":"421802.0",
    "gn:asciiname":"Rusasa I",
    "gn:country_code":"RW",
    "gn:dem":1728,
    "gn:feature_class":"P",
    "gn:feature_code":"PPLL",
    "gn:name":"Rusasa I",
    "gn:population":0,
    "gn:timezone":"Africa/Kigali",
    "iso:country":"RW",
    "name:und_x_variant":[
        "Rusasa",
        "Lusaza",
        "Rusasa I",
        "Lusasa"
    ],
    "wof:name":"Rusasa I",
    "wof:placetype":"locality"
},
  "geometry": {"coordinates":[29.6573,-1.6386],"type":"Point"}
}