{
  "type": "Feature",
  "properties": {
    "gn:admin1_code":"13",
    "gn:admin2_code":"41.0",
    "gn:admin3_code":"4114.0",
    "gn:admin4_code":"411404.0",
    "gn:asciiname":"Gakubo",
    "gn:country_code":"RW",
    "gn:dem":2111,
    "gn:feature_class":"P",
    "gn:feature_code":"PPLL",
    "gn:name":"Gakubo",
    "gn:population":0,
    "gn:timezone":"Africa/Kigali",
    "iso:country":"RW",
    "wof:name":"Gakubo",
    "wof:placetype":"locality"
},
  "geometry": {"coordinates":[29.95947,-1.62642],"type":"Point"}
}