{
  "type": "Feature",
  "properties": {
    "gn:admin1_code":"13.0",
    "gn:admin2_code":"44",
    "gn:admin3_code":"4408.0",
    "gn:admin4_code":"440803.0",
    "gn:asciiname":"Kagogo",
    "gn:country_code":"RW",
    "gn:dem":1982,
    "gn:feature_class":"P",
    "gn:feature_code":"PPLL",
    "gn:name":"Kagogo",
    "gn:population":0,
    "gn:timezone":"Africa/Kigali",
    "iso:country":"RW",
    "name:und_x_variant":[
        "Kadogo",
        "Colline Kagogo",
        "Kagogo"
    ],
    "wof:name":"Kagogo",
    "wof:placetype":"locality"
},
  "geometry": {"coordinates":[29.7687,-1.3683],"type":"Point"}
}