{
  "type": "Feature",
  "properties": {
    "gn:admin1_code":"15.0",
    "gn:admin2_code":"25",
    "gn:admin3_code":"2501.0",
    "gn:admin4_code":"250103.0",
    "gn:asciiname":"Nganzo",
    "gn:country_code":"RW",
    "gn:dem":2291,
    "gn:feature_class":"P",
    "gn:feature_code":"PPLL",
    "gn:name":"Nganzo",
    "gn:population":0,
    "gn:timezone":"Africa/Kigali",
    "iso:country":"RW",
    "wof:name":"Nganzo",
    "wof:placetype":"locality"
},
  "geometry": {"coordinates":[29.427,-2.4228],"type":"Point"}
}