{
  "type": "Feature",
  "properties": {
    "gn:admin1_code":"14.0",
    "gn:admin2_code":"36",
    "gn:admin3_code":"3617.0",
    "gn:admin4_code":"361704.0",
    "gn:asciiname":"Gatare",
    "gn:country_code":"RW",
    "gn:dem":1434,
    "gn:feature_class":"P",
    "gn:feature_code":"PPLL",
    "gn:name":"Gatare",
    "gn:population":0,
    "gn:timezone":"Africa/Kigali",
    "iso:country":"RW",
    "wof:name":"Gatare",
    "wof:placetype":"locality"
},
  "geometry": {"coordinates":[28.9082,-2.6357],"type":"Point"}
}