{
  "type": "Feature",
  "properties": {
    "gn:admin1_code":"13.0",
    "gn:admin2_code":"44",
    "gn:admin3_code":"4402.0",
    "gn:admin4_code":"440201.0",
    "gn:asciiname":"Kadehero",
    "gn:country_code":"RW",
    "gn:dem":2262,
    "gn:feature_class":"P",
    "gn:feature_code":"PPLL",
    "gn:name":"Kadehero",
    "gn:population":0,
    "gn:timezone":"Africa/Kigali",
    "iso:country":"RW",
    "name:und_x_variant":[
        "Kademero"
    ],
    "wof:name":"Kadehero",
    "wof:placetype":"locality"
},
  "geometry": {"coordinates":[29.8319,-1.3911],"type":"Point"}
}