{
  "type": "Feature",
  "properties": {
    "gn:admin1_code":"15",
    "gn:admin2_code":"28.0",
    "gn:admin3_code":"2806.0",
    "gn:admin4_code":"280605.0",
    "gn:asciiname":"Kabere",
    "gn:country_code":"RW",
    "gn:dem":1733,
    "gn:feature_class":"P",
    "gn:feature_code":"PPLL",
    "gn:name":"Kabere",
    "gn:population":0,
    "gn:timezone":"Africa/Kigali",
    "iso:country":"RW",
    "wof:name":"Kabere",
    "wof:placetype":"locality"
},
  "geometry": {"coordinates":[29.8159,-2.0162],"type":"Point"}
}