{
  "type": "Feature",
  "properties": {
    "gn:admin1_code":"12",
    "gn:admin2_code":"12.0",
    "gn:admin3_code":"1211.0",
    "gn:admin4_code":"121102.0",
    "gn:asciiname":"Gashure",
    "gn:country_code":"RW",
    "gn:dem":1450,
    "gn:feature_class":"P",
    "gn:feature_code":"PPLL",
    "gn:name":"Gashure",
    "gn:population":0,
    "gn:timezone":"Africa/Kigali",
    "iso:country":"RW",
    "wof:name":"Gashure",
    "wof:placetype":"locality"
},
  "geometry": {"coordinates":[30.1979,-1.9355],"type":"Point"}
}