{
  "type": "Feature",
  "properties": {
    "gn:admin1_code":"13.0",
    "gn:admin2_code":"44",
    "gn:admin3_code":"4416.0",
    "gn:admin4_code":"441602.0",
    "gn:asciiname":"Ndago",
    "gn:country_code":"RW",
    "gn:dem":1918,
    "gn:feature_class":"P",
    "gn:feature_code":"PPLL",
    "gn:name":"Ndago",
    "gn:population":0,
    "gn:timezone":"Africa/Kigali",
    "iso:country":"RW",
    "name:ceb_x_preferred":[
        "Ndago"
    ],
    "name:ita_x_preferred":[
        "Ndago"
    ],
    "name:swa_x_preferred":[
        "Ndago"
    ],
    "name:und_x_variant":[
        "Ndogo"
    ],
    "wof:name":"Ndago",
    "wof:placetype":"locality"
},
  "geometry": {"coordinates":[29.80739,-1.46222],"type":"Point"}
}