{
  "type": "Feature",
  "properties": {
    "gn:admin1_code":"14",
    "gn:admin2_code":"33.0",
    "gn:admin3_code":"3307.0",
    "gn:admin4_code":"330707.0",
    "gn:asciiname":"Kanyamizinga",
    "gn:country_code":"RW",
    "gn:dem":2260,
    "gn:feature_class":"P",
    "gn:feature_code":"PPL",
    "gn:name":"Kanyamizinga",
    "gn:population":0,
    "gn:timezone":"Africa/Kigali",
    "iso:country":"RW",
    "wof:name":"Kanyamizinga",
    "wof:placetype":"locality"
},
  "geometry": {"coordinates":[29.3663,-1.5854],"type":"Point"}
}