{
  "type": "Feature",
  "properties": {
    "gn:admin1_code":"15",
    "gn:admin2_code":"22.0",
    "gn:admin3_code":"2201.0",
    "gn:admin4_code":"220104.0",
    "gn:asciiname":"Nyakabuye",
    "gn:country_code":"RW",
    "gn:dem":1438,
    "gn:feature_class":"P",
    "gn:feature_code":"PPL",
    "gn:name":"Nyakabuye",
    "gn:population":0,
    "gn:timezone":"Africa/Kigali",
    "iso:country":"RW",
    "wof:name":"Nyakabuye",
    "wof:placetype":"locality"
},
  "geometry": {"coordinates":[29.8873,-2.4718],"type":"Point"}
}