{
  "type": "Feature",
  "properties": {
    "gn:admin1_code":"11",
    "gn:admin2_code":"51.0",
    "gn:admin3_code":"5103.0",
    "gn:admin4_code":"510303.0",
    "gn:asciiname":"Nyagacyamo",
    "gn:country_code":"RW",
    "gn:dem":1528,
    "gn:feature_class":"P",
    "gn:feature_code":"PPLL",
    "gn:name":"Nyagacyamo",
    "gn:population":0,
    "gn:timezone":"Africa/Kigali",
    "iso:country":"RW",
    "wof:name":"Nyagacyamo",
    "wof:placetype":"locality"
},
  "geometry": {"coordinates":[30.3916,-1.916],"type":"Point"}
}