{
  "type": "Feature",
  "properties": {
    "gn:admin1_code":"13",
    "gn:admin2_code":"42.0",
    "gn:admin3_code":"4219.0",
    "gn:admin4_code":"421906.0",
    "gn:asciiname":"Mulihi",
    "gn:country_code":"RW",
    "gn:dem":1812,
    "gn:feature_class":"P",
    "gn:feature_code":"PPLL",
    "gn:name":"Mulihi",
    "gn:population":0,
    "gn:timezone":"Africa/Kigali",
    "iso:country":"RW",
    "wof:name":"Mulihi",
    "wof:placetype":"locality"
},
  "geometry": {"coordinates":[29.8703,-1.7083],"type":"Point"}
}