{
  "type": "Feature",
  "properties": {
    "gn:admin1_code":"11",
    "gn:admin2_code":"53.0",
    "gn:admin3_code":"5312.0",
    "gn:admin4_code":"531204.0",
    "gn:asciiname":"Cyarutabire",
    "gn:country_code":"RW",
    "gn:dem":1518,
    "gn:feature_class":"P",
    "gn:feature_code":"PPLL",
    "gn:name":"Cyarutabire",
    "gn:population":0,
    "gn:timezone":"Africa/Kigali",
    "iso:country":"RW",
    "wof:name":"Cyarutabire",
    "wof:placetype":"locality"
},
  "geometry": {"coordinates":[30.3433,-1.6984],"type":"Point"}
}