{
  "type": "Feature",
  "properties": {
    "gn:admin1_code":"11.0",
    "gn:admin2_code":"51",
    "gn:admin3_code":"5102.0",
    "gn:admin4_code":"510204.0",
    "gn:asciiname":"Gahengeri",
    "gn:country_code":"RW",
    "gn:dem":1672,
    "gn:feature_class":"P",
    "gn:feature_code":"PPLL",
    "gn:name":"Gahengeri",
    "gn:population":0,
    "gn:timezone":"Africa/Kigali",
    "iso:country":"RW",
    "wof:name":"Gahengeri",
    "wof:placetype":"locality"
},
  "geometry": {"coordinates":[30.309,-1.977],"type":"Point"}
}