{
  "type": "Feature",
  "properties": {
    "gn:admin1_code":"14.0",
    "gn:admin2_code":"35",
    "gn:admin3_code":"3504.0",
    "gn:admin4_code":"350403.0",
    "gn:asciiname":"Mahungubuye",
    "gn:country_code":"RW",
    "gn:dem":2242,
    "gn:feature_class":"P",
    "gn:feature_code":"PPLL",
    "gn:name":"Mahungubuye",
    "gn:population":0,
    "gn:timezone":"Africa/Kigali",
    "iso:country":"RW",
    "wof:name":"Mahungubuye",
    "wof:placetype":"locality"
},
  "geometry": {"coordinates":[29.53444,-1.75139],"type":"Point"}
}