{
  "type": "Feature",
  "properties": {
    "gn:admin1_code":"11",
    "gn:admin2_code":"54.0",
    "gn:admin3_code":"5410.0",
    "gn:admin4_code":"541002.0",
    "gn:asciiname":"Butimba",
    "gn:country_code":"RW",
    "gn:dem":1491,
    "gn:feature_class":"P",
    "gn:feature_code":"PPLL",
    "gn:name":"Butimba",
    "gn:population":0,
    "gn:timezone":"Africa/Kigali",
    "iso:country":"RW",
    "wof:name":"Butimba",
    "wof:placetype":"locality"
},
  "geometry": {"coordinates":[30.4627,-1.8225],"type":"Point"}
}