{
  "type": "Feature",
  "properties": {
    "gn:admin1_code":"14",
    "gn:admin2_code":"31.0",
    "gn:admin3_code":"3103.0",
    "gn:admin4_code":"310302.0",
    "gn:asciiname":"Mpatsi",
    "gn:country_code":"RW",
    "gn:dem":1683,
    "gn:feature_class":"P",
    "gn:feature_code":"PPLL",
    "gn:name":"Mpatsi",
    "gn:population":0,
    "gn:timezone":"Africa/Kigali",
    "iso:country":"RW",
    "wof:name":"Mpatsi",
    "wof:placetype":"locality"
},
  "geometry": {"coordinates":[29.3012,-2.1597],"type":"Point"}
}