{
  "type": "Feature",
  "properties": {
    "gn:admin1_code":"11",
    "gn:admin2_code":"57.0",
    "gn:admin3_code":"5703.0",
    "gn:admin4_code":"570305.0",
    "gn:asciiname":"Uwibiraro",
    "gn:country_code":"RW",
    "gn:dem":1439,
    "gn:feature_class":"P",
    "gn:feature_code":"PPLL",
    "gn:name":"Uwibiraro",
    "gn:population":0,
    "gn:timezone":"Africa/Kigali",
    "iso:country":"RW",
    "wof:name":"Uwibiraro",
    "wof:placetype":"locality"
},
  "geometry": {"coordinates":[30.1009,-2.381],"type":"Point"}
}