{
  "type": "Feature",
  "properties": {
    "gn:admin1_code":"13",
    "gn:admin2_code":"44.0",
    "gn:admin3_code":"4404.0",
    "gn:admin4_code":"440402.0",
    "gn:asciiname":"Mugomero",
    "gn:country_code":"RW",
    "gn:dem":1988,
    "gn:feature_class":"P",
    "gn:feature_code":"PPLL",
    "gn:name":"Mugomero",
    "gn:population":0,
    "gn:timezone":"Africa/Kigali",
    "iso:country":"RW",
    "wof:name":"Mugomero",
    "wof:placetype":"locality"
},
  "geometry": {"coordinates":[29.8213,-1.5263],"type":"Point"}
}