{
  "type": "Feature",
  "properties": {
    "gn:admin1_code":"11",
    "gn:admin2_code":"56.0",
    "gn:admin3_code":"5612.0",
    "gn:admin4_code":"561205.0",
    "gn:asciiname":"Gitaraga",
    "gn:country_code":"RW",
    "gn:dem":1457,
    "gn:feature_class":"P",
    "gn:feature_code":"PPL",
    "gn:name":"Gitaraga",
    "gn:population":0,
    "gn:timezone":"Africa/Kigali",
    "iso:country":"RW",
    "wof:name":"Gitaraga",
    "wof:placetype":"locality"
},
  "geometry": {"coordinates":[30.5128,-2.0998],"type":"Point"}
}