{
  "type": "Feature",
  "properties": {
    "gn:admin1_code":"15.0",
    "gn:admin2_code":"24",
    "gn:admin3_code":"2401.0",
    "gn:admin4_code":"240104.0",
    "gn:asciiname":"Buguli",
    "gn:country_code":"RW",
    "gn:dem":1813,
    "gn:feature_class":"P",
    "gn:feature_code":"PPLL",
    "gn:name":"Buguli",
    "gn:population":0,
    "gn:timezone":"Africa/Kigali",
    "iso:country":"RW",
    "wof:name":"Buguli",
    "wof:placetype":"locality"
},
  "geometry": {"coordinates":[29.712,-2.6505],"type":"Point"}
}