{
  "type": "Feature",
  "properties": {
    "gn:admin1_code":"15.0",
    "gn:admin2_code":"23",
    "gn:admin3_code":"2307.0",
    "gn:admin4_code":"230704.0",
    "gn:asciiname":"Uwimfizi",
    "gn:country_code":"RW",
    "gn:dem":1904,
    "gn:feature_class":"P",
    "gn:feature_code":"PPLL",
    "gn:name":"Uwimfizi",
    "gn:population":0,
    "gn:timezone":"Africa/Kigali",
    "iso:country":"RW",
    "wof:name":"Uwimfizi",
    "wof:placetype":"locality"
},
  "geometry": {"coordinates":[29.5132,-2.6864],"type":"Point"}
}