{
  "type": "Feature",
  "properties": {
    "gn:admin1_code":"11",
    "gn:admin2_code":"55.0",
    "gn:admin3_code":"5509.0",
    "gn:admin4_code":"550903.0",
    "gn:asciiname":"Rugarama",
    "gn:country_code":"RW",
    "gn:dem":1766,
    "gn:feature_class":"P",
    "gn:feature_code":"PPLL",
    "gn:name":"Rugarama",
    "gn:population":0,
    "gn:timezone":"Africa/Kigali",
    "iso:country":"RW",
    "wof:name":"Rugarama",
    "wof:placetype":"locality"
},
  "geometry": {"coordinates":[30.6667,-2.1459],"type":"Point"}
}