{
  "type": "Feature",
  "properties": {
    "gn:admin1_code":"14.0",
    "gn:admin2_code":"37",
    "gn:admin3_code":"3702.0",
    "gn:admin4_code":"370203.0",
    "gn:asciiname":"Gatare",
    "gn:country_code":"RW",
    "gn:dem":1696,
    "gn:feature_class":"P",
    "gn:feature_code":"PPLL",
    "gn:name":"Gatare",
    "gn:population":0,
    "gn:timezone":"Africa/Kigali",
    "iso:country":"RW",
    "wof:name":"Gatare",
    "wof:placetype":"locality"
},
  "geometry": {"coordinates":[28.9849,-2.4382],"type":"Point"}
}