{
  "type": "Feature",
  "properties": {
    "gn:admin1_code":"11.0",
    "gn:admin2_code":"55",
    "gn:admin3_code":"5501.0",
    "gn:admin4_code":"550104.0",
    "gn:asciiname":"Nyakabungo",
    "gn:country_code":"RW",
    "gn:dem":1402,
    "gn:feature_class":"P",
    "gn:feature_code":"PPLL",
    "gn:name":"Nyakabungo",
    "gn:population":0,
    "gn:timezone":"Africa/Kigali",
    "iso:country":"RW",
    "wof:name":"Nyakabungo",
    "wof:placetype":"locality"
},
  "geometry": {"coordinates":[30.5373,-2.3376],"type":"Point"}
}