{
  "type": "Feature",
  "properties": {
    "gn:admin1_code":"13",
    "gn:admin2_code":"42.0",
    "gn:admin3_code":"4202.0",
    "gn:admin4_code":"420203.0",
    "gn:asciiname":"Mugera",
    "gn:country_code":"RW",
    "gn:dem":1517,
    "gn:feature_class":"P",
    "gn:feature_code":"PPLL",
    "gn:name":"Mugera",
    "gn:population":0,
    "gn:timezone":"Africa/Kigali",
    "iso:country":"RW",
    "wof:name":"Mugera",
    "wof:placetype":"locality"
},
  "geometry": {"coordinates":[29.7912,-1.7959],"type":"Point"}
}