{
  "type": "Feature",
  "properties": {
    "gn:admin1_code":"11",
    "gn:admin2_code":"56.0",
    "gn:admin3_code":"5609.0",
    "gn:admin4_code":"560901.0",
    "gn:asciiname":"Mukenke",
    "gn:country_code":"RW",
    "gn:dem":1444,
    "gn:feature_class":"P",
    "gn:feature_code":"PPLL",
    "gn:name":"Mukenke",
    "gn:population":0,
    "gn:timezone":"Africa/Kigali",
    "iso:country":"RW",
    "wof:name":"Mukenke",
    "wof:placetype":"locality"
},
  "geometry": {"coordinates":[30.5227,-2.083],"type":"Point"}
}