{
  "type": "Feature",
  "properties": {
    "gn:admin1_code":"15",
    "gn:admin2_code":"26.0",
    "gn:admin3_code":"2602.0",
    "gn:admin4_code":"260206.0",
    "gn:asciiname":"Gako",
    "gn:country_code":"RW",
    "gn:dem":1596,
    "gn:feature_class":"P",
    "gn:feature_code":"PPLL",
    "gn:name":"Gako",
    "gn:population":0,
    "gn:timezone":"Africa/Kigali",
    "iso:country":"RW",
    "wof:name":"Gako",
    "wof:placetype":"locality"
},
  "geometry": {"coordinates":[29.7989,-2.1826],"type":"Point"}
}