{
  "type": "Feature",
  "properties": {
    "gn:admin1_code":"14.0",
    "gn:admin2_code":"37",
    "gn:admin3_code":"3701.0",
    "gn:admin4_code":"370103.0",
    "gn:asciiname":"Mashuhera",
    "gn:country_code":"RW",
    "gn:dem":1495,
    "gn:feature_class":"P",
    "gn:feature_code":"PPLL",
    "gn:name":"Mashuhera",
    "gn:population":0,
    "gn:timezone":"Africa/Kigali",
    "iso:country":"RW",
    "wof:name":"Mashuhera",
    "wof:placetype":"locality"
},
  "geometry": {"coordinates":[29.063,-2.3872],"type":"Point"}
}