{
  "type": "Feature",
  "properties": {
    "gn:admin1_code":"14",
    "gn:admin2_code":"31.0",
    "gn:admin3_code":"3106.0",
    "gn:admin4_code":"310603.0",
    "gn:asciiname":"Murondwe",
    "gn:country_code":"RW",
    "gn:dem":1746,
    "gn:feature_class":"P",
    "gn:feature_code":"PPLL",
    "gn:name":"Murondwe",
    "gn:population":0,
    "gn:timezone":"Africa/Kigali",
    "iso:country":"RW",
    "wof:name":"Murondwe",
    "wof:placetype":"locality"
},
  "geometry": {"coordinates":[29.5376,-2.1835],"type":"Point"}
}