{
  "type": "Feature",
  "properties": {
    "gn:admin1_code":"11",
    "gn:admin2_code":"51.0",
    "gn:admin3_code":"5107.0",
    "gn:admin4_code":"510702.0",
    "gn:asciiname":"Nyagakombe",
    "gn:country_code":"RW",
    "gn:dem":1490,
    "gn:feature_class":"P",
    "gn:feature_code":"PPLL",
    "gn:name":"Nyagakombe",
    "gn:population":0,
    "gn:timezone":"Africa/Kigali",
    "iso:country":"RW",
    "wof:name":"Nyagakombe",
    "wof:placetype":"locality"
},
  "geometry": {"coordinates":[30.4346,-2.0403],"type":"Point"}
}