{
  "type": "Feature",
  "properties": {
    "iso:country":"RW",
    "name:chi_x_preferred":[
        "\u5409\u5b54\u6208\u7f85"
    ],
    "name:dut_x_preferred":[
        "Gikongoro"
    ],
    "name:eng_x_preferred":[
        "Gikongoro"
    ],
    "name:fre_x_preferred":[
        "Gikongoro"
    ],
    "name:gre_x_preferred":[
        "\u0393\u03ba\u03b9\u03ba\u03bf\u03bd\u03b3\u03ba\u03cc\u03c1\u03bf"
    ],
    "name:hrv_x_preferred":[
        "Gikongoro"
    ],
    "name:jpn_x_preferred":[
        "\u30ae\u30b3\u30f3\u30b4\u30ed"
    ],
    "name:kor_x_preferred":[
        "\uae30\ucf69\uace0\ub85c"
    ],
    "name:mrj_x_preferred":[
        "\u0413\u0438\u043a\u043e\u043d\u0433\u043e\u0440\u043e"
    ],
    "name:pol_x_preferred":[
        "Gikongoro"
    ],
    "name:por_x_preferred":[
        "Gikongoro"
    ],
    "name:rus_x_preferred":[
        "\u0413\u0438\u043a\u043e\u043d\u0433\u043e\u0440\u043e"
    ],
    "ne:ADM0CAP":0.0,
    "ne:ADM0NAME":"Rwanda",
    "ne:ADM0_A3":"RWA",
    "ne:ADM1NAME":"Southern",
    "ne:ADMIN1_COD":15,
    "ne:CAPALT":0,
    "ne:CHANGED":4,
    "ne:CHECKME":0,
    "ne:COMPARE":0,
    "ne:DIFFASCII":0,
    "ne:DIFFNOTE":"Added missing admin-1 capital. Population from GeoNames.",
    "ne:ELEVATION":0.0,
    "ne:FEATURECLA":"Admin-1 capital",
    "ne:FEATURE_CL":"P",
    "ne:FEATURE_CO":"PPLA",
    "ne:GEONAMEID":202239,
    "ne:GEONAMESNO":"GeoNames match general.",
    "ne:GN_ASCII":"Gikongoro",
    "ne:GN_POP":0,
    "ne:GTOPO30":1796.0,
    "ne:ISO_A2":"RW",
    "ne:LABELRANK":0,
    "ne:LATITUDE":-2.483298,
    "ne:LONGITUDE":29.566702,
    "ne:LS_MATCH":0,
    "ne:MAX_AREAKM":0.0,
    "ne:MAX_AREAMI":0.0,
    "ne:MAX_BBXMAX":0.0,
    "ne:MAX_BBXMIN":0.0,
    "ne:MAX_BBYMAX":0.0,
    "ne:MAX_BBYMIN":0.0,
    "ne:MAX_NATSCA":0.0,
    "ne:MAX_PERKM":0.0,
    "ne:MAX_PERMI":0.0,
    "ne:MAX_POP10":0,
    "ne:MAX_POP20":0,
    "ne:MAX_POP300":0,
    "ne:MAX_POP310":0,
    "ne:MAX_POP50":0,
    "ne:MEAN_BBXC":0.0,
    "ne:MEAN_BBYC":0.0,
    "ne:MEGACITY":0,
    "ne:MIN_AREAKM":0.0,
    "ne:MIN_AREAMI":0.0,
    "ne:MIN_BBXMAX":0.0,
    "ne:MIN_BBXMIN":0.0,
    "ne:MIN_BBYMAX":0.0,
    "ne:MIN_BBYMIN":0.0,
    "ne:MIN_PERKM":0.0,
    "ne:MIN_PERMI":0.0,
    "ne:NAME":"Gikongoro",
    "ne:NAMEASCII":"Gikongoro",
    "ne:NAMEDIFF":1,
    "ne:NATSCALE":1,
    "ne:POP1950":0,
    "ne:POP1955":0,
    "ne:POP1960":0,
    "ne:POP1965":0,
    "ne:POP1970":0,
    "ne:POP1975":0,
    "ne:POP1980":0,
    "ne:POP1985":0,
    "ne:POP1990":0,
    "ne:POP1995":0,
    "ne:POP2000":0,
    "ne:POP2005":0,
    "ne:POP2010":0,
    "ne:POP2015":0,
    "ne:POP2020":0,
    "ne:POP2025":0,
    "ne:POP2050":0,
    "ne:POP_MAX":15000,
    "ne:POP_MIN":15000,
    "ne:POP_OTHER":0,
    "ne:RANK_MAX":6,
    "ne:RANK_MIN":6,
    "ne:SCALERANK":10,
    "ne:SOV0NAME":"Rwanda",
    "ne:SOV_A3":"RWA",
    "ne:TIMEZONE":"Africa/Kigali",
    "ne:UN_FID":0,
    "ne:UN_LAT":0.0,
    "ne:UN_LONG":0.0,
    "ne:WORLDCITY":0,
    "ne:min_zoom":9.0,
    "wof:name":"Gikongoro",
    "wof:placetype":"locality"
},
  "geometry": {"coordinates":[29.56670160203078,-2.48329794473966],"type":"Point"}
}