{
  "type": "Feature",
  "properties": {
    "gn:admin1_code":"13",
    "gn:admin2_code":"43.0",
    "gn:admin3_code":"4310.0",
    "gn:admin4_code":"431003.0",
    "gn:asciiname":"Rwunga",
    "gn:country_code":"RW",
    "gn:dem":2406,
    "gn:feature_class":"P",
    "gn:feature_code":"PPLL",
    "gn:name":"Rwunga",
    "gn:population":0,
    "gn:timezone":"Africa/Kigali",
    "iso:country":"RW",
    "wof:name":"Rwunga",
    "wof:placetype":"locality"
},
  "geometry": {"coordinates":[29.5427,-1.4657],"type":"Point"}
}