{
  "type": "Feature",
  "properties": {
    "gn:admin1_code":"11",
    "gn:admin2_code":"57.0",
    "gn:admin3_code":"5712.0",
    "gn:admin4_code":"571205.0",
    "gn:asciiname":"Gasarwe",
    "gn:country_code":"RW",
    "gn:dem":1385,
    "gn:feature_class":"P",
    "gn:feature_code":"PPLL",
    "gn:name":"Gasarwe",
    "gn:population":0,
    "gn:timezone":"Africa/Kigali",
    "iso:country":"RW",
    "wof:name":"Gasarwe",
    "wof:placetype":"locality"
},
  "geometry": {"coordinates":[30.2031,-2.2214],"type":"Point"}
}