{
  "type": "Feature",
  "properties": {
    "gn:admin1_code":"13",
    "gn:admin2_code":"43.0",
    "gn:admin3_code":"4301.0",
    "gn:admin4_code":"430101.0",
    "gn:asciiname":"Kamatongo",
    "gn:country_code":"RW",
    "gn:dem":2159,
    "gn:feature_class":"P",
    "gn:feature_code":"PPLL",
    "gn:name":"Kamatongo",
    "gn:population":0,
    "gn:timezone":"Africa/Kigali",
    "iso:country":"RW",
    "name:und_x_variant":[
        "Kamatonge"
    ],
    "wof:name":"Kamatongo",
    "wof:placetype":"locality"
},
  "geometry": {"coordinates":[29.5682,-1.5428],"type":"Point"}
}