{
  "type": "Feature",
  "properties": {
    "gn:admin1_code":"14.0",
    "gn:admin2_code":"34",
    "gn:admin3_code":"3408.0",
    "gn:admin4_code":"340804.0",
    "gn:asciiname":"Muremure",
    "gn:country_code":"RW",
    "gn:dem":2343,
    "gn:feature_class":"P",
    "gn:feature_code":"PPLL",
    "gn:name":"Muremure",
    "gn:population":0,
    "gn:timezone":"Africa/Kigali",
    "iso:country":"RW",
    "name:und_x_variant":[
        "Colline Mulemule",
        "Muremure",
        "Mulemule"
    ],
    "wof:name":"Muremure",
    "wof:placetype":"locality"
},
  "geometry": {"coordinates":[29.5317,-1.7248],"type":"Point"}
}