{
  "type": "Feature",
  "properties": {
    "gn:admin1_code":"11",
    "gn:admin2_code":"54.0",
    "gn:admin3_code":"5411.0",
    "gn:admin4_code":"541103.0",
    "gn:asciiname":"Rukoma Il",
    "gn:country_code":"RW",
    "gn:dem":1529,
    "gn:feature_class":"P",
    "gn:feature_code":"PPLL",
    "gn:name":"Rukoma Il",
    "gn:population":0,
    "gn:timezone":"Africa/Kigali",
    "iso:country":"RW",
    "wof:name":"Rukoma Il",
    "wof:placetype":"locality"
},
  "geometry": {"coordinates":[30.5185,-2.0051],"type":"Point"}
}