{
  "type": "Feature",
  "properties": {
    "gn:admin1_code":"14",
    "gn:admin2_code":"35.0",
    "gn:admin3_code":"3507.0",
    "gn:admin4_code":"350704.0",
    "gn:asciiname":"Rwamabuye",
    "gn:country_code":"RW",
    "gn:dem":1869,
    "gn:feature_class":"P",
    "gn:feature_code":"PPLL",
    "gn:name":"Rwamabuye",
    "gn:population":0,
    "gn:timezone":"Africa/Kigali",
    "iso:country":"RW",
    "wof:name":"Rwamabuye",
    "wof:placetype":"locality"
},
  "geometry": {"coordinates":[29.6017,-1.7484],"type":"Point"}
}