{
  "type": "Feature",
  "properties": {
    "gn:admin1_code":"15.0",
    "gn:admin2_code":"23",
    "gn:admin3_code":"2310.0",
    "gn:admin4_code":"231003.0",
    "gn:asciiname":"Muyira",
    "gn:country_code":"RW",
    "gn:dem":2005,
    "gn:feature_class":"P",
    "gn:feature_code":"PPLL",
    "gn:name":"Muyira",
    "gn:population":0,
    "gn:timezone":"Africa/Kigali",
    "iso:country":"RW",
    "wof:name":"Muyira",
    "wof:placetype":"locality"
},
  "geometry": {"coordinates":[29.4581,-2.7224],"type":"Point"}
}