{
  "type": "Feature",
  "properties": {
    "gn:admin1_code":"15",
    "gn:admin2_code":"22.0",
    "gn:admin3_code":"2205.0",
    "gn:admin4_code":"220503.0",
    "gn:asciiname":"Rwimpyisi",
    "gn:country_code":"RW",
    "gn:dem":1746,
    "gn:feature_class":"P",
    "gn:feature_code":"PPL",
    "gn:name":"Rwimpyisi",
    "gn:population":0,
    "gn:timezone":"Africa/Kigali",
    "iso:country":"RW",
    "wof:name":"Rwimpyisi",
    "wof:placetype":"locality"
},
  "geometry": {"coordinates":[29.7686,-2.7129],"type":"Point"}
}