{
  "type": "Feature",
  "properties": {
    "gn:admin1_code":"12",
    "gn:admin2_code":"11.0",
    "gn:admin3_code":"1103.0",
    "gn:admin4_code":"110303.0",
    "gn:asciiname":"Karama",
    "gn:country_code":"RW",
    "gn:dem":1506,
    "gn:feature_class":"P",
    "gn:feature_code":"PPL",
    "gn:name":"Karama",
    "gn:population":0,
    "gn:timezone":"Africa/Kigali",
    "iso:country":"RW",
    "name:ceb_x_preferred":[
        "Karama"
    ],
    "name:fra_x_preferred":[
        "Karama"
    ],
    "name:ita_x_preferred":[
        "Karama"
    ],
    "name:swe_x_preferred":[
        "Karama"
    ],
    "wof:name":"Karama",
    "wof:placetype":"locality"
},
  "geometry": {"coordinates":[30.01624,-1.95878],"type":"Point"}
}