{
  "type": "Feature",
  "properties": {
    "gn:admin1_code":"11",
    "gn:admin2_code":"55.0",
    "gn:admin3_code":"5503.0",
    "gn:admin4_code":"550305.0",
    "gn:asciiname":"Kiyanzi",
    "gn:country_code":"RW",
    "gn:dem":1419,
    "gn:feature_class":"P",
    "gn:feature_code":"PPLL",
    "gn:name":"Kiyanzi",
    "gn:population":0,
    "gn:timezone":"Africa/Kigali",
    "iso:country":"RW",
    "wof:name":"Kiyanzi",
    "wof:placetype":"locality"
},
  "geometry": {"coordinates":[30.76257,-2.3673],"type":"Point"}
}