{
  "type": "Feature",
  "properties": {
    "gn:admin1_code":"14.0",
    "gn:admin2_code":"35",
    "gn:admin3_code":"3508.0",
    "gn:admin4_code":"350803.0",
    "gn:asciiname":"Gahurura",
    "gn:country_code":"RW",
    "gn:dem":2366,
    "gn:feature_class":"P",
    "gn:feature_code":"PPLL",
    "gn:name":"Gahurura",
    "gn:population":0,
    "gn:timezone":"Africa/Kigali",
    "iso:country":"RW",
    "wof:name":"Gahurura",
    "wof:placetype":"locality"
},
  "geometry": {"coordinates":[29.4915,-1.7918],"type":"Point"}
}