{
  "type": "Feature",
  "properties": {
    "gn:admin1_code":"14",
    "gn:admin2_code":"34.0",
    "gn:admin3_code":"3405.0",
    "gn:admin4_code":"340506.0",
    "gn:asciiname":"Rayebe",
    "gn:country_code":"RW",
    "gn:dem":2329,
    "gn:feature_class":"P",
    "gn:feature_code":"PPLL",
    "gn:name":"Rayebe",
    "gn:population":0,
    "gn:timezone":"Africa/Kigali",
    "iso:country":"RW",
    "wof:name":"Rayebe",
    "wof:placetype":"locality"
},
  "geometry": {"coordinates":[29.5241,-1.65],"type":"Point"}
}