{
  "type": "Feature",
  "properties": {
    "gn:admin1_code":"15.0",
    "gn:admin2_code":"23",
    "gn:admin3_code":"2303.0",
    "gn:admin4_code":"230303.0",
    "gn:asciiname":"Kinazi",
    "gn:country_code":"RW",
    "gn:dem":1914,
    "gn:feature_class":"P",
    "gn:feature_code":"PPLL",
    "gn:name":"Kinazi",
    "gn:population":0,
    "gn:timezone":"Africa/Kigali",
    "iso:country":"RW",
    "wof:name":"Kinazi",
    "wof:placetype":"locality"
},
  "geometry": {"coordinates":[29.5758,-2.6153],"type":"Point"}
}