{
  "type": "Feature",
  "properties": {
    "gn:admin1_code":"15",
    "gn:admin2_code":"28.0",
    "gn:admin3_code":"2810.0",
    "gn:admin4_code":"281005.0",
    "gn:asciiname":"Sheli",
    "gn:country_code":"RW",
    "gn:dem":1572,
    "gn:feature_class":"P",
    "gn:feature_code":"PPL",
    "gn:name":"Sheli",
    "gn:population":0,
    "gn:timezone":"Africa/Kigali",
    "iso:country":"RW",
    "wof:name":"Sheli",
    "wof:placetype":"locality"
},
  "geometry": {"coordinates":[29.9466,-1.9911],"type":"Point"}
}