{
  "type": "Feature",
  "properties": {
    "gn:admin1_code":"14",
    "gn:admin2_code":"31.0",
    "gn:admin3_code":"3112.0",
    "gn:admin4_code":"311208.0",
    "gn:asciiname":"Gishwaki",
    "gn:country_code":"RW",
    "gn:dem":2043,
    "gn:feature_class":"P",
    "gn:feature_code":"PPL",
    "gn:name":"Gishwaki",
    "gn:population":0,
    "gn:timezone":"Africa/Kigali",
    "iso:country":"RW",
    "wof:name":"Gishwaki",
    "wof:placetype":"locality"
},
  "geometry": {"coordinates":[29.4185,-2.1902],"type":"Point"}
}