{
  "type": "Feature",
  "properties": {
    "gn:admin1_code":"15",
    "gn:admin2_code":"26.0",
    "gn:admin3_code":"2607.0",
    "gn:admin4_code":"260706.0",
    "gn:asciiname":"Gakoma",
    "gn:country_code":"RW",
    "gn:dem":1816,
    "gn:feature_class":"P",
    "gn:feature_code":"PPLL",
    "gn:name":"Gakoma",
    "gn:population":0,
    "gn:timezone":"Africa/Kigali",
    "iso:country":"RW",
    "wof:name":"Gakoma",
    "wof:placetype":"locality"
},
  "geometry": {"coordinates":[29.6543,-2.1368],"type":"Point"}
}