{
  "type": "Feature",
  "properties": {
    "gn:admin1_code":"14.0",
    "gn:admin2_code":"37",
    "gn:admin3_code":"3710.0",
    "gn:admin4_code":"371004.0",
    "gn:asciiname":"Rwamiko",
    "gn:country_code":"RW",
    "gn:dem":1528,
    "gn:feature_class":"P",
    "gn:feature_code":"PPLL",
    "gn:name":"Rwamiko",
    "gn:population":0,
    "gn:timezone":"Africa/Kigali",
    "iso:country":"RW",
    "name:und_x_variant":[
        "Rwamika",
        "Rwamiko"
    ],
    "wof:name":"Rwamiko",
    "wof:placetype":"locality"
},
  "geometry": {"coordinates":[29.1747,-2.2635],"type":"Point"}
}