{
  "type": "Feature",
  "properties": {
    "gn:admin1_code":"13",
    "gn:admin2_code":"45.0",
    "gn:admin3_code":"4518.0",
    "gn:admin4_code":"451801.0",
    "gn:asciiname":"Rugarama",
    "gn:country_code":"RW",
    "gn:dem":1909,
    "gn:feature_class":"P",
    "gn:feature_code":"PPLL",
    "gn:name":"Rugarama",
    "gn:population":0,
    "gn:timezone":"Africa/Kigali",
    "iso:country":"RW",
    "wof:name":"Rugarama",
    "wof:placetype":"locality"
},
  "geometry": {"coordinates":[30.1725,-1.6933],"type":"Point"}
}