{
  "type": "Feature",
  "properties": {
    "gn:admin1_code":"13",
    "gn:admin2_code":"42.0",
    "gn:admin3_code":"4207.0",
    "gn:admin4_code":"420703.0",
    "gn:asciiname":"Kalingorera",
    "gn:country_code":"RW",
    "gn:dem":2214,
    "gn:feature_class":"P",
    "gn:feature_code":"PPLL",
    "gn:name":"Kalingorera",
    "gn:population":0,
    "gn:timezone":"Africa/Kigali",
    "iso:country":"RW",
    "wof:name":"Kalingorera",
    "wof:placetype":"locality"
},
  "geometry": {"coordinates":[29.7724,-1.5746],"type":"Point"}
}