{
  "type": "Feature",
  "properties": {
    "gn:admin1_code":"15",
    "gn:admin2_code":"28.0",
    "gn:admin3_code":"2807.0",
    "gn:admin4_code":"280701.0",
    "gn:asciiname":"Gacanzogera",
    "gn:country_code":"RW",
    "gn:dem":1579,
    "gn:feature_class":"P",
    "gn:feature_code":"PPLL",
    "gn:name":"Gacanzogera",
    "gn:population":0,
    "gn:timezone":"Africa/Kigali",
    "iso:country":"RW",
    "name:und_x_variant":[
        "Cacanzogera"
    ],
    "wof:name":"Gacanzogera",
    "wof:placetype":"locality"
},
  "geometry": {"coordinates":[29.9281,-1.8913],"type":"Point"}
}