{
  "type": "Feature",
  "properties": {
    "gn:admin1_code":"13.0",
    "gn:admin2_code":"42",
    "gn:admin3_code":"4218.0",
    "gn:admin4_code":"421806.0",
    "gn:asciiname":"Nyonilima",
    "gn:country_code":"RW",
    "gn:dem":1837,
    "gn:feature_class":"P",
    "gn:feature_code":"PPLL",
    "gn:name":"Nyonilima",
    "gn:population":0,
    "gn:timezone":"Africa/Kigali",
    "iso:country":"RW",
    "name:und_x_variant":[
        "Colline Nyonilima",
        "Nyonilima"
    ],
    "wof:name":"Nyonilima",
    "wof:placetype":"locality"
},
  "geometry": {"coordinates":[29.66667,-1.61667],"type":"Point"}
}