{
  "type": "Feature",
  "properties": {
    "gn:admin1_code":"14.0",
    "gn:admin2_code":"36",
    "gn:admin3_code":"3615.0",
    "gn:admin4_code":"361503.0",
    "gn:asciiname":"Bugumya",
    "gn:country_code":"RW",
    "gn:dem":1231,
    "gn:feature_class":"P",
    "gn:feature_code":"PPL",
    "gn:name":"Bugumya",
    "gn:population":0,
    "gn:timezone":"Africa/Kigali",
    "iso:country":"RW",
    "wof:name":"Bugumya",
    "wof:placetype":"locality"
},
  "geometry": {"coordinates":[29.0272,-2.5616],"type":"Point"}
}