{
  "type": "Feature",
  "properties": {
    "gn:admin1_code":"15.0",
    "gn:admin2_code":"25",
    "gn:admin3_code":"2512.0",
    "gn:admin4_code":"251201.0",
    "gn:asciiname":"Murambi",
    "gn:country_code":"RW",
    "gn:dem":1741,
    "gn:feature_class":"P",
    "gn:feature_code":"PPL",
    "gn:name":"Murambi",
    "gn:population":0,
    "gn:timezone":"Africa/Kigali",
    "iso:country":"RW",
    "name:ita_x_preferred":[
        "Murambi"
    ],
    "wof:name":"Murambi",
    "wof:placetype":"locality"
},
  "geometry": {"coordinates":[29.5488,-2.2535],"type":"Point"}
}