{
  "type": "Feature",
  "properties": {
    "gn:admin1_code":"13",
    "gn:admin2_code":"44.0",
    "gn:admin3_code":"4403.0",
    "gn:admin4_code":"440301.0",
    "gn:asciiname":"Gasiza",
    "gn:country_code":"RW",
    "gn:dem":2296,
    "gn:feature_class":"P",
    "gn:feature_code":"PPLL",
    "gn:name":"Gasiza",
    "gn:population":0,
    "gn:timezone":"Africa/Kigali",
    "iso:country":"RW",
    "wof:name":"Gasiza",
    "wof:placetype":"locality"
},
  "geometry": {"coordinates":[29.7153,-1.3969],"type":"Point"}
}