{
  "type": "Feature",
  "properties": {
    "gn:admin1_code":"15.0",
    "gn:admin2_code":"21",
    "gn:admin3_code":"2109.0",
    "gn:admin4_code":"210905.0",
    "gn:asciiname":"Rushubi",
    "gn:country_code":"RW",
    "gn:dem":1580,
    "gn:feature_class":"P",
    "gn:feature_code":"PPLL",
    "gn:name":"Rushubi",
    "gn:population":0,
    "gn:timezone":"Africa/Kigali",
    "iso:country":"RW",
    "wof:name":"Rushubi",
    "wof:placetype":"locality"
},
  "geometry": {"coordinates":[29.6541,-2.3402],"type":"Point"}
}