{
  "type": "Feature",
  "properties": {
    "gn:admin1_code":"11",
    "gn:admin2_code":"54.0",
    "gn:admin3_code":"5409.0",
    "gn:admin4_code":"540902.0",
    "gn:asciiname":"Nyagasambu",
    "gn:country_code":"RW",
    "gn:dem":1585,
    "gn:feature_class":"P",
    "gn:feature_code":"PPLL",
    "gn:name":"Nyagasambu",
    "gn:population":0,
    "gn:timezone":"Africa/Kigali",
    "iso:country":"RW",
    "wof:name":"Nyagasambu",
    "wof:placetype":"locality"
},
  "geometry": {"coordinates":[30.5515,-1.957],"type":"Point"}
}