{
  "type": "Feature",
  "properties": {
    "gn:admin1_code":"14",
    "gn:admin2_code":"35.0",
    "gn:admin3_code":"3512.0",
    "gn:admin4_code":"351204.0",
    "gn:asciiname":"Kinkuba",
    "gn:country_code":"RW",
    "gn:dem":2243,
    "gn:feature_class":"P",
    "gn:feature_code":"PPLL",
    "gn:name":"Kinkuba",
    "gn:population":0,
    "gn:timezone":"Africa/Kigali",
    "iso:country":"RW",
    "wof:name":"Kinkuba",
    "wof:placetype":"locality"
},
  "geometry": {"coordinates":[29.5493,-2.0617],"type":"Point"}
}