{
  "type": "Feature",
  "properties": {
    "gn:admin1_code":"11",
    "gn:admin2_code":"52.0",
    "gn:admin3_code":"5208.0",
    "gn:admin4_code":"520803.0",
    "gn:asciiname":"Kabongoya",
    "gn:country_code":"RW",
    "gn:dem":1805,
    "gn:feature_class":"P",
    "gn:feature_code":"PPLL",
    "gn:name":"Kabongoya",
    "gn:population":0,
    "gn:timezone":"Africa/Kigali",
    "iso:country":"RW",
    "wof:name":"Kabongoya",
    "wof:placetype":"locality"
},
  "geometry": {"coordinates":[30.16042,-1.51126],"type":"Point"}
}