{
  "type": "Feature",
  "properties": {
    "gn:admin1_code":"13",
    "gn:admin2_code":"45.0",
    "gn:admin3_code":"4503.0",
    "gn:admin4_code":"450302.0",
    "gn:asciiname":"Rebero",
    "gn:country_code":"RW",
    "gn:dem":2082,
    "gn:feature_class":"P",
    "gn:feature_code":"PPL",
    "gn:name":"Rebero",
    "gn:population":0,
    "gn:timezone":"Africa/Kigali",
    "iso:country":"RW",
    "wof:name":"Rebero",
    "wof:placetype":"locality"
},
  "geometry": {"coordinates":[30.0633,-1.5695],"type":"Point"}
}