{
  "type": "Feature",
  "properties": {
    "gn:admin1_code":"15.0",
    "gn:admin2_code":"25",
    "gn:admin3_code":"2501.0",
    "gn:admin4_code":"250105.0",
    "gn:asciiname":"Rukwandu",
    "gn:country_code":"RW",
    "gn:dem":2119,
    "gn:feature_class":"P",
    "gn:feature_code":"PPLL",
    "gn:name":"Rukwandu",
    "gn:population":0,
    "gn:timezone":"Africa/Kigali",
    "iso:country":"RW",
    "wof:name":"Rukwandu",
    "wof:placetype":"locality"
},
  "geometry": {"coordinates":[29.4201,-2.4015],"type":"Point"}
}