{
  "type": "Feature",
  "properties": {
    "gn:admin1_code":"15.0",
    "gn:admin2_code":"25",
    "gn:admin3_code":"2510.0",
    "gn:admin4_code":"251003.0",
    "gn:asciiname":"Munanira",
    "gn:country_code":"RW",
    "gn:dem":1856,
    "gn:feature_class":"P",
    "gn:feature_code":"PPLL",
    "gn:name":"Munanira",
    "gn:population":0,
    "gn:timezone":"Africa/Kigali",
    "iso:country":"RW",
    "wof:name":"Munanira",
    "wof:placetype":"locality"
},
  "geometry": {"coordinates":[29.5893,-2.4039],"type":"Point"}
}