{
  "type": "Feature",
  "properties": {
    "gn:admin1_code":"14.0",
    "gn:asciiname":"Kadasomwa",
    "gn:country_code":"RW",
    "gn:dem":2220,
    "gn:feature_class":"P",
    "gn:feature_code":"PPLL",
    "gn:name":"Kadasomwa",
    "gn:population":0,
    "gn:timezone":"Africa/Kigali",
    "iso:country":"RW",
    "wof:name":"Kadasomwa",
    "wof:placetype":"locality"
},
  "geometry": {"coordinates":[29.401,-2.2824],"type":"Point"}
}