{
  "type": "Feature",
  "properties": {
    "gn:admin1_code":"14.0",
    "gn:admin2_code":"36",
    "gn:admin3_code":"3617.0",
    "gn:admin4_code":"361706.0",
    "gn:asciiname":"Kagenge",
    "gn:country_code":"RW",
    "gn:dem":1558,
    "gn:feature_class":"P",
    "gn:feature_code":"PPLL",
    "gn:name":"Kagenge",
    "gn:population":0,
    "gn:timezone":"Africa/Kigali",
    "iso:country":"RW",
    "wof:name":"Kagenge",
    "wof:placetype":"locality"
},
  "geometry": {"coordinates":[28.9085,-2.6241],"type":"Point"}
}