{
  "type": "Feature",
  "properties": {
    "gn:admin1_code":"11",
    "gn:admin2_code":"54.0",
    "gn:admin3_code":"5406.0",
    "gn:admin4_code":"540602.0",
    "gn:asciiname":"Nyamirama",
    "gn:country_code":"RW",
    "gn:dem":1450,
    "gn:feature_class":"P",
    "gn:feature_code":"PPLL",
    "gn:name":"Nyamirama",
    "gn:population":0,
    "gn:timezone":"Africa/Kigali",
    "iso:country":"RW",
    "wof:name":"Nyamirama",
    "wof:placetype":"locality"
},
  "geometry": {"coordinates":[30.4928,-1.7127],"type":"Point"}
}