{
  "type": "Feature",
  "properties": {
    "gn:admin1_code":"11",
    "gn:admin2_code":"51.0",
    "gn:admin3_code":"5108.0",
    "gn:admin4_code":"510803.0",
    "gn:asciiname":"Ndago",
    "gn:country_code":"RW",
    "gn:dem":1514,
    "gn:feature_class":"P",
    "gn:feature_code":"PPLL",
    "gn:name":"Ndago",
    "gn:population":0,
    "gn:timezone":"Africa/Kigali",
    "iso:country":"RW",
    "name:ceb_x_preferred":[
        "Ndago"
    ],
    "name:ita_x_preferred":[
        "Ndago"
    ],
    "name:swa_x_preferred":[
        "Ndago"
    ],
    "wof:name":"Ndago",
    "wof:placetype":"locality"
},
  "geometry": {"coordinates":[30.3821,-1.9435],"type":"Point"}
}