{
  "type": "Feature",
  "properties": {
    "gn:admin1_code":"13",
    "gn:asciiname":"Kiyumba",
    "gn:country_code":"RW",
    "gn:dem":2408,
    "gn:feature_class":"P",
    "gn:feature_code":"PPL",
    "gn:name":"Kiyumba",
    "gn:population":0,
    "gn:timezone":"Africa/Kigali",
    "iso:country":"RW",
    "name:und_x_variant":[
        "Kyumba"
    ],
    "wof:name":"Kiyumba",
    "wof:placetype":"locality"
},
  "geometry": {"coordinates":[29.5493,-1.5799],"type":"Point"}
}