{
  "type": "Feature",
  "properties": {
    "gn:admin1_code":"14.0",
    "gn:admin2_code":"37",
    "gn:admin3_code":"3702.0",
    "gn:admin4_code":"370202.0",
    "gn:asciiname":"Nyarutovu",
    "gn:country_code":"RW",
    "gn:dem":1689,
    "gn:feature_class":"P",
    "gn:feature_code":"PPL",
    "gn:name":"Nyarutovu",
    "gn:population":0,
    "gn:timezone":"Africa/Kigali",
    "iso:country":"RW",
    "wof:name":"Nyarutovu",
    "wof:placetype":"locality"
},
  "geometry": {"coordinates":[29.0125,-2.423],"type":"Point"}
}