{
  "type": "Feature",
  "properties": {
    "gn:admin1_code":"14",
    "gn:admin2_code":"34.0",
    "gn:admin3_code":"3401.0",
    "gn:admin4_code":"340106.0",
    "gn:asciiname":"Rega",
    "gn:country_code":"RW",
    "gn:dem":2351,
    "gn:feature_class":"P",
    "gn:feature_code":"PPL",
    "gn:name":"Rega",
    "gn:population":0,
    "gn:timezone":"Africa/Kigali",
    "iso:country":"RW",
    "wof:name":"Rega",
    "wof:placetype":"locality"
},
  "geometry": {"coordinates":[29.4059,-1.6396],"type":"Point"}
}