{
  "type": "Feature",
  "properties": {
    "gn:admin1_code":"14",
    "gn:admin2_code":"34.0",
    "gn:admin3_code":"3401.0",
    "gn:admin4_code":"340106.0",
    "gn:asciiname":"Rega",
    "gn:country_code":"RW",
    "gn:dem":2351,
    "gn:feature_class":"P",
    "gn:feature_code":"PPL",
    "gn:name":"Rega",
    "gn:population":0,
    "gn:timezone":"Africa/Kigali",
    "iso:country":"RW",
    "name:als_x_preferred":[
        "Rega"
    ],
    "name:arg_x_preferred":[
        "R\u00edo Rega"
    ],
    "name:bel_x_preferred":[
        "\u0420\u044d\u0433\u0430"
    ],
    "name:ceb_x_preferred":[
        "Rega"
    ],
    "name:ces_x_preferred":[
        "Rega"
    ],
    "name:chv_x_preferred":[
        "\u0420\u0435\u0433\u0430"
    ],
    "name:deu_x_preferred":[
        "Rega"
    ],
    "name:fra_x_preferred":[
        "Rega"
    ],
    "name:fry_x_preferred":[
        "Rega"
    ],
    "name:hrv_x_preferred":[
        "Rega"
    ],
    "name:ita_x_preferred":[
        "Rega"
    ],
    "name:kat_x_preferred":[
        "\u10e0\u10d4\u10d2\u10d0"
    ],
    "name:lit_x_preferred":[
        "Rega"
    ],
    "name:nds_x_preferred":[
        "Reej"
    ],
    "name:nld_x_preferred":[
        "Rega"
    ],
    "name:nno_x_preferred":[
        "Rega"
    ],
    "name:nor_x_preferred":[
        "Rega"
    ],
    "name:pol_x_preferred":[
        "Rega"
    ],
    "name:rus_x_preferred":[
        "\u0420\u0435\u0433\u0430"
    ],
    "name:spa_x_preferred":[
        "R\u00edo Rega"
    ],
    "name:srp_x_preferred":[
        "\u0420\u0435\u0433\u0430"
    ],
    "name:swe_x_preferred":[
        "Rega"
    ],
    "name:szl_x_preferred":[
        "Rega"
    ],
    "name:ukr_x_preferred":[
        "\u0420\u0435\u0433\u0430"
    ],
    "name:zho_x_preferred":[
        "\u96f7\u52a0\u6cb3"
    ],
    "wof:name":"Rega",
    "wof:placetype":"locality"
},
  "geometry": {"coordinates":[29.4059,-1.6396],"type":"Point"}
}