{
  "type": "Feature",
  "properties": {
    "gn:admin1_code":"13",
    "gn:admin2_code":"44.0",
    "gn:admin3_code":"4414.0",
    "gn:admin4_code":"441403.0",
    "gn:asciiname":"Rusarabuge",
    "gn:country_code":"RW",
    "gn:dem":2040,
    "gn:feature_class":"P",
    "gn:feature_code":"PPLL",
    "gn:name":"Rusarabuge",
    "gn:population":0,
    "gn:timezone":"Africa/Kigali",
    "iso:country":"RW",
    "wof:name":"Rusarabuge",
    "wof:placetype":"locality"
},
  "geometry": {"coordinates":[29.8185,-1.5454],"type":"Point"}
}