{
  "type": "Feature",
  "properties": {
    "gn:admin1_code":"13",
    "gn:admin2_code":"41.0",
    "gn:admin3_code":"4116.0",
    "gn:admin4_code":"411603.0",
    "gn:asciiname":"Kavumu",
    "gn:country_code":"RW",
    "gn:dem":1536,
    "gn:feature_class":"P",
    "gn:feature_code":"PPLL",
    "gn:name":"Kavumu",
    "gn:population":0,
    "gn:timezone":"Africa/Kigali",
    "iso:country":"RW",
    "wof:name":"Kavumu",
    "wof:placetype":"locality"
},
  "geometry": {"coordinates":[29.915,-1.8516],"type":"Point"}
}