{
  "type": "Feature",
  "properties": {
    "gn:admin1_code":"11",
    "gn:admin2_code":"57.0",
    "gn:admin3_code":"5709.0",
    "gn:admin4_code":"570901.0",
    "gn:asciiname":"Kidudu",
    "gn:country_code":"RW",
    "gn:dem":1433,
    "gn:feature_class":"P",
    "gn:feature_code":"PPLL",
    "gn:name":"Kidudu",
    "gn:population":0,
    "gn:timezone":"Africa/Kigali",
    "iso:country":"RW",
    "wof:name":"Kidudu",
    "wof:placetype":"locality"
},
  "geometry": {"coordinates":[30.0298,-2.1207],"type":"Point"}
}