{
  "type": "Feature",
  "properties": {
    "gn:admin1_code":"15.0",
    "gn:admin2_code":"24",
    "gn:admin3_code":"2404.0",
    "gn:admin4_code":"240401.0",
    "gn:asciiname":"Karambi",
    "gn:country_code":"RW",
    "gn:dem":1617,
    "gn:feature_class":"P",
    "gn:feature_code":"PPLL",
    "gn:name":"Karambi",
    "gn:population":0,
    "gn:timezone":"Africa/Kigali",
    "iso:country":"RW",
    "wof:name":"Karambi",
    "wof:placetype":"locality"
},
  "geometry": {"coordinates":[29.6514,-2.4868],"type":"Point"}
}