{
  "type": "Feature",
  "properties": {
    "gn:admin1_code":"14.0",
    "gn:admin2_code":"37",
    "gn:admin3_code":"3702.0",
    "gn:admin4_code":"370202.0",
    "gn:asciiname":"Buninda",
    "gn:country_code":"RW",
    "gn:dem":1796,
    "gn:feature_class":"P",
    "gn:feature_code":"PPLL",
    "gn:name":"Buninda",
    "gn:population":0,
    "gn:timezone":"Africa/Kigali",
    "iso:country":"RW",
    "wof:name":"Buninda",
    "wof:placetype":"locality"
},
  "geometry": {"coordinates":[29.0019,-2.4346],"type":"Point"}
}