{
  "type": "Feature",
  "properties": {
    "gn:admin1_code":"15.0",
    "gn:admin2_code":"25",
    "gn:admin3_code":"2512.0",
    "gn:admin4_code":"251205.0",
    "gn:asciiname":"Munini",
    "gn:country_code":"RW",
    "gn:dem":1696,
    "gn:feature_class":"P",
    "gn:feature_code":"PPLL",
    "gn:name":"Munini",
    "gn:population":0,
    "gn:timezone":"Africa/Kigali",
    "iso:country":"RW",
    "wof:name":"Munini",
    "wof:placetype":"locality"
},
  "geometry": {"coordinates":[29.5812,-2.2757],"type":"Point"}
}