{
  "type": "Feature",
  "properties": {
    "gn:admin1_code":"13",
    "gn:admin2_code":"41.0",
    "gn:admin3_code":"4111.0",
    "gn:admin4_code":"411104.0",
    "gn:asciiname":"Nyiragapfunsi",
    "gn:country_code":"RW",
    "gn:dem":1924,
    "gn:feature_class":"P",
    "gn:feature_code":"PPLL",
    "gn:name":"Nyiragapfunsi",
    "gn:population":0,
    "gn:timezone":"Africa/Kigali",
    "iso:country":"RW",
    "wof:name":"Nyiragapfunsi",
    "wof:placetype":"locality"
},
  "geometry": {"coordinates":[30.024,-1.8028],"type":"Point"}
}