{
  "type": "Feature",
  "properties": {
    "gn:admin1_code":"15",
    "gn:admin2_code":"24.0",
    "gn:admin3_code":"2411.0",
    "gn:admin4_code":"241103.0",
    "gn:asciiname":"Kato",
    "gn:country_code":"RW",
    "gn:dem":1668,
    "gn:feature_class":"P",
    "gn:feature_code":"PPL",
    "gn:name":"Kato",
    "gn:population":0,
    "gn:timezone":"Africa/Kigali",
    "iso:country":"RW",
    "name:ceb_x_preferred":[
        "Kato"
    ],
    "name:deu_x_preferred":[
        "Kat\u014d"
    ],
    "name:epo_x_preferred":[
        "Kato"
    ],
    "name:fas_x_preferred":[
        "\u06a9\u0627\u062a\u0648"
    ],
    "name:fin_x_preferred":[
        "Kato"
    ],
    "name:fra_x_preferred":[
        "Kato"
    ],
    "name:fry_x_preferred":[
        "Kato"
    ],
    "name:ita_x_preferred":[
        "Kato"
    ],
    "name:nld_x_preferred":[
        "Kato"
    ],
    "name:pol_x_preferred":[
        "Kato"
    ],
    "name:por_x_preferred":[
        "Kato"
    ],
    "name:ron_x_preferred":[
        "Kato"
    ],
    "name:rus_x_preferred":[
        "\u041a\u0430\u0442\u043e"
    ],
    "name:spa_x_preferred":[
        "Kato"
    ],
    "name:swe_x_preferred":[
        "Kato"
    ],
    "name:ukr_x_preferred":[
        "\u041a\u0430\u0442\u043e"
    ],
    "name:und_x_variant":[
        "Kati"
    ],
    "wof:name":"Kato",
    "wof:placetype":"locality"
},
  "geometry": {"coordinates":[29.78,-2.4531],"type":"Point"}
}