{
  "type": "Feature",
  "properties": {
    "gn:admin1_code":"15",
    "gn:admin2_code":"24.0",
    "gn:admin3_code":"2411.0",
    "gn:admin4_code":"241103.0",
    "gn:asciiname":"Kato",
    "gn:country_code":"RW",
    "gn:dem":1668,
    "gn:feature_class":"P",
    "gn:feature_code":"PPL",
    "gn:name":"Kato",
    "gn:population":0,
    "gn:timezone":"Africa/Kigali",
    "iso:country":"RW",
    "name:und_x_variant":[
        "Kati"
    ],
    "wof:name":"Kato",
    "wof:placetype":"locality"
},
  "geometry": {"coordinates":[29.78,-2.4531],"type":"Point"}
}