{
  "type": "Feature",
  "properties": {
    "gn:admin1_code":"14.0",
    "gn:admin2_code":"37",
    "gn:admin3_code":"3705.0",
    "gn:admin4_code":"370501.0",
    "gn:asciiname":"Nyakabingo",
    "gn:country_code":"RW",
    "gn:dem":1516,
    "gn:feature_class":"P",
    "gn:feature_code":"PPLL",
    "gn:name":"Nyakabingo",
    "gn:population":0,
    "gn:timezone":"Africa/Kigali",
    "iso:country":"RW",
    "name:und_x_variant":[
        "Colline Nyakabingo",
        "Nyakabingo"
    ],
    "wof:name":"Nyakabingo",
    "wof:placetype":"locality"
},
  "geometry": {"coordinates":[29.1275,-2.3458],"type":"Point"}
}