{
  "type": "Feature",
  "properties": {
    "gn:admin1_code":"13",
    "gn:admin2_code":"42.0",
    "gn:admin3_code":"4210.0",
    "gn:admin4_code":"421002.0",
    "gn:asciiname":"Muhororo",
    "gn:country_code":"RW",
    "gn:dem":1550,
    "gn:feature_class":"P",
    "gn:feature_code":"PPLL",
    "gn:name":"Muhororo",
    "gn:population":0,
    "gn:timezone":"Africa/Kigali",
    "iso:country":"RW",
    "wof:name":"Muhororo",
    "wof:placetype":"locality"
},
  "geometry": {"coordinates":[29.741,-1.7449],"type":"Point"}
}