{
  "type": "Feature",
  "properties": {
    "gn:admin1_code":"11",
    "gn:admin2_code":"54.0",
    "gn:admin3_code":"5405.0",
    "gn:admin4_code":"540503.0",
    "gn:asciiname":"Rwabugengeri",
    "gn:country_code":"RW",
    "gn:dem":1692,
    "gn:feature_class":"P",
    "gn:feature_code":"PPLL",
    "gn:name":"Rwabugengeri",
    "gn:population":0,
    "gn:timezone":"Africa/Kigali",
    "iso:country":"RW",
    "wof:name":"Rwabugengeri",
    "wof:placetype":"locality"
},
  "geometry": {"coordinates":[30.6198,-2.0234],"type":"Point"}
}