{
  "type": "Feature",
  "properties": {
    "gn:admin1_code":"15.0",
    "gn:admin2_code":"22",
    "gn:admin3_code":"2206.0",
    "gn:admin4_code":"220603.0",
    "gn:asciiname":"Muyaga",
    "gn:country_code":"RW",
    "gn:dem":1489,
    "gn:feature_class":"P",
    "gn:feature_code":"PPL",
    "gn:name":"Muyaga",
    "gn:population":0,
    "gn:timezone":"Africa/Kigali",
    "iso:country":"RW",
    "wof:name":"Muyaga",
    "wof:placetype":"locality"
},
  "geometry": {"coordinates":[29.9179,-2.4791],"type":"Point"}
}