{
  "type": "Feature",
  "properties": {
    "gn:admin1_code":"15.0",
    "gn:admin2_code":"26",
    "gn:admin3_code":"2604.0",
    "gn:admin4_code":"260405.0",
    "gn:asciiname":"Rutabo",
    "gn:country_code":"RW",
    "gn:dem":1482,
    "gn:feature_class":"P",
    "gn:feature_code":"PPL",
    "gn:name":"Rutabo",
    "gn:population":0,
    "gn:timezone":"Africa/Kigali",
    "iso:country":"RW",
    "name:und_x_variant":[
        "Colline Rutabo",
        "Rutabo"
    ],
    "wof:name":"Rutabo",
    "wof:placetype":"locality"
},
  "geometry": {"coordinates":[29.9534,-2.2156],"type":"Point"}
}