{
  "type": "Feature",
  "properties": {
    "gn:admin1_code":"11.0",
    "gn:admin2_code":"55",
    "gn:admin3_code":"5502.0",
    "gn:admin4_code":"550204.0",
    "gn:asciiname":"Gatore",
    "gn:country_code":"RW",
    "gn:dem":1519,
    "gn:feature_class":"P",
    "gn:feature_code":"PPL",
    "gn:name":"Gatore",
    "gn:population":0,
    "gn:timezone":"Africa/Kigali",
    "iso:country":"RW",
    "wof:name":"Gatore",
    "wof:placetype":"locality"
},
  "geometry": {"coordinates":[30.5897,-2.2752],"type":"Point"}
}