{
  "type": "Feature",
  "properties": {
    "gn:admin1_code":"13.0",
    "gn:admin2_code":"45",
    "gn:admin3_code":"4509.0",
    "gn:admin4_code":"450902.0",
    "gn:asciiname":"Miyove",
    "gn:country_code":"RW",
    "gn:dem":2202,
    "gn:feature_class":"P",
    "gn:feature_code":"PPL",
    "gn:name":"Miyove",
    "gn:population":0,
    "gn:timezone":"Africa/Kigali",
    "iso:country":"RW",
    "name:und_x_variant":[
        "Myove",
        "Miyove"
    ],
    "wof:name":"Miyove",
    "wof:placetype":"locality"
},
  "geometry": {"coordinates":[29.97563,-1.6096],"type":"Point"}
}