{
  "type": "Feature",
  "properties": {
    "gn:admin1_code":"15",
    "gn:admin2_code":"26.0",
    "gn:admin3_code":"2605.0",
    "gn:admin4_code":"260503.0",
    "gn:asciiname":"Muyange",
    "gn:country_code":"RW",
    "gn:dem":1698,
    "gn:feature_class":"P",
    "gn:feature_code":"PPLL",
    "gn:name":"Muyange",
    "gn:population":0,
    "gn:timezone":"Africa/Kigali",
    "iso:country":"RW",
    "name:run_x_preferred":[
        "Muyange"
    ],
    "wof:name":"Muyange",
    "wof:placetype":"locality"
},
  "geometry": {"coordinates":[29.6462,-2.1977],"type":"Point"}
}