{
  "type": "Feature",
  "properties": {
    "gn:admin1_code":"14.0",
    "gn:admin2_code":"36",
    "gn:admin3_code":"3605.0",
    "gn:admin4_code":"360504.0",
    "gn:asciiname":"Isha",
    "gn:country_code":"RW",
    "gn:dem":1680,
    "gn:feature_class":"P",
    "gn:feature_code":"PPL",
    "gn:name":"Isha",
    "gn:population":0,
    "gn:timezone":"Africa/Kigali",
    "iso:country":"RW",
    "name:ceb_x_preferred":[
        "Isha"
    ],
    "name:swe_x_preferred":[
        "Isha"
    ],
    "name:uzb_x_preferred":[
        "Xufton namozi"
    ],
    "wof:name":"Isha",
    "wof:placetype":"locality"
},
  "geometry": {"coordinates":[28.9428,-2.4464],"type":"Point"}
}