{
  "type": "Feature",
  "properties": {
    "gn:admin1_code":"13",
    "gn:admin2_code":"42.0",
    "gn:admin3_code":"4215.0",
    "gn:admin4_code":"421505.0",
    "gn:asciiname":"Muzo",
    "gn:country_code":"RW",
    "gn:dem":2093,
    "gn:feature_class":"P",
    "gn:feature_code":"PPLL",
    "gn:name":"Muzo",
    "gn:population":0,
    "gn:timezone":"Africa/Kigali",
    "iso:country":"RW",
    "name:ceb_x_preferred":[
        "Muzo"
    ],
    "name:deu_x_preferred":[
        "Muzo"
    ],
    "name:fra_x_preferred":[
        "Muzo"
    ],
    "name:ita_x_preferred":[
        "Muzo"
    ],
    "name:kat_x_preferred":[
        "\u10db\u10e3\u10e1\u10dd"
    ],
    "name:msa_x_preferred":[
        "Muzo"
    ],
    "name:nld_x_preferred":[
        "Muzo"
    ],
    "name:por_x_preferred":[
        "Muzo"
    ],
    "name:rus_x_preferred":[
        "\u041c\u0443\u0441\u043e"
    ],
    "name:spa_x_preferred":[
        "Muzo"
    ],
    "name:swe_x_preferred":[
        "Muzo"
    ],
    "name:tgl_x_preferred":[
        "Muzo"
    ],
    "name:ukr_x_preferred":[
        "\u041c\u0443\u0441\u043e"
    ],
    "name:vie_x_preferred":[
        "Muzo"
    ],
    "name:war_x_preferred":[
        "Muzo"
    ],
    "name:zho_x_preferred":[
        "\u7a46\u7d22"
    ],
    "wof:name":"Muzo",
    "wof:placetype":"locality"
},
  "geometry": {"coordinates":[29.7056,-1.6976],"type":"Point"}
}