{
  "type": "Feature",
  "properties": {
    "gn:admin1_code":"15.0",
    "gn:admin2_code":"24",
    "gn:admin3_code":"2414.0",
    "gn:admin4_code":"241403.0",
    "gn:asciiname":"Igitwa",
    "gn:country_code":"RW",
    "gn:dem":1765,
    "gn:feature_class":"P",
    "gn:feature_code":"PPLL",
    "gn:name":"Igitwa",
    "gn:population":0,
    "gn:timezone":"Africa/Kigali",
    "iso:country":"RW",
    "wof:name":"Igitwa",
    "wof:placetype":"locality"
},
  "geometry": {"coordinates":[29.7389,-2.6331],"type":"Point"}
}