{
  "type": "Feature",
  "properties": {
    "gn:admin1_code":"14.0",
    "gn:admin2_code":"37",
    "gn:admin3_code":"3703.0",
    "gn:admin4_code":"370304.0",
    "gn:asciiname":"Ntsinduka",
    "gn:country_code":"RW",
    "gn:dem":2216,
    "gn:feature_class":"P",
    "gn:feature_code":"PPLL",
    "gn:name":"Ntsinduka",
    "gn:population":0,
    "gn:timezone":"Africa/Kigali",
    "iso:country":"RW",
    "wof:name":"Ntsinduka",
    "wof:placetype":"locality"
},
  "geometry": {"coordinates":[29.2421,-2.4064],"type":"Point"}
}