{
  "type": "Feature",
  "properties": {
    "gn:admin1_code":"14",
    "gn:admin2_code":"32.0",
    "gn:admin3_code":"3211.0",
    "gn:admin4_code":"321101.0",
    "gn:asciiname":"Gatare",
    "gn:country_code":"RW",
    "gn:dem":1971,
    "gn:feature_class":"P",
    "gn:feature_code":"PPL",
    "gn:name":"Gatare",
    "gn:population":0,
    "gn:timezone":"Africa/Kigali",
    "iso:country":"RW",
    "wof:name":"Gatare",
    "wof:placetype":"locality"
},
  "geometry": {"coordinates":[29.3736,-1.7443],"type":"Point"}
}