{
  "type": "Feature",
  "properties": {
    "gn:admin1_code":"14.0",
    "gn:admin2_code":"37",
    "gn:admin3_code":"3715.0",
    "gn:admin4_code":"371502.0",
    "gn:asciiname":"Gasumo",
    "gn:country_code":"RW",
    "gn:dem":1601,
    "gn:feature_class":"P",
    "gn:feature_code":"PPLL",
    "gn:name":"Gasumo",
    "gn:population":0,
    "gn:timezone":"Africa/Kigali",
    "iso:country":"RW",
    "wof:name":"Gasumo",
    "wof:placetype":"locality"
},
  "geometry": {"coordinates":[29.0321,-2.4246],"type":"Point"}
}