{
  "type": "Feature",
  "properties": {
    "gn:admin1_code":"11",
    "gn:admin2_code":"51.0",
    "gn:admin3_code":"5102.0",
    "gn:admin4_code":"510201.0",
    "gn:asciiname":"Gihumuza",
    "gn:country_code":"RW",
    "gn:dem":1691,
    "gn:feature_class":"P",
    "gn:feature_code":"PPLL",
    "gn:name":"Gihumuza",
    "gn:population":0,
    "gn:timezone":"Africa/Kigali",
    "iso:country":"RW",
    "wof:name":"Gihumuza",
    "wof:placetype":"locality"
},
  "geometry": {"coordinates":[30.3106,-1.9541],"type":"Point"}
}