{
  "type": "Feature",
  "properties": {
    "gn:admin1_code":"14.0",
    "gn:admin2_code":"36",
    "gn:admin3_code":"3605.0",
    "gn:admin4_code":"360506.0",
    "gn:asciiname":"Kirambi",
    "gn:country_code":"RW",
    "gn:dem":1564,
    "gn:feature_class":"P",
    "gn:feature_code":"PPLL",
    "gn:name":"Kirambi",
    "gn:population":0,
    "gn:timezone":"Africa/Kigali",
    "iso:country":"RW",
    "wof:name":"Kirambi",
    "wof:placetype":"locality"
},
  "geometry": {"coordinates":[28.9534,-2.4366],"type":"Point"}
}