{
  "type": "Feature",
  "properties": {
    "gn:admin1_code":"14",
    "gn:admin2_code":"33.0",
    "gn:admin3_code":"3310.0",
    "gn:admin4_code":"331003.0",
    "gn:asciiname":"Rugomero",
    "gn:country_code":"RW",
    "gn:dem":1690,
    "gn:feature_class":"P",
    "gn:feature_code":"PPLL",
    "gn:name":"Rugomero",
    "gn:population":0,
    "gn:timezone":"Africa/Kigali",
    "iso:country":"RW",
    "wof:name":"Rugomero",
    "wof:placetype":"locality"
},
  "geometry": {"coordinates":[29.3099,-1.7279],"type":"Point"}
}