{
  "type": "Feature",
  "properties": {
    "gn:admin1_code":"15",
    "gn:admin2_code":"26.0",
    "gn:admin3_code":"2601.0",
    "gn:admin4_code":"260103.0",
    "gn:asciiname":"Rwingwe",
    "gn:country_code":"RW",
    "gn:dem":1652,
    "gn:feature_class":"P",
    "gn:feature_code":"PPLL",
    "gn:name":"Rwingwe",
    "gn:population":0,
    "gn:timezone":"Africa/Kigali",
    "iso:country":"RW",
    "wof:name":"Rwingwe",
    "wof:placetype":"locality"
},
  "geometry": {"coordinates":[29.6958,-2.2157],"type":"Point"}
}