{
  "type": "Feature",
  "properties": {
    "gn:admin1_code":"14.0",
    "gn:admin2_code":"37",
    "gn:admin3_code":"3707.0",
    "gn:admin4_code":"370701.0",
    "gn:asciiname":"Karambo",
    "gn:country_code":"RW",
    "gn:dem":1801,
    "gn:feature_class":"P",
    "gn:feature_code":"PPLL",
    "gn:name":"Karambo",
    "gn:population":0,
    "gn:timezone":"Africa/Kigali",
    "iso:country":"RW",
    "wof:name":"Karambo",
    "wof:placetype":"locality"
},
  "geometry": {"coordinates":[29.241,-2.3227],"type":"Point"}
}