{
  "type": "Feature",
  "properties": {
    "gn:admin1_code":"13.0",
    "gn:admin2_code":"43",
    "gn:admin3_code":"4315.0",
    "gn:admin4_code":"431504.0",
    "gn:asciiname":"Shingiro",
    "gn:country_code":"RW",
    "gn:dem":2483,
    "gn:feature_class":"P",
    "gn:feature_code":"PPLL",
    "gn:name":"Shingiro",
    "gn:population":0,
    "gn:timezone":"Africa/Kigali",
    "iso:country":"RW",
    "wof:name":"Shingiro",
    "wof:placetype":"locality"
},
  "geometry": {"coordinates":[29.5322,-1.4854],"type":"Point"}
}