{
  "type": "Feature",
  "properties": {
    "gn:admin1_code":"15.0",
    "gn:admin2_code":"25",
    "gn:admin3_code":"2517.0",
    "gn:admin4_code":"251702.0",
    "gn:asciiname":"Gahira",
    "gn:country_code":"RW",
    "gn:dem":2054,
    "gn:feature_class":"P",
    "gn:feature_code":"PPLL",
    "gn:name":"Gahira",
    "gn:population":0,
    "gn:timezone":"Africa/Kigali",
    "iso:country":"RW",
    "wof:name":"Gahira",
    "wof:placetype":"locality"
},
  "geometry": {"coordinates":[29.4732,-2.4674],"type":"Point"}
}