{
  "type": "Feature",
  "properties": {
    "gn:admin1_code":"15",
    "gn:admin2_code":"28.0",
    "gn:admin3_code":"2810.0",
    "gn:admin4_code":"281003.0",
    "gn:asciiname":"Masaka",
    "gn:country_code":"RW",
    "gn:dem":1447,
    "gn:feature_class":"P",
    "gn:feature_code":"PPLL",
    "gn:name":"Masaka",
    "gn:population":0,
    "gn:timezone":"Africa/Kigali",
    "iso:country":"RW",
    "name:ceb_x_preferred":[
        "Masaka"
    ],
    "name:dan_x_preferred":[
        "Masaka"
    ],
    "name:deu_x_preferred":[
        "Masaka"
    ],
    "name:fas_x_preferred":[
        "\u0645\u0627\u0632\u0627\u06a9\u0627"
    ],
    "name:fra_x_preferred":[
        "Masaka"
    ],
    "name:heb_x_preferred":[
        "\u05de\u05e1\u05e7\u05d4"
    ],
    "name:hrv_x_preferred":[
        "Masaka"
    ],
    "name:hun_x_preferred":[
        "Masaka"
    ],
    "name:ita_x_preferred":[
        "Masaka"
    ],
    "name:jpn_x_preferred":[
        "\u30de\u30b5\u30ab"
    ],
    "name:lit_x_preferred":[
        "Masaka"
    ],
    "name:lug_x_preferred":[
        "Masaka"
    ],
    "name:nld_x_preferred":[
        "Masaka"
    ],
    "name:pol_x_preferred":[
        "Masaka"
    ],
    "name:ron_x_preferred":[
        "Masaka"
    ],
    "name:rus_x_preferred":[
        "\u041c\u0430\u0441\u0430\u043a\u0430"
    ],
    "name:spa_x_preferred":[
        "Masaka"
    ],
    "name:swa_x_preferred":[
        "Masaka"
    ],
    "name:swe_x_preferred":[
        "Masaka"
    ],
    "wof:name":"Masaka",
    "wof:placetype":"locality"
},
  "geometry": {"coordinates":[29.9943,-2.0064],"type":"Point"}
}