{
  "type": "Feature",
  "properties": {
    "gn:admin1_code":"11.0",
    "gn:admin2_code":"53",
    "gn:admin3_code":"5308.0",
    "gn:admin4_code":"530803.0",
    "gn:asciiname":"Mamfu",
    "gn:country_code":"RW",
    "gn:dem":1706,
    "gn:feature_class":"P",
    "gn:feature_code":"PPLL",
    "gn:name":"Mamfu",
    "gn:population":0,
    "gn:timezone":"Africa/Kigali",
    "iso:country":"RW",
    "name:und_x_variant":[
        "Colline Mamfu",
        "Mamfu"
    ],
    "wof:name":"Mamfu",
    "wof:placetype":"locality"
},
  "geometry": {"coordinates":[30.3188,-1.7314],"type":"Point"}
}