{
  "type": "Feature",
  "properties": {
    "gn:admin1_code":"11",
    "gn:admin2_code":"57.0",
    "gn:admin3_code":"5715.0",
    "gn:admin4_code":"571505.0",
    "gn:asciiname":"Kamweru",
    "gn:country_code":"RW",
    "gn:dem":1515,
    "gn:feature_class":"P",
    "gn:feature_code":"PPLL",
    "gn:name":"Kamweru",
    "gn:population":0,
    "gn:timezone":"Africa/Kigali",
    "iso:country":"RW",
    "wof:name":"Kamweru",
    "wof:placetype":"locality"
},
  "geometry": {"coordinates":[30.0024,-2.2784],"type":"Point"}
}