{
  "type": "Feature",
  "properties": {
    "gn:admin1_code":"13",
    "gn:admin2_code":"45.0",
    "gn:admin3_code":"4508.0",
    "gn:admin4_code":"450801.0",
    "gn:asciiname":"Murehe",
    "gn:country_code":"RW",
    "gn:dem":1858,
    "gn:feature_class":"P",
    "gn:feature_code":"PPLL",
    "gn:name":"Murehe",
    "gn:population":0,
    "gn:timezone":"Africa/Kigali",
    "iso:country":"RW",
    "wof:name":"Murehe",
    "wof:placetype":"locality"
},
  "geometry": {"coordinates":[30.0295,-1.5103],"type":"Point"}
}