{
  "type": "Feature",
  "properties": {
    "gn:admin1_code":"11.0",
    "gn:admin2_code":"52",
    "gn:admin3_code":"5210.0",
    "gn:admin4_code":"521009.0",
    "gn:asciiname":"Ruyaraka",
    "gn:country_code":"RW",
    "gn:dem":1454,
    "gn:feature_class":"P",
    "gn:feature_code":"PPLL",
    "gn:name":"Ruyaraka",
    "gn:population":0,
    "gn:timezone":"Africa/Kigali",
    "iso:country":"RW",
    "name:und_x_variant":[
        "Colline Ruyaraka",
        "Ruyaraka"
    ],
    "wof:name":"Ruyaraka",
    "wof:placetype":"locality"
},
  "geometry": {"coordinates":[30.38333,-1.35],"type":"Point"}
}