{
  "type": "Feature",
  "properties": {
    "gn:admin1_code":"13",
    "gn:admin2_code":"45.0",
    "gn:admin3_code":"4512.0",
    "gn:admin4_code":"451203.0",
    "gn:asciiname":"Akimisugi",
    "gn:country_code":"RW",
    "gn:dem":1869,
    "gn:feature_class":"P",
    "gn:feature_code":"PPLL",
    "gn:name":"Akimisugi",
    "gn:population":0,
    "gn:timezone":"Africa/Kigali",
    "iso:country":"RW",
    "wof:name":"Akimisugi",
    "wof:placetype":"locality"
},
  "geometry": {"coordinates":[30.1096,-1.699],"type":"Point"}
}