{
  "type": "Feature",
  "properties": {
    "gn:admin1_code":"13",
    "gn:admin2_code":"41.0",
    "gn:admin3_code":"4102.0",
    "gn:admin4_code":"410202.0",
    "gn:asciiname":"Karengere",
    "gn:country_code":"RW",
    "gn:dem":1737,
    "gn:feature_class":"P",
    "gn:feature_code":"PPLL",
    "gn:name":"Karengere",
    "gn:population":0,
    "gn:timezone":"Africa/Kigali",
    "iso:country":"RW",
    "wof:name":"Karengere",
    "wof:placetype":"locality"
},
  "geometry": {"coordinates":[30.0445,-1.7295],"type":"Point"}
}