{
  "type": "Feature",
  "properties": {
    "gn:admin1_code":"14",
    "gn:admin2_code":"33.0",
    "gn:admin3_code":"3308.0",
    "gn:admin4_code":"330804.0",
    "gn:asciiname":"Gashunguru",
    "gn:country_code":"RW",
    "gn:dem":2073,
    "gn:feature_class":"P",
    "gn:feature_code":"PPL",
    "gn:name":"Gashunguru",
    "gn:population":0,
    "gn:timezone":"Africa/Kigali",
    "iso:country":"RW",
    "wof:name":"Gashunguru",
    "wof:placetype":"locality"
},
  "geometry": {"coordinates":[29.356,-1.6497],"type":"Point"}
}