{
  "type": "Feature",
  "properties": {
    "gn:admin1_code":"11",
    "gn:admin2_code":"57.0",
    "gn:admin3_code":"5715.0",
    "gn:admin4_code":"571502.0",
    "gn:asciiname":"Rubwirwa",
    "gn:country_code":"RW",
    "gn:dem":1440,
    "gn:feature_class":"P",
    "gn:feature_code":"PPLL",
    "gn:name":"Rubwirwa",
    "gn:population":0,
    "gn:timezone":"Africa/Kigali",
    "iso:country":"RW",
    "wof:name":"Rubwirwa",
    "wof:placetype":"locality"
},
  "geometry": {"coordinates":[30.0042,-2.2341],"type":"Point"}
}