{
  "type": "Feature",
  "properties": {
    "gn:admin1_code":"14.0",
    "gn:admin2_code":"37",
    "gn:admin3_code":"3708.0",
    "gn:admin4_code":"370801.0",
    "gn:asciiname":"Kanyinya",
    "gn:country_code":"RW",
    "gn:dem":1582,
    "gn:feature_class":"P",
    "gn:feature_code":"PPLL",
    "gn:name":"Kanyinya",
    "gn:population":0,
    "gn:timezone":"Africa/Kigali",
    "iso:country":"RW",
    "name:und_x_variant":[
        "Colline Kanyinya",
        "Kanyinya"
    ],
    "wof:name":"Kanyinya",
    "wof:placetype":"locality"
},
  "geometry": {"coordinates":[29.0608,-2.5262],"type":"Point"}
}