{
  "type": "Feature",
  "properties": {
    "gn:admin1_code":"15.0",
    "gn:admin2_code":"23",
    "gn:admin3_code":"2303.0",
    "gn:admin4_code":"230303.0",
    "gn:asciiname":"Mbasa",
    "gn:country_code":"RW",
    "gn:dem":1846,
    "gn:feature_class":"P",
    "gn:feature_code":"PPL",
    "gn:name":"Mbasa",
    "gn:population":0,
    "gn:timezone":"Africa/Kigali",
    "iso:country":"RW",
    "wof:name":"Mbasa",
    "wof:placetype":"locality"
},
  "geometry": {"coordinates":[29.592,-2.6129],"type":"Point"}
}