{
  "type": "Feature",
  "properties": {
    "gn:admin1_code":"11.0",
    "gn:admin2_code":"52",
    "gn:admin3_code":"5205.0",
    "gn:admin4_code":"520505.0",
    "gn:asciiname":"Kabare",
    "gn:country_code":"RW",
    "gn:dem":1939,
    "gn:feature_class":"P",
    "gn:feature_code":"PPLL",
    "gn:name":"Kabare",
    "gn:population":0,
    "gn:timezone":"Africa/Kigali",
    "iso:country":"RW",
    "name:und_x_variant":[
        "Colline Kabare",
        "Kabare"
    ],
    "wof:name":"Kabare",
    "wof:placetype":"locality"
},
  "geometry": {"coordinates":[30.1371,-1.455],"type":"Point"}
}