{
  "type": "Feature",
  "properties": {
    "gn:admin1_code":"15",
    "gn:admin2_code":"28.0",
    "gn:admin3_code":"2804.0",
    "gn:admin4_code":"280401.0",
    "gn:asciiname":"Manyana",
    "gn:country_code":"RW",
    "gn:dem":1738,
    "gn:feature_class":"P",
    "gn:feature_code":"PPLL",
    "gn:name":"Manyana",
    "gn:population":0,
    "gn:timezone":"Africa/Kigali",
    "iso:country":"RW",
    "name:fas_x_preferred":[
        "\u0645\u0627\u0646\u06cc\u0627\u0646\u0627"
    ],
    "wof:name":"Manyana",
    "wof:placetype":"locality"
},
  "geometry": {"coordinates":[29.81,-1.9877],"type":"Point"}
}