{
  "type": "Feature",
  "properties": {
    "gn:admin1_code":"11",
    "gn:admin2_code":"51.0",
    "gn:admin3_code":"5109.0",
    "gn:admin4_code":"510902.0",
    "gn:asciiname":"Budahanda",
    "gn:country_code":"RW",
    "gn:dem":1483,
    "gn:feature_class":"P",
    "gn:feature_code":"PPLL",
    "gn:name":"Budahanda",
    "gn:population":0,
    "gn:timezone":"Africa/Kigali",
    "iso:country":"RW",
    "wof:name":"Budahanda",
    "wof:placetype":"locality"
},
  "geometry": {"coordinates":[30.3252,-1.8655],"type":"Point"}
}