{
  "type": "Feature",
  "properties": {
    "gn:admin1_code":"15.0",
    "gn:admin2_code":"25",
    "gn:admin3_code":"2511.0",
    "gn:admin4_code":"251105.0",
    "gn:asciiname":"Turyango",
    "gn:country_code":"RW",
    "gn:dem":1728,
    "gn:feature_class":"P",
    "gn:feature_code":"PPLL",
    "gn:name":"Turyango",
    "gn:population":0,
    "gn:timezone":"Africa/Kigali",
    "iso:country":"RW",
    "wof:name":"Turyango",
    "wof:placetype":"locality"
},
  "geometry": {"coordinates":[29.513,-2.2532],"type":"Point"}
}