{
  "type": "Feature",
  "properties": {
    "gn:admin1_code":"13",
    "gn:admin2_code":"45.0",
    "gn:admin3_code":"4506.0",
    "gn:admin4_code":"450601.0",
    "gn:asciiname":"Murehe",
    "gn:country_code":"RW",
    "gn:dem":1922,
    "gn:feature_class":"P",
    "gn:feature_code":"PPLL",
    "gn:name":"Murehe",
    "gn:population":0,
    "gn:timezone":"Africa/Kigali",
    "iso:country":"RW",
    "name:run_x_preferred":[
        "Murehe"
    ],
    "wof:name":"Murehe",
    "wof:placetype":"locality"
},
  "geometry": {"coordinates":[30.0646,-1.5997],"type":"Point"}
}