{
  "type": "Feature",
  "properties": {
    "gn:admin1_code":"15.0",
    "gn:admin2_code":"25",
    "gn:admin3_code":"2513.0",
    "gn:admin4_code":"251303.0",
    "gn:asciiname":"Rusekera",
    "gn:country_code":"RW",
    "gn:dem":1998,
    "gn:feature_class":"P",
    "gn:feature_code":"PPLL",
    "gn:name":"Rusekera",
    "gn:population":0,
    "gn:timezone":"Africa/Kigali",
    "iso:country":"RW",
    "wof:name":"Rusekera",
    "wof:placetype":"locality"
},
  "geometry": {"coordinates":[29.4394,-2.3781],"type":"Point"}
}