{
  "type": "Feature",
  "properties": {
    "gn:admin1_code":"11.0",
    "gn:admin2_code":"55",
    "gn:admin3_code":"5505.0",
    "gn:admin4_code":"550502.0",
    "gn:asciiname":"Kirehe",
    "gn:country_code":"RW",
    "gn:dem":1570,
    "gn:feature_class":"P",
    "gn:feature_code":"PPLL",
    "gn:name":"Kirehe",
    "gn:population":0,
    "gn:timezone":"Africa/Kigali",
    "iso:country":"RW",
    "wof:name":"Kirehe",
    "wof:placetype":"locality"
},
  "geometry": {"coordinates":[30.65696,-2.26525],"type":"Point"}
}