{
  "type": "Feature",
  "properties": {
    "gn:admin1_code":"15",
    "gn:admin2_code":"25.0",
    "gn:admin3_code":"2512.0",
    "gn:admin4_code":"251201.0",
    "gn:asciiname":"Nyabivumu",
    "gn:country_code":"RW",
    "gn:dem":1726,
    "gn:feature_class":"P",
    "gn:feature_code":"PPL",
    "gn:name":"Nyabivumu",
    "gn:population":0,
    "gn:timezone":"Africa/Kigali",
    "iso:country":"RW",
    "wof:name":"Nyabivumu",
    "wof:placetype":"locality"
},
  "geometry": {"coordinates":[29.5564,-2.2449],"type":"Point"}
}