{
  "type": "Feature",
  "properties": {
    "gn:admin1_code":"14.0",
    "gn:admin2_code":"36",
    "gn:admin3_code":"3616.0",
    "gn:admin4_code":"361603.0",
    "gn:asciiname":"Kabacuzi",
    "gn:country_code":"RW",
    "gn:dem":1637,
    "gn:feature_class":"P",
    "gn:feature_code":"PPLL",
    "gn:name":"Kabacuzi",
    "gn:population":0,
    "gn:timezone":"Africa/Kigali",
    "iso:country":"RW",
    "wof:name":"Kabacuzi",
    "wof:placetype":"locality"
},
  "geometry": {"coordinates":[28.9042,-2.5674],"type":"Point"}
}