{
  "type": "Feature",
  "properties": {
    "gn:admin1_code":"14",
    "gn:admin2_code":"31.0",
    "gn:admin3_code":"3106.0",
    "gn:admin4_code":"310604.0",
    "gn:asciiname":"Nyarunyinya",
    "gn:country_code":"RW",
    "gn:dem":1649,
    "gn:feature_class":"P",
    "gn:feature_code":"PPLL",
    "gn:name":"Nyarunyinya",
    "gn:population":0,
    "gn:timezone":"Africa/Kigali",
    "iso:country":"RW",
    "wof:name":"Nyarunyinya",
    "wof:placetype":"locality"
},
  "geometry": {"coordinates":[29.5669,-2.198],"type":"Point"}
}