{
  "type": "Feature",
  "properties": {
    "gn:admin1_code":"15.0",
    "gn:admin2_code":"23",
    "gn:admin3_code":"2311.0",
    "gn:admin4_code":"231101.0",
    "gn:asciiname":"Maraba",
    "gn:country_code":"RW",
    "gn:dem":1823,
    "gn:feature_class":"P",
    "gn:feature_code":"PPL",
    "gn:name":"Maraba",
    "gn:population":0,
    "gn:timezone":"Africa/Kigali",
    "iso:country":"RW",
    "name:ceb_x_preferred":[
        "Maraba"
    ],
    "name:fra_x_preferred":[
        "Maraba"
    ],
    "name:ita_x_preferred":[
        "Maraba"
    ],
    "name:swe_x_preferred":[
        "Maraba"
    ],
    "wof:name":"Maraba",
    "wof:placetype":"locality"
},
  "geometry": {"coordinates":[29.6393,-2.7328],"type":"Point"}
}