{
  "type": "Feature",
  "properties": {
    "gn:admin1_code":"14",
    "gn:admin2_code":"37.0",
    "gn:admin3_code":"3704.0",
    "gn:admin4_code":"370402.0",
    "gn:asciiname":"Gasagara",
    "gn:country_code":"RW",
    "gn:dem":1512,
    "gn:feature_class":"P",
    "gn:feature_code":"PPL",
    "gn:name":"Gasagara",
    "gn:population":0,
    "gn:timezone":"Africa/Kigali",
    "iso:country":"RW",
    "wof:name":"Gasagara",
    "wof:placetype":"locality"
},
  "geometry": {"coordinates":[29.2327,-2.175],"type":"Point"}
}