{
  "type": "Feature",
  "properties": {
    "gn:admin1_code":"15",
    "gn:admin2_code":"28.0",
    "gn:admin3_code":"2805.0",
    "gn:admin4_code":"280501.0",
    "gn:asciiname":"Tenda",
    "gn:country_code":"RW",
    "gn:dem":1473,
    "gn:feature_class":"P",
    "gn:feature_code":"PPLL",
    "gn:name":"Tenda",
    "gn:population":0,
    "gn:timezone":"Africa/Kigali",
    "iso:country":"RW",
    "name:ceb_x_preferred":[
        "Tenda"
    ],
    "name:deu_x_preferred":[
        "Tenda"
    ],
    "name:fra_x_preferred":[
        "Tenda"
    ],
    "name:ita_x_preferred":[
        "Tenda"
    ],
    "name:swe_x_preferred":[
        "Tenda"
    ],
    "name:zho_x_preferred":[
        "Tenda"
    ],
    "wof:name":"Tenda",
    "wof:placetype":"locality"
},
  "geometry": {"coordinates":[29.9589,-2.1533],"type":"Point"}
}