{
  "type": "Feature",
  "properties": {
    "gn:admin1_code":"15.0",
    "gn:admin2_code":"26",
    "gn:admin3_code":"2601.0",
    "gn:admin4_code":"260101.0",
    "gn:asciiname":"Bikombe",
    "gn:country_code":"RW",
    "gn:dem":1951,
    "gn:feature_class":"P",
    "gn:feature_code":"PPLL",
    "gn:name":"Bikombe",
    "gn:population":0,
    "gn:timezone":"Africa/Kigali",
    "iso:country":"RW",
    "wof:name":"Bikombe",
    "wof:placetype":"locality"
},
  "geometry": {"coordinates":[29.664,-2.2554],"type":"Point"}
}