{
  "type": "Feature",
  "properties": {
    "gn:admin1_code":"15",
    "gn:admin2_code":"27.0",
    "gn:admin3_code":"2712.0",
    "gn:admin4_code":"271202.0",
    "gn:asciiname":"Rucunshu",
    "gn:country_code":"RW",
    "gn:dem":1799,
    "gn:feature_class":"P",
    "gn:feature_code":"PPLL",
    "gn:name":"Rucunshu",
    "gn:population":0,
    "gn:timezone":"Africa/Kigali",
    "iso:country":"RW",
    "wof:name":"Rucunshu",
    "wof:placetype":"locality"
},
  "geometry": {"coordinates":[29.7959,-2.1092],"type":"Point"}
}