{
  "type": "Feature",
  "properties": {
    "gn:admin1_code":"13",
    "gn:admin2_code":"44.0",
    "gn:admin3_code":"4407.0",
    "gn:admin4_code":"440702.0",
    "gn:asciiname":"Ruhombo",
    "gn:country_code":"RW",
    "gn:dem":1764,
    "gn:feature_class":"P",
    "gn:feature_code":"PPLL",
    "gn:name":"Ruhombo",
    "gn:population":0,
    "gn:timezone":"Africa/Kigali",
    "iso:country":"RW",
    "wof:name":"Ruhombo",
    "wof:placetype":"locality"
},
  "geometry": {"coordinates":[29.7696,-1.5148],"type":"Point"}
}