{
  "type": "Feature",
  "properties": {
    "gn:admin1_code":"14.0",
    "gn:admin2_code":"36",
    "gn:admin3_code":"3606.0",
    "gn:admin4_code":"360602.0",
    "gn:asciiname":"Kamembe",
    "gn:country_code":"RW",
    "gn:dem":1642,
    "gn:feature_class":"P",
    "gn:feature_code":"PPL",
    "gn:name":"Kamembe",
    "gn:population":0,
    "gn:timezone":"Africa/Kigali",
    "iso:country":"RW",
    "wof:name":"Kamembe",
    "wof:placetype":"locality"
},
  "geometry": {"coordinates":[28.9229,-2.4267],"type":"Point"}
}