{
  "type": "Feature",
  "properties": {
    "gn:admin1_code":"15.0",
    "gn:admin2_code":"24",
    "gn:admin3_code":"2414.0",
    "gn:admin4_code":"241404.0",
    "gn:asciiname":"Mpare",
    "gn:country_code":"RW",
    "gn:dem":1720,
    "gn:feature_class":"P",
    "gn:feature_code":"PPL",
    "gn:name":"Mpare",
    "gn:population":0,
    "gn:timezone":"Africa/Kigali",
    "iso:country":"RW",
    "wof:name":"Mpare",
    "wof:placetype":"locality"
},
  "geometry": {"coordinates":[29.7223,-2.6117],"type":"Point"}
}