{
  "type": "Feature",
  "properties": {
    "gn:admin1_code":"14.0",
    "gn:admin2_code":"36",
    "gn:admin3_code":"3612.0",
    "gn:admin4_code":"361201.0",
    "gn:asciiname":"Murambi",
    "gn:country_code":"RW",
    "gn:dem":1622,
    "gn:feature_class":"P",
    "gn:feature_code":"PPLL",
    "gn:name":"Murambi",
    "gn:population":0,
    "gn:timezone":"Africa/Kigali",
    "iso:country":"RW",
    "wof:name":"Murambi",
    "wof:placetype":"locality"
},
  "geometry": {"coordinates":[28.9412,-2.4124],"type":"Point"}
}