{
  "type": "Feature",
  "properties": {
    "gn:admin1_code":"15",
    "gn:admin2_code":"28.0",
    "gn:admin3_code":"2806.0",
    "gn:admin4_code":"280602.0",
    "gn:asciiname":"Rugarama",
    "gn:country_code":"RW",
    "gn:dem":1611,
    "gn:feature_class":"P",
    "gn:feature_code":"PPLL",
    "gn:name":"Rugarama",
    "gn:population":0,
    "gn:timezone":"Africa/Kigali",
    "iso:country":"RW",
    "wof:name":"Rugarama",
    "wof:placetype":"locality"
},
  "geometry": {"coordinates":[29.861,-2.0597],"type":"Point"}
}