{
  "type": "Feature",
  "properties": {
    "gn:admin1_code":"15",
    "gn:admin2_code":"28.0",
    "gn:admin3_code":"2812.0",
    "gn:admin4_code":"281205.0",
    "gn:asciiname":"Nyabitare",
    "gn:country_code":"RW",
    "gn:dem":1512,
    "gn:feature_class":"P",
    "gn:feature_code":"PPLL",
    "gn:name":"Nyabitare",
    "gn:population":0,
    "gn:timezone":"Africa/Kigali",
    "iso:country":"RW",
    "wof:name":"Nyabitare",
    "wof:placetype":"locality"
},
  "geometry": {"coordinates":[29.9744,-1.947],"type":"Point"}
}