{
  "type": "Feature",
  "properties": {
    "gn:admin1_code":"14.0",
    "gn:admin2_code":"37",
    "gn:admin3_code":"3712.0",
    "gn:admin4_code":"371205.0",
    "gn:asciiname":"Ruhamagaliro",
    "gn:country_code":"RW",
    "gn:dem":1648,
    "gn:feature_class":"P",
    "gn:feature_code":"PPLL",
    "gn:name":"Ruhamagaliro",
    "gn:population":0,
    "gn:timezone":"Africa/Kigali",
    "iso:country":"RW",
    "wof:name":"Ruhamagaliro",
    "wof:placetype":"locality"
},
  "geometry": {"coordinates":[29.0416,-2.305],"type":"Point"}
}