{
  "type": "Feature",
  "properties": {
    "gn:admin1_code":"13",
    "gn:admin2_code":"43.0",
    "gn:admin3_code":"4314.0",
    "gn:admin4_code":"431404.0",
    "gn:asciiname":"Rugali",
    "gn:country_code":"RW",
    "gn:dem":1820,
    "gn:feature_class":"P",
    "gn:feature_code":"PPL",
    "gn:name":"Rugali",
    "gn:population":0,
    "gn:timezone":"Africa/Kigali",
    "iso:country":"RW",
    "wof:name":"Rugali",
    "wof:placetype":"locality"
},
  "geometry": {"coordinates":[29.6604,-1.5558],"type":"Point"}
}