{
  "type": "Feature",
  "properties": {
    "gn:admin1_code":"13",
    "gn:admin2_code":"45.0",
    "gn:admin3_code":"4506.0",
    "gn:admin4_code":"450605.0",
    "gn:asciiname":"Kabare",
    "gn:country_code":"RW",
    "gn:dem":1897,
    "gn:feature_class":"P",
    "gn:feature_code":"PPLL",
    "gn:name":"Kabare",
    "gn:population":0,
    "gn:timezone":"Africa/Kigali",
    "iso:country":"RW",
    "wof:name":"Kabare",
    "wof:placetype":"locality"
},
  "geometry": {"coordinates":[30.0679,-1.6145],"type":"Point"}
}