{
  "type": "Feature",
  "properties": {
    "gn:admin1_code":"14",
    "gn:admin2_code":"34.0",
    "gn:admin3_code":"3404.0",
    "gn:admin4_code":"340403.0",
    "gn:asciiname":"Bisukiro",
    "gn:country_code":"RW",
    "gn:dem":2525,
    "gn:feature_class":"P",
    "gn:feature_code":"PPLF",
    "gn:name":"Bisukiro",
    "gn:population":0,
    "gn:timezone":"Africa/Kigali",
    "iso:country":"RW",
    "wof:name":"Bisukiro",
    "wof:placetype":"locality"
},
  "geometry": {"coordinates":[29.4186,-1.5794],"type":"Point"}
}