{
  "type": "Feature",
  "properties": {
    "gn:admin1_code":"12",
    "gn:admin2_code":"12.0",
    "gn:admin3_code":"1203.0",
    "gn:admin4_code":"120304.0",
    "gn:asciiname":"Munini",
    "gn:country_code":"RW",
    "gn:dem":1848,
    "gn:feature_class":"P",
    "gn:feature_code":"PPLL",
    "gn:name":"Munini",
    "gn:population":0,
    "gn:timezone":"Africa/Kigali",
    "iso:country":"RW",
    "wof:name":"Munini",
    "wof:placetype":"locality"
},
  "geometry": {"coordinates":[30.22300000000001,-1.8818],"type":"Point"}
}