{
  "type": "Feature",
  "properties": {
    "gn:admin1_code":"15.0",
    "gn:admin2_code":"25",
    "gn:admin3_code":"2507.0",
    "gn:admin4_code":"250702.0",
    "gn:asciiname":"Uwinyana",
    "gn:country_code":"RW",
    "gn:dem":1836,
    "gn:feature_class":"P",
    "gn:feature_code":"PPL",
    "gn:name":"Uwinyana",
    "gn:population":0,
    "gn:timezone":"Africa/Kigali",
    "iso:country":"RW",
    "wof:name":"Uwinyana",
    "wof:placetype":"locality"
},
  "geometry": {"coordinates":[29.5556,-2.4348],"type":"Point"}
}