{
  "type": "Feature",
  "properties": {
    "gn:admin1_code":"15.0",
    "gn:admin2_code":"25",
    "gn:admin3_code":"2508.0",
    "gn:admin4_code":"250804.0",
    "gn:asciiname":"Mubuga",
    "gn:country_code":"RW",
    "gn:dem":1811,
    "gn:feature_class":"P",
    "gn:feature_code":"PPLL",
    "gn:name":"Mubuga",
    "gn:population":0,
    "gn:timezone":"Africa/Kigali",
    "iso:country":"RW",
    "wof:name":"Mubuga",
    "wof:placetype":"locality"
},
  "geometry": {"coordinates":[29.5292,-2.3791],"type":"Point"}
}