{
  "type": "Feature",
  "properties": {
    "gn:admin1_code":"13.0",
    "gn:admin2_code":"42",
    "gn:admin3_code":"4216.0",
    "gn:admin4_code":"421602.0",
    "gn:asciiname":"Ruhinga I",
    "gn:country_code":"RW",
    "gn:dem":1743,
    "gn:feature_class":"P",
    "gn:feature_code":"PPL",
    "gn:name":"Ruhinga I",
    "gn:population":0,
    "gn:timezone":"Africa/Kigali",
    "iso:country":"RW",
    "name:und_x_variant":[
        "Colline Ruhinga",
        "Ruhinga I",
        "Ruhinga"
    ],
    "wof:name":"Ruhinga I",
    "wof:placetype":"locality"
},
  "geometry": {"coordinates":[29.7781,-1.6283],"type":"Point"}
}