{
  "type": "Feature",
  "properties": {
    "gn:admin1_code":"14.0",
    "gn:admin2_code":"37",
    "gn:admin3_code":"3715.0",
    "gn:admin4_code":"371503.0",
    "gn:asciiname":"Mugera",
    "gn:country_code":"RW",
    "gn:dem":1501,
    "gn:feature_class":"P",
    "gn:feature_code":"PPL",
    "gn:name":"Mugera",
    "gn:population":0,
    "gn:timezone":"Africa/Kigali",
    "iso:country":"RW",
    "wof:name":"Mugera",
    "wof:placetype":"locality"
},
  "geometry": {"coordinates":[29.0525,-2.3638],"type":"Point"}
}