{
  "type": "Feature",
  "properties": {
    "gn:admin1_code":"11",
    "gn:admin2_code":"56.0",
    "gn:admin3_code":"5610.0",
    "gn:admin4_code":"561001.0",
    "gn:asciiname":"Rurama",
    "gn:country_code":"RW",
    "gn:dem":1529,
    "gn:feature_class":"P",
    "gn:feature_code":"PPLL",
    "gn:name":"Rurama",
    "gn:population":0,
    "gn:timezone":"Africa/Kigali",
    "iso:country":"RW",
    "wof:name":"Rurama",
    "wof:placetype":"locality"
},
  "geometry": {"coordinates":[30.5873,-2.1705],"type":"Point"}
}