{
  "type": "Feature",
  "properties": {
    "gn:admin1_code":"15",
    "gn:admin2_code":"26.0",
    "gn:admin3_code":"2606.0",
    "gn:admin4_code":"260603.0",
    "gn:asciiname":"Musenyi",
    "gn:country_code":"RW",
    "gn:dem":1519,
    "gn:feature_class":"P",
    "gn:feature_code":"PPL",
    "gn:name":"Musenyi",
    "gn:population":0,
    "gn:timezone":"Africa/Kigali",
    "iso:country":"RW",
    "name:run_x_preferred":[
        "Musenyi"
    ],
    "wof:name":"Musenyi",
    "wof:placetype":"locality"
},
  "geometry": {"coordinates":[29.8786,-2.1202],"type":"Point"}
}