{
  "type": "Feature",
  "properties": {
    "gn:admin1_code":"11",
    "gn:admin2_code":"53.0",
    "gn:admin3_code":"5309.0",
    "gn:admin4_code":"530903.0",
    "gn:asciiname":"Umwiga",
    "gn:country_code":"RW",
    "gn:dem":1515,
    "gn:feature_class":"P",
    "gn:feature_code":"PPLL",
    "gn:name":"Umwiga",
    "gn:population":0,
    "gn:timezone":"Africa/Kigali",
    "iso:country":"RW",
    "name:und_x_variant":[
        "Unwiga",
        "Umwiga"
    ],
    "wof:name":"Umwiga",
    "wof:placetype":"locality"
},
  "geometry": {"coordinates":[30.3527,-1.8472],"type":"Point"}
}