{
  "type": "Feature",
  "properties": {
    "gn:admin1_code":"15.0",
    "gn:admin2_code":"25",
    "gn:admin3_code":"2513.0",
    "gn:admin4_code":"251302.0",
    "gn:asciiname":"Mujyejuru",
    "gn:country_code":"RW",
    "gn:dem":1967,
    "gn:feature_class":"P",
    "gn:feature_code":"PPLL",
    "gn:name":"Mujyejuru",
    "gn:population":0,
    "gn:timezone":"Africa/Kigali",
    "iso:country":"RW",
    "name:und_x_variant":[
        "Colline Mugejuru",
        "Mugejuri",
        "Mujyejuru"
    ],
    "wof:name":"Mujyejuru",
    "wof:placetype":"locality"
},
  "geometry": {"coordinates":[29.465,-2.3736],"type":"Point"}
}