{
  "type": "Feature",
  "properties": {
    "gn:admin1_code":"11",
    "gn:admin2_code":"55.0",
    "gn:admin3_code":"5504.0",
    "gn:admin4_code":"550403.0",
    "gn:asciiname":"Nyakibande",
    "gn:country_code":"RW",
    "gn:dem":1523,
    "gn:feature_class":"P",
    "gn:feature_code":"PPLL",
    "gn:name":"Nyakibande",
    "gn:population":0,
    "gn:timezone":"Africa/Kigali",
    "iso:country":"RW",
    "wof:name":"Nyakibande",
    "wof:placetype":"locality"
},
  "geometry": {"coordinates":[30.6831,-2.2804],"type":"Point"}
}