{
  "type": "Feature",
  "properties": {
    "gn:admin1_code":"14",
    "gn:admin2_code":"34.0",
    "gn:admin3_code":"3412.0",
    "gn:admin4_code":"341206.0",
    "gn:asciiname":"Rutoyi",
    "gn:country_code":"RW",
    "gn:dem":2116,
    "gn:feature_class":"P",
    "gn:feature_code":"PPLL",
    "gn:name":"Rutoyi",
    "gn:population":0,
    "gn:timezone":"Africa/Kigali",
    "iso:country":"RW",
    "wof:name":"Rutoyi",
    "wof:placetype":"locality"
},
  "geometry": {"coordinates":[29.5785,-1.6976],"type":"Point"}
}