{
  "type": "Feature",
  "properties": {
    "gn:admin1_code":"15.0",
    "gn:admin2_code":"24",
    "gn:admin3_code":"2413.0",
    "gn:admin4_code":"241302.0",
    "gn:asciiname":"Gasharu",
    "gn:country_code":"RW",
    "gn:dem":1612,
    "gn:feature_class":"P",
    "gn:feature_code":"PPLL",
    "gn:name":"Gasharu",
    "gn:population":0,
    "gn:timezone":"Africa/Kigali",
    "iso:country":"RW",
    "wof:name":"Gasharu",
    "wof:placetype":"locality"
},
  "geometry": {"coordinates":[29.6843,-2.4798],"type":"Point"}
}