{
  "type": "Feature",
  "properties": {
    "gn:admin1_code":"14.0",
    "gn:admin2_code":"36",
    "gn:admin3_code":"3613.0",
    "gn:admin4_code":"361302.0",
    "gn:asciiname":"Bugarura",
    "gn:country_code":"RW",
    "gn:dem":1496,
    "gn:feature_class":"P",
    "gn:feature_code":"PPL",
    "gn:name":"Bugarura",
    "gn:population":0,
    "gn:timezone":"Africa/Kigali",
    "iso:country":"RW",
    "wof:name":"Bugarura",
    "wof:placetype":"locality"
},
  "geometry": {"coordinates":[28.901,-2.4005],"type":"Point"}
}