{
  "type": "Feature",
  "properties": {
    "gn:admin1_code":"15.0",
    "gn:admin2_code":"21",
    "gn:admin3_code":"2110.0",
    "gn:admin4_code":"211005.0",
    "gn:asciiname":"Cyarwa",
    "gn:country_code":"RW",
    "gn:dem":1656,
    "gn:feature_class":"P",
    "gn:feature_code":"PPLL",
    "gn:name":"Cyarwa",
    "gn:population":0,
    "gn:timezone":"Africa/Kigali",
    "iso:country":"RW",
    "wof:name":"Cyarwa",
    "wof:placetype":"locality"
},
  "geometry": {"coordinates":[29.6621,-2.3354],"type":"Point"}
}