{
  "type": "Feature",
  "properties": {
    "gn:admin1_code":"13",
    "gn:admin2_code":"43.0",
    "gn:admin3_code":"4313.0",
    "gn:admin4_code":"431302.0",
    "gn:asciiname":"Kabara",
    "gn:country_code":"RW",
    "gn:dem":1885,
    "gn:feature_class":"P",
    "gn:feature_code":"PPL",
    "gn:name":"Kabara",
    "gn:population":0,
    "gn:timezone":"Africa/Kigali",
    "iso:country":"RW",
    "wof:name":"Kabara",
    "wof:placetype":"locality"
},
  "geometry": {"coordinates":[29.7138,-1.5457],"type":"Point"}
}