{
  "type": "Feature",
  "properties": {
    "gn:admin1_code":"11",
    "gn:admin2_code":"57.0",
    "gn:admin3_code":"5706.0",
    "gn:admin4_code":"570601.0",
    "gn:asciiname":"Kagusa",
    "gn:country_code":"RW",
    "gn:dem":1406,
    "gn:feature_class":"P",
    "gn:feature_code":"PPLL",
    "gn:name":"Kagusa",
    "gn:population":0,
    "gn:timezone":"Africa/Kigali",
    "iso:country":"RW",
    "wof:name":"Kagusa",
    "wof:placetype":"locality"
},
  "geometry": {"coordinates":[30.0308,-2.2193],"type":"Point"}
}