{
  "type": "Feature",
  "properties": {
    "gn:admin1_code":"11",
    "gn:admin2_code":"51.0",
    "gn:admin3_code":"5110.0",
    "gn:admin4_code":"511004.0",
    "gn:asciiname":"Samuramba",
    "gn:country_code":"RW",
    "gn:dem":1580,
    "gn:feature_class":"P",
    "gn:feature_code":"PPLL",
    "gn:name":"Samuramba",
    "gn:population":0,
    "gn:timezone":"Africa/Kigali",
    "iso:country":"RW",
    "wof:name":"Samuramba",
    "wof:placetype":"locality"
},
  "geometry": {"coordinates":[30.285,-1.9921],"type":"Point"}
}