{
  "type": "Feature",
  "properties": {
    "gn:admin1_code":"15.0",
    "gn:admin2_code":"24",
    "gn:admin3_code":"2403.0",
    "gn:admin4_code":"240302.0",
    "gn:asciiname":"Rushubi",
    "gn:country_code":"RW",
    "gn:dem":1682,
    "gn:feature_class":"P",
    "gn:feature_code":"PPLL",
    "gn:name":"Rushubi",
    "gn:population":0,
    "gn:timezone":"Africa/Kigali",
    "iso:country":"RW",
    "wof:name":"Rushubi",
    "wof:placetype":"locality"
},
  "geometry": {"coordinates":[29.6412,-2.6473],"type":"Point"}
}