{
  "type": "Feature",
  "properties": {
    "gn:admin1_code":"12",
    "gn:admin2_code":"11.0",
    "gn:admin3_code":"1102.0",
    "gn:admin4_code":"110201.0",
    "gn:asciiname":"Kiruhura",
    "gn:country_code":"RW",
    "gn:dem":1375,
    "gn:feature_class":"P",
    "gn:feature_code":"PPLL",
    "gn:name":"Kiruhura",
    "gn:population":0,
    "gn:timezone":"Africa/Kigali",
    "iso:country":"RW",
    "wof:name":"Kiruhura",
    "wof:placetype":"locality"
},
  "geometry": {"coordinates":[30.0341,-1.9425],"type":"Point"}
}