{
  "type": "Feature",
  "properties": {
    "gn:admin1_code":"15",
    "gn:admin2_code":"28.0",
    "gn:admin3_code":"2806.0",
    "gn:admin4_code":"280604.0",
    "gn:asciiname":"Kivumu-Nyerenga",
    "gn:country_code":"RW",
    "gn:dem":1856,
    "gn:feature_class":"P",
    "gn:feature_code":"PPLL",
    "gn:name":"Kivumu-Nyerenga",
    "gn:population":0,
    "gn:timezone":"Africa/Kigali",
    "iso:country":"RW",
    "wof:name":"Kivumu-Nyerenga",
    "wof:placetype":"locality"
},
  "geometry": {"coordinates":[29.8072,-2.0364],"type":"Point"}
}