{
  "type": "Feature",
  "properties": {
    "gn:admin1_code":"15.0",
    "gn:admin2_code":"23",
    "gn:admin3_code":"2306.0",
    "gn:admin4_code":"230603.0",
    "gn:asciiname":"Tangabo",
    "gn:country_code":"RW",
    "gn:dem":2181,
    "gn:feature_class":"P",
    "gn:feature_code":"PPL",
    "gn:name":"Tangabo",
    "gn:population":0,
    "gn:timezone":"Africa/Kigali",
    "iso:country":"RW",
    "name:und_x_variant":[
        "Colline Tangabo",
        "Tangabo"
    ],
    "wof:name":"Tangabo",
    "wof:placetype":"locality"
},
  "geometry": {"coordinates":[29.4379,-2.6743],"type":"Point"}
}