{
  "type": "Feature",
  "properties": {
    "gn:admin1_code":"14",
    "gn:admin2_code":"31.0",
    "gn:admin3_code":"3107.0",
    "gn:admin4_code":"310703.0",
    "gn:asciiname":"Rubona",
    "gn:country_code":"RW",
    "gn:dem":1742,
    "gn:feature_class":"P",
    "gn:feature_code":"PPLL",
    "gn:name":"Rubona",
    "gn:population":0,
    "gn:timezone":"Africa/Kigali",
    "iso:country":"RW",
    "wof:name":"Rubona",
    "wof:placetype":"locality"
},
  "geometry": {"coordinates":[29.5836,-2.0822],"type":"Point"}
}