{
  "type": "Feature",
  "properties": {
    "gn:admin1_code":"15.0",
    "gn:admin2_code":"23",
    "gn:admin3_code":"2305.0",
    "gn:admin4_code":"230505.0",
    "gn:asciiname":"Gasizi",
    "gn:country_code":"RW",
    "gn:dem":1893,
    "gn:feature_class":"P",
    "gn:feature_code":"PPL",
    "gn:name":"Gasizi",
    "gn:population":0,
    "gn:timezone":"Africa/Kigali",
    "iso:country":"RW",
    "wof:name":"Gasizi",
    "wof:placetype":"locality"
},
  "geometry": {"coordinates":[29.5469,-2.5807],"type":"Point"}
}