{
  "type": "Feature",
  "properties": {
    "gn:admin1_code":"15",
    "gn:admin2_code":"26.0",
    "gn:admin3_code":"2601.0",
    "gn:admin4_code":"260103.0",
    "gn:asciiname":"Kalima",
    "gn:country_code":"RW",
    "gn:dem":1691,
    "gn:feature_class":"P",
    "gn:feature_code":"PPLL",
    "gn:name":"Kalima",
    "gn:population":0,
    "gn:timezone":"Africa/Kigali",
    "iso:country":"RW",
    "name:ceb_x_preferred":[
        "Kalima"
    ],
    "name:deu_x_preferred":[
        "Kalima"
    ],
    "name:epo_x_preferred":[
        "Kalima"
    ],
    "name:fin_x_preferred":[
        "Kalima"
    ],
    "name:pol_x_preferred":[
        "Kalima"
    ],
    "name:swe_x_preferred":[
        "Kalima"
    ],
    "wof:name":"Kalima",
    "wof:placetype":"locality"
},
  "geometry": {"coordinates":[29.6987,-2.2241],"type":"Point"}
}