{
  "type": "Feature",
  "properties": {
    "gn:admin1_code":"14",
    "gn:admin2_code":"33.0",
    "gn:admin3_code":"3307.0",
    "gn:admin4_code":"330702.0",
    "gn:asciiname":"Mugongo",
    "gn:country_code":"RW",
    "gn:dem":2291,
    "gn:feature_class":"P",
    "gn:feature_code":"PPLL",
    "gn:name":"Mugongo",
    "gn:population":0,
    "gn:timezone":"Africa/Kigali",
    "iso:country":"RW",
    "wof:name":"Mugongo",
    "wof:placetype":"locality"
},
  "geometry": {"coordinates":[29.37326,-1.59086],"type":"Point"}
}