{
  "type": "Feature",
  "properties": {
    "gn:admin1_code":"11.0",
    "gn:admin2_code":"56",
    "gn:admin3_code":"5609.0",
    "gn:admin4_code":"560901.0",
    "gn:asciiname":"Kigarama",
    "gn:country_code":"RW",
    "gn:dem":1690,
    "gn:feature_class":"P",
    "gn:feature_code":"PPL",
    "gn:name":"Kigarama",
    "gn:population":0,
    "gn:timezone":"Africa/Kigali",
    "iso:country":"RW",
    "wof:name":"Kigarama",
    "wof:placetype":"locality"
},
  "geometry": {"coordinates":[30.5556,-2.0796],"type":"Point"}
}