{
  "type": "Feature",
  "properties": {
    "gn:admin1_code":"14.0",
    "gn:admin2_code":"32",
    "gn:admin3_code":"3203.0",
    "gn:admin4_code":"320304.0",
    "gn:asciiname":"Rusebeya",
    "gn:country_code":"RW",
    "gn:dem":1881,
    "gn:feature_class":"P",
    "gn:feature_code":"PPLL",
    "gn:name":"Rusebeya",
    "gn:population":0,
    "gn:timezone":"Africa/Kigali",
    "iso:country":"RW",
    "wof:name":"Rusebeya",
    "wof:placetype":"locality"
},
  "geometry": {"coordinates":[29.3217,-1.8206],"type":"Point"}
}