{
  "type": "Feature",
  "properties": {
    "gn:admin1_code":"15",
    "gn:admin2_code":"21.0",
    "gn:admin3_code":"2105.0",
    "gn:admin4_code":"210501.0",
    "gn:asciiname":"Nyarutovu",
    "gn:country_code":"RW",
    "gn:dem":1716,
    "gn:feature_class":"P",
    "gn:feature_code":"PPLL",
    "gn:name":"Nyarutovu",
    "gn:population":0,
    "gn:timezone":"Africa/Kigali",
    "iso:country":"RW",
    "wof:name":"Nyarutovu",
    "wof:placetype":"locality"
},
  "geometry": {"coordinates":[29.7971,-2.2819],"type":"Point"}
}