{
  "type": "Feature",
  "properties": {
    "gn:admin1_code":"11",
    "gn:admin2_code":"54.0",
    "gn:admin3_code":"5404.0",
    "gn:admin4_code":"540402.0",
    "gn:asciiname":"Gasogororo",
    "gn:country_code":"RW",
    "gn:dem":1567,
    "gn:feature_class":"P",
    "gn:feature_code":"PPLL",
    "gn:name":"Gasogororo",
    "gn:population":0,
    "gn:timezone":"Africa/Kigali",
    "iso:country":"RW",
    "wof:name":"Gasogororo",
    "wof:placetype":"locality"
},
  "geometry": {"coordinates":[30.5178,-1.8901],"type":"Point"}
}