{
  "type": "Feature",
  "properties": {
    "gn:admin1_code":"15.0",
    "gn:admin2_code":"21",
    "gn:admin3_code":"2106.0",
    "gn:admin4_code":"210603.0",
    "gn:asciiname":"Gasura",
    "gn:country_code":"RW",
    "gn:dem":1729,
    "gn:feature_class":"P",
    "gn:feature_code":"PPLL",
    "gn:name":"Gasura",
    "gn:population":0,
    "gn:timezone":"Africa/Kigali",
    "iso:country":"RW",
    "wof:name":"Gasura",
    "wof:placetype":"locality"
},
  "geometry": {"coordinates":[29.7191,-2.2685],"type":"Point"}
}