{
  "type": "Feature",
  "properties": {
    "gn:admin1_code":"11.0",
    "gn:admin2_code":"53",
    "gn:admin3_code":"5301.0",
    "gn:admin4_code":"530102.0",
    "gn:asciiname":"Rugarama",
    "gn:country_code":"RW",
    "gn:dem":1667,
    "gn:feature_class":"P",
    "gn:feature_code":"PPL",
    "gn:name":"Rugarama",
    "gn:population":0,
    "gn:timezone":"Africa/Kigali",
    "iso:country":"RW",
    "wof:name":"Rugarama",
    "wof:placetype":"locality"
},
  "geometry": {"coordinates":[30.2931,-1.7962],"type":"Point"}
}