{
  "type": "Feature",
  "properties": {
    "gn:admin1_code":"13",
    "gn:admin2_code":"45.0",
    "gn:admin3_code":"4519.0",
    "gn:admin4_code":"451906.0",
    "gn:asciiname":"Kamina",
    "gn:country_code":"RW",
    "gn:dem":1725,
    "gn:feature_class":"P",
    "gn:feature_code":"PPLL",
    "gn:name":"Kamina",
    "gn:population":0,
    "gn:timezone":"Africa/Kigali",
    "iso:country":"RW",
    "wof:name":"Kamina",
    "wof:placetype":"locality"
},
  "geometry": {"coordinates":[30.1599,-1.6472],"type":"Point"}
}