{
  "type": "Feature",
  "properties": {
    "gn:admin1_code":"15.0",
    "gn:admin2_code":"23",
    "gn:admin3_code":"2312.0",
    "gn:admin4_code":"231204.0",
    "gn:asciiname":"Ruvuru",
    "gn:country_code":"RW",
    "gn:dem":2268,
    "gn:feature_class":"P",
    "gn:feature_code":"PPLL",
    "gn:name":"Ruvuru",
    "gn:population":0,
    "gn:timezone":"Africa/Kigali",
    "iso:country":"RW",
    "name:und_x_variant":[
        "Luvulu",
        "Ruvuru"
    ],
    "wof:name":"Ruvuru",
    "wof:placetype":"locality"
},
  "geometry": {"coordinates":[29.4572,-2.7627],"type":"Point"}
}