{
  "type": "Feature",
  "properties": {
    "gn:admin1_code":"14.0",
    "gn:admin2_code":"37",
    "gn:admin3_code":"3701.0",
    "gn:admin4_code":"370104.0",
    "gn:asciiname":"Nyanza",
    "gn:country_code":"RW",
    "gn:dem":1636,
    "gn:feature_class":"P",
    "gn:feature_code":"PPL",
    "gn:name":"Nyanza",
    "gn:population":0,
    "gn:timezone":"Africa/Kigali",
    "iso:country":"RW",
    "name:bre_x_preferred":[
        "Nyanza"
    ],
    "name:ceb_x_preferred":[
        "Nyanza"
    ],
    "name:deu_x_preferred":[
        "Nyanza"
    ],
    "name:nld_x_preferred":[
        "Nyanza"
    ],
    "name:rus_x_preferred":[
        "\u041d\u044c\u044f\u043d\u0437\u0430"
    ],
    "wof:name":"Nyanza",
    "wof:placetype":"locality"
},
  "geometry": {"coordinates":[29.0668,-2.4149],"type":"Point"}
}