{
  "type": "Feature",
  "properties": {
    "gn:admin1_code":"15.0",
    "gn:admin2_code":"23",
    "gn:admin3_code":"2303.0",
    "gn:admin4_code":"230305.0",
    "gn:asciiname":"Ngarama",
    "gn:country_code":"RW",
    "gn:dem":1815,
    "gn:feature_class":"P",
    "gn:feature_code":"PPLL",
    "gn:name":"Ngarama",
    "gn:population":0,
    "gn:timezone":"Africa/Kigali",
    "iso:country":"RW",
    "wof:name":"Ngarama",
    "wof:placetype":"locality"
},
  "geometry": {"coordinates":[29.5757,-2.6899],"type":"Point"}
}