{
  "type": "Feature",
  "properties": {
    "gn:admin1_code":"15.0",
    "gn:admin2_code":"23",
    "gn:admin3_code":"2308.0",
    "gn:admin4_code":"230804.0",
    "gn:asciiname":"Nyamirama",
    "gn:country_code":"RW",
    "gn:dem":1769,
    "gn:feature_class":"P",
    "gn:feature_code":"PPLL",
    "gn:name":"Nyamirama",
    "gn:population":0,
    "gn:timezone":"Africa/Kigali",
    "iso:country":"RW",
    "wof:name":"Nyamirama",
    "wof:placetype":"locality"
},
  "geometry": {"coordinates":[29.7217,-2.6923],"type":"Point"}
}