{
  "type": "Feature",
  "properties": {
    "gn:admin1_code":"11",
    "gn:admin2_code":"53.0",
    "gn:admin3_code":"5306.0",
    "gn:admin4_code":"530604.0",
    "gn:asciiname":"Karaba",
    "gn:country_code":"RW",
    "gn:dem":1480,
    "gn:feature_class":"P",
    "gn:feature_code":"PPLL",
    "gn:name":"Karaba",
    "gn:population":0,
    "gn:timezone":"Africa/Kigali",
    "iso:country":"RW",
    "name:ceb_x_preferred":[
        "Karaba"
    ],
    "name:fra_x_preferred":[
        "Karaba"
    ],
    "name:swe_x_preferred":[
        "Karaba"
    ],
    "wof:name":"Karaba",
    "wof:placetype":"locality"
},
  "geometry": {"coordinates":[30.3598,-1.8398],"type":"Point"}
}