{
  "type": "Feature",
  "properties": {
    "gn:admin1_code":"14.0",
    "gn:admin2_code":"37",
    "gn:admin3_code":"3702.0",
    "gn:admin4_code":"370201.0",
    "gn:asciiname":"Kubagiramenyo",
    "gn:country_code":"RW",
    "gn:dem":1572,
    "gn:feature_class":"P",
    "gn:feature_code":"PPLL",
    "gn:name":"Kubagiramenyo",
    "gn:population":0,
    "gn:timezone":"Africa/Kigali",
    "iso:country":"RW",
    "wof:name":"Kubagiramenyo",
    "wof:placetype":"locality"
},
  "geometry": {"coordinates":[28.98602,-2.41432],"type":"Point"}
}