{
  "type": "Feature",
  "properties": {
    "gn:admin1_code":"11.0",
    "gn:admin2_code":"53",
    "gn:admin3_code":"5312.0",
    "gn:admin4_code":"531206.0",
    "gn:asciiname":"Rwarenga",
    "gn:country_code":"RW",
    "gn:dem":1707,
    "gn:feature_class":"P",
    "gn:feature_code":"PPL",
    "gn:name":"Rwarenga",
    "gn:population":0,
    "gn:timezone":"Africa/Kigali",
    "iso:country":"RW",
    "wof:name":"Rwarenga",
    "wof:placetype":"locality"
},
  "geometry": {"coordinates":[30.3387,-1.7326],"type":"Point"}
}