{
  "type": "Feature",
  "properties": {
    "gn:admin1_code":"14.0",
    "gn:admin2_code":"37",
    "gn:admin3_code":"3702.0",
    "gn:admin4_code":"370203.0",
    "gn:asciiname":"Ruhinga",
    "gn:country_code":"RW",
    "gn:dem":1830,
    "gn:feature_class":"P",
    "gn:feature_code":"PPLL",
    "gn:name":"Ruhinga",
    "gn:population":0,
    "gn:timezone":"Africa/Kigali",
    "iso:country":"RW",
    "wof:name":"Ruhinga",
    "wof:placetype":"locality"
},
  "geometry": {"coordinates":[28.9792,-2.4588],"type":"Point"}
}