{
  "type": "Feature",
  "properties": {
    "gn:admin1_code":"15.0",
    "gn:admin2_code":"25",
    "gn:admin3_code":"2502.0",
    "gn:admin4_code":"250206.0",
    "gn:asciiname":"Gafuhisha",
    "gn:country_code":"RW",
    "gn:dem":1690,
    "gn:feature_class":"P",
    "gn:feature_code":"PPLL",
    "gn:name":"Gafuhisha",
    "gn:population":0,
    "gn:timezone":"Africa/Kigali",
    "iso:country":"RW",
    "wof:name":"Gafuhisha",
    "wof:placetype":"locality"
},
  "geometry": {"coordinates":[29.6538,-2.4223],"type":"Point"}
}