{
  "type": "Feature",
  "properties": {
    "gn:admin1_code":"11",
    "gn:admin2_code":"57.0",
    "gn:admin3_code":"5706.0",
    "gn:admin4_code":"570603.0",
    "gn:asciiname":"Nyakajuri",
    "gn:country_code":"RW",
    "gn:dem":1417,
    "gn:feature_class":"P",
    "gn:feature_code":"PPLL",
    "gn:name":"Nyakajuri",
    "gn:population":0,
    "gn:timezone":"Africa/Kigali",
    "iso:country":"RW",
    "wof:name":"Nyakajuri",
    "wof:placetype":"locality"
},
  "geometry": {"coordinates":[30.0812,-2.2024],"type":"Point"}
}