{
  "type": "Feature",
  "properties": {
    "gn:admin1_code":"13",
    "gn:admin2_code":"42.0",
    "gn:admin3_code":"4209.0",
    "gn:admin4_code":"420903.0",
    "gn:asciiname":"Bugaragara",
    "gn:country_code":"RW",
    "gn:dem":1782,
    "gn:feature_class":"P",
    "gn:feature_code":"PPL",
    "gn:name":"Bugaragara",
    "gn:population":0,
    "gn:timezone":"Africa/Kigali",
    "iso:country":"RW",
    "wof:name":"Bugaragara",
    "wof:placetype":"locality"
},
  "geometry": {"coordinates":[29.7199,-1.6119],"type":"Point"}
}