{
  "type": "Feature",
  "properties": {
    "gn:admin1_code":"15",
    "gn:admin2_code":"26.0",
    "gn:admin3_code":"2601.0",
    "gn:admin4_code":"260104.0",
    "gn:asciiname":"Munyinya",
    "gn:country_code":"RW",
    "gn:dem":1693,
    "gn:feature_class":"P",
    "gn:feature_code":"PPLL",
    "gn:name":"Munyinya",
    "gn:population":0,
    "gn:timezone":"Africa/Kigali",
    "iso:country":"RW",
    "wof:name":"Munyinya",
    "wof:placetype":"locality"
},
  "geometry": {"coordinates":[29.7135,-2.215],"type":"Point"}
}