{
  "type": "Feature",
  "properties": {
    "gn:admin1_code":"11",
    "gn:admin2_code":"51.0",
    "gn:admin3_code":"5109.0",
    "gn:admin4_code":"510904.0",
    "gn:asciiname":"Gatika",
    "gn:country_code":"RW",
    "gn:dem":1693,
    "gn:feature_class":"P",
    "gn:feature_code":"PPLL",
    "gn:name":"Gatika",
    "gn:population":0,
    "gn:timezone":"Africa/Kigali",
    "iso:country":"RW",
    "wof:name":"Gatika",
    "wof:placetype":"locality"
},
  "geometry": {"coordinates":[30.3385,-1.9383],"type":"Point"}
}