{
  "type": "Feature",
  "properties": {
    "gn:admin1_code":"11",
    "gn:admin2_code":"51.0",
    "gn:admin3_code":"5109.0",
    "gn:admin4_code":"510904.0",
    "gn:asciiname":"Gatika",
    "gn:country_code":"RW",
    "gn:dem":1693,
    "gn:feature_class":"P",
    "gn:feature_code":"PPLL",
    "gn:name":"Gatika",
    "gn:population":0,
    "gn:timezone":"Africa/Kigali",
    "iso:country":"RW",
    "name:ara_x_preferred":[
        "\u063a\u0627\u062a\u064a\u0643\u0627"
    ],
    "name:arg_x_preferred":[
        "Gatika"
    ],
    "name:bre_x_preferred":[
        "Gatika"
    ],
    "name:cat_x_preferred":[
        "Gatika"
    ],
    "name:ceb_x_preferred":[
        "Gatika"
    ],
    "name:eus_x_preferred":[
        "Gatika"
    ],
    "name:fra_x_preferred":[
        "Gatika"
    ],
    "name:glg_x_preferred":[
        "Gatika"
    ],
    "name:hun_x_preferred":[
        "Gatika"
    ],
    "name:ita_x_preferred":[
        "Gatika"
    ],
    "name:lat_x_preferred":[
        "Gatica"
    ],
    "name:msa_x_preferred":[
        "Gatika"
    ],
    "name:nld_x_preferred":[
        "Gatika"
    ],
    "name:oci_x_preferred":[
        "Gatika"
    ],
    "name:pol_x_preferred":[
        "Gatika"
    ],
    "name:por_x_preferred":[
        "Gatica"
    ],
    "name:rus_x_preferred":[
        "\u0413\u0430\u0442\u0438\u043a\u0430"
    ],
    "name:sco_x_preferred":[
        "Gatika"
    ],
    "name:spa_x_preferred":[
        "Gatica"
    ],
    "name:swe_x_preferred":[
        "Gatika"
    ],
    "name:ukr_x_preferred":[
        "\u0413\u0430\u0442\u0456\u043a\u0430"
    ],
    "name:uzb_x_preferred":[
        "Gatica"
    ],
    "name:war_x_preferred":[
        "Gatika"
    ],
    "name:zho_x_preferred":[
        "\u52a0\u8482\u5361"
    ],
    "wof:name":"Gatika",
    "wof:placetype":"locality"
},
  "geometry": {"coordinates":[30.3385,-1.9383],"type":"Point"}
}