{
  "type": "Feature",
  "properties": {
    "gn:admin1_code":"14.0",
    "gn:admin2_code":"32",
    "gn:admin3_code":"3205.0",
    "gn:admin4_code":"320501.0",
    "gn:asciiname":"Manihira",
    "gn:country_code":"RW",
    "gn:dem":2413,
    "gn:feature_class":"P",
    "gn:feature_code":"PPL",
    "gn:name":"Manihira",
    "gn:population":0,
    "gn:timezone":"Africa/Kigali",
    "iso:country":"RW",
    "wof:name":"Manihira",
    "wof:placetype":"locality"
},
  "geometry": {"coordinates":[29.442,-1.9508],"type":"Point"}
}