{
  "type": "Feature",
  "properties": {
    "gn:admin1_code":"12.0",
    "gn:admin2_code":"13",
    "gn:admin3_code":"1302.0",
    "gn:admin4_code":"130202.0",
    "gn:asciiname":"Murambi",
    "gn:country_code":"RW",
    "gn:dem":1527,
    "gn:feature_class":"P",
    "gn:feature_code":"PPLL",
    "gn:name":"Murambi",
    "gn:population":0,
    "gn:timezone":"Africa/Kigali",
    "iso:country":"RW",
    "name:ita_x_preferred":[
        "Murambi"
    ],
    "name:und_x_variant":[
        "Colline Murambi",
        "Murambi"
    ],
    "wof:name":"Murambi",
    "wof:placetype":"locality"
},
  "geometry": {"coordinates":[30.0852,-1.9849],"type":"Point"}
}