{
  "type": "Feature",
  "properties": {
    "gn:admin1_code":"14",
    "gn:admin2_code":"31.0",
    "gn:admin3_code":"3104.0",
    "gn:admin4_code":"310403.0",
    "gn:asciiname":"Nyagisozi",
    "gn:country_code":"RW",
    "gn:dem":2160,
    "gn:feature_class":"P",
    "gn:feature_code":"PPLL",
    "gn:name":"Nyagisozi",
    "gn:population":0,
    "gn:timezone":"Africa/Kigali",
    "iso:country":"RW",
    "wof:name":"Nyagisozi",
    "wof:placetype":"locality"
},
  "geometry": {"coordinates":[29.3738,-2.1194],"type":"Point"}
}