{
  "type": "Feature",
  "properties": {
    "gn:admin1_code":"13",
    "gn:admin2_code":"44.0",
    "gn:admin3_code":"4417.0",
    "gn:admin4_code":"441701.0",
    "gn:asciiname":"Sarambwe",
    "gn:country_code":"RW",
    "gn:dem":2264,
    "gn:feature_class":"P",
    "gn:feature_code":"PPLL",
    "gn:name":"Sarambwe",
    "gn:population":0,
    "gn:timezone":"Africa/Kigali",
    "iso:country":"RW",
    "wof:name":"Sarambwe",
    "wof:placetype":"locality"
},
  "geometry": {"coordinates":[29.8433,-1.4791],"type":"Point"}
}