{
  "type": "Feature",
  "properties": {
    "gn:admin1_code":"14",
    "gn:admin2_code":"33.0",
    "gn:admin3_code":"3312.0",
    "gn:admin4_code":"331204.0",
    "gn:asciiname":"Rugalika",
    "gn:country_code":"RW",
    "gn:dem":1763,
    "gn:feature_class":"P",
    "gn:feature_code":"PPL",
    "gn:name":"Rugalika",
    "gn:population":0,
    "gn:timezone":"Africa/Kigali",
    "iso:country":"RW",
    "wof:name":"Rugalika",
    "wof:placetype":"locality"
},
  "geometry": {"coordinates":[29.3186,-1.696],"type":"Point"}
}