{
  "type": "Feature",
  "properties": {
    "gn:admin1_code":"15",
    "gn:admin2_code":"26.0",
    "gn:admin3_code":"2605.0",
    "gn:admin4_code":"260503.0",
    "gn:asciiname":"Kirwa",
    "gn:country_code":"RW",
    "gn:dem":1842,
    "gn:feature_class":"P",
    "gn:feature_code":"PPL",
    "gn:name":"Kirwa",
    "gn:population":0,
    "gn:timezone":"Africa/Kigali",
    "iso:country":"RW",
    "name:deu_x_preferred":[
        "Kirwa"
    ],
    "name:fin_x_preferred":[
        "Kirwa"
    ],
    "wof:name":"Kirwa",
    "wof:placetype":"locality"
},
  "geometry": {"coordinates":[29.6529,-2.1911],"type":"Point"}
}