{
  "type": "Feature",
  "properties": {
    "gn:admin1_code":"13",
    "gn:admin2_code":"43.0",
    "gn:admin3_code":"4314.0",
    "gn:admin4_code":"431402.0",
    "gn:asciiname":"Gihango",
    "gn:country_code":"RW",
    "gn:dem":1761,
    "gn:feature_class":"P",
    "gn:feature_code":"PPLL",
    "gn:name":"Gihango",
    "gn:population":0,
    "gn:timezone":"Africa/Kigali",
    "iso:country":"RW",
    "wof:name":"Gihango",
    "wof:placetype":"locality"
},
  "geometry": {"coordinates":[29.6954,-1.5551],"type":"Point"}
}