{
  "type": "Feature",
  "properties": {
    "gn:admin1_code":"15.0",
    "gn:admin2_code":"24",
    "gn:admin3_code":"2412.0",
    "gn:admin4_code":"241201.0",
    "gn:asciiname":"Rwaniro",
    "gn:country_code":"RW",
    "gn:dem":1659,
    "gn:feature_class":"P",
    "gn:feature_code":"PPLL",
    "gn:name":"Rwaniro",
    "gn:population":0,
    "gn:timezone":"Africa/Kigali",
    "iso:country":"RW",
    "name:und_x_variant":[
        "Gwaniro",
        "Mwirwaniro",
        "Murgwaniro",
        "Rwanira",
        "Rwaniro"
    ],
    "wof:name":"Rwaniro",
    "wof:placetype":"locality"
},
  "geometry": {"coordinates":[29.70689,-2.4469],"type":"Point"}
}