{
  "type": "Feature",
  "properties": {
    "gn:admin1_code":"15",
    "gn:admin2_code":"26.0",
    "gn:admin3_code":"2604.0",
    "gn:admin4_code":"260401.0",
    "gn:asciiname":"Nyarugenge",
    "gn:country_code":"RW",
    "gn:dem":1560,
    "gn:feature_class":"P",
    "gn:feature_code":"PPLL",
    "gn:name":"Nyarugenge",
    "gn:population":0,
    "gn:timezone":"Africa/Kigali",
    "iso:country":"RW",
    "name:ita_x_preferred":[
        "Nyarugenge"
    ],
    "name:zho_x_preferred":[
        "\u5c3c\u4e9e\u9b6f\u5ca1\u71b1"
    ],
    "wof:name":"Nyarugenge",
    "wof:placetype":"locality"
},
  "geometry": {"coordinates":[29.9017,-2.1781],"type":"Point"}
}