{
  "type": "Feature",
  "properties": {
    "gn:admin1_code":"13",
    "gn:admin2_code":"43.0",
    "gn:admin3_code":"4311.0",
    "gn:admin4_code":"431105.0",
    "gn:asciiname":"Muguta",
    "gn:country_code":"RW",
    "gn:dem":1721,
    "gn:feature_class":"P",
    "gn:feature_code":"PPLL",
    "gn:name":"Muguta",
    "gn:population":0,
    "gn:timezone":"Africa/Kigali",
    "iso:country":"RW",
    "name:und_x_variant":[
        "Mugute"
    ],
    "wof:name":"Muguta",
    "wof:placetype":"locality"
},
  "geometry": {"coordinates":[29.6154,-1.5688],"type":"Point"}
}