{
  "type": "Feature",
  "properties": {
    "gn:admin1_code":"15.0",
    "gn:admin2_code":"22",
    "gn:admin3_code":"2205.0",
    "gn:admin4_code":"220502.0",
    "gn:asciiname":"Bimba",
    "gn:country_code":"RW",
    "gn:dem":1647,
    "gn:feature_class":"P",
    "gn:feature_code":"PPL",
    "gn:name":"Bimba",
    "gn:population":0,
    "gn:timezone":"Africa/Kigali",
    "iso:country":"RW",
    "wof:name":"Bimba",
    "wof:placetype":"locality"
},
  "geometry": {"coordinates":[29.7684,-2.7313],"type":"Point"}
}