{
  "type": "Feature",
  "properties": {
    "gn:admin1_code":"11.0",
    "gn:admin2_code":"52",
    "gn:admin3_code":"5212.0",
    "gn:admin4_code":"521210.0",
    "gn:asciiname":"Ruhilima",
    "gn:country_code":"RW",
    "gn:dem":1437,
    "gn:feature_class":"P",
    "gn:feature_code":"PPL",
    "gn:name":"Ruhilima",
    "gn:population":0,
    "gn:timezone":"Africa/Kigali",
    "iso:country":"RW",
    "wof:name":"Ruhilima",
    "wof:placetype":"locality"
},
  "geometry": {"coordinates":[30.28695,-1.20652],"type":"Point"}
}