{
  "type": "Feature",
  "properties": {
    "gn:admin1_code":"15.0",
    "gn:admin2_code":"26",
    "gn:admin3_code":"2609.0",
    "gn:admin4_code":"260904.0",
    "gn:asciiname":"Ruhango",
    "gn:country_code":"RW",
    "gn:dem":1703,
    "gn:feature_class":"P",
    "gn:feature_code":"PPLL",
    "gn:name":"Ruhango",
    "gn:population":0,
    "gn:timezone":"Africa/Kigali",
    "iso:country":"RW",
    "wof:name":"Ruhango",
    "wof:placetype":"locality"
},
  "geometry": {"coordinates":[29.79088,-2.2246],"type":"Point"}
}