{
  "type": "Feature",
  "properties": {
    "gn:admin1_code":"11.0",
    "gn:admin2_code":"53",
    "gn:admin3_code":"5302.0",
    "gn:admin4_code":"530202.0",
    "gn:asciiname":"Mwenya",
    "gn:country_code":"RW",
    "gn:dem":1584,
    "gn:feature_class":"P",
    "gn:feature_code":"PPLL",
    "gn:name":"Mwenya",
    "gn:population":0,
    "gn:timezone":"Africa/Kigali",
    "iso:country":"RW",
    "name:und_x_variant":[
        "Colline Mwenya",
        "Mwenya"
    ],
    "wof:name":"Mwenya",
    "wof:placetype":"locality"
},
  "geometry": {"coordinates":[30.2351,-1.632],"type":"Point"}
}