{
  "type": "Feature",
  "properties": {
    "gn:admin1_code":"12",
    "gn:admin2_code":"12.0",
    "gn:admin3_code":"1206.0",
    "gn:admin4_code":"120606.0",
    "gn:asciiname":"Kigufi",
    "gn:country_code":"RW",
    "gn:dem":1650,
    "gn:feature_class":"P",
    "gn:feature_code":"PPLL",
    "gn:name":"Kigufi",
    "gn:population":0,
    "gn:timezone":"Africa/Kigali",
    "iso:country":"RW",
    "wof:name":"Kigufi",
    "wof:placetype":"locality"
},
  "geometry": {"coordinates":[30.0232,-1.8784],"type":"Point"}
}