{
  "type": "Feature",
  "properties": {
    "gn:admin1_code":"13",
    "gn:admin2_code":"42.0",
    "gn:admin3_code":"4212.0",
    "gn:admin4_code":"421202.0",
    "gn:asciiname":"Burenga",
    "gn:country_code":"RW",
    "gn:dem":1549,
    "gn:feature_class":"P",
    "gn:feature_code":"PPLL",
    "gn:name":"Burenga",
    "gn:population":0,
    "gn:timezone":"Africa/Kigali",
    "iso:country":"RW",
    "wof:name":"Burenga",
    "wof:placetype":"locality"
},
  "geometry": {"coordinates":[29.6453,-1.6681],"type":"Point"}
}