{
  "type": "Feature",
  "properties": {
    "gn:admin1_code":"15.0",
    "gn:admin2_code":"24",
    "gn:admin3_code":"2409.0",
    "gn:admin4_code":"240902.0",
    "gn:asciiname":"Runga",
    "gn:country_code":"RW",
    "gn:dem":1786,
    "gn:feature_class":"P",
    "gn:feature_code":"PPLL",
    "gn:name":"Runga",
    "gn:population":0,
    "gn:timezone":"Africa/Kigali",
    "iso:country":"RW",
    "wof:name":"Runga",
    "wof:placetype":"locality"
},
  "geometry": {"coordinates":[29.7122,-2.6061],"type":"Point"}
}