{
  "type": "Feature",
  "properties": {
    "gn:admin1_code":"15.0",
    "gn:admin2_code":"25",
    "gn:admin3_code":"2502.0",
    "gn:admin4_code":"250203.0",
    "gn:asciiname":"Kagarama",
    "gn:country_code":"RW",
    "gn:dem":1806,
    "gn:feature_class":"P",
    "gn:feature_code":"PPLL",
    "gn:name":"Kagarama",
    "gn:population":0,
    "gn:timezone":"Africa/Kigali",
    "iso:country":"RW",
    "wof:name":"Kagarama",
    "wof:placetype":"locality"
},
  "geometry": {"coordinates":[29.6286,-2.4478],"type":"Point"}
}