{
  "type": "Feature",
  "properties": {
    "gn:admin1_code":"13",
    "gn:admin2_code":"41.0",
    "gn:admin3_code":"4117.0",
    "gn:admin4_code":"411702.0",
    "gn:asciiname":"Kamararyi",
    "gn:country_code":"RW",
    "gn:dem":2033,
    "gn:feature_class":"P",
    "gn:feature_code":"PPLL",
    "gn:name":"Kamararyi",
    "gn:population":0,
    "gn:timezone":"Africa/Kigali",
    "iso:country":"RW",
    "wof:name":"Kamararyi",
    "wof:placetype":"locality"
},
  "geometry": {"coordinates":[29.9473,-1.7237],"type":"Point"}
}