{
  "type": "Feature",
  "properties": {
    "gn:admin1_code":"14",
    "gn:admin2_code":"31.0",
    "gn:admin3_code":"3107.0",
    "gn:admin4_code":"310704.0",
    "gn:asciiname":"Mujyojyo",
    "gn:country_code":"RW",
    "gn:dem":1695,
    "gn:feature_class":"P",
    "gn:feature_code":"PPLL",
    "gn:name":"Mujyojyo",
    "gn:population":0,
    "gn:timezone":"Africa/Kigali",
    "iso:country":"RW",
    "wof:name":"Mujyojyo",
    "wof:placetype":"locality"
},
  "geometry": {"coordinates":[29.5843,-2.1171],"type":"Point"}
}