{
  "type": "Feature",
  "properties": {
    "gn:admin1_code":"15.0",
    "gn:admin2_code":"25",
    "gn:admin3_code":"2508.0",
    "gn:admin4_code":"250803.0",
    "gn:asciiname":"Rubona",
    "gn:country_code":"RW",
    "gn:dem":1793,
    "gn:feature_class":"P",
    "gn:feature_code":"PPLL",
    "gn:name":"Rubona",
    "gn:population":0,
    "gn:timezone":"Africa/Kigali",
    "iso:country":"RW",
    "name:ceb_x_preferred":[
        "Rubona"
    ],
    "name:swe_x_preferred":[
        "Rubona"
    ],
    "wof:name":"Rubona",
    "wof:placetype":"locality"
},
  "geometry": {"coordinates":[29.534,-2.3825],"type":"Point"}
}