{
  "type": "Feature",
  "properties": {
    "gn:admin1_code":"14.0",
    "gn:admin2_code":"37",
    "gn:admin3_code":"3708.0",
    "gn:admin4_code":"370802.0",
    "gn:asciiname":"Ruganda",
    "gn:country_code":"RW",
    "gn:dem":1877,
    "gn:feature_class":"P",
    "gn:feature_code":"PPL",
    "gn:name":"Ruganda",
    "gn:population":0,
    "gn:timezone":"Africa/Kigali",
    "iso:country":"RW",
    "wof:name":"Ruganda",
    "wof:placetype":"locality"
},
  "geometry": {"coordinates":[29.0124,-2.4997],"type":"Point"}
}