{
  "type": "Feature",
  "properties": {
    "gn:admin1_code":"13",
    "gn:admin2_code":"44.0",
    "gn:admin3_code":"4417.0",
    "gn:admin4_code":"441702.0",
    "gn:asciiname":"Gashoro",
    "gn:country_code":"RW",
    "gn:dem":2051,
    "gn:feature_class":"P",
    "gn:feature_code":"PPLL",
    "gn:name":"Gashoro",
    "gn:population":0,
    "gn:timezone":"Africa/Kigali",
    "iso:country":"RW",
    "wof:name":"Gashoro",
    "wof:placetype":"locality"
},
  "geometry": {"coordinates":[29.8606,-1.5014],"type":"Point"}
}