{
  "type": "Feature",
  "properties": {
    "gn:admin1_code":"14",
    "gn:admin2_code":"31.0",
    "gn:admin3_code":"3106.0",
    "gn:admin4_code":"310602.0",
    "gn:asciiname":"Mubuga",
    "gn:country_code":"RW",
    "gn:dem":1780,
    "gn:feature_class":"P",
    "gn:feature_code":"PPLL",
    "gn:name":"Mubuga",
    "gn:population":0,
    "gn:timezone":"Africa/Kigali",
    "iso:country":"RW",
    "wof:name":"Mubuga",
    "wof:placetype":"locality"
},
  "geometry": {"coordinates":[29.5667,-2.1464],"type":"Point"}
}