{
  "type": "Feature",
  "properties": {
    "gn:admin1_code":"14",
    "gn:admin2_code":"35.0",
    "gn:admin3_code":"3504.0",
    "gn:admin4_code":"350402.0",
    "gn:asciiname":"Kabwacya",
    "gn:country_code":"RW",
    "gn:dem":2164,
    "gn:feature_class":"P",
    "gn:feature_code":"PPLL",
    "gn:name":"Kabwacya",
    "gn:population":0,
    "gn:timezone":"Africa/Kigali",
    "iso:country":"RW",
    "wof:name":"Kabwacya",
    "wof:placetype":"locality"
},
  "geometry": {"coordinates":[29.5717,-1.7437],"type":"Point"}
}