{
  "type": "Feature",
  "properties": {
    "gn:admin1_code":"15.0",
    "gn:admin2_code":"25",
    "gn:admin3_code":"2505.0",
    "gn:admin4_code":"250501.0",
    "gn:asciiname":"Bunyambilili",
    "gn:country_code":"RW",
    "gn:dem":1911,
    "gn:feature_class":"P",
    "gn:feature_code":"PPL",
    "gn:name":"Bunyambilili",
    "gn:population":0,
    "gn:timezone":"Africa/Kigali",
    "iso:country":"RW",
    "wof:name":"Bunyambilili",
    "wof:placetype":"locality"
},
  "geometry": {"coordinates":[29.53028,-2.32833],"type":"Point"}
}