{
  "type": "Feature",
  "properties": {
    "gn:admin1_code":"14",
    "gn:admin2_code":"35.0",
    "gn:admin3_code":"3512.0",
    "gn:admin4_code":"351202.0",
    "gn:asciiname":"Bugabe",
    "gn:country_code":"RW",
    "gn:dem":1617,
    "gn:feature_class":"P",
    "gn:feature_code":"PPLL",
    "gn:name":"Bugabe",
    "gn:population":0,
    "gn:timezone":"Africa/Kigali",
    "iso:country":"RW",
    "wof:name":"Bugabe",
    "wof:placetype":"locality"
},
  "geometry": {"coordinates":[29.6111,-2.042],"type":"Point"}
}