{
  "type": "Feature",
  "properties": {
    "gn:admin1_code":"15.0",
    "gn:admin2_code":"22",
    "gn:admin3_code":"2207.0",
    "gn:admin4_code":"220704.0",
    "gn:asciiname":"Rwamiko",
    "gn:country_code":"RW",
    "gn:dem":1439,
    "gn:feature_class":"P",
    "gn:feature_code":"PPLL",
    "gn:name":"Rwamiko",
    "gn:population":0,
    "gn:timezone":"Africa/Kigali",
    "iso:country":"RW",
    "name:und_x_variant":[
        "Colline Rwamiko",
        "Rwamiko"
    ],
    "wof:name":"Rwamiko",
    "wof:placetype":"locality"
},
  "geometry": {"coordinates":[29.9023,-2.6556],"type":"Point"}
}