{
  "type": "Feature",
  "properties": {
    "gn:admin1_code":"11",
    "gn:admin2_code":"55.0",
    "gn:admin3_code":"5509.0",
    "gn:admin4_code":"550904.0",
    "gn:asciiname":"Rutoma",
    "gn:country_code":"RW",
    "gn:dem":1519,
    "gn:feature_class":"P",
    "gn:feature_code":"PPLL",
    "gn:name":"Rutoma",
    "gn:population":0,
    "gn:timezone":"Africa/Kigali",
    "iso:country":"RW",
    "wof:name":"Rutoma",
    "wof:placetype":"locality"
},
  "geometry": {"coordinates":[30.591,-2.2348],"type":"Point"}
}