{
  "type": "Feature",
  "properties": {
    "gn:admin1_code":"15",
    "gn:admin2_code":"28.0",
    "gn:admin3_code":"2808.0",
    "gn:admin4_code":"280801.0",
    "gn:asciiname":"Nyamabare",
    "gn:country_code":"RW",
    "gn:dem":1543,
    "gn:feature_class":"P",
    "gn:feature_code":"PPLL",
    "gn:name":"Nyamabare",
    "gn:population":0,
    "gn:timezone":"Africa/Kigali",
    "iso:country":"RW",
    "wof:name":"Nyamabare",
    "wof:placetype":"locality"
},
  "geometry": {"coordinates":[29.8877,-2.0846],"type":"Point"}
}