{
  "type": "Feature",
  "properties": {
    "gn:admin1_code":"11",
    "gn:admin2_code":"51.0",
    "gn:admin3_code":"5114.0",
    "gn:admin4_code":"511404.0",
    "gn:asciiname":"Byobo",
    "gn:country_code":"RW",
    "gn:dem":1484,
    "gn:feature_class":"P",
    "gn:feature_code":"PPLL",
    "gn:name":"Byobo",
    "gn:population":0,
    "gn:timezone":"Africa/Kigali",
    "iso:country":"RW",
    "wof:name":"Byobo",
    "wof:placetype":"locality"
},
  "geometry": {"coordinates":[30.3709,-2.0292],"type":"Point"}
}