{
  "type": "Feature",
  "properties": {
    "gn:admin1_code":"15",
    "gn:admin2_code":"21.0",
    "gn:admin3_code":"2102.0",
    "gn:admin4_code":"210205.0",
    "gn:asciiname":"Cyamugani",
    "gn:country_code":"RW",
    "gn:dem":1564,
    "gn:feature_class":"P",
    "gn:feature_code":"PPLL",
    "gn:name":"Cyamugani",
    "gn:population":0,
    "gn:timezone":"Africa/Kigali",
    "iso:country":"RW",
    "wof:name":"Cyamugani",
    "wof:placetype":"locality"
},
  "geometry": {"coordinates":[29.9051,-2.3178],"type":"Point"}
}