{
  "type": "Feature",
  "properties": {
    "gn:admin1_code":"11.0",
    "gn:admin2_code":"56",
    "gn:admin3_code":"5614.0",
    "gn:admin4_code":"561401.0",
    "gn:asciiname":"Mugesera",
    "gn:country_code":"RW",
    "gn:dem":1491,
    "gn:feature_class":"P",
    "gn:feature_code":"PPL",
    "gn:name":"Mugesera",
    "gn:population":0,
    "gn:timezone":"Africa/Kigali",
    "iso:country":"RW",
    "name:und_x_variant":[
        "Bugesera"
    ],
    "wof:name":"Mugesera",
    "wof:placetype":"locality"
},
  "geometry": {"coordinates":[30.424,-2.13182],"type":"Point"}
}