{
  "type": "Feature",
  "properties": {
    "gn:admin1_code":"15.0",
    "gn:admin2_code":"24",
    "gn:admin3_code":"2407.0",
    "gn:admin4_code":"240702.0",
    "gn:asciiname":"Kibabara",
    "gn:country_code":"RW",
    "gn:dem":1699,
    "gn:feature_class":"P",
    "gn:feature_code":"PPL",
    "gn:name":"Kibabara",
    "gn:population":0,
    "gn:timezone":"Africa/Kigali",
    "iso:country":"RW",
    "wof:name":"Kibabara",
    "wof:placetype":"locality"
},
  "geometry": {"coordinates":[29.7353,-2.5714],"type":"Point"}
}