{
  "type": "Feature",
  "properties": {
    "gn:admin1_code":"14.0",
    "gn:admin2_code":"32",
    "gn:admin3_code":"3202.0",
    "gn:admin4_code":"320206.0",
    "gn:asciiname":"Rugarambiro",
    "gn:country_code":"RW",
    "gn:dem":2176,
    "gn:feature_class":"P",
    "gn:feature_code":"PPLL",
    "gn:name":"Rugarambiro",
    "gn:population":0,
    "gn:timezone":"Africa/Kigali",
    "iso:country":"RW",
    "wof:name":"Rugarambiro",
    "wof:placetype":"locality"
},
  "geometry": {"coordinates":[29.4021,-1.9296],"type":"Point"}
}