{
  "type": "Feature",
  "properties": {
    "gn:admin1_code":"15.0",
    "gn:admin2_code":"25",
    "gn:admin3_code":"2508.0",
    "gn:admin4_code":"250803.0",
    "gn:asciiname":"Kabarera",
    "gn:country_code":"RW",
    "gn:dem":1900,
    "gn:feature_class":"P",
    "gn:feature_code":"PPLL",
    "gn:name":"Kabarera",
    "gn:population":0,
    "gn:timezone":"Africa/Kigali",
    "iso:country":"RW",
    "wof:name":"Kabarera",
    "wof:placetype":"locality"
},
  "geometry": {"coordinates":[29.5291,-2.4108],"type":"Point"}
}