{
  "type": "Feature",
  "properties": {
    "gn:admin1_code":"13.0",
    "gn:admin2_code":"41",
    "gn:admin3_code":"4117.0",
    "gn:admin4_code":"411703.0",
    "gn:asciiname":"Tumba",
    "gn:country_code":"RW",
    "gn:dem":2051,
    "gn:feature_class":"P",
    "gn:feature_code":"PPL",
    "gn:name":"Tumba",
    "gn:population":0,
    "gn:timezone":"Africa/Kigali",
    "iso:country":"RW",
    "name:und_x_variant":[
        "Colline Tumba",
        "Tumba"
    ],
    "wof:name":"Tumba",
    "wof:placetype":"locality"
},
  "geometry": {"coordinates":[29.9542,-1.6989],"type":"Point"}
}