{
  "type": "Feature",
  "properties": {
    "gn:admin1_code":"15.0",
    "gn:admin2_code":"25",
    "gn:admin3_code":"2503.0",
    "gn:admin4_code":"250306.0",
    "gn:asciiname":"Rwuya",
    "gn:country_code":"RW",
    "gn:dem":1949,
    "gn:feature_class":"P",
    "gn:feature_code":"PPLL",
    "gn:name":"Rwuya",
    "gn:population":0,
    "gn:timezone":"Africa/Kigali",
    "iso:country":"RW",
    "wof:name":"Rwuya",
    "wof:placetype":"locality"
},
  "geometry": {"coordinates":[29.5326,-2.4699],"type":"Point"}
}