{
  "type": "Feature",
  "properties": {
    "gn:admin1_code":"14",
    "gn:admin2_code":"34.0",
    "gn:admin3_code":"3405.0",
    "gn:admin4_code":"340505.0",
    "gn:asciiname":"Nyaburaro",
    "gn:country_code":"RW",
    "gn:dem":2277,
    "gn:feature_class":"P",
    "gn:feature_code":"PPLL",
    "gn:name":"Nyaburaro",
    "gn:population":0,
    "gn:timezone":"Africa/Kigali",
    "iso:country":"RW",
    "wof:name":"Nyaburaro",
    "wof:placetype":"locality"
},
  "geometry": {"coordinates":[29.5218,-1.6422],"type":"Point"}
}