{
  "type": "Feature",
  "properties": {
    "gn:admin1_code":"13.0",
    "gn:admin2_code":"45",
    "gn:admin3_code":"4520.0",
    "gn:admin4_code":"452002.0",
    "gn:asciiname":"Mutambiko",
    "gn:country_code":"RW",
    "gn:dem":1733,
    "gn:feature_class":"P",
    "gn:feature_code":"PPLL",
    "gn:name":"Mutambiko",
    "gn:population":0,
    "gn:timezone":"Africa/Kigali",
    "iso:country":"RW",
    "name:und_x_variant":[
        "Colline Mutambiko",
        "Mutambiko"
    ],
    "wof:name":"Mutambiko",
    "wof:placetype":"locality"
},
  "geometry": {"coordinates":[30.174,-1.7517],"type":"Point"}
}