{
  "type": "Feature",
  "properties": {
    "gn:admin1_code":"11",
    "gn:admin2_code":"55.0",
    "gn:admin3_code":"5506.0",
    "gn:admin4_code":"550603.0",
    "gn:asciiname":"Paysannat E",
    "gn:country_code":"RW",
    "gn:dem":1325,
    "gn:feature_class":"P",
    "gn:feature_code":"PPLL",
    "gn:name":"Paysannat E",
    "gn:population":0,
    "gn:timezone":"Africa/Kigali",
    "iso:country":"RW",
    "wof:name":"Paysannat E",
    "wof:placetype":"locality"
},
  "geometry": {"coordinates":[30.8307,-2.2532],"type":"Point"}
}