{
  "type": "Feature",
  "properties": {
    "gn:admin1_code":"13",
    "gn:admin2_code":"44.0",
    "gn:admin3_code":"4409.0",
    "gn:admin4_code":"440904.0",
    "gn:asciiname":"Ruta",
    "gn:country_code":"RW",
    "gn:dem":1777,
    "gn:feature_class":"P",
    "gn:feature_code":"PPLL",
    "gn:name":"Ruta",
    "gn:population":0,
    "gn:timezone":"Africa/Kigali",
    "iso:country":"RW",
    "name:ara_x_preferred":[
        "\u0633\u0630\u0627\u0628"
    ],
    "name:azb_x_preferred":[
        "\u0633\u062f\u0648"
    ],
    "name:aze_x_preferred":[
        "S\u0259do"
    ],
    "name:cat_x_preferred":[
        "Ruda"
    ],
    "name:ceb_x_preferred":[
        "Ruta"
    ],
    "name:ckb_x_preferred":[
        "\u067e\u06ce\u0686\u0646"
    ],
    "name:dan_x_preferred":[
        "Rude-sl\u00e6gten"
    ],
    "name:deu_x_preferred":[
        "Rauten"
    ],
    "name:epo_x_preferred":[
        "Ruto"
    ],
    "name:est_x_preferred":[
        "Ruut"
    ],
    "name:eus_x_preferred":[
        "Erruda"
    ],
    "name:fas_x_preferred":[
        "\u0633\u062f\u0627\u0628"
    ],
    "name:fin_x_preferred":[
        "Ruudat"
    ],
    "name:fra_x_preferred":[
        "Ruta"
    ],
    "name:frr_x_preferred":[
        "Winr\u00fctjen"
    ],
    "name:hrv_x_preferred":[
        "Rutvica"
    ],
    "name:hsb_x_preferred":[
        "Ruta"
    ],
    "name:hun_x_preferred":[
        "Ruta"
    ],
    "name:ido_x_preferred":[
        "Ruto"
    ],
    "name:ita_x_preferred":[
        "Ruta"
    ],
    "name:kat_x_preferred":[
        "\u10e2\u10d4\u10d2\u10d0\u10dc\u10d8"
    ],
    "name:lat_x_preferred":[
        "Ruta"
    ],
    "name:lit_x_preferred":[
        "R\u016bta"
    ],
    "name:nap_x_preferred":[
        "Aruta"
    ],
    "name:nor_x_preferred":[
        "Ruteslekten"
    ],
    "name:oci_x_preferred":[
        "Ruta"
    ],
    "name:pol_x_preferred":[
        "Ruta"
    ],
    "name:por_x_preferred":[
        "Ruta"
    ],
    "name:rus_x_preferred":[
        "\u0420\u0443\u0442\u0430"
    ],
    "name:spa_x_preferred":[
        "Ruta"
    ],
    "name:swe_x_preferred":[
        "Vinrutesl\u00e4ktet"
    ],
    "name:tel_x_preferred":[
        "\u0c30\u0c42\u0c1f\u0c3e"
    ],
    "name:ukr_x_preferred":[
        "\u0420\u0443\u0442\u0430"
    ],
    "name:war_x_preferred":[
        "Ruta"
    ],
    "name:zho_x_preferred":[
        "\u82b8\u9999\u5c5e"
    ],
    "wof:name":"Ruta",
    "wof:placetype":"locality"
},
  "geometry": {"coordinates":[29.7358,-1.4735],"type":"Point"}
}