{
  "type": "Feature",
  "properties": {
    "gn:admin1_code":"13",
    "gn:admin2_code":"44.0",
    "gn:admin3_code":"4409.0",
    "gn:admin4_code":"440904.0",
    "gn:asciiname":"Ruta",
    "gn:country_code":"RW",
    "gn:dem":1777,
    "gn:feature_class":"P",
    "gn:feature_code":"PPLL",
    "gn:name":"Ruta",
    "gn:population":0,
    "gn:timezone":"Africa/Kigali",
    "iso:country":"RW",
    "wof:name":"Ruta",
    "wof:placetype":"locality"
},
  "geometry": {"coordinates":[29.7358,-1.4735],"type":"Point"}
}