{
  "type": "Feature",
  "properties": {
    "gn:admin1_code":"14",
    "gn:admin2_code":"33.0",
    "gn:admin3_code":"3312.0",
    "gn:admin4_code":"331203.0",
    "gn:asciiname":"Nkama",
    "gn:country_code":"RW",
    "gn:dem":1640,
    "gn:feature_class":"P",
    "gn:feature_code":"PPLL",
    "gn:name":"Nkama",
    "gn:population":0,
    "gn:timezone":"Africa/Kigali",
    "iso:country":"RW",
    "wof:name":"Nkama",
    "wof:placetype":"locality"
},
  "geometry": {"coordinates":[29.2905,-1.6953],"type":"Point"}
}