{
  "type": "Feature",
  "properties": {
    "gn:admin1_code":"15.0",
    "gn:admin2_code":"25",
    "gn:admin3_code":"2513.0",
    "gn:admin4_code":"251304.0",
    "gn:asciiname":"Gacundura",
    "gn:country_code":"RW",
    "gn:dem":2092,
    "gn:feature_class":"P",
    "gn:feature_code":"PPLL",
    "gn:name":"Gacundura",
    "gn:population":0,
    "gn:timezone":"Africa/Kigali",
    "iso:country":"RW",
    "wof:name":"Gacundura",
    "wof:placetype":"locality"
},
  "geometry": {"coordinates":[29.4685,-2.4418],"type":"Point"}
}