{
  "type": "Feature",
  "properties": {
    "gn:admin1_code":"14",
    "gn:admin2_code":"34.0",
    "gn:admin3_code":"3412.0",
    "gn:admin4_code":"341203.0",
    "gn:asciiname":"Muhare",
    "gn:country_code":"RW",
    "gn:dem":1810,
    "gn:feature_class":"P",
    "gn:feature_code":"PPLL",
    "gn:name":"Muhare",
    "gn:population":0,
    "gn:timezone":"Africa/Kigali",
    "iso:country":"RW",
    "wof:name":"Muhare",
    "wof:placetype":"locality"
},
  "geometry": {"coordinates":[29.6135,-1.7208],"type":"Point"}
}