{
  "type": "Feature",
  "properties": {
    "gn:admin1_code":"11",
    "gn:admin2_code":"51.0",
    "gn:admin3_code":"5111.0",
    "gn:admin4_code":"511103.0",
    "gn:asciiname":"Munini",
    "gn:country_code":"RW",
    "gn:dem":1569,
    "gn:feature_class":"P",
    "gn:feature_code":"PPLL",
    "gn:name":"Munini",
    "gn:population":0,
    "gn:timezone":"Africa/Kigali",
    "iso:country":"RW",
    "wof:name":"Munini",
    "wof:placetype":"locality"
},
  "geometry": {"coordinates":[30.4005,-1.9831],"type":"Point"}
}