{
  "type": "Feature",
  "properties": {
    "gn:admin1_code":"13.0",
    "gn:admin2_code":"43",
    "gn:admin3_code":"4303.0",
    "gn:admin4_code":"430303.0",
    "gn:asciiname":"Gasanze",
    "gn:country_code":"RW",
    "gn:dem":1888,
    "gn:feature_class":"P",
    "gn:feature_code":"PPLL",
    "gn:name":"Gasanze",
    "gn:population":0,
    "gn:timezone":"Africa/Kigali",
    "iso:country":"RW",
    "name:und_x_variant":[
        "Colline Gasanze",
        "Gasanze"
    ],
    "wof:name":"Gasanze",
    "wof:placetype":"locality"
},
  "geometry": {"coordinates":[29.679,-1.5039],"type":"Point"}
}