{
  "type": "Feature",
  "properties": {
    "gn:admin1_code":"15.0",
    "gn:admin2_code":"25",
    "gn:admin3_code":"2517.0",
    "gn:admin4_code":"251705.0",
    "gn:asciiname":"Nyarurambi",
    "gn:country_code":"RW",
    "gn:dem":2005,
    "gn:feature_class":"P",
    "gn:feature_code":"PPLL",
    "gn:name":"Nyarurambi",
    "gn:population":0,
    "gn:timezone":"Africa/Kigali",
    "iso:country":"RW",
    "wof:name":"Nyarurambi",
    "wof:placetype":"locality"
},
  "geometry": {"coordinates":[29.4963,-2.4747],"type":"Point"}
}