{
  "type": "Feature",
  "properties": {
    "gn:admin1_code":"14.0",
    "gn:admin2_code":"36",
    "gn:admin3_code":"3616.0",
    "gn:admin4_code":"361605.0",
    "gn:asciiname":"Kabuye",
    "gn:country_code":"RW",
    "gn:dem":1607,
    "gn:feature_class":"P",
    "gn:feature_code":"PPLL",
    "gn:name":"Kabuye",
    "gn:population":0,
    "gn:timezone":"Africa/Kigali",
    "iso:country":"RW",
    "wof:name":"Kabuye",
    "wof:placetype":"locality"
},
  "geometry": {"coordinates":[28.89822,-2.54804],"type":"Point"}
}