{
  "type": "Feature",
  "properties": {
    "gn:admin1_code":"14",
    "gn:admin2_code":"31.0",
    "gn:admin3_code":"3104.0",
    "gn:admin4_code":"310405.0",
    "gn:asciiname":"Munanira",
    "gn:country_code":"RW",
    "gn:dem":1668,
    "gn:feature_class":"P",
    "gn:feature_code":"PPLL",
    "gn:name":"Munanira",
    "gn:population":0,
    "gn:timezone":"Africa/Kigali",
    "iso:country":"RW",
    "wof:name":"Munanira",
    "wof:placetype":"locality"
},
  "geometry": {"coordinates":[29.4002,-2.0966],"type":"Point"}
}