{
  "type": "Feature",
  "properties": {
    "gn:admin1_code":"13",
    "gn:admin2_code":"43.0",
    "gn:admin3_code":"4307.0",
    "gn:admin4_code":"430702.0",
    "gn:asciiname":"Nyarusizi",
    "gn:country_code":"RW",
    "gn:dem":2686,
    "gn:feature_class":"P",
    "gn:feature_code":"PPLL",
    "gn:name":"Nyarusizi",
    "gn:population":0,
    "gn:timezone":"Africa/Kigali",
    "iso:country":"RW",
    "wof:name":"Nyarusizi",
    "wof:placetype":"locality"
},
  "geometry": {"coordinates":[29.5088,-1.4409],"type":"Point"}
}