{
  "type": "Feature",
  "properties": {
    "gn:admin1_code":"14",
    "gn:admin2_code":"33.0",
    "gn:admin3_code":"3312.0",
    "gn:admin4_code":"331205.0",
    "gn:asciiname":"Rukingo",
    "gn:country_code":"RW",
    "gn:dem":1679,
    "gn:feature_class":"P",
    "gn:feature_code":"PPLL",
    "gn:name":"Rukingo",
    "gn:population":0,
    "gn:timezone":"Africa/Kigali",
    "iso:country":"RW",
    "wof:name":"Rukingo",
    "wof:placetype":"locality"
},
  "geometry": {"coordinates":[29.3047,-1.6874],"type":"Point"}
}