{
  "type": "Feature",
  "properties": {
    "gn:admin1_code":"15.0",
    "gn:admin2_code":"24",
    "gn:admin3_code":"2410.0",
    "gn:admin4_code":"241005.0",
    "gn:asciiname":"Karama",
    "gn:country_code":"RW",
    "gn:dem":1727,
    "gn:feature_class":"P",
    "gn:feature_code":"PPL",
    "gn:name":"Karama",
    "gn:population":0,
    "gn:timezone":"Africa/Kigali",
    "iso:country":"RW",
    "wof:name":"Karama",
    "wof:placetype":"locality"
},
  "geometry": {"coordinates":[29.7595,-2.5301],"type":"Point"}
}