{
  "type": "Feature",
  "properties": {
    "gn:admin1_code":"15",
    "gn:admin2_code":"27.0",
    "gn:admin3_code":"2704.0",
    "gn:admin4_code":"270402.0",
    "gn:asciiname":"Mushyitsi",
    "gn:country_code":"RW",
    "gn:dem":1591,
    "gn:feature_class":"P",
    "gn:feature_code":"PPLL",
    "gn:name":"Mushyitsi",
    "gn:population":0,
    "gn:timezone":"Africa/Kigali",
    "iso:country":"RW",
    "wof:name":"Mushyitsi",
    "wof:placetype":"locality"
},
  "geometry": {"coordinates":[29.7692,-1.8965],"type":"Point"}
}