{
  "type": "Feature",
  "properties": {
    "gn:admin1_code":"14",
    "gn:admin2_code":"35.0",
    "gn:admin3_code":"3512.0",
    "gn:admin4_code":"351204.0",
    "gn:asciiname":"Vuganyana",
    "gn:country_code":"RW",
    "gn:dem":1800,
    "gn:feature_class":"P",
    "gn:feature_code":"PPLL",
    "gn:name":"Vuganyana",
    "gn:population":0,
    "gn:timezone":"Africa/Kigali",
    "iso:country":"RW",
    "wof:name":"Vuganyana",
    "wof:placetype":"locality"
},
  "geometry": {"coordinates":[29.5737,-2.0348],"type":"Point"}
}