{
  "type": "Feature",
  "properties": {
    "gn:admin1_code":"15.0",
    "gn:admin2_code":"24",
    "gn:admin3_code":"2406.0",
    "gn:admin4_code":"240605.0",
    "gn:asciiname":"Shanga",
    "gn:country_code":"RW",
    "gn:dem":1742,
    "gn:feature_class":"P",
    "gn:feature_code":"PPL",
    "gn:name":"Shanga",
    "gn:population":0,
    "gn:timezone":"Africa/Kigali",
    "iso:country":"RW",
    "name:ceb_x_preferred":[
        "Shanga"
    ],
    "name:swe_x_preferred":[
        "Shanga"
    ],
    "name:und_x_variant":[
        "Colline Sanga",
        "Sanga"
    ],
    "wof:name":"Shanga",
    "wof:placetype":"locality"
},
  "geometry": {"coordinates":[29.6315,-2.5394],"type":"Point"}
}