{
  "type": "Feature",
  "properties": {
    "gn:admin1_code":"15",
    "gn:admin2_code":"26.0",
    "gn:admin3_code":"2609.0",
    "gn:admin4_code":"260908.0",
    "gn:asciiname":"Nyundo",
    "gn:country_code":"RW",
    "gn:dem":1559,
    "gn:feature_class":"P",
    "gn:feature_code":"PPL",
    "gn:name":"Nyundo",
    "gn:population":0,
    "gn:timezone":"Africa/Kigali",
    "iso:country":"RW",
    "name:ceb_x_preferred":[
        "Nyundo"
    ],
    "wof:name":"Nyundo",
    "wof:placetype":"locality"
},
  "geometry": {"coordinates":[29.8296,-2.203],"type":"Point"}
}