{
  "type": "Feature",
  "properties": {
    "gn:admin1_code":"15.0",
    "gn:admin2_code":"24",
    "gn:admin3_code":"2404.0",
    "gn:admin4_code":"240401.0",
    "gn:asciiname":"Busesa",
    "gn:country_code":"RW",
    "gn:dem":1639,
    "gn:feature_class":"P",
    "gn:feature_code":"PPLL",
    "gn:name":"Busesa",
    "gn:population":0,
    "gn:timezone":"Africa/Kigali",
    "iso:country":"RW",
    "wof:name":"Busesa",
    "wof:placetype":"locality"
},
  "geometry": {"coordinates":[29.6424,-2.4988],"type":"Point"}
}