{
  "type": "Feature",
  "properties": {
    "gn:admin1_code":"15",
    "gn:admin2_code":"22.0",
    "gn:admin3_code":"2209.0",
    "gn:admin4_code":"220904.0",
    "gn:asciiname":"Munyegera",
    "gn:country_code":"RW",
    "gn:dem":1365,
    "gn:feature_class":"P",
    "gn:feature_code":"PPLL",
    "gn:name":"Munyegera",
    "gn:population":0,
    "gn:timezone":"Africa/Kigali",
    "iso:country":"RW",
    "name:swa_x_preferred":[
        "Munyegera"
    ],
    "wof:name":"Munyegera",
    "wof:placetype":"locality"
},
  "geometry": {"coordinates":[29.8973,-2.7112],"type":"Point"}
}