{
  "type": "Feature",
  "properties": {
    "gn:admin1_code":"13",
    "gn:admin2_code":"41.0",
    "gn:admin3_code":"4108.0",
    "gn:admin4_code":"410805.0",
    "gn:asciiname":"Mpamo",
    "gn:country_code":"RW",
    "gn:dem":2090,
    "gn:feature_class":"P",
    "gn:feature_code":"PPL",
    "gn:name":"Mpamo",
    "gn:population":0,
    "gn:timezone":"Africa/Kigali",
    "iso:country":"RW",
    "wof:name":"Mpamo",
    "wof:placetype":"locality"
},
  "geometry": {"coordinates":[30.03124,-1.63383],"type":"Point"}
}