{
  "type": "Feature",
  "properties": {
    "gn:admin1_code":"13",
    "gn:admin2_code":"44.0",
    "gn:admin3_code":"4405.0",
    "gn:admin4_code":"440501.0",
    "gn:asciiname":"Akuruheshyi",
    "gn:country_code":"RW",
    "gn:dem":2355,
    "gn:feature_class":"P",
    "gn:feature_code":"PPLL",
    "gn:name":"Akuruheshyi",
    "gn:population":0,
    "gn:timezone":"Africa/Kigali",
    "iso:country":"RW",
    "wof:name":"Akuruheshyi",
    "wof:placetype":"locality"
},
  "geometry": {"coordinates":[29.6903,-1.4187],"type":"Point"}
}