{
  "type": "Feature",
  "properties": {
    "gn:admin1_code":"14",
    "gn:admin2_code":"31.0",
    "gn:admin3_code":"3108.0",
    "gn:admin4_code":"310802.0",
    "gn:asciiname":"Nyabiguli",
    "gn:country_code":"RW",
    "gn:dem":1991,
    "gn:feature_class":"P",
    "gn:feature_code":"PPLL",
    "gn:name":"Nyabiguli",
    "gn:population":0,
    "gn:timezone":"Africa/Kigali",
    "iso:country":"RW",
    "wof:name":"Nyabiguli",
    "wof:placetype":"locality"
},
  "geometry": {"coordinates":[29.4211,-2.227],"type":"Point"}
}