{
  "type": "Feature",
  "properties": {
    "gn:admin1_code":"14.0",
    "gn:admin2_code":"36",
    "gn:admin3_code":"3604.0",
    "gn:admin4_code":"360408.0",
    "gn:asciiname":"Nyamutarama",
    "gn:country_code":"RW",
    "gn:dem":1645,
    "gn:feature_class":"P",
    "gn:feature_code":"PPLL",
    "gn:name":"Nyamutarama",
    "gn:population":0,
    "gn:timezone":"Africa/Kigali",
    "iso:country":"RW",
    "wof:name":"Nyamutarama",
    "wof:placetype":"locality"
},
  "geometry": {"coordinates":[28.94047,-2.60608],"type":"Point"}
}