{
  "type": "Feature",
  "properties": {
    "gn:admin1_code":"13",
    "gn:admin2_code":"41.0",
    "gn:admin3_code":"4116.0",
    "gn:admin4_code":"411603.0",
    "gn:asciiname":"Cyikera",
    "gn:country_code":"RW",
    "gn:dem":1512,
    "gn:feature_class":"P",
    "gn:feature_code":"PPLL",
    "gn:name":"Cyikera",
    "gn:population":0,
    "gn:timezone":"Africa/Kigali",
    "iso:country":"RW",
    "wof:name":"Cyikera",
    "wof:placetype":"locality"
},
  "geometry": {"coordinates":[29.9228,-1.8327],"type":"Point"}
}