{
  "type": "Feature",
  "properties": {
    "gn:admin1_code":"11",
    "gn:admin2_code":"51.0",
    "gn:admin3_code":"5112.0",
    "gn:admin4_code":"511205.0",
    "gn:asciiname":"Cyaruhinda",
    "gn:country_code":"RW",
    "gn:dem":1435,
    "gn:feature_class":"P",
    "gn:feature_code":"PPLL",
    "gn:name":"Cyaruhinda",
    "gn:population":0,
    "gn:timezone":"Africa/Kigali",
    "iso:country":"RW",
    "wof:name":"Cyaruhinda",
    "wof:placetype":"locality"
},
  "geometry": {"coordinates":[30.2626,-2.0872],"type":"Point"}
}