{
  "type": "Feature",
  "properties": {
    "gn:admin1_code":"15.0",
    "gn:admin2_code":"23",
    "gn:admin3_code":"2310.0",
    "gn:admin4_code":"231001.0",
    "gn:asciiname":"Masunzu",
    "gn:country_code":"RW",
    "gn:dem":2103,
    "gn:feature_class":"P",
    "gn:feature_code":"PPL",
    "gn:name":"Masunzu",
    "gn:population":0,
    "gn:timezone":"Africa/Kigali",
    "iso:country":"RW",
    "wof:name":"Masunzu",
    "wof:placetype":"locality"
},
  "geometry": {"coordinates":[29.4637,-2.6987],"type":"Point"}
}