{
  "type": "Feature",
  "properties": {
    "gn:admin1_code":"15",
    "gn:admin2_code":"28.0",
    "gn:admin3_code":"2805.0",
    "gn:admin4_code":"280504.0",
    "gn:asciiname":"Mparo",
    "gn:country_code":"RW",
    "gn:dem":1526,
    "gn:feature_class":"P",
    "gn:feature_code":"PPL",
    "gn:name":"Mparo",
    "gn:population":0,
    "gn:timezone":"Africa/Kigali",
    "iso:country":"RW",
    "name:ceb_x_preferred":[
        "Mparo"
    ],
    "name:swe_x_preferred":[
        "Mparo"
    ],
    "wof:name":"Mparo",
    "wof:placetype":"locality"
},
  "geometry": {"coordinates":[29.9663,-2.1146],"type":"Point"}
}