{
  "type": "Feature",
  "properties": {
    "gn:admin1_code":"13",
    "gn:admin2_code":"44.0",
    "gn:admin3_code":"4408.0",
    "gn:admin4_code":"440804.0",
    "gn:asciiname":"Nyamabuye",
    "gn:country_code":"RW",
    "gn:dem":1916,
    "gn:feature_class":"P",
    "gn:feature_code":"PPLL",
    "gn:name":"Nyamabuye",
    "gn:population":0,
    "gn:timezone":"Africa/Kigali",
    "iso:country":"RW",
    "wof:name":"Nyamabuye",
    "wof:placetype":"locality"
},
  "geometry": {"coordinates":[29.7606,-1.3912],"type":"Point"}
}