{
  "type": "Feature",
  "properties": {
    "gn:admin1_code":"13",
    "gn:admin2_code":"42.0",
    "gn:admin3_code":"4203.0",
    "gn:admin4_code":"420305.0",
    "gn:asciiname":"Mutanda",
    "gn:country_code":"RW",
    "gn:dem":1844,
    "gn:feature_class":"P",
    "gn:feature_code":"PPLL",
    "gn:name":"Mutanda",
    "gn:population":0,
    "gn:timezone":"Africa/Kigali",
    "iso:country":"RW",
    "wof:name":"Mutanda",
    "wof:placetype":"locality"
},
  "geometry": {"coordinates":[29.6831,-1.5862],"type":"Point"}
}