{
  "type": "Feature",
  "properties": {
    "gn:admin1_code":"13.0",
    "gn:admin2_code":"43",
    "gn:admin3_code":"4307.0",
    "gn:admin4_code":"430701.0",
    "gn:asciiname":"Bannyisogo",
    "gn:country_code":"RW",
    "gn:dem":2582,
    "gn:feature_class":"P",
    "gn:feature_code":"PPLL",
    "gn:name":"Bannyisogo",
    "gn:population":0,
    "gn:timezone":"Africa/Kigali",
    "iso:country":"RW",
    "name:und_x_variant":[
        "Banyisongo"
    ],
    "wof:name":"Bannyisogo",
    "wof:placetype":"locality"
},
  "geometry": {"coordinates":[29.5167,-1.4569],"type":"Point"}
}