{
  "type": "Feature",
  "properties": {
    "gn:admin1_code":"11",
    "gn:admin2_code":"56.0",
    "gn:admin3_code":"5613.0",
    "gn:admin4_code":"561301.0",
    "gn:asciiname":"Umurenge",
    "gn:country_code":"RW",
    "gn:dem":1389,
    "gn:feature_class":"P",
    "gn:feature_code":"PPLL",
    "gn:name":"Umurenge",
    "gn:population":0,
    "gn:timezone":"Africa/Kigali",
    "iso:country":"RW",
    "wof:name":"Umurenge",
    "wof:placetype":"locality"
},
  "geometry": {"coordinates":[30.4033,-2.2438],"type":"Point"}
}