{
  "type": "Feature",
  "properties": {
    "gn:admin1_code":"15.0",
    "gn:admin2_code":"25",
    "gn:admin3_code":"2507.0",
    "gn:admin4_code":"250704.0",
    "gn:asciiname":"Muyange",
    "gn:country_code":"RW",
    "gn:dem":1865,
    "gn:feature_class":"P",
    "gn:feature_code":"PPLL",
    "gn:name":"Muyange",
    "gn:population":0,
    "gn:timezone":"Africa/Kigali",
    "iso:country":"RW",
    "name:run_x_preferred":[
        "Muyange"
    ],
    "wof:name":"Muyange",
    "wof:placetype":"locality"
},
  "geometry": {"coordinates":[29.5642,-2.4258],"type":"Point"}
}