{
  "type": "Feature",
  "properties": {
    "gn:admin1_code":"11",
    "gn:admin2_code":"51.0",
    "gn:admin3_code":"5105.0",
    "gn:admin4_code":"510501.0",
    "gn:asciiname":"Gitega",
    "gn:country_code":"RW",
    "gn:dem":1395,
    "gn:feature_class":"P",
    "gn:feature_code":"PPLL",
    "gn:name":"Gitega",
    "gn:population":0,
    "gn:timezone":"Africa/Kigali",
    "iso:country":"RW",
    "wof:name":"Gitega",
    "wof:placetype":"locality"
},
  "geometry": {"coordinates":[30.4505,-1.9677],"type":"Point"}
}