{
  "type": "Feature",
  "properties": {
    "gn:admin1_code":"13",
    "gn:admin2_code":"42.0",
    "gn:admin3_code":"4206.0",
    "gn:admin4_code":"420601.0",
    "gn:asciiname":"Kibonwa",
    "gn:country_code":"RW",
    "gn:dem":1875,
    "gn:feature_class":"P",
    "gn:feature_code":"PPLL",
    "gn:name":"Kibonwa",
    "gn:population":0,
    "gn:timezone":"Africa/Kigali",
    "iso:country":"RW",
    "wof:name":"Kibonwa",
    "wof:placetype":"locality"
},
  "geometry": {"coordinates":[29.6796,-1.6648],"type":"Point"}
}