{
  "type": "Feature",
  "properties": {
    "gn:admin1_code":"11",
    "gn:admin2_code":"54.0",
    "gn:admin3_code":"5406.0",
    "gn:admin4_code":"540604.0",
    "gn:asciiname":"Ngugu",
    "gn:country_code":"RW",
    "gn:dem":1353,
    "gn:feature_class":"P",
    "gn:feature_code":"PPLL",
    "gn:name":"Ngugu",
    "gn:population":0,
    "gn:timezone":"Africa/Kigali",
    "iso:country":"RW",
    "wof:name":"Ngugu",
    "wof:placetype":"locality"
},
  "geometry": {"coordinates":[30.5186,-1.7339],"type":"Point"}
}