{
  "type": "Feature",
  "properties": {
    "gn:admin1_code":"12.0",
    "gn:admin2_code":"11",
    "gn:admin3_code":"1103.0",
    "gn:admin4_code":"110302.0",
    "gn:asciiname":"Mwendo",
    "gn:country_code":"RW",
    "gn:dem":1476,
    "gn:feature_class":"P",
    "gn:feature_code":"PPL",
    "gn:name":"Mwendo",
    "gn:population":0,
    "gn:timezone":"Africa/Kigali",
    "iso:country":"RW",
    "name:und_x_variant":[
        "Colline Mwendo",
        "Mwendo"
    ],
    "wof:name":"Mwendo",
    "wof:placetype":"locality"
},
  "geometry": {"coordinates":[30.0116,-1.9806],"type":"Point"}
}