{
  "type": "Feature",
  "properties": {
    "gn:admin1_code":"13",
    "gn:admin2_code":"43.0",
    "gn:admin3_code":"4311.0",
    "gn:admin4_code":"431104.0",
    "gn:asciiname":"Gisoro",
    "gn:country_code":"RW",
    "gn:dem":2175,
    "gn:feature_class":"P",
    "gn:feature_code":"PPLL",
    "gn:name":"Gisoro",
    "gn:population":0,
    "gn:timezone":"Africa/Kigali",
    "iso:country":"RW",
    "wof:name":"Gisoro",
    "wof:placetype":"locality"
},
  "geometry": {"coordinates":[29.5981,-1.5777],"type":"Point"}
}