{
  "type": "Feature",
  "properties": {
    "gn:admin1_code":"13",
    "gn:admin2_code":"43.0",
    "gn:admin3_code":"4314.0",
    "gn:admin4_code":"431402.0",
    "gn:asciiname":"Murambi",
    "gn:country_code":"RW",
    "gn:dem":1828,
    "gn:feature_class":"P",
    "gn:feature_code":"PPLL",
    "gn:name":"Murambi",
    "gn:population":0,
    "gn:timezone":"Africa/Kigali",
    "iso:country":"RW",
    "name:ita_x_preferred":[
        "Murambi"
    ],
    "wof:name":"Murambi",
    "wof:placetype":"locality"
},
  "geometry": {"coordinates":[29.686,-1.5533],"type":"Point"}
}