{
  "type": "Feature",
  "properties": {
    "gn:admin1_code":"11",
    "gn:admin2_code":"53.0",
    "gn:admin3_code":"5308.0",
    "gn:admin4_code":"530804.0",
    "gn:asciiname":"Ruhinga",
    "gn:country_code":"RW",
    "gn:dem":1658,
    "gn:feature_class":"P",
    "gn:feature_code":"PPLL",
    "gn:name":"Ruhinga",
    "gn:population":0,
    "gn:timezone":"Africa/Kigali",
    "iso:country":"RW",
    "wof:name":"Ruhinga",
    "wof:placetype":"locality"
},
  "geometry": {"coordinates":[30.3079,-1.7425],"type":"Point"}
}