{
  "type": "Feature",
  "properties": {
    "gn:admin1_code":"11.0",
    "gn:admin2_code":"54",
    "gn:admin3_code":"5412.0",
    "gn:admin4_code":"541204.0",
    "gn:asciiname":"Rwinkwavu",
    "gn:country_code":"RW",
    "gn:dem":1380,
    "gn:feature_class":"P",
    "gn:feature_code":"PPL",
    "gn:name":"Rwinkwavu",
    "gn:population":0,
    "gn:timezone":"Africa/Kigali",
    "iso:country":"RW",
    "wof:name":"Rwinkwavu",
    "wof:placetype":"locality"
},
  "geometry": {"coordinates":[30.6111,-1.9588],"type":"Point"}
}