{
  "type": "Feature",
  "properties": {
    "gn:admin1_code":"15.0",
    "gn:admin2_code":"25",
    "gn:admin3_code":"2509.0",
    "gn:admin4_code":"250905.0",
    "gn:asciiname":"Kigali",
    "gn:country_code":"RW",
    "gn:dem":2160,
    "gn:feature_class":"P",
    "gn:feature_code":"PPLL",
    "gn:name":"Kigali",
    "gn:population":0,
    "gn:timezone":"Africa/Kigali",
    "iso:country":"RW",
    "wof:name":"Kigali",
    "wof:placetype":"locality"
},
  "geometry": {"coordinates":[29.4799,-2.5507],"type":"Point"}
}