{
  "type": "Feature",
  "properties": {
    "gn:admin1_code":"11",
    "gn:admin2_code":"51.0",
    "gn:admin3_code":"5113.0",
    "gn:admin4_code":"511301.0",
    "gn:asciiname":"Cyerwa",
    "gn:country_code":"RW",
    "gn:dem":1644,
    "gn:feature_class":"P",
    "gn:feature_code":"PPL",
    "gn:name":"Cyerwa",
    "gn:population":0,
    "gn:timezone":"Africa/Kigali",
    "iso:country":"RW",
    "wof:name":"Cyerwa",
    "wof:placetype":"locality"
},
  "geometry": {"coordinates":[30.3314,-2.0307],"type":"Point"}
}