{
  "type": "Feature",
  "properties": {
    "gn:admin1_code":"14.0",
    "gn:admin2_code":"37",
    "gn:admin3_code":"3714.0",
    "gn:admin4_code":"371403.0",
    "gn:asciiname":"Nyamuhunga",
    "gn:country_code":"RW",
    "gn:dem":1954,
    "gn:feature_class":"P",
    "gn:feature_code":"PPLL",
    "gn:name":"Nyamuhunga",
    "gn:population":0,
    "gn:timezone":"Africa/Kigali",
    "iso:country":"RW",
    "name:und_x_variant":[
        "Colline Nyamuhunga",
        "Nyamuhunga"
    ],
    "wof:name":"Nyamuhunga",
    "wof:placetype":"locality"
},
  "geometry": {"coordinates":[28.9855,-2.4797],"type":"Point"}
}