{
  "type": "Feature",
  "properties": {
    "gn:admin1_code":"12",
    "gn:admin2_code":"11.0",
    "gn:admin3_code":"1105.0",
    "gn:admin4_code":"110503.0",
    "gn:asciiname":"Gahombo",
    "gn:country_code":"RW",
    "gn:dem":1710,
    "gn:feature_class":"P",
    "gn:feature_code":"PPLL",
    "gn:name":"Gahombo",
    "gn:population":0,
    "gn:timezone":"Africa/Kigali",
    "iso:country":"RW",
    "wof:name":"Gahombo",
    "wof:placetype":"locality"
},
  "geometry": {"coordinates":[30.0657,-2.0236],"type":"Point"}
}