{
  "type": "Feature",
  "properties": {
    "gn:admin1_code":"15",
    "gn:admin2_code":"26.0",
    "gn:admin3_code":"2609.0",
    "gn:admin4_code":"260907.0",
    "gn:asciiname":"Kabambati",
    "gn:country_code":"RW",
    "gn:dem":1630,
    "gn:feature_class":"P",
    "gn:feature_code":"PPLL",
    "gn:name":"Kabambati",
    "gn:population":0,
    "gn:timezone":"Africa/Kigali",
    "iso:country":"RW",
    "wof:name":"Kabambati",
    "wof:placetype":"locality"
},
  "geometry": {"coordinates":[29.8014,-2.2604],"type":"Point"}
}