{
  "type": "Feature",
  "properties": {
    "gn:admin1_code":"14",
    "gn:admin2_code":"35.0",
    "gn:admin3_code":"3507.0",
    "gn:admin4_code":"350701.0",
    "gn:asciiname":"Matare",
    "gn:country_code":"RW",
    "gn:dem":1956,
    "gn:feature_class":"P",
    "gn:feature_code":"PPL",
    "gn:name":"Matare",
    "gn:population":0,
    "gn:timezone":"Africa/Kigali",
    "iso:country":"RW",
    "name:und_x_variant":[
        "Mataie"
    ],
    "wof:name":"Matare",
    "wof:placetype":"locality"
},
  "geometry": {"coordinates":[29.6385,-1.7443],"type":"Point"}
}