{
  "type": "Feature",
  "properties": {
    "gn:admin1_code":"15",
    "gn:admin2_code":"23.0",
    "gn:admin3_code":"2301.0",
    "gn:admin4_code":"230102.0",
    "gn:asciiname":"Mutobo",
    "gn:country_code":"RW",
    "gn:dem":2122,
    "gn:feature_class":"P",
    "gn:feature_code":"PPL",
    "gn:name":"Mutobo",
    "gn:population":0,
    "gn:timezone":"Africa/Kigali",
    "iso:country":"RW",
    "wof:name":"Mutobo",
    "wof:placetype":"locality"
},
  "geometry": {"coordinates":[29.5045,-2.8067],"type":"Point"}
}