{
  "type": "Feature",
  "properties": {
    "gn:admin1_code":"15.0",
    "gn:admin2_code":"28",
    "gn:admin3_code":"2801.0",
    "gn:admin4_code":"280102.0",
    "gn:asciiname":"Kibanza",
    "gn:country_code":"RW",
    "gn:dem":1660,
    "gn:feature_class":"P",
    "gn:feature_code":"PPLL",
    "gn:name":"Kibanza",
    "gn:population":0,
    "gn:timezone":"Africa/Kigali",
    "iso:country":"RW",
    "name:und_x_variant":[
        "Colline Kibanza",
        "Kibanza"
    ],
    "wof:name":"Kibanza",
    "wof:placetype":"locality"
},
  "geometry": {"coordinates":[29.8813,-1.954],"type":"Point"}
}