{
  "type": "Feature",
  "properties": {
    "gn:admin1_code":"15",
    "gn:admin2_code":"28.0",
    "gn:admin3_code":"2805.0",
    "gn:admin4_code":"280505.0",
    "gn:asciiname":"Nyagisozi",
    "gn:country_code":"RW",
    "gn:dem":1416,
    "gn:feature_class":"P",
    "gn:feature_code":"PPLL",
    "gn:name":"Nyagisozi",
    "gn:population":0,
    "gn:timezone":"Africa/Kigali",
    "iso:country":"RW",
    "wof:name":"Nyagisozi",
    "wof:placetype":"locality"
},
  "geometry": {"coordinates":[29.9646,-2.0941],"type":"Point"}
}