{
  "type": "Feature",
  "properties": {
    "gn:admin1_code":"11.0",
    "gn:admin2_code":"51",
    "gn:admin3_code":"5103.0",
    "gn:admin4_code":"510307.0",
    "gn:asciiname":"Muhazi",
    "gn:country_code":"RW",
    "gn:dem":1534,
    "gn:feature_class":"P",
    "gn:feature_code":"PPL",
    "gn:name":"Muhazi",
    "gn:population":0,
    "gn:timezone":"Africa/Kigali",
    "iso:country":"RW",
    "name:ita_x_preferred":[
        "Muhazi"
    ],
    "wof:name":"Muhazi",
    "wof:placetype":"locality"
},
  "geometry": {"coordinates":[30.41,-1.9006],"type":"Point"}
}