{
  "type": "Feature",
  "properties": {
    "gn:admin1_code":"14.0",
    "gn:admin2_code":"36",
    "gn:admin3_code":"3617.0",
    "gn:admin4_code":"361704.0",
    "gn:asciiname":"Rufunika",
    "gn:country_code":"RW",
    "gn:dem":1640,
    "gn:feature_class":"P",
    "gn:feature_code":"PPLL",
    "gn:name":"Rufunika",
    "gn:population":0,
    "gn:timezone":"Africa/Kigali",
    "iso:country":"RW",
    "name:und_x_variant":[
        "Rufinika",
        "Rufunika"
    ],
    "wof:name":"Rufunika",
    "wof:placetype":"locality"
},
  "geometry": {"coordinates":[28.9164,-2.6615],"type":"Point"}
}