{
  "type": "Feature",
  "properties": {
    "gn:admin1_code":"15.0",
    "gn:admin2_code":"24",
    "gn:admin3_code":"2404.0",
    "gn:admin4_code":"240404.0",
    "gn:asciiname":"Gitwa",
    "gn:country_code":"RW",
    "gn:dem":1756,
    "gn:feature_class":"P",
    "gn:feature_code":"PPL",
    "gn:name":"Gitwa",
    "gn:population":0,
    "gn:timezone":"Africa/Kigali",
    "iso:country":"RW",
    "wof:name":"Gitwa",
    "wof:placetype":"locality"
},
  "geometry": {"coordinates":[29.6129,-2.5044],"type":"Point"}
}