{
  "type": "Feature",
  "properties": {
    "gn:admin1_code":"15",
    "gn:admin2_code":"28.0",
    "gn:admin3_code":"2804.0",
    "gn:admin4_code":"280403.0",
    "gn:asciiname":"MU GAHINGA Village",
    "gn:country_code":"RW",
    "gn:dem":1748,
    "gn:feature_class":"P",
    "gn:feature_code":"PPLL",
    "gn:name":"MU GAHINGA Village",
    "gn:population":0,
    "gn:timezone":"Africa/Kigali",
    "iso:country":"RW",
    "wof:name":"MU GAHINGA Village",
    "wof:placetype":"locality"
},
  "geometry": {"coordinates":[29.799,-1.93741],"type":"Point"}
}