{
  "type": "Feature",
  "properties": {
    "gn:admin1_code":"11",
    "gn:admin2_code":"57.0",
    "gn:admin3_code":"5708.0",
    "gn:admin4_code":"570801.0",
    "gn:asciiname":"Buhara",
    "gn:country_code":"RW",
    "gn:dem":1411,
    "gn:feature_class":"P",
    "gn:feature_code":"PPLL",
    "gn:name":"Buhara",
    "gn:population":0,
    "gn:timezone":"Africa/Kigali",
    "iso:country":"RW",
    "wof:name":"Buhara",
    "wof:placetype":"locality"
},
  "geometry": {"coordinates":[30.1238,-2.2746],"type":"Point"}
}