{
  "type": "Feature",
  "properties": {
    "gn:admin1_code":"15",
    "gn:admin2_code":"26.0",
    "gn:admin3_code":"2608.0",
    "gn:admin4_code":"260806.0",
    "gn:asciiname":"Karama",
    "gn:country_code":"RW",
    "gn:dem":1501,
    "gn:feature_class":"P",
    "gn:feature_code":"PPLL",
    "gn:name":"Karama",
    "gn:population":0,
    "gn:timezone":"Africa/Kigali",
    "iso:country":"RW",
    "wof:name":"Karama",
    "wof:placetype":"locality"
},
  "geometry": {"coordinates":[29.896,-2.2005],"type":"Point"}
}