{
  "type": "Feature",
  "properties": {
    "gn:admin1_code":"13.0",
    "gn:admin2_code":"45",
    "gn:admin3_code":"4502.0",
    "gn:admin4_code":"450201.0",
    "gn:asciiname":"Kilambi",
    "gn:cc2":"RW",
    "gn:country_code":"RW",
    "gn:dem":1880,
    "gn:feature_class":"P",
    "gn:feature_code":"PPLL",
    "gn:name":"Kilambi",
    "gn:population":0,
    "gn:timezone":"Africa/Kigali",
    "iso:country":"RW",
    "name:und_x_variant":[
        "Colline Kilambi",
        "Kilambi"
    ],
    "wof:name":"Kilambi",
    "wof:placetype":"locality"
},
  "geometry": {"coordinates":[30.15,-1.56667],"type":"Point"}
}