{
  "type": "Feature",
  "properties": {
    "gn:admin1_code":"15.0",
    "gn:admin2_code":"24",
    "gn:admin3_code":"2404.0",
    "gn:admin4_code":"240406.0",
    "gn:asciiname":"Kibuye",
    "gn:country_code":"RW",
    "gn:dem":1708,
    "gn:feature_class":"P",
    "gn:feature_code":"PPLL",
    "gn:name":"Kibuye",
    "gn:population":0,
    "gn:timezone":"Africa/Kigali",
    "iso:country":"RW",
    "name:ceb_x_preferred":[
        "Kibuye"
    ],
    "name:swe_x_preferred":[
        "Kibuye"
    ],
    "wof:name":"Kibuye",
    "wof:placetype":"locality"
},
  "geometry": {"coordinates":[29.6363,-2.4568],"type":"Point"}
}