{
  "type": "Feature",
  "properties": {
    "gn:admin1_code":"11",
    "gn:admin2_code":"51.0",
    "gn:admin3_code":"5106.0",
    "gn:admin4_code":"510604.0",
    "gn:asciiname":"Gatare",
    "gn:country_code":"RW",
    "gn:dem":1524,
    "gn:feature_class":"P",
    "gn:feature_code":"PPLL",
    "gn:name":"Gatare",
    "gn:population":0,
    "gn:timezone":"Africa/Kigali",
    "iso:country":"RW",
    "wof:name":"Gatare",
    "wof:placetype":"locality"
},
  "geometry": {"coordinates":[30.4424,-1.9206],"type":"Point"}
}