{
  "type": "Feature",
  "properties": {
    "gn:admin1_code":"11",
    "gn:admin2_code":"53.0",
    "gn:admin3_code":"5312.0",
    "gn:admin4_code":"531202.0",
    "gn:asciiname":"Urubare",
    "gn:country_code":"RW",
    "gn:dem":1770,
    "gn:feature_class":"P",
    "gn:feature_code":"PPLL",
    "gn:name":"Urubare",
    "gn:population":0,
    "gn:timezone":"Africa/Kigali",
    "iso:country":"RW",
    "wof:name":"Urubare",
    "wof:placetype":"locality"
},
  "geometry": {"coordinates":[30.3096,-1.7015],"type":"Point"}
}