{
  "type": "Feature",
  "properties": {
    "gn:admin1_code":"15.0",
    "gn:admin2_code":"21",
    "gn:admin3_code":"2101.0",
    "gn:admin4_code":"210105.0",
    "gn:asciiname":"Taba",
    "gn:country_code":"RW",
    "gn:dem":1667,
    "gn:feature_class":"P",
    "gn:feature_code":"PPLL",
    "gn:name":"Taba",
    "gn:population":0,
    "gn:timezone":"Africa/Kigali",
    "iso:country":"RW",
    "name:ceb_x_preferred":[
        "Taba"
    ],
    "name:deu_x_preferred":[
        "Taba"
    ],
    "name:fra_x_preferred":[
        "Taba"
    ],
    "name:nld_x_preferred":[
        "Taba"
    ],
    "name:spa_x_preferred":[
        "Taba"
    ],
    "name:swe_x_preferred":[
        "Taba"
    ],
    "wof:name":"Taba",
    "wof:placetype":"locality"
},
  "geometry": {"coordinates":[29.736,-2.3805],"type":"Point"}
}