{
  "type": "Feature",
  "properties": {
    "gn:admin1_code":"15.0",
    "gn:admin2_code":"22",
    "gn:admin3_code":"2211.0",
    "gn:admin4_code":"221102.0",
    "gn:asciiname":"Cyamukuza",
    "gn:country_code":"RW",
    "gn:dem":1649,
    "gn:feature_class":"P",
    "gn:feature_code":"PPL",
    "gn:name":"Cyamukuza",
    "gn:population":0,
    "gn:timezone":"Africa/Kigali",
    "iso:country":"RW",
    "name:und_x_variant":[
        "Shyamukuza",
        "Cyamukuza",
        "Ghyamukuza"
    ],
    "wof:name":"Cyamukuza",
    "wof:placetype":"locality"
},
  "geometry": {"coordinates":[29.8229,-2.5852],"type":"Point"}
}