{
  "type": "Feature",
  "properties": {
    "gn:admin1_code":"13.0",
    "gn:admin2_code":"42",
    "gn:admin3_code":"4209.0",
    "gn:admin4_code":"420905.0",
    "gn:asciiname":"Mugamba",
    "gn:country_code":"RW",
    "gn:dem":2312,
    "gn:feature_class":"P",
    "gn:feature_code":"PPLL",
    "gn:name":"Mugamba",
    "gn:population":0,
    "gn:timezone":"Africa/Kigali",
    "iso:country":"RW",
    "name:run_x_preferred":[
        "Mugamba"
    ],
    "name:und_x_variant":[
        "Colline Mugamba"
    ],
    "wof:name":"Mugamba",
    "wof:placetype":"locality"
},
  "geometry": {"coordinates":[29.763,-1.5801],"type":"Point"}
}