{
  "type": "Feature",
  "properties": {
    "gn:admin1_code":"14",
    "gn:admin2_code":"33.0",
    "gn:admin3_code":"3303.0",
    "gn:admin4_code":"330305.0",
    "gn:asciiname":"Kabere",
    "gn:country_code":"RW",
    "gn:dem":2092,
    "gn:feature_class":"P",
    "gn:feature_code":"PPL",
    "gn:name":"Kabere",
    "gn:population":0,
    "gn:timezone":"Africa/Kigali",
    "iso:country":"RW",
    "wof:name":"Kabere",
    "wof:placetype":"locality"
},
  "geometry": {"coordinates":[29.349,-1.6378],"type":"Point"}
}