{
  "type": "Feature",
  "properties": {
    "gn:admin1_code":"13.0",
    "gn:admin2_code":"45",
    "gn:admin3_code":"4515.0",
    "gn:admin4_code":"451501.0",
    "gn:asciiname":"Rubaya",
    "gn:country_code":"RW",
    "gn:dem":2164,
    "gn:feature_class":"P",
    "gn:feature_code":"PPLL",
    "gn:name":"Rubaya",
    "gn:population":0,
    "gn:timezone":"Africa/Kigali",
    "iso:country":"RW",
    "name:und_x_variant":[
        "Murubaya"
    ],
    "wof:name":"Rubaya",
    "wof:placetype":"locality"
},
  "geometry": {"coordinates":[30.00244,-1.47461],"type":"Point"}
}