{
  "type": "Feature",
  "properties": {
    "gn:admin1_code":"11",
    "gn:admin2_code":"51.0",
    "gn:admin3_code":"5101.0",
    "gn:admin4_code":"510104.0",
    "gn:asciiname":"Ntungamo",
    "gn:country_code":"RW",
    "gn:dem":1551,
    "gn:feature_class":"P",
    "gn:feature_code":"PPLL",
    "gn:name":"Ntungamo",
    "gn:population":0,
    "gn:timezone":"Africa/Kigali",
    "iso:country":"RW",
    "name:bar_x_preferred":[
        "Ntungamo"
    ],
    "name:ben_x_preferred":[
        "\u098f\u09a8\u09cd\u09a4\u09c1\u0999\u09cd\u0997\u09be\u09ae\u09cb"
    ],
    "name:ceb_x_preferred":[
        "Ntungamo"
    ],
    "name:deu_x_preferred":[
        "Ntungamo"
    ],
    "name:fas_x_preferred":[
        "\u0627\u0646\u062a\u0648\u0646\u06af\u0627\u0645\u0648"
    ],
    "name:fra_x_preferred":[
        "Ntungamo"
    ],
    "name:heb_x_preferred":[
        "\u05e0\u05d8\u05d5\u05e0\u05d2\u05d0\u05de\u05d5"
    ],
    "name:hin_x_preferred":[
        "\u090f\u0902\u0924\u0941\u0902\u0917\u092e\u094b"
    ],
    "name:hun_x_preferred":[
        "Ntungamo"
    ],
    "name:ind_x_preferred":[
        "Ntungamo"
    ],
    "name:ita_x_preferred":[
        "Ntungamo"
    ],
    "name:kor_x_preferred":[
        "\uc740\ud241\uac00\ubaa8"
    ],
    "name:nld_x_preferred":[
        "Ntungamo"
    ],
    "name:ron_x_preferred":[
        "Ntungamo"
    ],
    "name:spa_x_preferred":[
        "Ntungamo"
    ],
    "name:swa_x_preferred":[
        "Ntungamo"
    ],
    "name:swe_x_preferred":[
        "Ntungamo"
    ],
    "name:tur_x_preferred":[
        "Ntungamo"
    ],
    "name:ukr_x_preferred":[
        "\u041d\u0442\u0443\u043d\u0433\u0430\u043c\u043e"
    ],
    "name:urd_x_preferred":[
        "\u0646\u062a\u0648\u0646\u06af\u0627\u0645\u0648"
    ],
    "name:vie_x_preferred":[
        "Ntungamo"
    ],
    "name:zho_cn_x_preferred":[
        "\u6069\u901a\u52a0\u83ab"
    ],
    "name:zho_tw_x_preferred":[
        "\u6069\u901a\u52a0\u83ab"
    ],
    "wof:name":"Ntungamo",
    "wof:placetype":"locality"
},
  "geometry": {"coordinates":[30.2536,-1.8536],"type":"Point"}
}