{
  "type": "Feature",
  "properties": {
    "gn:admin1_code":"13",
    "gn:asciiname":"Gihuli",
    "gn:country_code":"RW",
    "gn:dem":1953,
    "gn:feature_class":"P",
    "gn:feature_code":"PPLL",
    "gn:name":"Gihuli",
    "gn:population":0,
    "gn:timezone":"Africa/Kigali",
    "iso:country":"RW",
    "wof:name":"Gihuli",
    "wof:placetype":"locality"
},
  "geometry": {"coordinates":[29.6034,-1.5895],"type":"Point"}
}