{
  "type": "Feature",
  "properties": {
    "gn:admin1_code":"14.0",
    "gn:admin2_code":"32",
    "gn:admin3_code":"3204.0",
    "gn:admin4_code":"320406.0",
    "gn:asciiname":"Gashashi",
    "gn:country_code":"RW",
    "gn:dem":1808,
    "gn:feature_class":"P",
    "gn:feature_code":"PPLL",
    "gn:name":"Gashashi",
    "gn:population":0,
    "gn:timezone":"Africa/Kigali",
    "iso:country":"RW",
    "wof:name":"Gashashi",
    "wof:placetype":"locality"
},
  "geometry": {"coordinates":[29.29729,-1.79174],"type":"Point"}
}