{
  "type": "Feature",
  "properties": {
    "gn:admin1_code":"15",
    "gn:admin2_code":"28.0",
    "gn:admin3_code":"2803.0",
    "gn:admin4_code":"280302.0",
    "gn:asciiname":"Cubi-Gitwa",
    "gn:country_code":"RW",
    "gn:dem":1702,
    "gn:feature_class":"P",
    "gn:feature_code":"PPLL",
    "gn:name":"Cubi-Gitwa",
    "gn:population":0,
    "gn:timezone":"Africa/Kigali",
    "iso:country":"RW",
    "wof:name":"Cubi-Gitwa",
    "wof:placetype":"locality"
},
  "geometry": {"coordinates":[29.8276,-1.8796],"type":"Point"}
}