{
  "type": "Feature",
  "properties": {
    "gn:admin1_code":"12",
    "gn:admin2_code":"13.0",
    "gn:admin3_code":"1308.0",
    "gn:admin4_code":"130806.0",
    "gn:asciiname":"Kanyetabi",
    "gn:country_code":"RW",
    "gn:dem":1389,
    "gn:feature_class":"P",
    "gn:feature_code":"PPL",
    "gn:name":"Kanyetabi",
    "gn:population":0,
    "gn:timezone":"Africa/Kigali",
    "iso:country":"RW",
    "wof:name":"Kanyetabi",
    "wof:placetype":"locality"
},
  "geometry": {"coordinates":[30.192,-2.03],"type":"Point"}
}