{
  "type": "Feature",
  "properties": {
    "gn:admin1_code":"14",
    "gn:admin2_code":"31.0",
    "gn:admin3_code":"3107.0",
    "gn:admin4_code":"310706.0",
    "gn:asciiname":"Rumarampamba",
    "gn:country_code":"RW",
    "gn:dem":1798,
    "gn:feature_class":"P",
    "gn:feature_code":"PPLL",
    "gn:name":"Rumarampamba",
    "gn:population":0,
    "gn:timezone":"Africa/Kigali",
    "iso:country":"RW",
    "wof:name":"Rumarampamba",
    "wof:placetype":"locality"
},
  "geometry": {"coordinates":[29.5451,-2.1385],"type":"Point"}
}