{
  "type": "Feature",
  "properties": {
    "gn:admin1_code":"13.0",
    "gn:admin2_code":"41",
    "gn:admin3_code":"4102.0",
    "gn:admin4_code":"410201.0",
    "gn:asciiname":"Kisigiro",
    "gn:country_code":"RW",
    "gn:dem":1738,
    "gn:feature_class":"P",
    "gn:feature_code":"PPLL",
    "gn:name":"Kisigiro",
    "gn:population":0,
    "gn:timezone":"Africa/Kigali",
    "iso:country":"RW",
    "name:und_x_variant":[
        "Colline Kisigiro",
        "Kisigiro"
    ],
    "wof:name":"Kisigiro",
    "wof:placetype":"locality"
},
  "geometry": {"coordinates":[30.0517,-1.7336],"type":"Point"}
}