{
  "type": "Feature",
  "properties": {
    "gn:admin1_code":"13.0",
    "gn:admin2_code":"42",
    "gn:admin3_code":"4214.0",
    "gn:admin4_code":"421405.0",
    "gn:asciiname":"Gisozi",
    "gn:country_code":"RW",
    "gn:dem":1564,
    "gn:feature_class":"P",
    "gn:feature_code":"PPLL",
    "gn:name":"Gisozi",
    "gn:population":0,
    "gn:timezone":"Africa/Kigali",
    "iso:country":"RW",
    "name:ceb_x_preferred":[
        "Gisozi"
    ],
    "name:ita_x_preferred":[
        "Gisozi"
    ],
    "name:swe_x_preferred":[
        "Gisozi"
    ],
    "name:und_x_variant":[
        "Colline Gisodzi",
        "Gisodzi",
        "Gisozi"
    ],
    "wof:name":"Gisozi",
    "wof:placetype":"locality"
},
  "geometry": {"coordinates":[29.8894,-1.7858],"type":"Point"}
}