{
  "type": "Feature",
  "properties": {
    "gn:admin1_code":"14",
    "gn:admin2_code":"34.0",
    "gn:admin3_code":"3403.0",
    "gn:admin4_code":"340304.0",
    "gn:asciiname":"Ngabo",
    "gn:country_code":"RW",
    "gn:dem":2255,
    "gn:feature_class":"P",
    "gn:feature_code":"PPLL",
    "gn:name":"Ngabo",
    "gn:population":0,
    "gn:timezone":"Africa/Kigali",
    "iso:country":"RW",
    "wof:name":"Ngabo",
    "wof:placetype":"locality"
},
  "geometry": {"coordinates":[29.5623,-1.7332],"type":"Point"}
}