{
  "type": "Feature",
  "properties": {
    "gn:admin1_code":"13",
    "gn:admin2_code":"45.0",
    "gn:admin3_code":"4504.0",
    "gn:admin4_code":"450401.0",
    "gn:asciiname":"Mugera",
    "gn:country_code":"RW",
    "gn:dem":2005,
    "gn:feature_class":"P",
    "gn:feature_code":"PPLL",
    "gn:name":"Mugera",
    "gn:population":0,
    "gn:timezone":"Africa/Kigali",
    "iso:country":"RW",
    "wof:name":"Mugera",
    "wof:placetype":"locality"
},
  "geometry": {"coordinates":[30.0196,-1.5061],"type":"Point"}
}