{
  "type": "Feature",
  "properties": {
    "gn:admin1_code":"11.0",
    "gn:admin2_code":"52",
    "gn:admin3_code":"5206.0",
    "gn:admin4_code":"520608.0",
    "gn:asciiname":"Kakole",
    "gn:country_code":"RW",
    "gn:dem":1306,
    "gn:feature_class":"P",
    "gn:feature_code":"PPLL",
    "gn:name":"Kakole",
    "gn:population":0,
    "gn:timezone":"Africa/Kigali",
    "iso:country":"RW",
    "name:und_x_variant":[
        "Colline Kakole",
        "Kakole"
    ],
    "wof:name":"Kakole",
    "wof:placetype":"locality"
},
  "geometry": {"coordinates":[30.41667,-1.06667],"type":"Point"}
}