{
  "type": "Feature",
  "properties": {
    "gn:admin1_code":"12",
    "gn:admin2_code":"12.0",
    "gn:admin3_code":"1201.0",
    "gn:admin4_code":"120103.0",
    "gn:asciiname":"Kiyoro",
    "gn:country_code":"RW",
    "gn:dem":1650,
    "gn:feature_class":"P",
    "gn:feature_code":"PPLL",
    "gn:name":"Kiyoro",
    "gn:population":0,
    "gn:timezone":"Africa/Kigali",
    "iso:country":"RW",
    "wof:name":"Kiyoro",
    "wof:placetype":"locality"
},
  "geometry": {"coordinates":[30.1379,-1.8903],"type":"Point"}
}