{
  "type": "Feature",
  "properties": {
    "gn:admin1_code":"11",
    "gn:admin2_code":"56.0",
    "gn:admin3_code":"5607.0",
    "gn:admin4_code":"560702.0",
    "gn:asciiname":"Kigabiro",
    "gn:country_code":"RW",
    "gn:dem":1591,
    "gn:feature_class":"P",
    "gn:feature_code":"PPLL",
    "gn:name":"Kigabiro",
    "gn:population":0,
    "gn:timezone":"Africa/Kigali",
    "iso:country":"RW",
    "wof:name":"Kigabiro",
    "wof:placetype":"locality"
},
  "geometry": {"coordinates":[30.5864,-2.2003],"type":"Point"}
}