{
  "type": "Feature",
  "properties": {
    "gn:admin1_code":"15",
    "gn:admin2_code":"26.0",
    "gn:admin3_code":"2604.0",
    "gn:admin4_code":"260405.0",
    "gn:asciiname":"Gitwa",
    "gn:country_code":"RW",
    "gn:dem":1440,
    "gn:feature_class":"P",
    "gn:feature_code":"PPL",
    "gn:name":"Gitwa",
    "gn:population":0,
    "gn:timezone":"Africa/Kigali",
    "iso:country":"RW",
    "wof:name":"Gitwa",
    "wof:placetype":"locality"
},
  "geometry": {"coordinates":[29.9611,-2.2144],"type":"Point"}
}