{
  "type": "Feature",
  "properties": {
    "gn:admin1_code":"13",
    "gn:admin2_code":"43.0",
    "gn:admin3_code":"4307.0",
    "gn:admin4_code":"430701.0",
    "gn:asciiname":"Bushokoro",
    "gn:country_code":"RW",
    "gn:dem":2748,
    "gn:feature_class":"P",
    "gn:feature_code":"PPLL",
    "gn:name":"Bushokoro",
    "gn:population":0,
    "gn:timezone":"Africa/Kigali",
    "iso:country":"RW",
    "wof:name":"Bushokoro",
    "wof:placetype":"locality"
},
  "geometry": {"coordinates":[29.5104,-1.4681],"type":"Point"}
}