{
  "type": "Feature",
  "properties": {
    "gn:admin1_code":"11",
    "gn:admin2_code":"55.0",
    "gn:admin3_code":"5501.0",
    "gn:admin4_code":"550106.0",
    "gn:asciiname":"Kagarama",
    "gn:country_code":"RW",
    "gn:dem":1461,
    "gn:feature_class":"P",
    "gn:feature_code":"PPLL",
    "gn:name":"Kagarama",
    "gn:population":0,
    "gn:timezone":"Africa/Kigali",
    "iso:country":"RW",
    "wof:name":"Kagarama",
    "wof:placetype":"locality"
},
  "geometry": {"coordinates":[30.5137,-2.3274],"type":"Point"}
}