{
  "type": "Feature",
  "properties": {
    "gn:admin1_code":"11",
    "gn:admin2_code":"52.0",
    "gn:admin3_code":"5208.0",
    "gn:admin4_code":"520806.0",
    "gn:asciiname":"Nyagatare",
    "gn:country_code":"RW",
    "gn:dem":1464,
    "gn:feature_class":"P",
    "gn:feature_code":"PPLL",
    "gn:name":"Nyagatare",
    "gn:population":0,
    "gn:timezone":"Africa/Kigali",
    "iso:country":"RW",
    "name:cat_x_preferred":[
        "Nyagatare"
    ],
    "name:ceb_x_preferred":[
        "Nyagatare"
    ],
    "name:ell_x_preferred":[
        "\u039d\u03c5\u03b1\u03b3\u03ba\u03b1\u03c4\u03ac\u03c1\u03b5"
    ],
    "name:est_x_preferred":[
        "Nyagatare"
    ],
    "name:fra_x_preferred":[
        "Nyagatare"
    ],
    "name:ita_x_preferred":[
        "Nyagatare"
    ],
    "name:lit_x_preferred":[
        "Njagatar\u0117"
    ],
    "name:pol_x_preferred":[
        "Nyagatare"
    ],
    "name:zho_x_preferred":[
        "\u5c3c\u4e9e\u52a0\u5854\u96f7"
    ],
    "wof:name":"Nyagatare",
    "wof:placetype":"locality"
},
  "geometry": {"coordinates":[30.1955,-1.4233],"type":"Point"}
}