{
  "type": "Feature",
  "properties": {
    "gn:admin1_code":"13",
    "gn:admin2_code":"44.0",
    "gn:admin3_code":"4409.0",
    "gn:admin4_code":"440904.0",
    "gn:asciiname":"Gikoro",
    "gn:country_code":"RW",
    "gn:dem":1793,
    "gn:feature_class":"P",
    "gn:feature_code":"PPL",
    "gn:name":"Gikoro",
    "gn:population":0,
    "gn:timezone":"Africa/Kigali",
    "iso:country":"RW",
    "wof:name":"Gikoro",
    "wof:placetype":"locality"
},
  "geometry": {"coordinates":[29.7362,-1.4708],"type":"Point"}
}