{
  "type": "Feature",
  "properties": {
    "gn:admin1_code":"14",
    "gn:admin2_code":"34.0",
    "gn:admin3_code":"3408.0",
    "gn:admin4_code":"340804.0",
    "gn:asciiname":"Nkomane",
    "gn:country_code":"RW",
    "gn:dem":2378,
    "gn:feature_class":"P",
    "gn:feature_code":"PPLL",
    "gn:name":"Nkomane",
    "gn:population":0,
    "gn:timezone":"Africa/Kigali",
    "iso:country":"RW",
    "wof:name":"Nkomane",
    "wof:placetype":"locality"
},
  "geometry": {"coordinates":[29.5246,-1.7301],"type":"Point"}
}