{
  "type": "Feature",
  "properties": {
    "gn:admin1_code":"15",
    "gn:admin2_code":"28.0",
    "gn:admin3_code":"2812.0",
    "gn:admin4_code":"281204.0",
    "gn:asciiname":"Musebeya",
    "gn:country_code":"RW",
    "gn:dem":1567,
    "gn:feature_class":"P",
    "gn:feature_code":"PPLL",
    "gn:name":"Musebeya",
    "gn:population":0,
    "gn:timezone":"Africa/Kigali",
    "iso:country":"RW",
    "wof:name":"Musebeya",
    "wof:placetype":"locality"
},
  "geometry": {"coordinates":[29.9705,-1.9526],"type":"Point"}
}