{
  "type": "Feature",
  "properties": {
    "gn:admin1_code":"11",
    "gn:admin2_code":"56.0",
    "gn:admin3_code":"5614.0",
    "gn:admin4_code":"561402.0",
    "gn:asciiname":"Kilira",
    "gn:country_code":"RW",
    "gn:dem":1422,
    "gn:feature_class":"P",
    "gn:feature_code":"PPLL",
    "gn:name":"Kilira",
    "gn:population":0,
    "gn:timezone":"Africa/Kigali",
    "iso:country":"RW",
    "wof:name":"Kilira",
    "wof:placetype":"locality"
},
  "geometry": {"coordinates":[30.403,-2.1595],"type":"Point"}
}