{
  "type": "Feature",
  "properties": {
    "gn:admin1_code":"14",
    "gn:admin2_code":"37.0",
    "gn:admin3_code":"3704.0",
    "gn:admin4_code":"370404.0",
    "gn:asciiname":"Rusuzumiro",
    "gn:country_code":"RW",
    "gn:dem":1518,
    "gn:feature_class":"P",
    "gn:feature_code":"PPLL",
    "gn:name":"Rusuzumiro",
    "gn:population":0,
    "gn:timezone":"Africa/Kigali",
    "iso:country":"RW",
    "wof:name":"Rusuzumiro",
    "wof:placetype":"locality"
},
  "geometry": {"coordinates":[29.2633,-2.1691],"type":"Point"}
}