{
  "type": "Feature",
  "properties": {
    "gn:admin1_code":"11",
    "gn:admin2_code":"53.0",
    "gn:admin3_code":"5312.0",
    "gn:admin4_code":"531201.0",
    "gn:asciiname":"Nkoronko",
    "gn:country_code":"RW",
    "gn:dem":1569,
    "gn:feature_class":"P",
    "gn:feature_code":"PPLL",
    "gn:name":"Nkoronko",
    "gn:population":0,
    "gn:timezone":"Africa/Kigali",
    "iso:country":"RW",
    "wof:name":"Nkoronko",
    "wof:placetype":"locality"
},
  "geometry": {"coordinates":[30.3564,-1.7309],"type":"Point"}
}