{
  "type": "Feature",
  "properties": {
    "gn:admin1_code":"15.0",
    "gn:admin2_code":"25",
    "gn:admin3_code":"2501.0",
    "gn:admin4_code":"250104.0",
    "gn:asciiname":"Mujerenge",
    "gn:country_code":"RW",
    "gn:dem":2369,
    "gn:feature_class":"P",
    "gn:feature_code":"PPLL",
    "gn:name":"Mujerenge",
    "gn:population":0,
    "gn:timezone":"Africa/Kigali",
    "iso:country":"RW",
    "wof:name":"Mujerenge",
    "wof:placetype":"locality"
},
  "geometry": {"coordinates":[29.4043,-2.4413],"type":"Point"}
}