{
  "type": "Feature",
  "properties": {
    "gn:admin1_code":"13.0",
    "gn:admin2_code":"45",
    "gn:admin3_code":"4518.0",
    "gn:admin4_code":"451803.0",
    "gn:asciiname":"Kabira",
    "gn:country_code":"RW",
    "gn:dem":2092,
    "gn:feature_class":"P",
    "gn:feature_code":"PPL",
    "gn:name":"Kabira",
    "gn:population":0,
    "gn:timezone":"Africa/Kigali",
    "iso:country":"RW",
    "name:ceb_x_preferred":[
        "Kabira"
    ],
    "name:swe_x_preferred":[
        "Kabira"
    ],
    "name:und_x_variant":[
        "Colline Kukabira",
        "Kukabira"
    ],
    "wof:name":"Kabira",
    "wof:placetype":"locality"
},
  "geometry": {"coordinates":[30.179,-1.7284],"type":"Point"}
}