{
  "type": "Feature",
  "properties": {
    "gn:admin1_code":"11.0",
    "gn:admin2_code":"52",
    "gn:admin3_code":"5206.0",
    "gn:admin4_code":"520604.0",
    "gn:asciiname":"Kagitumba",
    "gn:country_code":"RW",
    "gn:dem":1299,
    "gn:feature_class":"P",
    "gn:feature_code":"PPLL",
    "gn:name":"Kagitumba",
    "gn:population":0,
    "gn:timezone":"Africa/Kigali",
    "iso:country":"RW",
    "name:und_x_variant":[
        "Kanitumba",
        "Kakitumba",
        "Kagitumba"
    ],
    "wof:name":"Kagitumba",
    "wof:placetype":"locality"
},
  "geometry": {"coordinates":[30.4451,-1.0625],"type":"Point"}
}