{
  "type": "Feature",
  "properties": {
    "gn:admin1_code":"14.0",
    "gn:admin2_code":"35",
    "gn:admin3_code":"3508.0",
    "gn:admin4_code":"350801.0",
    "gn:asciiname":"Muhumyo",
    "gn:country_code":"RW",
    "gn:dem":2415,
    "gn:feature_class":"P",
    "gn:feature_code":"PPLL",
    "gn:name":"Muhumyo",
    "gn:population":0,
    "gn:timezone":"Africa/Kigali",
    "iso:country":"RW",
    "wof:name":"Muhumyo",
    "wof:placetype":"locality"
},
  "geometry": {"coordinates":[29.4874,-1.7939],"type":"Point"}
}