{
  "type": "Feature",
  "properties": {
    "gn:admin1_code":"15",
    "gn:admin2_code":"22.0",
    "gn:admin3_code":"2206.0",
    "gn:admin4_code":"220603.0",
    "gn:asciiname":"Kirase",
    "gn:country_code":"RW",
    "gn:dem":1415,
    "gn:feature_class":"P",
    "gn:feature_code":"PPLL",
    "gn:name":"Kirase",
    "gn:population":0,
    "gn:timezone":"Africa/Kigali",
    "iso:country":"RW",
    "wof:name":"Kirase",
    "wof:placetype":"locality"
},
  "geometry": {"coordinates":[29.9258,-2.4856],"type":"Point"}
}