{
  "type": "Feature",
  "properties": {
    "gn:admin1_code":"14",
    "gn:admin2_code":"33.0",
    "gn:admin3_code":"3304.0",
    "gn:admin4_code":"330401.0",
    "gn:asciiname":"Mubuga",
    "gn:country_code":"RW",
    "gn:dem":1524,
    "gn:feature_class":"P",
    "gn:feature_code":"PPL",
    "gn:name":"Mubuga",
    "gn:population":0,
    "gn:timezone":"Africa/Kigali",
    "iso:country":"RW",
    "wof:name":"Mubuga",
    "wof:placetype":"locality"
},
  "geometry": {"coordinates":[29.2643,-1.6923],"type":"Point"}
}