{
  "type": "Feature",
  "properties": {
    "gn:admin1_code":"11",
    "gn:admin2_code":"54.0",
    "gn:admin3_code":"5411.0",
    "gn:admin4_code":"541102.0",
    "gn:asciiname":"Agatare",
    "gn:country_code":"RW",
    "gn:dem":1405,
    "gn:feature_class":"P",
    "gn:feature_code":"PPLL",
    "gn:name":"Agatare",
    "gn:population":0,
    "gn:timezone":"Africa/Kigali",
    "iso:country":"RW",
    "wof:name":"Agatare",
    "wof:placetype":"locality"
},
  "geometry": {"coordinates":[30.474,-1.96],"type":"Point"}
}