{
  "type": "Feature",
  "properties": {
    "gn:admin1_code":"15",
    "gn:admin2_code":"27.0",
    "gn:admin3_code":"2701.0",
    "gn:admin4_code":"270106.0",
    "gn:asciiname":"Kankuri",
    "gn:country_code":"RW",
    "gn:dem":1733,
    "gn:feature_class":"P",
    "gn:feature_code":"PPLL",
    "gn:name":"Kankuri",
    "gn:population":0,
    "gn:timezone":"Africa/Kigali",
    "iso:country":"RW",
    "wof:name":"Kankuri",
    "wof:placetype":"locality"
},
  "geometry": {"coordinates":[29.7715,-2.0104],"type":"Point"}
}