{
  "type": "Feature",
  "properties": {
    "gn:admin1_code":"15.0",
    "gn:admin2_code":"25",
    "gn:admin3_code":"2505.0",
    "gn:admin4_code":"250504.0",
    "gn:asciiname":"Muduha",
    "gn:country_code":"RW",
    "gn:dem":1773,
    "gn:feature_class":"P",
    "gn:feature_code":"PPLL",
    "gn:name":"Muduha",
    "gn:population":0,
    "gn:timezone":"Africa/Kigali",
    "iso:country":"RW",
    "wof:name":"Muduha",
    "wof:placetype":"locality"
},
  "geometry": {"coordinates":[29.5519,-2.3443],"type":"Point"}
}