{
  "type": "Feature",
  "properties": {
    "gn:admin1_code":"11.0",
    "gn:admin2_code":"57",
    "gn:admin3_code":"5707.0",
    "gn:admin4_code":"570702.0",
    "gn:asciiname":"Mwogo",
    "gn:country_code":"RW",
    "gn:dem":1374,
    "gn:feature_class":"P",
    "gn:feature_code":"PPLL",
    "gn:name":"Mwogo",
    "gn:population":0,
    "gn:timezone":"Africa/Kigali",
    "iso:country":"RW",
    "wof:name":"Mwogo",
    "wof:placetype":"locality"
},
  "geometry": {"coordinates":[30.13661,-2.0694],"type":"Point"}
}