{
  "type": "Feature",
  "properties": {
    "gn:admin1_code":"13.0",
    "gn:admin2_code":"45",
    "gn:admin3_code":"4510.0",
    "gn:admin4_code":"451002.0",
    "gn:asciiname":"Mugina",
    "gn:country_code":"RW",
    "gn:dem":2019,
    "gn:feature_class":"P",
    "gn:feature_code":"PPLL",
    "gn:name":"Mugina",
    "gn:population":0,
    "gn:timezone":"Africa/Kigali",
    "iso:country":"RW",
    "name:und_x_variant":[
        "Colline Mugina",
        "Mugina"
    ],
    "wof:name":"Mugina",
    "wof:placetype":"locality"
},
  "geometry": {"coordinates":[30.0861,-1.4811],"type":"Point"}
}