{
  "type": "Feature",
  "properties": {
    "gn:admin1_code":"13",
    "gn:admin2_code":"42.0",
    "gn:admin3_code":"4202.0",
    "gn:admin4_code":"420204.0",
    "gn:asciiname":"Nyanza",
    "gn:country_code":"RW",
    "gn:dem":1910,
    "gn:feature_class":"P",
    "gn:feature_code":"PPLL",
    "gn:name":"Nyanza",
    "gn:population":0,
    "gn:timezone":"Africa/Kigali",
    "iso:country":"RW",
    "name:ben_x_preferred":[
        "\u098f\u09a8\u09bf\u09df\u09be\u099e\u09cd\u099c\u09be"
    ],
    "name:bre_x_preferred":[
        "Nyanza"
    ],
    "name:ceb_x_preferred":[
        "Nyanza"
    ],
    "name:deu_x_preferred":[
        "Nyanza"
    ],
    "name:fas_x_preferred":[
        "\u0646\u06cc\u0627\u0646\u0632\u0627"
    ],
    "name:heb_x_preferred":[
        "\u05e0\u05d9\u05d0\u05e0\u05d6\u05d4"
    ],
    "name:hin_x_preferred":[
        "\u0928\u094d\u092f\u093e\u0902\u091c\u093c\u093e"
    ],
    "name:hun_x_preferred":[
        "Nyanza"
    ],
    "name:ind_x_preferred":[
        "Nyanza"
    ],
    "name:ita_x_preferred":[
        "Nyanza"
    ],
    "name:nld_x_preferred":[
        "Nyanza"
    ],
    "name:rus_x_preferred":[
        "\u041d\u044c\u044f\u043d\u0437\u0430"
    ],
    "name:vie_x_preferred":[
        "Nyanza"
    ],
    "wof:name":"Nyanza",
    "wof:placetype":"locality"
},
  "geometry": {"coordinates":[29.8055,-1.7678],"type":"Point"}
}