{
  "type": "Feature",
  "properties": {
    "gn:admin1_code":"13",
    "gn:admin2_code":"42.0",
    "gn:admin3_code":"4202.0",
    "gn:admin4_code":"420204.0",
    "gn:asciiname":"Nyanza",
    "gn:country_code":"RW",
    "gn:dem":1910,
    "gn:feature_class":"P",
    "gn:feature_code":"PPLL",
    "gn:name":"Nyanza",
    "gn:population":0,
    "gn:timezone":"Africa/Kigali",
    "iso:country":"RW",
    "name:bre_x_preferred":[
        "Nyanza"
    ],
    "name:ceb_x_preferred":[
        "Nyanza"
    ],
    "name:deu_x_preferred":[
        "Nyanza"
    ],
    "name:nld_x_preferred":[
        "Nyanza"
    ],
    "name:rus_x_preferred":[
        "\u041d\u044c\u044f\u043d\u0437\u0430"
    ],
    "wof:name":"Nyanza",
    "wof:placetype":"locality"
},
  "geometry": {"coordinates":[29.8055,-1.7678],"type":"Point"}
}