{
  "type": "Feature",
  "properties": {
    "gn:admin1_code":"11",
    "gn:admin2_code":"56.0",
    "gn:admin3_code":"5601.0",
    "gn:admin4_code":"560101.0",
    "gn:asciiname":"Ruyema I",
    "gn:country_code":"RW",
    "gn:dem":1424,
    "gn:feature_class":"P",
    "gn:feature_code":"PPLL",
    "gn:name":"Ruyema I",
    "gn:population":0,
    "gn:timezone":"Africa/Kigali",
    "iso:country":"RW",
    "wof:name":"Ruyema I",
    "wof:placetype":"locality"
},
  "geometry": {"coordinates":[30.4462,-2.2036],"type":"Point"}
}