{
  "type": "Feature",
  "properties": {
    "gn:admin1_code":"13",
    "gn:admin2_code":"42.0",
    "gn:admin3_code":"4205.0",
    "gn:admin4_code":"420502.0",
    "gn:asciiname":"Gahini",
    "gn:country_code":"RW",
    "gn:dem":1663,
    "gn:feature_class":"P",
    "gn:feature_code":"PPLL",
    "gn:name":"Gahini",
    "gn:population":0,
    "gn:timezone":"Africa/Kigali",
    "iso:country":"RW",
    "name:ita_x_preferred":[
        "Gahini"
    ],
    "name:mrj_x_preferred":[
        "\u0413\u0430\u0445\u0438\u043d\u0438"
    ],
    "wof:name":"Gahini",
    "wof:placetype":"locality"
},
  "geometry": {"coordinates":[29.8282,-1.6857],"type":"Point"}
}