{
  "type": "Feature",
  "properties": {
    "gn:admin1_code":"14.0",
    "gn:admin2_code":"36",
    "gn:admin3_code":"3604.0",
    "gn:admin4_code":"360401.0",
    "gn:asciiname":"Kagomero",
    "gn:country_code":"RW",
    "gn:dem":1525,
    "gn:feature_class":"P",
    "gn:feature_code":"PPLL",
    "gn:name":"Kagomero",
    "gn:population":0,
    "gn:timezone":"Africa/Kigali",
    "iso:country":"RW",
    "wof:name":"Kagomero",
    "wof:placetype":"locality"
},
  "geometry": {"coordinates":[28.9671,-2.6067],"type":"Point"}
}