{
  "type": "Feature",
  "properties": {
    "gn:admin1_code":"15",
    "gn:admin2_code":"26.0",
    "gn:admin3_code":"2607.0",
    "gn:admin4_code":"260708.0",
    "gn:asciiname":"Nyakabanda",
    "gn:country_code":"RW",
    "gn:dem":1774,
    "gn:feature_class":"P",
    "gn:feature_code":"PPLL",
    "gn:name":"Nyakabanda",
    "gn:population":0,
    "gn:timezone":"Africa/Kigali",
    "iso:country":"RW",
    "wof:name":"Nyakabanda",
    "wof:placetype":"locality"
},
  "geometry": {"coordinates":[29.7022,-2.18088],"type":"Point"}
}