{
  "type": "Feature",
  "properties": {
    "gn:admin1_code":"14",
    "gn:admin2_code":"33.0",
    "gn:admin3_code":"3305.0",
    "gn:admin4_code":"330506.0",
    "gn:asciiname":"Mashoza",
    "gn:country_code":"RW",
    "gn:dem":2164,
    "gn:feature_class":"P",
    "gn:feature_code":"PPLL",
    "gn:name":"Mashoza",
    "gn:population":0,
    "gn:timezone":"Africa/Kigali",
    "iso:country":"RW",
    "wof:name":"Mashoza",
    "wof:placetype":"locality"
},
  "geometry": {"coordinates":[29.393,-1.7319],"type":"Point"}
}