{
  "type": "Feature",
  "properties": {
    "gn:admin1_code":"15.0",
    "gn:admin2_code":"27",
    "gn:admin3_code":"2706.0",
    "gn:admin4_code":"270603.0",
    "gn:asciiname":"Bugaramantare",
    "gn:country_code":"RW",
    "gn:dem":1763,
    "gn:feature_class":"P",
    "gn:feature_code":"PPLL",
    "gn:name":"Bugaramantare",
    "gn:population":0,
    "gn:timezone":"Africa/Kigali",
    "iso:country":"RW",
    "wof:name":"Bugaramantare",
    "wof:placetype":"locality"
},
  "geometry": {"coordinates":[29.68333,-2.01667],"type":"Point"}
}