{
  "type": "Feature",
  "properties": {
    "gn:admin1_code":"11",
    "gn:admin2_code":"53.0",
    "gn:admin3_code":"5310.0",
    "gn:admin4_code":"531004.0",
    "gn:asciiname":"Cyamuganga",
    "gn:country_code":"RW",
    "gn:dem":1452,
    "gn:feature_class":"P",
    "gn:feature_code":"PPLL",
    "gn:name":"Cyamuganga",
    "gn:population":0,
    "gn:timezone":"Africa/Kigali",
    "iso:country":"RW",
    "wof:name":"Cyamuganga",
    "wof:placetype":"locality"
},
  "geometry": {"coordinates":[30.2386,-1.5514],"type":"Point"}
}