{
  "type": "Feature",
  "properties": {
    "gn:admin1_code":"15.0",
    "gn:admin2_code":"23",
    "gn:admin3_code":"2301.0",
    "gn:admin4_code":"230105.0",
    "gn:asciiname":"Bukinga",
    "gn:country_code":"RW",
    "gn:dem":2127,
    "gn:feature_class":"P",
    "gn:feature_code":"PPLL",
    "gn:name":"Bukinga",
    "gn:population":0,
    "gn:timezone":"Africa/Kigali",
    "iso:country":"RW",
    "wof:name":"Bukinga",
    "wof:placetype":"locality"
},
  "geometry": {"coordinates":[29.4928,-2.77],"type":"Point"}
}