{
  "type": "Feature",
  "properties": {
    "gn:admin1_code":"14.0",
    "gn:admin2_code":"36",
    "gn:admin3_code":"3616.0",
    "gn:admin4_code":"361601.0",
    "gn:asciiname":"Kakabaga",
    "gn:country_code":"RW",
    "gn:dem":1878,
    "gn:feature_class":"P",
    "gn:feature_code":"PPLL",
    "gn:name":"Kakabaga",
    "gn:population":0,
    "gn:timezone":"Africa/Kigali",
    "iso:country":"RW",
    "wof:name":"Kakabaga",
    "wof:placetype":"locality"
},
  "geometry": {"coordinates":[28.941,-2.5478],"type":"Point"}
}