{
  "type": "Feature",
  "properties": {
    "gn:admin1_code":"13.0",
    "gn:admin2_code":"43",
    "gn:admin3_code":"4305.0",
    "gn:admin4_code":"430503.0",
    "gn:asciiname":"Mukingo",
    "gn:country_code":"RW",
    "gn:dem":2210,
    "gn:feature_class":"P",
    "gn:feature_code":"PPL",
    "gn:name":"Mukingo",
    "gn:population":0,
    "gn:timezone":"Africa/Kigali",
    "iso:country":"RW",
    "wof:name":"Mukingo",
    "wof:placetype":"locality"
},
  "geometry": {"coordinates":[29.5558,-1.5394],"type":"Point"}
}