{
  "type": "Feature",
  "properties": {
    "gn:admin1_code":"11",
    "gn:admin2_code":"56.0",
    "gn:admin3_code":"5612.0",
    "gn:admin4_code":"561203.0",
    "gn:asciiname":"Musya",
    "gn:country_code":"RW",
    "gn:dem":1541,
    "gn:feature_class":"P",
    "gn:feature_code":"PPL",
    "gn:name":"Musya",
    "gn:population":0,
    "gn:timezone":"Africa/Kigali",
    "iso:country":"RW",
    "name:ita_x_preferred":[
        "Musya"
    ],
    "name:jpn_x_preferred":[
        "\u8c6a\u69cd\u795e\u96f7\u4f1d\u8aac\u300c\u6b66\u8005\u300d"
    ],
    "wof:name":"Musya",
    "wof:placetype":"locality"
},
  "geometry": {"coordinates":[30.5169,-2.1364],"type":"Point"}
}