{
  "type": "Feature",
  "properties": {
    "gn:admin1_code":"14.0",
    "gn:admin2_code":"37",
    "gn:admin3_code":"3706.0",
    "gn:admin4_code":"370601.0",
    "gn:asciiname":"Kagarama",
    "gn:country_code":"RW",
    "gn:dem":1502,
    "gn:feature_class":"P",
    "gn:feature_code":"PPLL",
    "gn:name":"Kagarama",
    "gn:population":0,
    "gn:timezone":"Africa/Kigali",
    "iso:country":"RW",
    "wof:name":"Kagarama",
    "wof:placetype":"locality"
},
  "geometry": {"coordinates":[29.1386,-2.3195],"type":"Point"}
}