{
  "type": "Feature",
  "properties": {
    "gn:admin1_code":"15",
    "gn:admin2_code":"28.0",
    "gn:admin3_code":"2801.0",
    "gn:admin4_code":"280103.0",
    "gn:asciiname":"Munanira",
    "gn:country_code":"RW",
    "gn:dem":1667,
    "gn:feature_class":"P",
    "gn:feature_code":"PPLL",
    "gn:name":"Munanira",
    "gn:population":0,
    "gn:timezone":"Africa/Kigali",
    "iso:country":"RW",
    "wof:name":"Munanira",
    "wof:placetype":"locality"
},
  "geometry": {"coordinates":[29.875,-2.0191],"type":"Point"}
}