{
  "type": "Feature",
  "properties": {
    "gn:admin1_code":"11",
    "gn:admin2_code":"54.0",
    "gn:admin3_code":"5411.0",
    "gn:admin4_code":"541101.0",
    "gn:asciiname":"Rukira",
    "gn:country_code":"RW",
    "gn:dem":1435,
    "gn:feature_class":"P",
    "gn:feature_code":"PPLL",
    "gn:name":"Rukira",
    "gn:population":0,
    "gn:timezone":"Africa/Kigali",
    "iso:country":"RW",
    "wof:name":"Rukira",
    "wof:placetype":"locality"
},
  "geometry": {"coordinates":[30.4895,-2.0413],"type":"Point"}
}