{
  "type": "Feature",
  "properties": {
    "gn:admin1_code":"13.0",
    "gn:admin2_code":"45",
    "gn:admin3_code":"4501.0",
    "gn:admin4_code":"450104.0",
    "gn:asciiname":"Karagali",
    "gn:country_code":"RW",
    "gn:dem":1737,
    "gn:feature_class":"P",
    "gn:feature_code":"PPLL",
    "gn:name":"Karagali",
    "gn:population":0,
    "gn:timezone":"Africa/Kigali",
    "iso:country":"RW",
    "name:und_x_variant":[
        "Colline Karagari",
        "Karagali",
        "Karagari"
    ],
    "wof:name":"Karagali",
    "wof:placetype":"locality"
},
  "geometry": {"coordinates":[30.2032,-1.80949],"type":"Point"}
}