{
  "type": "Feature",
  "properties": {
    "gn:admin1_code":"14.0",
    "gn:admin2_code":"32",
    "gn:admin3_code":"3210.0",
    "gn:admin4_code":"321003.0",
    "gn:asciiname":"Nyabugoro",
    "gn:country_code":"RW",
    "gn:dem":2254,
    "gn:feature_class":"P",
    "gn:feature_code":"PPLL",
    "gn:name":"Nyabugoro",
    "gn:population":0,
    "gn:timezone":"Africa/Kigali",
    "iso:country":"RW",
    "wof:name":"Nyabugoro",
    "wof:placetype":"locality"
},
  "geometry": {"coordinates":[29.4206,-1.9896],"type":"Point"}
}