{
  "type": "Feature",
  "properties": {
    "gn:admin1_code":"15.0",
    "gn:admin2_code":"24",
    "gn:admin3_code":"2407.0",
    "gn:admin4_code":"240705.0",
    "gn:asciiname":"Gahanga",
    "gn:country_code":"RW",
    "gn:dem":1657,
    "gn:feature_class":"P",
    "gn:feature_code":"PPLL",
    "gn:name":"Gahanga",
    "gn:population":0,
    "gn:timezone":"Africa/Kigali",
    "iso:country":"RW",
    "wof:name":"Gahanga",
    "wof:placetype":"locality"
},
  "geometry": {"coordinates":[29.7284,-2.5179],"type":"Point"}
}