{
  "type": "Feature",
  "properties": {
    "gn:admin1_code":"11",
    "gn:admin2_code":"53.0",
    "gn:admin3_code":"5309.0",
    "gn:admin4_code":"530901.0",
    "gn:asciiname":"Gatagara",
    "gn:country_code":"RW",
    "gn:dem":1618,
    "gn:feature_class":"P",
    "gn:feature_code":"PPLL",
    "gn:name":"Gatagara",
    "gn:population":0,
    "gn:timezone":"Africa/Kigali",
    "iso:country":"RW",
    "wof:name":"Gatagara",
    "wof:placetype":"locality"
},
  "geometry": {"coordinates":[30.3431,-1.7752],"type":"Point"}
}