{
  "type": "Feature",
  "properties": {
    "gn:admin1_code":"15",
    "gn:admin2_code":"27.0",
    "gn:admin3_code":"2701.0",
    "gn:admin4_code":"270101.0",
    "gn:asciiname":"Bwilika-Mpenge",
    "gn:country_code":"RW",
    "gn:dem":1812,
    "gn:feature_class":"P",
    "gn:feature_code":"PPLL",
    "gn:name":"Bwilika-Mpenge",
    "gn:population":0,
    "gn:timezone":"Africa/Kigali",
    "iso:country":"RW",
    "name:und_x_variant":[
        "Bwilika-Mpemge"
    ],
    "wof:name":"Bwilika-Mpenge",
    "wof:placetype":"locality"
},
  "geometry": {"coordinates":[29.7717,-2.0385],"type":"Point"}
}