{
  "type": "Feature",
  "properties": {
    "gn:admin1_code":"15.0",
    "gn:admin2_code":"25",
    "gn:admin3_code":"2507.0",
    "gn:admin4_code":"250702.0",
    "gn:asciiname":"Bugarura",
    "gn:country_code":"RW",
    "gn:dem":1865,
    "gn:feature_class":"P",
    "gn:feature_code":"PPLL",
    "gn:name":"Bugarura",
    "gn:population":0,
    "gn:timezone":"Africa/Kigali",
    "iso:country":"RW",
    "wof:name":"Bugarura",
    "wof:placetype":"locality"
},
  "geometry": {"coordinates":[29.5482,-2.433],"type":"Point"}
}