{
  "type": "Feature",
  "properties": {
    "gn:admin1_code":"13",
    "gn:admin2_code":"45.0",
    "gn:admin3_code":"4505.0",
    "gn:admin4_code":"450501.0",
    "gn:asciiname":"Kababito",
    "gn:country_code":"RW",
    "gn:dem":1877,
    "gn:feature_class":"P",
    "gn:feature_code":"PPL",
    "gn:name":"Kababito",
    "gn:population":0,
    "gn:timezone":"Africa/Kigali",
    "iso:country":"RW",
    "wof:name":"Kababito",
    "wof:placetype":"locality"
},
  "geometry": {"coordinates":[30.2279,-1.7622],"type":"Point"}
}