{
  "type": "Feature",
  "properties": {
    "gn:admin1_code":"15",
    "gn:admin2_code":"22.0",
    "gn:admin3_code":"2210.0",
    "gn:admin4_code":"221004.0",
    "gn:asciiname":"Rusenyi",
    "gn:country_code":"RW",
    "gn:dem":1586,
    "gn:feature_class":"P",
    "gn:feature_code":"PPLL",
    "gn:name":"Rusenyi",
    "gn:population":0,
    "gn:timezone":"Africa/Kigali",
    "iso:country":"RW",
    "wof:name":"Rusenyi",
    "wof:placetype":"locality"
},
  "geometry": {"coordinates":[29.8366,-2.508],"type":"Point"}
}