{
  "type": "Feature",
  "properties": {
    "gn:admin1_code":"11.0",
    "gn:admin2_code":"52",
    "gn:admin3_code":"5214.0",
    "gn:admin4_code":"521404.0",
    "gn:asciiname":"Kangoma",
    "gn:country_code":"RW",
    "gn:dem":1466,
    "gn:feature_class":"P",
    "gn:feature_code":"PPLL",
    "gn:name":"Kangoma",
    "gn:population":0,
    "gn:timezone":"Africa/Kigali",
    "iso:country":"RW",
    "name:und_x_variant":[
        "Colline Kangoma",
        "Kangoma"
    ],
    "wof:name":"Kangoma",
    "wof:placetype":"locality"
},
  "geometry": {"coordinates":[30.25,-1.28333],"type":"Point"}
}