{
  "type": "Feature",
  "properties": {
    "gn:admin1_code":"13",
    "gn:admin2_code":"42.0",
    "gn:admin3_code":"4201.0",
    "gn:admin4_code":"420101.0",
    "gn:asciiname":"Burushya",
    "gn:country_code":"RW",
    "gn:dem":1721,
    "gn:feature_class":"P",
    "gn:feature_code":"PPLL",
    "gn:name":"Burushya",
    "gn:population":0,
    "gn:timezone":"Africa/Kigali",
    "iso:country":"RW",
    "wof:name":"Burushya",
    "wof:placetype":"locality"
},
  "geometry": {"coordinates":[29.6829,-1.6234],"type":"Point"}
}