{
  "type": "Feature",
  "properties": {
    "gn:admin1_code":"15.0",
    "gn:admin2_code":"23",
    "gn:admin3_code":"2312.0",
    "gn:admin4_code":"231204.0",
    "gn:asciiname":"Ruyenzi",
    "gn:country_code":"RW",
    "gn:dem":2174,
    "gn:feature_class":"P",
    "gn:feature_code":"PPLL",
    "gn:name":"Ruyenzi",
    "gn:population":0,
    "gn:timezone":"Africa/Kigali",
    "iso:country":"RW",
    "wof:name":"Ruyenzi",
    "wof:placetype":"locality"
},
  "geometry": {"coordinates":[29.4506,-2.7559],"type":"Point"}
}