{
  "type": "Feature",
  "properties": {
    "gn:admin1_code":"14.0",
    "gn:admin2_code":"35",
    "gn:admin3_code":"3502.0",
    "gn:admin4_code":"350204.0",
    "gn:asciiname":"Ngurunguzu",
    "gn:country_code":"RW",
    "gn:dem":1908,
    "gn:feature_class":"P",
    "gn:feature_code":"PPL",
    "gn:name":"Ngurunguzu",
    "gn:population":0,
    "gn:timezone":"Africa/Kigali",
    "iso:country":"RW",
    "name:und_x_variant":[
        "Colline Ngurugunzu",
        "Ngurunguzu"
    ],
    "wof:name":"Ngurunguzu",
    "wof:placetype":"locality"
},
  "geometry": {"coordinates":[29.6126,-1.9597],"type":"Point"}
}