{
  "type": "Feature",
  "properties": {
    "gn:admin1_code":"15.0",
    "gn:admin2_code":"21",
    "gn:admin3_code":"2101.0",
    "gn:admin4_code":"210104.0",
    "gn:asciiname":"Gishike",
    "gn:country_code":"RW",
    "gn:dem":1692,
    "gn:feature_class":"P",
    "gn:feature_code":"PPLL",
    "gn:name":"Gishike",
    "gn:population":0,
    "gn:timezone":"Africa/Kigali",
    "iso:country":"RW",
    "name:und_x_variant":[
        "Colline Gishike",
        "Gishike"
    ],
    "wof:name":"Gishike",
    "wof:placetype":"locality"
},
  "geometry": {"coordinates":[29.7491,-2.3843],"type":"Point"}
}