{
  "type": "Feature",
  "properties": {
    "gn:admin1_code":"11",
    "gn:admin2_code":"55.0",
    "gn:admin3_code":"5508.0",
    "gn:admin4_code":"550802.0",
    "gn:asciiname":"Kabugili",
    "gn:country_code":"RW",
    "gn:dem":1576,
    "gn:feature_class":"P",
    "gn:feature_code":"PPLL",
    "gn:name":"Kabugili",
    "gn:population":0,
    "gn:timezone":"Africa/Kigali",
    "iso:country":"RW",
    "wof:name":"Kabugili",
    "wof:placetype":"locality"
},
  "geometry": {"coordinates":[30.6039,-2.3397],"type":"Point"}
}