{
  "type": "Feature",
  "properties": {
    "gn:admin1_code":"14.0",
    "gn:admin2_code":"36",
    "gn:admin3_code":"3618.0",
    "gn:admin4_code":"361801.0",
    "gn:asciiname":"Ndogomba",
    "gn:country_code":"RW",
    "gn:dem":1688,
    "gn:feature_class":"P",
    "gn:feature_code":"PPLL",
    "gn:name":"Ndogomba",
    "gn:population":0,
    "gn:timezone":"Africa/Kigali",
    "iso:country":"RW",
    "wof:name":"Ndogomba",
    "wof:placetype":"locality"
},
  "geometry": {"coordinates":[28.9456,-2.6214],"type":"Point"}
}