{
  "type": "Feature",
  "properties": {
    "gn:admin1_code":"15.0",
    "gn:admin2_code":"25",
    "gn:admin3_code":"2507.0",
    "gn:admin4_code":"250705.0",
    "gn:asciiname":"Cyamashya",
    "gn:country_code":"RW",
    "gn:dem":1958,
    "gn:feature_class":"P",
    "gn:feature_code":"PPLL",
    "gn:name":"Cyamashya",
    "gn:population":0,
    "gn:timezone":"Africa/Kigali",
    "iso:country":"RW",
    "wof:name":"Cyamashya",
    "wof:placetype":"locality"
},
  "geometry": {"coordinates":[29.5157,-2.4545],"type":"Point"}
}