{
  "type": "Feature",
  "properties": {
    "gn:admin1_code":"14.0",
    "gn:admin2_code":"36",
    "gn:admin3_code":"3604.0",
    "gn:admin4_code":"360407.0",
    "gn:asciiname":"Gisagara",
    "gn:country_code":"RW",
    "gn:dem":1711,
    "gn:feature_class":"P",
    "gn:feature_code":"PPL",
    "gn:name":"Gisagara",
    "gn:population":0,
    "gn:timezone":"Africa/Kigali",
    "iso:country":"RW",
    "name:und_x_variant":[
        "Colline Gisagara",
        "Gisagara"
    ],
    "wof:name":"Gisagara",
    "wof:placetype":"locality"
},
  "geometry": {"coordinates":[28.91947,-2.60186],"type":"Point"}
}