{
  "type": "Feature",
  "properties": {
    "gn:admin1_code":"13",
    "gn:admin2_code":"41.0",
    "gn:admin3_code":"4104.0",
    "gn:admin4_code":"410401.0",
    "gn:asciiname":"Gashana",
    "gn:country_code":"RW",
    "gn:dem":1971,
    "gn:feature_class":"P",
    "gn:feature_code":"PPL",
    "gn:name":"Gashana",
    "gn:population":0,
    "gn:timezone":"Africa/Kigali",
    "iso:country":"RW",
    "wof:name":"Gashana",
    "wof:placetype":"locality"
},
  "geometry": {"coordinates":[29.9969,-1.7006],"type":"Point"}
}