{
  "type": "Feature",
  "properties": {
    "gn:admin1_code":"13",
    "gn:admin2_code":"41.0",
    "gn:admin3_code":"4104.0",
    "gn:admin4_code":"410406.0",
    "gn:asciiname":"Buyoga",
    "gn:country_code":"RW",
    "gn:dem":1772,
    "gn:feature_class":"P",
    "gn:feature_code":"PPLL",
    "gn:name":"Buyoga",
    "gn:population":0,
    "gn:timezone":"Africa/Kigali",
    "iso:country":"RW",
    "name:ita_x_preferred":[
        "Buyoga"
    ],
    "wof:name":"Buyoga",
    "wof:placetype":"locality"
},
  "geometry": {"coordinates":[29.9957,-1.6835],"type":"Point"}
}