{
  "type": "Feature",
  "properties": {
    "gn:admin1_code":"14",
    "gn:admin2_code":"31.0",
    "gn:admin3_code":"3104.0",
    "gn:admin4_code":"310404.0",
    "gn:asciiname":"Buye",
    "gn:country_code":"RW",
    "gn:dem":1953,
    "gn:feature_class":"P",
    "gn:feature_code":"PPL",
    "gn:name":"Buye",
    "gn:population":0,
    "gn:timezone":"Africa/Kigali",
    "iso:country":"RW",
    "wof:name":"Buye",
    "wof:placetype":"locality"
},
  "geometry": {"coordinates":[29.414,-2.1305],"type":"Point"}
}