{
  "type": "Feature",
  "properties": {
    "gn:admin1_code":"13.0",
    "gn:admin2_code":"44",
    "gn:admin3_code":"4415.0",
    "gn:admin4_code":"441503.0",
    "gn:asciiname":"Gitovu",
    "gn:country_code":"RW",
    "gn:dem":2174,
    "gn:feature_class":"P",
    "gn:feature_code":"PPLL",
    "gn:name":"Gitovu",
    "gn:population":0,
    "gn:timezone":"Africa/Kigali",
    "iso:country":"RW",
    "name:und_x_variant":[
        "Colline Gitovu",
        "Gitovu"
    ],
    "wof:name":"Gitovu",
    "wof:placetype":"locality"
},
  "geometry": {"coordinates":[29.9342,-1.578],"type":"Point"}
}