{
  "type": "Feature",
  "properties": {
    "gn:admin1_code":"14.0",
    "gn:admin2_code":"31",
    "gn:admin3_code":"3102.0",
    "gn:admin4_code":"310202.0",
    "gn:asciiname":"Birambo",
    "gn:country_code":"RW",
    "gn:dem":1653,
    "gn:feature_class":"P",
    "gn:feature_code":"PPL",
    "gn:name":"Birambo",
    "gn:population":0,
    "gn:timezone":"Africa/Kigali",
    "iso:country":"RW",
    "wof:name":"Birambo",
    "wof:placetype":"locality"
},
  "geometry": {"coordinates":[29.5249,-2.1422],"type":"Point"}
}