{
  "type": "Feature",
  "properties": {
    "gn:admin1_code":"14",
    "gn:admin2_code":"33.0",
    "gn:admin3_code":"3311.0",
    "gn:admin4_code":"331102.0",
    "gn:asciiname":"Gasenyi",
    "gn:country_code":"RW",
    "gn:dem":1709,
    "gn:feature_class":"P",
    "gn:feature_code":"PPL",
    "gn:name":"Gasenyi",
    "gn:population":0,
    "gn:timezone":"Africa/Kigali",
    "iso:country":"RW",
    "wof:name":"Gasenyi",
    "wof:placetype":"locality"
},
  "geometry": {"coordinates":[29.3153,-1.6545],"type":"Point"}
}