{
  "type": "Feature",
  "properties": {
    "gn:admin1_code":"14",
    "gn:admin2_code":"33.0",
    "gn:admin3_code":"3312.0",
    "gn:admin4_code":"331201.0",
    "gn:asciiname":"Kabeza",
    "gn:country_code":"RW",
    "gn:dem":1747,
    "gn:feature_class":"P",
    "gn:feature_code":"PPLL",
    "gn:name":"Kabeza",
    "gn:population":0,
    "gn:timezone":"Africa/Kigali",
    "iso:country":"RW",
    "wof:name":"Kabeza",
    "wof:placetype":"locality"
},
  "geometry": {"coordinates":[29.323,-1.68],"type":"Point"}
}