{
  "type": "Feature",
  "properties": {
    "gn:admin1_code":"13",
    "gn:admin2_code":"43.0",
    "gn:admin3_code":"4313.0",
    "gn:admin4_code":"431302.0",
    "gn:asciiname":"Gashunga",
    "gn:country_code":"RW",
    "gn:dem":1852,
    "gn:feature_class":"P",
    "gn:feature_code":"PPLL",
    "gn:name":"Gashunga",
    "gn:population":0,
    "gn:timezone":"Africa/Kigali",
    "iso:country":"RW",
    "wof:name":"Gashunga",
    "wof:placetype":"locality"
},
  "geometry": {"coordinates":[29.7106,-1.5536],"type":"Point"}
}