{
  "type": "Feature",
  "properties": {
    "gn:admin1_code":"15",
    "gn:admin2_code":"27.0",
    "gn:admin3_code":"2708.0",
    "gn:admin4_code":"270804.0",
    "gn:asciiname":"Munini",
    "gn:country_code":"RW",
    "gn:dem":1806,
    "gn:feature_class":"P",
    "gn:feature_code":"PPL",
    "gn:name":"Munini",
    "gn:population":0,
    "gn:timezone":"Africa/Kigali",
    "iso:country":"RW",
    "wof:name":"Munini",
    "wof:placetype":"locality"
},
  "geometry": {"coordinates":[29.7519,-2.0567],"type":"Point"}
}