{
  "type": "Feature",
  "properties": {
    "gn:admin1_code":"15",
    "gn:admin2_code":"26.0",
    "gn:admin3_code":"2606.0",
    "gn:admin4_code":"260607.0",
    "gn:asciiname":"Nyaruyonga",
    "gn:country_code":"RW",
    "gn:dem":1576,
    "gn:feature_class":"P",
    "gn:feature_code":"PPLL",
    "gn:name":"Nyaruyonga",
    "gn:population":0,
    "gn:timezone":"Africa/Kigali",
    "iso:country":"RW",
    "wof:name":"Nyaruyonga",
    "wof:placetype":"locality"
},
  "geometry": {"coordinates":[29.8484,-2.1216],"type":"Point"}
}