{
  "type": "Feature",
  "properties": {
    "gn:admin1_code":"11.0",
    "gn:admin2_code":"52",
    "gn:admin3_code":"5212.0",
    "gn:admin4_code":"521207.0",
    "gn:asciiname":"Rukorota",
    "gn:country_code":"RW",
    "gn:dem":1401,
    "gn:feature_class":"P",
    "gn:feature_code":"PPLL",
    "gn:name":"Rukorota",
    "gn:population":0,
    "gn:timezone":"Africa/Kigali",
    "iso:country":"RW",
    "wof:name":"Rukorota",
    "wof:placetype":"locality"
},
  "geometry": {"coordinates":[30.3259,-1.2278],"type":"Point"}
}