{
  "type": "Feature",
  "properties": {
    "gn:admin1_code":"13",
    "gn:admin2_code":"44.0",
    "gn:admin3_code":"4403.0",
    "gn:admin4_code":"440304.0",
    "gn:asciiname":"Ntarama",
    "gn:country_code":"RW",
    "gn:dem":2026,
    "gn:feature_class":"P",
    "gn:feature_code":"PPLL",
    "gn:name":"Ntarama",
    "gn:population":0,
    "gn:timezone":"Africa/Kigali",
    "iso:country":"RW",
    "wof:name":"Ntarama",
    "wof:placetype":"locality"
},
  "geometry": {"coordinates":[29.7347,-1.361],"type":"Point"}
}