{
  "type": "Feature",
  "properties": {
    "gn:admin1_code":"14",
    "gn:admin2_code":"31.0",
    "gn:admin3_code":"3106.0",
    "gn:admin4_code":"310602.0",
    "gn:asciiname":"Muhororo",
    "gn:country_code":"RW",
    "gn:dem":1715,
    "gn:feature_class":"P",
    "gn:feature_code":"PPL",
    "gn:name":"Muhororo",
    "gn:population":0,
    "gn:timezone":"Africa/Kigali",
    "iso:country":"RW",
    "wof:name":"Muhororo",
    "wof:placetype":"locality"
},
  "geometry": {"coordinates":[29.553,-2.1487],"type":"Point"}
}