{
  "type": "Feature",
  "properties": {
    "gn:admin1_code":"15.0",
    "gn:admin2_code":"23",
    "gn:admin3_code":"2313.0",
    "gn:admin4_code":"231305.0",
    "gn:asciiname":"Gatwaro",
    "gn:country_code":"RW",
    "gn:dem":1940,
    "gn:feature_class":"P",
    "gn:feature_code":"PPLL",
    "gn:name":"Gatwaro",
    "gn:population":0,
    "gn:timezone":"Africa/Kigali",
    "iso:country":"RW",
    "wof:name":"Gatwaro",
    "wof:placetype":"locality"
},
  "geometry": {"coordinates":[29.5427,-2.5657],"type":"Point"}
}