{
  "type": "Feature",
  "properties": {
    "gn:admin1_code":"15",
    "gn:admin2_code":"26.0",
    "gn:admin3_code":"2601.0",
    "gn:admin4_code":"260101.0",
    "gn:asciiname":"Buhanda",
    "gn:country_code":"RW",
    "gn:dem":1757,
    "gn:feature_class":"P",
    "gn:feature_code":"PPLL",
    "gn:name":"Buhanda",
    "gn:population":0,
    "gn:timezone":"Africa/Kigali",
    "iso:country":"RW",
    "wof:name":"Buhanda",
    "wof:placetype":"locality"
},
  "geometry": {"coordinates":[29.6618,-2.2318],"type":"Point"}
}