{
  "type": "Feature",
  "properties": {
    "gn:admin1_code":"12",
    "gn:admin2_code":"13.0",
    "gn:admin3_code":"1302.0",
    "gn:admin4_code":"130204.0",
    "gn:asciiname":"Bigo",
    "gn:country_code":"RW",
    "gn:dem":1662,
    "gn:feature_class":"P",
    "gn:feature_code":"PPLL",
    "gn:name":"Bigo",
    "gn:population":0,
    "gn:timezone":"Africa/Kigali",
    "iso:country":"RW",
    "wof:name":"Bigo",
    "wof:placetype":"locality"
},
  "geometry": {"coordinates":[30.0725,-2.0032],"type":"Point"}
}