{
  "type": "Feature",
  "properties": {
    "gn:admin1_code":"15",
    "gn:admin2_code":"27.0",
    "gn:admin3_code":"2705.0",
    "gn:admin4_code":"270503.0",
    "gn:asciiname":"Ruzuru",
    "gn:country_code":"RW",
    "gn:dem":1957,
    "gn:feature_class":"P",
    "gn:feature_code":"PPLL",
    "gn:name":"Ruzuru",
    "gn:population":0,
    "gn:timezone":"Africa/Kigali",
    "iso:country":"RW",
    "wof:name":"Ruzuru",
    "wof:placetype":"locality"
},
  "geometry": {"coordinates":[29.7479,-2.0193],"type":"Point"}
}