{
  "type": "Feature",
  "properties": {
    "gn:admin1_code":"12",
    "gn:admin2_code":"12.0",
    "gn:admin3_code":"1210.0",
    "gn:admin4_code":"121003.0",
    "gn:asciiname":"Batsinda",
    "gn:country_code":"RW",
    "gn:dem":1405,
    "gn:feature_class":"P",
    "gn:feature_code":"PPLL",
    "gn:name":"Batsinda",
    "gn:population":0,
    "gn:timezone":"Africa/Kigali",
    "iso:country":"RW",
    "wof:name":"Batsinda",
    "wof:placetype":"locality"
},
  "geometry": {"coordinates":[30.06900000000001,-1.8969],"type":"Point"}
}