{
  "type": "Feature",
  "properties": {
    "gn:admin1_code":"13",
    "gn:admin2_code":"45.0",
    "gn:admin3_code":"4501.0",
    "gn:admin4_code":"450101.0",
    "gn:asciiname":"Kabuga",
    "gn:country_code":"RW",
    "gn:dem":1718,
    "gn:feature_class":"P",
    "gn:feature_code":"PPLL",
    "gn:name":"Kabuga",
    "gn:population":0,
    "gn:timezone":"Africa/Kigali",
    "iso:country":"RW",
    "name:cat_x_preferred":[
        "Kabuga"
    ],
    "name:fra_x_preferred":[
        "Kabuga"
    ],
    "name:pol_x_preferred":[
        "Kabuga"
    ],
    "wof:name":"Kabuga",
    "wof:placetype":"locality"
},
  "geometry": {"coordinates":[30.2099,-1.8027],"type":"Point"}
}