{
  "type": "Feature",
  "properties": {
    "gn:admin1_code":"15.0",
    "gn:admin2_code":"25",
    "gn:admin3_code":"2514.0",
    "gn:admin4_code":"251401.0",
    "gn:asciiname":"Murambi",
    "gn:country_code":"RW",
    "gn:dem":1765,
    "gn:feature_class":"P",
    "gn:feature_code":"PPLL",
    "gn:name":"Murambi",
    "gn:population":0,
    "gn:timezone":"Africa/Kigali",
    "iso:country":"RW",
    "wof:name":"Murambi",
    "wof:placetype":"locality"
},
  "geometry": {"coordinates":[29.4436,-2.2773],"type":"Point"}
}