{
  "type": "Feature",
  "properties": {
    "gn:admin1_code":"13",
    "gn:admin2_code":"42.0",
    "gn:admin3_code":"4210.0",
    "gn:admin4_code":"421001.0",
    "gn:asciiname":"Munihi",
    "gn:country_code":"RW",
    "gn:dem":1611,
    "gn:feature_class":"P",
    "gn:feature_code":"PPLL",
    "gn:name":"Munihi",
    "gn:population":0,
    "gn:timezone":"Africa/Kigali",
    "iso:country":"RW",
    "wof:name":"Munihi",
    "wof:placetype":"locality"
},
  "geometry": {"coordinates":[29.7997,-1.7056],"type":"Point"}
}