{
  "type": "Feature",
  "properties": {
    "gn:admin1_code":"13",
    "gn:admin2_code":"42.0",
    "gn:admin3_code":"4211.0",
    "gn:admin4_code":"421103.0",
    "gn:asciiname":"Gisovu",
    "gn:country_code":"RW",
    "gn:dem":1584,
    "gn:feature_class":"P",
    "gn:feature_code":"PPLL",
    "gn:name":"Gisovu",
    "gn:population":0,
    "gn:timezone":"Africa/Kigali",
    "iso:country":"RW",
    "wof:name":"Gisovu",
    "wof:placetype":"locality"
},
  "geometry": {"coordinates":[29.752,-1.7578],"type":"Point"}
}