{
  "type": "Feature",
  "properties": {
    "gn:admin1_code":"12",
    "gn:admin2_code":"11.0",
    "gn:admin3_code":"1102.0",
    "gn:admin4_code":"110202.0",
    "gn:asciiname":"Ruyenzi",
    "gn:country_code":"RW",
    "gn:dem":1448,
    "gn:feature_class":"P",
    "gn:feature_code":"PPLL",
    "gn:name":"Ruyenzi",
    "gn:population":0,
    "gn:timezone":"Africa/Kigali",
    "iso:country":"RW",
    "wof:name":"Ruyenzi",
    "wof:placetype":"locality"
},
  "geometry": {"coordinates":[30.0041,-1.9373],"type":"Point"}
}