{
  "type": "Feature",
  "properties": {
    "gn:admin1_code":"15.0",
    "gn:admin2_code":"21",
    "gn:admin3_code":"2101.0",
    "gn:admin4_code":"210104.0",
    "gn:asciiname":"Kabare",
    "gn:country_code":"RW",
    "gn:dem":1799,
    "gn:feature_class":"P",
    "gn:feature_code":"PPL",
    "gn:name":"Kabare",
    "gn:population":0,
    "gn:timezone":"Africa/Kigali",
    "iso:country":"RW",
    "wof:name":"Kabare",
    "wof:placetype":"locality"
},
  "geometry": {"coordinates":[29.7451,-2.3505],"type":"Point"}
}