{
  "type": "Feature",
  "properties": {
    "gn:admin1_code":"15.0",
    "gn:admin2_code":"24",
    "gn:admin3_code":"2403.0",
    "gn:admin4_code":"240301.0",
    "gn:asciiname":"Kibingo",
    "gn:country_code":"RW",
    "gn:dem":1808,
    "gn:feature_class":"P",
    "gn:feature_code":"PPLL",
    "gn:name":"Kibingo",
    "gn:population":0,
    "gn:timezone":"Africa/Kigali",
    "iso:country":"RW",
    "name:lug_x_preferred":[
        "Kibingo"
    ],
    "name:urd_x_preferred":[
        "\u06a9\u06cc\u0628\u06cc\u0646\u06af\u0648"
    ],
    "wof:name":"Kibingo",
    "wof:placetype":"locality"
},
  "geometry": {"coordinates":[29.6268,-2.6081],"type":"Point"}
}