{
  "type": "Feature",
  "properties": {
    "gn:admin1_code":"15.0",
    "gn:admin2_code":"26",
    "gn:admin3_code":"2603.0",
    "gn:admin4_code":"260304.0",
    "gn:asciiname":"Kanyinya",
    "gn:country_code":"RW",
    "gn:dem":1737,
    "gn:feature_class":"P",
    "gn:feature_code":"PPLL",
    "gn:name":"Kanyinya",
    "gn:population":0,
    "gn:timezone":"Africa/Kigali",
    "iso:country":"RW",
    "name:und_x_variant":[
        "Colline Kinyanja",
        "Kanyinya",
        "Kinyanja"
    ],
    "wof:name":"Kanyinya",
    "wof:placetype":"locality"
},
  "geometry": {"coordinates":[29.611,-2.2395],"type":"Point"}
}