{
  "type": "Feature",
  "properties": {
    "gn:admin1_code":"13",
    "gn:admin2_code":"41.0",
    "gn:admin3_code":"4110.0",
    "gn:admin4_code":"411004.0",
    "gn:asciiname":"Nkondo",
    "gn:country_code":"RW",
    "gn:dem":1963,
    "gn:feature_class":"P",
    "gn:feature_code":"PPLL",
    "gn:name":"Nkondo",
    "gn:population":0,
    "gn:timezone":"Africa/Kigali",
    "iso:country":"RW",
    "wof:name":"Nkondo",
    "wof:placetype":"locality"
},
  "geometry": {"coordinates":[29.9551,-1.7627],"type":"Point"}
}