{
  "type": "Feature",
  "properties": {
    "gn:admin1_code":"13",
    "gn:admin2_code":"44.0",
    "gn:admin3_code":"4401.0",
    "gn:admin4_code":"440103.0",
    "gn:asciiname":"Bunigo",
    "gn:country_code":"RW",
    "gn:dem":2215,
    "gn:feature_class":"P",
    "gn:feature_code":"PPLL",
    "gn:name":"Bunigo",
    "gn:population":0,
    "gn:timezone":"Africa/Kigali",
    "iso:country":"RW",
    "wof:name":"Bunigo",
    "wof:placetype":"locality"
},
  "geometry": {"coordinates":[29.95300000000001,-1.4956],"type":"Point"}
}