{
  "type": "Feature",
  "properties": {
    "gn:admin1_code":"11",
    "gn:admin2_code":"55.0",
    "gn:admin3_code":"5502.0",
    "gn:admin4_code":"550206.0",
    "gn:asciiname":"Mukiha",
    "gn:country_code":"RW",
    "gn:dem":1362,
    "gn:feature_class":"P",
    "gn:feature_code":"PPL",
    "gn:name":"Mukiha",
    "gn:population":0,
    "gn:timezone":"Africa/Kigali",
    "iso:country":"RW",
    "wof:name":"Mukiha",
    "wof:placetype":"locality"
},
  "geometry": {"coordinates":[30.5711,-2.3912],"type":"Point"}
}