{
  "type": "Feature",
  "properties": {
    "gn:admin1_code":"13.0",
    "gn:admin2_code":"45",
    "gn:admin3_code":"4507.0",
    "gn:admin4_code":"450702.0",
    "gn:asciiname":"Kizinga",
    "gn:country_code":"RW",
    "gn:dem":1836,
    "gn:feature_class":"P",
    "gn:feature_code":"PPLL",
    "gn:name":"Kizinga",
    "gn:population":0,
    "gn:timezone":"Africa/Kigali",
    "iso:country":"RW",
    "name:und_x_variant":[
        "Plateau Kaniga",
        "Kaninga",
        "Kizinga",
        "Kazinga"
    ],
    "wof:name":"Kizinga",
    "wof:placetype":"locality"
},
  "geometry": {"coordinates":[30.07803,-1.40853],"type":"Point"}
}