{
  "type": "Feature",
  "properties": {
    "gn:admin1_code":"14.0",
    "gn:admin2_code":"36",
    "gn:admin3_code":"3611.0",
    "gn:admin4_code":"361103.0",
    "gn:asciiname":"Nyakanyinya",
    "gn:country_code":"RW",
    "gn:dem":1811,
    "gn:feature_class":"P",
    "gn:feature_code":"PPLL",
    "gn:name":"Nyakanyinya",
    "gn:population":0,
    "gn:timezone":"Africa/Kigali",
    "iso:country":"RW",
    "name:und_x_variant":[
        "Colline Nyakanyinya",
        "Nyakanyinya"
    ],
    "wof:name":"Nyakanyinya",
    "wof:placetype":"locality"
},
  "geometry": {"coordinates":[28.9359,-2.5178],"type":"Point"}
}