{
  "type": "Feature",
  "properties": {
    "gn:admin1_code":"11",
    "gn:admin2_code":"55.0",
    "gn:admin3_code":"5509.0",
    "gn:admin4_code":"550905.0",
    "gn:asciiname":"Rwamuhigi",
    "gn:country_code":"RW",
    "gn:dem":1550,
    "gn:feature_class":"P",
    "gn:feature_code":"PPLL",
    "gn:name":"Rwamuhigi",
    "gn:population":0,
    "gn:timezone":"Africa/Kigali",
    "iso:country":"RW",
    "wof:name":"Rwamuhigi",
    "wof:placetype":"locality"
},
  "geometry": {"coordinates":[30.7027,-2.1937],"type":"Point"}
}