{
  "type": "Feature",
  "properties": {
    "gn:admin1_code":"15",
    "gn:admin2_code":"24.0",
    "gn:admin3_code":"2405.0",
    "gn:admin4_code":"240501.0",
    "gn:asciiname":"Nyarurama",
    "gn:country_code":"RW",
    "gn:dem":1530,
    "gn:feature_class":"P",
    "gn:feature_code":"PPLL",
    "gn:name":"Nyarurama",
    "gn:population":0,
    "gn:timezone":"Africa/Kigali",
    "iso:country":"RW",
    "wof:name":"Nyarurama",
    "wof:placetype":"locality"
},
  "geometry": {"coordinates":[29.7982,-2.4535],"type":"Point"}
}