{
  "type": "Feature",
  "properties": {
    "gn:admin1_code":"14.0",
    "gn:asciiname":"Kibogora",
    "gn:country_code":"RW",
    "gn:dem":1461,
    "gn:feature_class":"P",
    "gn:feature_code":"PPL",
    "gn:name":"Kibogora",
    "gn:population":0,
    "gn:timezone":"Africa/Kigali",
    "iso:country":"RW",
    "name:und_x_variant":[
        "Kibogoro",
        "Kibogora"
    ],
    "wof:name":"Kibogora",
    "wof:placetype":"locality"
},
  "geometry": {"coordinates":[29.1309,-2.3212],"type":"Point"}
}