{
  "type": "Feature",
  "properties": {
    "gn:admin1_code":"14.0",
    "gn:admin2_code":"37",
    "gn:admin3_code":"3712.0",
    "gn:admin4_code":"371201.0",
    "gn:asciiname":"Kamahongo",
    "gn:country_code":"RW",
    "gn:dem":1517,
    "gn:feature_class":"P",
    "gn:feature_code":"PPLL",
    "gn:name":"Kamahongo",
    "gn:population":0,
    "gn:timezone":"Africa/Kigali",
    "iso:country":"RW",
    "wof:name":"Kamahongo",
    "wof:placetype":"locality"
},
  "geometry": {"coordinates":[29.0501,-2.3179],"type":"Point"}
}