{
  "type": "Feature",
  "properties": {
    "gn:admin1_code":"14",
    "gn:admin2_code":"35.0",
    "gn:admin3_code":"3512.0",
    "gn:admin4_code":"351201.0",
    "gn:asciiname":"Gakoma",
    "gn:country_code":"RW",
    "gn:dem":1641,
    "gn:feature_class":"P",
    "gn:feature_code":"PPLL",
    "gn:name":"Gakoma",
    "gn:population":0,
    "gn:timezone":"Africa/Kigali",
    "iso:country":"RW",
    "wof:name":"Gakoma",
    "wof:placetype":"locality"
},
  "geometry": {"coordinates":[29.6168,-2.0289],"type":"Point"}
}