{
  "type": "Feature",
  "properties": {
    "gn:admin1_code":"11",
    "gn:admin2_code":"55.0",
    "gn:admin3_code":"5511.0",
    "gn:admin4_code":"551103.0",
    "gn:asciiname":"Paysannat A",
    "gn:country_code":"RW",
    "gn:dem":1429,
    "gn:feature_class":"P",
    "gn:feature_code":"PPLL",
    "gn:name":"Paysannat A",
    "gn:population":0,
    "gn:timezone":"Africa/Kigali",
    "iso:country":"RW",
    "wof:name":"Paysannat A",
    "wof:placetype":"locality"
},
  "geometry": {"coordinates":[30.7605,-2.2663],"type":"Point"}
}