{
  "type": "Feature",
  "properties": {
    "gn:admin1_code":"14",
    "gn:admin2_code":"34.0",
    "gn:admin3_code":"3407.0",
    "gn:admin4_code":"340702.0",
    "gn:asciiname":"Kivunja",
    "gn:country_code":"RW",
    "gn:dem":2314,
    "gn:feature_class":"P",
    "gn:feature_code":"PPLL",
    "gn:name":"Kivunja",
    "gn:population":0,
    "gn:timezone":"Africa/Kigali",
    "iso:country":"RW",
    "wof:name":"Kivunja",
    "wof:placetype":"locality"
},
  "geometry": {"coordinates":[29.51126,-1.61744],"type":"Point"}
}