{
  "type": "Feature",
  "properties": {
    "gn:admin1_code":"13.0",
    "gn:admin2_code":"44",
    "gn:admin3_code":"4413.0",
    "gn:admin4_code":"441303.0",
    "gn:asciiname":"Maya",
    "gn:country_code":"RW",
    "gn:dem":2063,
    "gn:feature_class":"P",
    "gn:feature_code":"PPLL",
    "gn:name":"Maya",
    "gn:population":0,
    "gn:timezone":"Africa/Kigali",
    "iso:country":"RW",
    "name:und_x_variant":[
        "Colline Maya",
        "Maya"
    ],
    "wof:name":"Maya",
    "wof:placetype":"locality"
},
  "geometry": {"coordinates":[29.7064,-1.4357],"type":"Point"}
}