{
  "type": "Feature",
  "properties": {
    "gn:admin1_code":"14",
    "gn:admin2_code":"31.0",
    "gn:admin3_code":"3106.0",
    "gn:admin4_code":"310603.0",
    "gn:asciiname":"Nyabiranga",
    "gn:country_code":"RW",
    "gn:dem":1761,
    "gn:feature_class":"P",
    "gn:feature_code":"PPL",
    "gn:name":"Nyabiranga",
    "gn:population":0,
    "gn:timezone":"Africa/Kigali",
    "iso:country":"RW",
    "wof:name":"Nyabiranga",
    "wof:placetype":"locality"
},
  "geometry": {"coordinates":[29.5367,-2.1713],"type":"Point"}
}