{
  "type": "Feature",
  "properties": {
    "gn:admin1_code":"15",
    "gn:admin2_code":"28.0",
    "gn:admin3_code":"2810.0",
    "gn:admin4_code":"281002.0",
    "gn:asciiname":"Mibilizi",
    "gn:country_code":"RW",
    "gn:dem":1484,
    "gn:feature_class":"P",
    "gn:feature_code":"PPLL",
    "gn:name":"Mibilizi",
    "gn:population":0,
    "gn:timezone":"Africa/Kigali",
    "iso:country":"RW",
    "wof:name":"Mibilizi",
    "wof:placetype":"locality"
},
  "geometry": {"coordinates":[29.9573,-2.025],"type":"Point"}
}