{
  "type": "Feature",
  "properties": {
    "gn:admin1_code":"14.0",
    "gn:admin2_code":"35",
    "gn:admin3_code":"3509.0",
    "gn:admin4_code":"350903.0",
    "gn:asciiname":"Mikingo",
    "gn:country_code":"RW",
    "gn:dem":1766,
    "gn:feature_class":"P",
    "gn:feature_code":"PPLL",
    "gn:name":"Mikingo",
    "gn:population":0,
    "gn:timezone":"Africa/Kigali",
    "iso:country":"RW",
    "name:und_x_variant":[
        "Colline Mikingo",
        "Mikingo"
    ],
    "wof:name":"Mikingo",
    "wof:placetype":"locality"
},
  "geometry": {"coordinates":[29.6297,-1.8921],"type":"Point"}
}