{
  "type": "Feature",
  "properties": {
    "gn:admin1_code":"11",
    "gn:admin2_code":"51.0",
    "gn:admin3_code":"5107.0",
    "gn:admin4_code":"510703.0",
    "gn:asciiname":"Kinganzwa",
    "gn:country_code":"RW",
    "gn:dem":1431,
    "gn:feature_class":"P",
    "gn:feature_code":"PPLL",
    "gn:name":"Kinganzwa",
    "gn:population":0,
    "gn:timezone":"Africa/Kigali",
    "iso:country":"RW",
    "wof:name":"Kinganzwa",
    "wof:placetype":"locality"
},
  "geometry": {"coordinates":[30.4399,-2.0263],"type":"Point"}
}