{
  "type": "Feature",
  "properties": {
    "gn:admin1_code":"12.0",
    "gn:admin2_code":"12",
    "gn:admin3_code":"1214.0",
    "gn:admin4_code":"121402.0",
    "gn:asciiname":"Bandazi",
    "gn:country_code":"RW",
    "gn:dem":1392,
    "gn:feature_class":"P",
    "gn:feature_code":"PPLL",
    "gn:name":"Bandazi",
    "gn:population":0,
    "gn:timezone":"Africa/Kigali",
    "iso:country":"RW",
    "name:und_x_variant":[
        "Colline Bandazi",
        "Bandazi"
    ],
    "wof:name":"Bandazi",
    "wof:placetype":"locality"
},
  "geometry": {"coordinates":[30.23333,-1.93333],"type":"Point"}
}