{
  "type": "Feature",
  "properties": {
    "gn:admin1_code":"15",
    "gn:admin2_code":"23.0",
    "gn:admin3_code":"2311.0",
    "gn:admin4_code":"231104.0",
    "gn:asciiname":"Karamba",
    "gn:country_code":"RW",
    "gn:dem":1757,
    "gn:feature_class":"P",
    "gn:feature_code":"PPLL",
    "gn:name":"Karamba",
    "gn:population":0,
    "gn:timezone":"Africa/Kigali",
    "iso:country":"RW",
    "name:ceb_x_preferred":[
        "Karamba"
    ],
    "name:swe_x_preferred":[
        "Karamba"
    ],
    "wof:name":"Karamba",
    "wof:placetype":"locality"
},
  "geometry": {"coordinates":[29.6231,-2.7519],"type":"Point"}
}