{
  "type": "Feature",
  "properties": {
    "gn:admin1_code":"12",
    "gn:admin2_code":"11.0",
    "gn:admin3_code":"1105.0",
    "gn:admin4_code":"110502.0",
    "gn:asciiname":"Buye",
    "gn:country_code":"RW",
    "gn:dem":1385,
    "gn:feature_class":"P",
    "gn:feature_code":"PPLL",
    "gn:name":"Buye",
    "gn:population":0,
    "gn:timezone":"Africa/Kigali",
    "iso:country":"RW",
    "wof:name":"Buye",
    "wof:placetype":"locality"
},
  "geometry": {"coordinates":[30.0065,-2.0361],"type":"Point"}
}