{
  "type": "Feature",
  "properties": {
    "gn:admin1_code":"13",
    "gn:admin2_code":"41.0",
    "gn:admin3_code":"4110.0",
    "gn:admin4_code":"411002.0",
    "gn:asciiname":"Mushali",
    "gn:country_code":"RW",
    "gn:dem":2011,
    "gn:feature_class":"P",
    "gn:feature_code":"PPLL",
    "gn:name":"Mushali",
    "gn:population":0,
    "gn:timezone":"Africa/Kigali",
    "iso:country":"RW",
    "wof:name":"Mushali",
    "wof:placetype":"locality"
},
  "geometry": {"coordinates":[29.9734,-1.762],"type":"Point"}
}