{
  "type": "Feature",
  "properties": {
    "gn:admin1_code":"11",
    "gn:admin2_code":"53.0",
    "gn:admin3_code":"5308.0",
    "gn:admin4_code":"530804.0",
    "gn:asciiname":"Nyange II",
    "gn:country_code":"RW",
    "gn:dem":1820,
    "gn:feature_class":"P",
    "gn:feature_code":"PPLL",
    "gn:name":"Nyange II",
    "gn:population":0,
    "gn:timezone":"Africa/Kigali",
    "iso:country":"RW",
    "wof:name":"Nyange II",
    "wof:placetype":"locality"
},
  "geometry": {"coordinates":[30.2938,-1.7445],"type":"Point"}
}