{
  "type": "Feature",
  "properties": {
    "gn:admin1_code":"13",
    "gn:admin2_code":"45.0",
    "gn:admin3_code":"4518.0",
    "gn:admin4_code":"451805.0",
    "gn:asciiname":"Rambura",
    "gn:country_code":"RW",
    "gn:dem":1741,
    "gn:feature_class":"P",
    "gn:feature_code":"PPLL",
    "gn:name":"Rambura",
    "gn:population":0,
    "gn:timezone":"Africa/Kigali",
    "iso:country":"RW",
    "wof:name":"Rambura",
    "wof:placetype":"locality"
},
  "geometry": {"coordinates":[30.1412,-1.7276],"type":"Point"}
}