{
  "type": "Feature",
  "properties": {
    "gn:admin1_code":"14.0",
    "gn:admin2_code":"36",
    "gn:admin3_code":"3612.0",
    "gn:admin4_code":"361204.0",
    "gn:asciiname":"Rugaragara",
    "gn:country_code":"RW",
    "gn:dem":1634,
    "gn:feature_class":"P",
    "gn:feature_code":"PPLL",
    "gn:name":"Rugaragara",
    "gn:population":0,
    "gn:timezone":"Africa/Kigali",
    "iso:country":"RW",
    "name:und_x_variant":[
        "Colline Rugaragara",
        "Rugaragara"
    ],
    "wof:name":"Rugaragara",
    "wof:placetype":"locality"
},
  "geometry": {"coordinates":[28.9428,-2.4025],"type":"Point"}
}