{
  "type": "Feature",
  "properties": {
    "gn:admin1_code":"13",
    "gn:admin2_code":"42.0",
    "gn:admin3_code":"4218.0",
    "gn:admin4_code":"421801.0",
    "gn:asciiname":"Gahama",
    "gn:country_code":"RW",
    "gn:dem":1635,
    "gn:feature_class":"P",
    "gn:feature_code":"PPLL",
    "gn:name":"Gahama",
    "gn:population":0,
    "gn:timezone":"Africa/Kigali",
    "iso:country":"RW",
    "name:run_x_preferred":[
        "Gahama"
    ],
    "wof:name":"Gahama",
    "wof:placetype":"locality"
},
  "geometry": {"coordinates":[29.646,-1.6207],"type":"Point"}
}