{
  "type": "Feature",
  "properties": {
    "gn:admin1_code":"15.0",
    "gn:admin2_code":"22",
    "gn:admin3_code":"2209.0",
    "gn:admin4_code":"220904.0",
    "gn:asciiname":"Runyinya",
    "gn:country_code":"RW",
    "gn:dem":1605,
    "gn:feature_class":"P",
    "gn:feature_code":"PPL",
    "gn:name":"Runyinya",
    "gn:population":0,
    "gn:timezone":"Africa/Kigali",
    "iso:country":"RW",
    "name:und_x_variant":[
        "Colline Runyinya",
        "Runyinya"
    ],
    "wof:name":"Runyinya",
    "wof:placetype":"locality"
},
  "geometry": {"coordinates":[29.8761,-2.7127],"type":"Point"}
}