{
  "type": "Feature",
  "properties": {
    "gn:admin1_code":"13",
    "gn:admin2_code":"42.0",
    "gn:admin3_code":"4218.0",
    "gn:admin4_code":"421802.0",
    "gn:asciiname":"Kidomo",
    "gn:country_code":"RW",
    "gn:dem":1726,
    "gn:feature_class":"P",
    "gn:feature_code":"PPLL",
    "gn:name":"Kidomo",
    "gn:population":0,
    "gn:timezone":"Africa/Kigali",
    "iso:country":"RW",
    "wof:name":"Kidomo",
    "wof:placetype":"locality"
},
  "geometry": {"coordinates":[29.6715,-1.645],"type":"Point"}
}