{
  "type": "Feature",
  "properties": {
    "gn:admin1_code":"15.0",
    "gn:admin2_code":"23",
    "gn:admin3_code":"2306.0",
    "gn:admin4_code":"230601.0",
    "gn:asciiname":"Nyamatama",
    "gn:country_code":"RW",
    "gn:dem":1902,
    "gn:feature_class":"P",
    "gn:feature_code":"PPLL",
    "gn:name":"Nyamatama",
    "gn:population":0,
    "gn:timezone":"Africa/Kigali",
    "iso:country":"RW",
    "wof:name":"Nyamatama",
    "wof:placetype":"locality"
},
  "geometry": {"coordinates":[29.5081,-2.6552],"type":"Point"}
}