{
  "type": "Feature",
  "properties": {
    "gn:admin1_code":"13",
    "gn:admin2_code":"44.0",
    "gn:admin3_code":"4410.0",
    "gn:admin4_code":"441004.0",
    "gn:asciiname":"Gisiza",
    "gn:country_code":"RW",
    "gn:dem":2073,
    "gn:feature_class":"P",
    "gn:feature_code":"PPLL",
    "gn:name":"Gisiza",
    "gn:population":0,
    "gn:timezone":"Africa/Kigali",
    "iso:country":"RW",
    "wof:name":"Gisiza",
    "wof:placetype":"locality"
},
  "geometry": {"coordinates":[29.8311,-1.3486],"type":"Point"}
}