{
  "type": "Feature",
  "properties": {
    "gn:admin1_code":"13",
    "gn:admin2_code":"42.0",
    "gn:admin3_code":"4213.0",
    "gn:admin4_code":"421305.0",
    "gn:asciiname":"Gahinga",
    "gn:country_code":"RW",
    "gn:dem":1795,
    "gn:feature_class":"P",
    "gn:feature_code":"PPLL",
    "gn:name":"Gahinga",
    "gn:population":0,
    "gn:timezone":"Africa/Kigali",
    "iso:country":"RW",
    "wof:name":"Gahinga",
    "wof:placetype":"locality"
},
  "geometry": {"coordinates":[29.8659,-1.7816],"type":"Point"}
}