{
  "type": "Feature",
  "properties": {
    "gn:admin1_code":"11",
    "gn:admin2_code":"56.0",
    "gn:admin3_code":"5614.0",
    "gn:admin4_code":"561403.0",
    "gn:asciiname":"Rubago",
    "gn:country_code":"RW",
    "gn:dem":1459,
    "gn:feature_class":"P",
    "gn:feature_code":"PPLL",
    "gn:name":"Rubago",
    "gn:population":0,
    "gn:timezone":"Africa/Kigali",
    "iso:country":"RW",
    "wof:name":"Rubago",
    "wof:placetype":"locality"
},
  "geometry": {"coordinates":[30.4308,-2.1617],"type":"Point"}
}