{
  "type": "Feature",
  "properties": {
    "gn:admin1_code":"14",
    "gn:admin2_code":"34.0",
    "gn:admin3_code":"3412.0",
    "gn:admin4_code":"341203.0",
    "gn:asciiname":"Kabuguzo",
    "gn:country_code":"RW",
    "gn:dem":2152,
    "gn:feature_class":"P",
    "gn:feature_code":"PPLL",
    "gn:name":"Kabuguzo",
    "gn:population":0,
    "gn:timezone":"Africa/Kigali",
    "iso:country":"RW",
    "wof:name":"Kabuguzo",
    "wof:placetype":"locality"
},
  "geometry": {"coordinates":[29.6075,-1.7129],"type":"Point"}
}