{
  "type": "Feature",
  "properties": {
    "gn:admin1_code":"14",
    "gn:admin2_code":"34.0",
    "gn:admin3_code":"3403.0",
    "gn:admin4_code":"340302.0",
    "gn:asciiname":"Gasura",
    "gn:country_code":"RW",
    "gn:dem":2170,
    "gn:feature_class":"P",
    "gn:feature_code":"PPLL",
    "gn:name":"Gasura",
    "gn:population":0,
    "gn:timezone":"Africa/Kigali",
    "iso:country":"RW",
    "wof:name":"Gasura",
    "wof:placetype":"locality"
},
  "geometry": {"coordinates":[29.5465,-1.7237],"type":"Point"}
}