{
  "type": "Feature",
  "properties": {
    "gn:admin1_code":"11",
    "gn:admin2_code":"51.0",
    "gn:admin3_code":"5108.0",
    "gn:admin4_code":"510805.0",
    "gn:asciiname":"Nkomangwa",
    "gn:country_code":"RW",
    "gn:dem":1563,
    "gn:feature_class":"P",
    "gn:feature_code":"PPLL",
    "gn:name":"Nkomangwa",
    "gn:population":0,
    "gn:timezone":"Africa/Kigali",
    "iso:country":"RW",
    "wof:name":"Nkomangwa",
    "wof:placetype":"locality"
},
  "geometry": {"coordinates":[30.3822,-1.9097],"type":"Point"}
}