{
  "type": "Feature",
  "properties": {
    "gn:admin1_code":"15.0",
    "gn:admin2_code":"25",
    "gn:admin3_code":"2515.0",
    "gn:admin4_code":"251501.0",
    "gn:asciiname":"Rugeyo",
    "gn:country_code":"RW",
    "gn:dem":2190,
    "gn:feature_class":"P",
    "gn:feature_code":"PPL",
    "gn:name":"Rugeyo",
    "gn:population":0,
    "gn:timezone":"Africa/Kigali",
    "iso:country":"RW",
    "wof:name":"Rugeyo",
    "wof:placetype":"locality"
},
  "geometry": {"coordinates":[29.4143,-2.317],"type":"Point"}
}