{
  "type": "Feature",
  "properties": {
    "gn:admin1_code":"11",
    "gn:admin2_code":"57.0",
    "gn:admin3_code":"5704.0",
    "gn:admin4_code":"570404.0",
    "gn:asciiname":"Rango",
    "gn:country_code":"RW",
    "gn:dem":1455,
    "gn:feature_class":"P",
    "gn:feature_code":"PPLL",
    "gn:name":"Rango",
    "gn:population":0,
    "gn:timezone":"Africa/Kigali",
    "iso:country":"RW",
    "name:ceb_x_preferred":[
        "Rango"
    ],
    "name:ces_x_preferred":[
        "Rango"
    ],
    "name:deu_x_preferred":[
        "Rango"
    ],
    "name:epo_x_preferred":[
        "Rango"
    ],
    "name:eus_x_preferred":[
        "Rango"
    ],
    "name:fin_x_preferred":[
        "Rango"
    ],
    "name:fra_x_preferred":[
        "Rango"
    ],
    "name:ita_x_preferred":[
        "Rango"
    ],
    "name:msa_x_preferred":[
        "Rango"
    ],
    "name:nld_x_preferred":[
        "Rango"
    ],
    "name:spa_x_preferred":[
        "Rango"
    ],
    "name:swe_x_preferred":[
        "Rango"
    ],
    "name:uzb_x_preferred":[
        "Rango"
    ],
    "wof:name":"Rango",
    "wof:placetype":"locality"
},
  "geometry": {"coordinates":[30.0392,-2.288],"type":"Point"}
}