{
  "type": "Feature",
  "properties": {
    "gn:admin1_code":"15.0",
    "gn:admin2_code":"25",
    "gn:admin3_code":"2511.0",
    "gn:admin4_code":"251101.0",
    "gn:asciiname":"Karambi",
    "gn:country_code":"RW",
    "gn:dem":1876,
    "gn:feature_class":"P",
    "gn:feature_code":"PPLL",
    "gn:name":"Karambi",
    "gn:population":0,
    "gn:timezone":"Africa/Kigali",
    "iso:country":"RW",
    "wof:name":"Karambi",
    "wof:placetype":"locality"
},
  "geometry": {"coordinates":[29.5188,-2.3216],"type":"Point"}
}