{
  "type": "Feature",
  "properties": {
    "gn:admin1_code":"14.0",
    "gn:admin2_code":"34",
    "gn:admin3_code":"3407.0",
    "gn:admin4_code":"340706.0",
    "gn:asciiname":"Rukoma",
    "gn:country_code":"RW",
    "gn:dem":2300,
    "gn:feature_class":"P",
    "gn:feature_code":"PPLL",
    "gn:name":"Rukoma",
    "gn:population":0,
    "gn:timezone":"Africa/Kigali",
    "iso:country":"RW",
    "name:und_x_variant":[
        "Colline Rukoma",
        "Rukoma"
    ],
    "wof:name":"Rukoma",
    "wof:placetype":"locality"
},
  "geometry": {"coordinates":[29.5337,-1.6043],"type":"Point"}
}