{
  "type": "Feature",
  "properties": {
    "gn:admin1_code":"13",
    "gn:admin2_code":"43.0",
    "gn:admin3_code":"4312.0",
    "gn:admin4_code":"431201.0",
    "gn:asciiname":"Kamwumba",
    "gn:country_code":"RW",
    "gn:dem":2144,
    "gn:feature_class":"P",
    "gn:feature_code":"PPLL",
    "gn:name":"Kamwumba",
    "gn:population":0,
    "gn:timezone":"Africa/Kigali",
    "iso:country":"RW",
    "wof:name":"Kamwumba",
    "wof:placetype":"locality"
},
  "geometry": {"coordinates":[29.5997,-1.4513],"type":"Point"}
}