{
  "type": "Feature",
  "properties": {
    "gn:admin1_code":"15",
    "gn:admin2_code":"28.0",
    "gn:admin3_code":"2807.0",
    "gn:admin4_code":"280701.0",
    "gn:asciiname":"Musenyi",
    "gn:country_code":"RW",
    "gn:dem":1416,
    "gn:feature_class":"P",
    "gn:feature_code":"PPLL",
    "gn:name":"Musenyi",
    "gn:population":0,
    "gn:timezone":"Africa/Kigali",
    "iso:country":"RW",
    "wof:name":"Musenyi",
    "wof:placetype":"locality"
},
  "geometry": {"coordinates":[29.9315,-1.8852],"type":"Point"}
}