{
  "type": "Feature",
  "properties": {
    "gn:admin1_code":"13.0",
    "gn:admin2_code":"41",
    "gn:admin3_code":"4113.0",
    "gn:admin4_code":"411303.0",
    "gn:asciiname":"Ntarabana",
    "gn:country_code":"RW",
    "gn:dem":1715,
    "gn:feature_class":"P",
    "gn:feature_code":"PPL",
    "gn:name":"Ntarabana",
    "gn:population":0,
    "gn:timezone":"Africa/Kigali",
    "iso:country":"RW",
    "name:und_x_variant":[
        "Colline Ntarabana",
        "Ntarabana"
    ],
    "wof:name":"Ntarabana",
    "wof:placetype":"locality"
},
  "geometry": {"coordinates":[30.0966,-1.7873],"type":"Point"}
}