{
  "type": "Feature",
  "properties": {
    "gn:admin1_code":"15.0",
    "gn:admin2_code":"25",
    "gn:admin3_code":"2501.0",
    "gn:admin4_code":"250102.0",
    "gn:asciiname":"Bitebo",
    "gn:country_code":"RW",
    "gn:dem":2166,
    "gn:feature_class":"P",
    "gn:feature_code":"PPLL",
    "gn:name":"Bitebo",
    "gn:population":0,
    "gn:timezone":"Africa/Kigali",
    "iso:country":"RW",
    "wof:name":"Bitebo",
    "wof:placetype":"locality"
},
  "geometry": {"coordinates":[29.4499,-2.4443],"type":"Point"}
}