{
  "type": "Feature",
  "properties": {
    "gn:admin1_code":"14.0",
    "gn:asciiname":"Bitare",
    "gn:country_code":"RW",
    "gn:dem":1461,
    "gn:feature_class":"P",
    "gn:feature_code":"PPLL",
    "gn:name":"Bitare",
    "gn:population":0,
    "gn:timezone":"Africa/Kigali",
    "iso:country":"RW",
    "name:und_x_variant":[
        "Colline Bitare",
        "Bitare"
    ],
    "wof:name":"Bitare",
    "wof:placetype":"locality"
},
  "geometry": {"coordinates":[29.05381,-2.39943],"type":"Point"}
}