{
  "type": "Feature",
  "properties": {
    "gn:admin1_code":"11",
    "gn:admin2_code":"56.0",
    "gn:admin3_code":"5610.0",
    "gn:admin4_code":"561002.0",
    "gn:asciiname":"Rwamuyaga",
    "gn:country_code":"RW",
    "gn:dem":1491,
    "gn:feature_class":"P",
    "gn:feature_code":"PPLL",
    "gn:name":"Rwamuyaga",
    "gn:population":0,
    "gn:timezone":"Africa/Kigali",
    "iso:country":"RW",
    "wof:name":"Rwamuyaga",
    "wof:placetype":"locality"
},
  "geometry": {"coordinates":[30.6262,-2.1309],"type":"Point"}
}