{
  "type": "Feature",
  "properties": {
    "gn:admin1_code":"13",
    "gn:admin2_code":"42.0",
    "gn:admin3_code":"4201.0",
    "gn:admin4_code":"420104.0",
    "gn:asciiname":"Rwankuba",
    "gn:country_code":"RW",
    "gn:dem":1871,
    "gn:feature_class":"P",
    "gn:feature_code":"PPLL",
    "gn:name":"Rwankuba",
    "gn:population":0,
    "gn:timezone":"Africa/Kigali",
    "iso:country":"RW",
    "wof:name":"Rwankuba",
    "wof:placetype":"locality"
},
  "geometry": {"coordinates":[29.7448,-1.634],"type":"Point"}
}