{
  "type": "Feature",
  "properties": {
    "gn:admin1_code":"15.0",
    "gn:admin2_code":"24",
    "gn:admin3_code":"2406.0",
    "gn:admin4_code":"240605.0",
    "gn:asciiname":"Maraba",
    "gn:country_code":"RW",
    "gn:dem":1681,
    "gn:feature_class":"P",
    "gn:feature_code":"PPL",
    "gn:name":"Maraba",
    "gn:population":0,
    "gn:timezone":"Africa/Kigali",
    "iso:country":"RW",
    "name:ceb_x_preferred":[
        "Maraba"
    ],
    "name:fra_x_preferred":[
        "Maraba"
    ],
    "name:ita_x_preferred":[
        "Maraba"
    ],
    "name:swe_x_preferred":[
        "Maraba"
    ],
    "wof:name":"Maraba",
    "wof:placetype":"locality"
},
  "geometry": {"coordinates":[29.6413,-2.534],"type":"Point"}
}