{
  "type": "Feature",
  "properties": {
    "gn:admin1_code":"13",
    "gn:admin2_code":"45.0",
    "gn:admin3_code":"4513.0",
    "gn:admin4_code":"451307.0",
    "gn:asciiname":"Miyange",
    "gn:country_code":"RW",
    "gn:dem":2070,
    "gn:feature_class":"P",
    "gn:feature_code":"PPLL",
    "gn:name":"Miyange",
    "gn:population":0,
    "gn:timezone":"Africa/Kigali",
    "iso:country":"RW",
    "wof:name":"Miyange",
    "wof:placetype":"locality"
},
  "geometry": {"coordinates":[30.123,-1.681],"type":"Point"}
}