{
  "type": "Feature",
  "properties": {
    "gn:admin1_code":"15.0",
    "gn:admin2_code":"22",
    "gn:admin3_code":"2205.0",
    "gn:admin4_code":"220506.0",
    "gn:asciiname":"Akankuba",
    "gn:country_code":"RW",
    "gn:dem":1676,
    "gn:feature_class":"P",
    "gn:feature_code":"PPLL",
    "gn:name":"Akankuba",
    "gn:population":0,
    "gn:timezone":"Africa/Kigali",
    "iso:country":"RW",
    "wof:name":"Akankuba",
    "wof:placetype":"locality"
},
  "geometry": {"coordinates":[29.7452,-2.7187],"type":"Point"}
}