{
  "type": "Feature",
  "properties": {
    "gn:admin1_code":"14.0",
    "gn:admin2_code":"37",
    "gn:admin3_code":"3705.0",
    "gn:admin4_code":"370503.0",
    "gn:asciiname":"Murwa",
    "gn:country_code":"RW",
    "gn:dem":1481,
    "gn:feature_class":"P",
    "gn:feature_code":"PPLL",
    "gn:name":"Murwa",
    "gn:population":0,
    "gn:timezone":"Africa/Kigali",
    "iso:country":"RW",
    "wof:name":"Murwa",
    "wof:placetype":"locality"
},
  "geometry": {"coordinates":[29.0768,-2.3373],"type":"Point"}
}