{
  "type": "Feature",
  "properties": {
    "gn:admin1_code":"11.0",
    "gn:admin2_code":"56",
    "gn:admin3_code":"5611.0",
    "gn:admin4_code":"561101.0",
    "gn:asciiname":"Rugendo",
    "gn:country_code":"RW",
    "gn:dem":1369,
    "gn:feature_class":"P",
    "gn:feature_code":"PPL",
    "gn:name":"Rugendo",
    "gn:population":0,
    "gn:timezone":"Africa/Kigali",
    "iso:country":"RW",
    "wof:name":"Rugendo",
    "wof:placetype":"locality"
},
  "geometry": {"coordinates":[30.28333,-2.20222],"type":"Point"}
}