{
  "type": "Feature",
  "properties": {
    "gn:admin1_code":"15",
    "gn:admin2_code":"24.0",
    "gn:admin3_code":"2405.0",
    "gn:admin4_code":"240503.0",
    "gn:asciiname":"Kigufi",
    "gn:country_code":"RW",
    "gn:dem":1529,
    "gn:feature_class":"P",
    "gn:feature_code":"PPLL",
    "gn:name":"Kigufi",
    "gn:population":0,
    "gn:timezone":"Africa/Kigali",
    "iso:country":"RW",
    "wof:name":"Kigufi",
    "wof:placetype":"locality"
},
  "geometry": {"coordinates":[29.8072,-2.4073],"type":"Point"}
}