{
  "type": "Feature",
  "properties": {
    "gn:admin1_code":"13",
    "gn:admin2_code":"42.0",
    "gn:admin3_code":"4202.0",
    "gn:admin4_code":"420202.0",
    "gn:asciiname":"Matavu",
    "gn:country_code":"RW",
    "gn:dem":2057,
    "gn:feature_class":"P",
    "gn:feature_code":"PPLL",
    "gn:name":"Matavu",
    "gn:population":0,
    "gn:timezone":"Africa/Kigali",
    "iso:country":"RW",
    "wof:name":"Matavu",
    "wof:placetype":"locality"
},
  "geometry": {"coordinates":[29.8248,-1.7834],"type":"Point"}
}