{
  "type": "Feature",
  "properties": {
    "gn:admin1_code":"15",
    "gn:admin2_code":"28.0",
    "gn:admin3_code":"2809.0",
    "gn:admin4_code":"280905.0",
    "gn:asciiname":"Bahimba",
    "gn:country_code":"RW",
    "gn:dem":1697,
    "gn:feature_class":"P",
    "gn:feature_code":"PPLL",
    "gn:name":"Bahimba",
    "gn:population":0,
    "gn:timezone":"Africa/Kigali",
    "iso:country":"RW",
    "wof:name":"Bahimba",
    "wof:placetype":"locality"
},
  "geometry": {"coordinates":[29.8181,-2.0792],"type":"Point"}
}