{
  "type": "Feature",
  "properties": {
    "gn:admin1_code":"15.0",
    "gn:admin2_code":"23",
    "gn:admin3_code":"2314.0",
    "gn:admin4_code":"231402.0",
    "gn:asciiname":"Remera",
    "gn:country_code":"RW",
    "gn:dem":1826,
    "gn:feature_class":"P",
    "gn:feature_code":"PPLL",
    "gn:name":"Remera",
    "gn:population":0,
    "gn:timezone":"Africa/Kigali",
    "iso:country":"RW",
    "wof:name":"Remera",
    "wof:placetype":"locality"
},
  "geometry": {"coordinates":[29.5933,-2.6892],"type":"Point"}
}