{
  "type": "Feature",
  "properties": {
    "gn:admin1_code":"14",
    "gn:asciiname":"Nyamishaba",
    "gn:country_code":"RW",
    "gn:dem":1461,
    "gn:feature_class":"P",
    "gn:feature_code":"PPL",
    "gn:name":"Nyamishaba",
    "gn:population":0,
    "gn:timezone":"Africa/Kigali",
    "iso:country":"RW",
    "wof:name":"Nyamishaba",
    "wof:placetype":"locality"
},
  "geometry": {"coordinates":[29.3323,-2.0672],"type":"Point"}
}