{
  "type": "Feature",
  "properties": {
    "gn:admin1_code":"11",
    "gn:admin2_code":"56.0",
    "gn:admin3_code":"5605.0",
    "gn:admin4_code":"560505.0",
    "gn:asciiname":"Ruhinga",
    "gn:country_code":"RW",
    "gn:dem":1569,
    "gn:feature_class":"P",
    "gn:feature_code":"PPLL",
    "gn:name":"Ruhinga",
    "gn:population":0,
    "gn:timezone":"Africa/Kigali",
    "iso:country":"RW",
    "wof:name":"Ruhinga",
    "wof:placetype":"locality"
},
  "geometry": {"coordinates":[30.565,-2.1663],"type":"Point"}
}