{
  "type": "Feature",
  "properties": {
    "gn:admin1_code":"12.0",
    "gn:admin2_code":"12",
    "gn:admin3_code":"1212.0",
    "gn:admin4_code":"121206.0",
    "gn:asciiname":"Sha",
    "gn:country_code":"RW",
    "gn:dem":1546,
    "gn:feature_class":"P",
    "gn:feature_code":"PPL",
    "gn:name":"Sha",
    "gn:population":0,
    "gn:timezone":"Africa/Kigali",
    "iso:country":"RW",
    "name:cat_x_preferred":[
        "Sha"
    ],
    "name:ceb_x_preferred":[
        "Sha"
    ],
    "name:fin_x_preferred":[
        "SHA"
    ],
    "name:pol_x_preferred":[
        "Sha"
    ],
    "name:spa_x_preferred":[
        "Sha"
    ],
    "name:swe_x_preferred":[
        "Sha"
    ],
    "wof:name":"Sha",
    "wof:placetype":"locality"
},
  "geometry": {"coordinates":[30.1064,-1.83],"type":"Point"}
}