{
  "type": "Feature",
  "properties": {
    "gn:admin1_code":"15",
    "gn:admin2_code":"28.0",
    "gn:admin3_code":"2803.0",
    "gn:admin4_code":"280304.0",
    "gn:asciiname":"Kirwa",
    "gn:country_code":"RW",
    "gn:dem":1781,
    "gn:feature_class":"P",
    "gn:feature_code":"PPLL",
    "gn:name":"Kirwa",
    "gn:population":0,
    "gn:timezone":"Africa/Kigali",
    "iso:country":"RW",
    "name:deu_x_preferred":[
        "Kirwa"
    ],
    "name:fin_x_preferred":[
        "Kirwa"
    ],
    "wof:name":"Kirwa",
    "wof:placetype":"locality"
},
  "geometry": {"coordinates":[29.8667,-1.8853],"type":"Point"}
}