{
  "type": "Feature",
  "properties": {
    "gn:admin1_code":"15.0",
    "gn:admin2_code":"23",
    "gn:admin3_code":"2303.0",
    "gn:admin4_code":"230306.0",
    "gn:asciiname":"Nyarushishi",
    "gn:country_code":"RW",
    "gn:dem":1869,
    "gn:feature_class":"P",
    "gn:feature_code":"PPL",
    "gn:name":"Nyarushishi",
    "gn:population":0,
    "gn:timezone":"Africa/Kigali",
    "iso:country":"RW",
    "wof:name":"Nyarushishi",
    "wof:placetype":"locality"
},
  "geometry": {"coordinates":[29.5619,-2.6629],"type":"Point"}
}