{
  "type": "Feature",
  "properties": {
    "gn:admin1_code":"15",
    "gn:admin2_code":"22.0",
    "gn:admin3_code":"2207.0",
    "gn:admin4_code":"220701.0",
    "gn:asciiname":"Gitwa",
    "gn:country_code":"RW",
    "gn:dem":1675,
    "gn:feature_class":"P",
    "gn:feature_code":"PPLL",
    "gn:name":"Gitwa",
    "gn:population":0,
    "gn:timezone":"Africa/Kigali",
    "iso:country":"RW",
    "wof:name":"Gitwa",
    "wof:placetype":"locality"
},
  "geometry": {"coordinates":[29.8768,-2.6521],"type":"Point"}
}