{
  "type": "Feature",
  "properties": {
    "gn:admin1_code":"11",
    "gn:admin2_code":"56.0",
    "gn:admin3_code":"5604.0",
    "gn:admin4_code":"560403.0",
    "gn:asciiname":"Mpandu",
    "gn:country_code":"RW",
    "gn:dem":1629,
    "gn:feature_class":"P",
    "gn:feature_code":"PPL",
    "gn:name":"Mpandu",
    "gn:population":0,
    "gn:timezone":"Africa/Kigali",
    "iso:country":"RW",
    "wof:name":"Mpandu",
    "wof:placetype":"locality"
},
  "geometry": {"coordinates":[30.5295,-2.1932],"type":"Point"}
}