{
  "type": "Feature",
  "properties": {
    "gn:admin1_code":"11",
    "gn:admin2_code":"51.0",
    "gn:admin3_code":"5113.0",
    "gn:admin4_code":"511304.0",
    "gn:asciiname":"Ruvomo",
    "gn:country_code":"RW",
    "gn:dem":1355,
    "gn:feature_class":"P",
    "gn:feature_code":"PPLL",
    "gn:name":"Ruvomo",
    "gn:population":0,
    "gn:timezone":"Africa/Kigali",
    "iso:country":"RW",
    "wof:name":"Ruvomo",
    "wof:placetype":"locality"
},
  "geometry": {"coordinates":[30.3045,-2.0594],"type":"Point"}
}