{
  "type": "Feature",
  "properties": {
    "gn:admin1_code":"13",
    "gn:admin2_code":"43.0",
    "gn:admin3_code":"4315.0",
    "gn:admin4_code":"431501.0",
    "gn:asciiname":"Gikoro II",
    "gn:country_code":"RW",
    "gn:dem":2125,
    "gn:feature_class":"P",
    "gn:feature_code":"PPLL",
    "gn:name":"Gikoro II",
    "gn:population":0,
    "gn:timezone":"Africa/Kigali",
    "iso:country":"RW",
    "wof:name":"Gikoro II",
    "wof:placetype":"locality"
},
  "geometry": {"coordinates":[29.5703,-1.5171],"type":"Point"}
}