{
  "type": "Feature",
  "properties": {
    "gn:admin1_code":"14.0",
    "gn:admin2_code":"36",
    "gn:admin3_code":"3617.0",
    "gn:admin4_code":"361704.0",
    "gn:asciiname":"Nyenji",
    "gn:country_code":"RW",
    "gn:dem":1644,
    "gn:feature_class":"P",
    "gn:feature_code":"PPLL",
    "gn:name":"Nyenji",
    "gn:population":0,
    "gn:timezone":"Africa/Kigali",
    "iso:country":"RW",
    "name:und_x_variant":[
        "Colline Nyenje",
        "Nyenje",
        "Nyenji"
    ],
    "wof:name":"Nyenji",
    "wof:placetype":"locality"
},
  "geometry": {"coordinates":[28.9082,-2.65473],"type":"Point"}
}