{
  "type": "Feature",
  "properties": {
    "gn:admin1_code":"13",
    "gn:admin2_code":"42.0",
    "gn:admin3_code":"4207.0",
    "gn:admin4_code":"420702.0",
    "gn:asciiname":"Nyagatovu",
    "gn:country_code":"RW",
    "gn:dem":2178,
    "gn:feature_class":"P",
    "gn:feature_code":"PPLL",
    "gn:name":"Nyagatovu",
    "gn:population":0,
    "gn:timezone":"Africa/Kigali",
    "iso:country":"RW",
    "wof:name":"Nyagatovu",
    "wof:placetype":"locality"
},
  "geometry": {"coordinates":[29.8294,-1.5657],"type":"Point"}
}