{
  "type": "Feature",
  "properties": {
    "gn:admin1_code":"15",
    "gn:admin2_code":"23.0",
    "gn:admin3_code":"2309.0",
    "gn:admin4_code":"230901.0",
    "gn:asciiname":"Fugi",
    "gn:country_code":"RW",
    "gn:dem":1730,
    "gn:feature_class":"P",
    "gn:feature_code":"PPL",
    "gn:name":"Fugi",
    "gn:population":0,
    "gn:timezone":"Africa/Kigali",
    "iso:country":"RW",
    "wof:name":"Fugi",
    "wof:placetype":"locality"
},
  "geometry": {"coordinates":[29.6817,-2.7799],"type":"Point"}
}