{
  "type": "Feature",
  "properties": {
    "gn:admin1_code":"14",
    "gn:admin2_code":"31.0",
    "gn:admin3_code":"3105.0",
    "gn:admin4_code":"310501.0",
    "gn:asciiname":"Buhali",
    "gn:country_code":"RW",
    "gn:dem":1774,
    "gn:feature_class":"P",
    "gn:feature_code":"PPLL",
    "gn:name":"Buhali",
    "gn:population":0,
    "gn:timezone":"Africa/Kigali",
    "iso:country":"RW",
    "wof:name":"Buhali",
    "wof:placetype":"locality"
},
  "geometry": {"coordinates":[29.3436,-2.1172],"type":"Point"}
}