{
  "type": "Feature",
  "properties": {
    "gn:admin1_code":"15.0",
    "gn:admin2_code":"25",
    "gn:admin3_code":"2501.0",
    "gn:admin4_code":"250104.0",
    "gn:asciiname":"Gishwati",
    "gn:country_code":"RW",
    "gn:dem":2309,
    "gn:feature_class":"P",
    "gn:feature_code":"PPLL",
    "gn:name":"Gishwati",
    "gn:population":0,
    "gn:timezone":"Africa/Kigali",
    "iso:country":"RW",
    "wof:name":"Gishwati",
    "wof:placetype":"locality"
},
  "geometry": {"coordinates":[29.4166,-2.4734],"type":"Point"}
}