{
  "type": "Feature",
  "properties": {
    "gn:admin1_code":"15.0",
    "gn:admin2_code":"24",
    "gn:admin3_code":"2406.0",
    "gn:admin4_code":"240603.0",
    "gn:asciiname":"Nyamvumba",
    "gn:country_code":"RW",
    "gn:dem":1792,
    "gn:feature_class":"P",
    "gn:feature_code":"PPLL",
    "gn:name":"Nyamvumba",
    "gn:population":0,
    "gn:timezone":"Africa/Kigali",
    "iso:country":"RW",
    "wof:name":"Nyamvumba",
    "wof:placetype":"locality"
},
  "geometry": {"coordinates":[29.6074,-2.5356],"type":"Point"}
}