{
  "type": "Feature",
  "properties": {
    "gn:admin1_code":"15",
    "gn:admin2_code":"28.0",
    "gn:admin3_code":"2810.0",
    "gn:admin4_code":"281003.0",
    "gn:asciiname":"Taba",
    "gn:country_code":"RW",
    "gn:dem":1422,
    "gn:feature_class":"P",
    "gn:feature_code":"PPLL",
    "gn:name":"Taba",
    "gn:population":0,
    "gn:timezone":"Africa/Kigali",
    "iso:country":"RW",
    "wof:name":"Taba",
    "wof:placetype":"locality"
},
  "geometry": {"coordinates":[29.9887,-2.0242],"type":"Point"}
}