{
  "type": "Feature",
  "properties": {
    "gn:admin1_code":"11.0",
    "gn:admin2_code":"51",
    "gn:admin3_code":"5109.0",
    "gn:admin4_code":"510904.0",
    "gn:asciiname":"Gikoro",
    "gn:country_code":"RW",
    "gn:dem":1665,
    "gn:feature_class":"P",
    "gn:feature_code":"PPL",
    "gn:name":"Gikoro",
    "gn:population":0,
    "gn:timezone":"Africa/Kigali",
    "iso:country":"RW",
    "wof:name":"Gikoro",
    "wof:placetype":"locality"
},
  "geometry": {"coordinates":[30.3332,-1.9323],"type":"Point"}
}