{
  "type": "Feature",
  "properties": {
    "gn:admin1_code":"14",
    "gn:admin2_code":"34.0",
    "gn:admin3_code":"3405.0",
    "gn:admin4_code":"340504.0",
    "gn:asciiname":"Rugogwe",
    "gn:country_code":"RW",
    "gn:dem":2523,
    "gn:feature_class":"P",
    "gn:feature_code":"PPLL",
    "gn:name":"Rugogwe",
    "gn:population":0,
    "gn:timezone":"Africa/Kigali",
    "iso:country":"RW",
    "wof:name":"Rugogwe",
    "wof:placetype":"locality"
},
  "geometry": {"coordinates":[29.4946,-1.6534],"type":"Point"}
}