{
  "type": "Feature",
  "properties": {
    "gn:admin1_code":"15.0",
    "gn:admin2_code":"24",
    "gn:admin3_code":"2401.0",
    "gn:admin4_code":"240102.0",
    "gn:asciiname":"Busoro",
    "gn:country_code":"RW",
    "gn:dem":1684,
    "gn:feature_class":"P",
    "gn:feature_code":"PPL",
    "gn:name":"Busoro",
    "gn:population":0,
    "gn:timezone":"Africa/Kigali",
    "iso:country":"RW",
    "wof:name":"Busoro",
    "wof:placetype":"locality"
},
  "geometry": {"coordinates":[29.6964,-2.6619],"type":"Point"}
}