{
  "type": "Feature",
  "properties": {
    "gn:admin1_code":"15.0",
    "gn:admin2_code":"21",
    "gn:admin3_code":"2109.0",
    "gn:admin4_code":"210903.0",
    "gn:asciiname":"Uwimpura",
    "gn:country_code":"RW",
    "gn:dem":1822,
    "gn:feature_class":"P",
    "gn:feature_code":"PPLL",
    "gn:name":"Uwimpura",
    "gn:population":0,
    "gn:timezone":"Africa/Kigali",
    "iso:country":"RW",
    "wof:name":"Uwimpura",
    "wof:placetype":"locality"
},
  "geometry": {"coordinates":[29.6067,-2.3379],"type":"Point"}
}