{
  "type": "Feature",
  "properties": {
    "gn:admin1_code":"11",
    "gn:admin2_code":"53.0",
    "gn:admin3_code":"5305.0",
    "gn:admin4_code":"530502.0",
    "gn:asciiname":"Mpama",
    "gn:country_code":"RW",
    "gn:dem":1842,
    "gn:feature_class":"P",
    "gn:feature_code":"PPLL",
    "gn:name":"Mpama",
    "gn:population":0,
    "gn:timezone":"Africa/Kigali",
    "iso:country":"RW",
    "name:ceb_x_preferred":[
        "Mpama"
    ],
    "name:swe_x_preferred":[
        "Mpama"
    ],
    "wof:name":"Mpama",
    "wof:placetype":"locality"
},
  "geometry": {"coordinates":[30.2714,-1.7037],"type":"Point"}
}