{
  "type": "Feature",
  "properties": {
    "gn:admin1_code":"11.0",
    "gn:admin2_code":"51",
    "gn:admin3_code":"5101.0",
    "gn:admin4_code":"510101.0",
    "gn:asciiname":"Janjagiro",
    "gn:country_code":"RW",
    "gn:dem":1625,
    "gn:feature_class":"P",
    "gn:feature_code":"PPLL",
    "gn:name":"Janjagiro",
    "gn:population":0,
    "gn:timezone":"Africa/Kigali",
    "iso:country":"RW",
    "name:und_x_variant":[
        "Colline Janjagiro",
        "Janjagiro"
    ],
    "wof:name":"Janjagiro",
    "wof:placetype":"locality"
},
  "geometry": {"coordinates":[30.3018,-1.8667],"type":"Point"}
}