{
  "type": "Feature",
  "properties": {
    "gn:admin1_code":"11",
    "gn:admin2_code":"51.0",
    "gn:admin3_code":"5106.0",
    "gn:admin4_code":"510602.0",
    "gn:asciiname":"Kigogo",
    "gn:country_code":"RW",
    "gn:dem":1522,
    "gn:feature_class":"P",
    "gn:feature_code":"PPLL",
    "gn:name":"Kigogo",
    "gn:population":0,
    "gn:timezone":"Africa/Kigali",
    "iso:country":"RW",
    "name:ita_x_preferred":[
        "Kigogo"
    ],
    "name:swa_x_preferred":[
        "Kigogo"
    ],
    "wof:name":"Kigogo",
    "wof:placetype":"locality"
},
  "geometry": {"coordinates":[30.4532,-1.8921],"type":"Point"}
}