{
  "type": "Feature",
  "properties": {
    "gn:admin1_code":"14",
    "gn:admin2_code":"31.0",
    "gn:admin3_code":"3101.0",
    "gn:admin4_code":"310103.0",
    "gn:asciiname":"Gitarama",
    "gn:country_code":"RW",
    "gn:dem":1884,
    "gn:feature_class":"P",
    "gn:feature_code":"PPLL",
    "gn:name":"Gitarama",
    "gn:population":0,
    "gn:timezone":"Africa/Kigali",
    "iso:country":"RW",
    "name:ara_x_preferred":[
        "\u062c\u064a\u062a\u0627\u0631\u0627\u0645\u0627"
    ],
    "name:ben_x_preferred":[
        "\u0997\u09bf\u09a4\u09be\u09b0\u09be\u09ae\u09be"
    ],
    "name:fas_x_preferred":[
        "\u06af\u06cc\u062a\u0627\u0631\u0627\u0645\u0627"
    ],
    "name:hin_x_preferred":[
        "\u0917\u093f\u0924\u093e\u0930\u093e\u092e\u093e"
    ],
    "name:hun_x_preferred":[
        "Gitarama"
    ],
    "name:ind_x_preferred":[
        "Gitarama"
    ],
    "name:vie_x_preferred":[
        "Gitarama"
    ],
    "wof:name":"Gitarama",
    "wof:placetype":"locality"
},
  "geometry": {"coordinates":[29.3715,-2.1014],"type":"Point"}
}