{
  "type": "Feature",
  "properties": {
    "gn:admin1_code":"14",
    "gn:admin2_code":"31.0",
    "gn:admin3_code":"3101.0",
    "gn:admin4_code":"310103.0",
    "gn:asciiname":"Gitarama",
    "gn:country_code":"RW",
    "gn:dem":1884,
    "gn:feature_class":"P",
    "gn:feature_code":"PPLL",
    "gn:name":"Gitarama",
    "gn:population":0,
    "gn:timezone":"Africa/Kigali",
    "iso:country":"RW",
    "wof:name":"Gitarama",
    "wof:placetype":"locality"
},
  "geometry": {"coordinates":[29.3715,-2.1014],"type":"Point"}
}