{
  "type": "Feature",
  "properties": {
    "gn:admin1_code":"13",
    "gn:admin2_code":"45.0",
    "gn:admin3_code":"4520.0",
    "gn:admin4_code":"452003.0",
    "gn:asciiname":"Nkoragaheto",
    "gn:country_code":"RW",
    "gn:dem":1783,
    "gn:feature_class":"P",
    "gn:feature_code":"PPLL",
    "gn:name":"Nkoragaheto",
    "gn:population":0,
    "gn:timezone":"Africa/Kigali",
    "iso:country":"RW",
    "wof:name":"Nkoragaheto",
    "wof:placetype":"locality"
},
  "geometry": {"coordinates":[30.1775,-1.7873],"type":"Point"}
}