{
  "type": "Feature",
  "properties": {
    "gn:admin1_code":"15.0",
    "gn:admin2_code":"25",
    "gn:admin3_code":"2505.0",
    "gn:admin4_code":"250501.0",
    "gn:asciiname":"Nyagane",
    "gn:country_code":"RW",
    "gn:dem":2126,
    "gn:feature_class":"P",
    "gn:feature_code":"PPLL",
    "gn:name":"Nyagane",
    "gn:population":0,
    "gn:timezone":"Africa/Kigali",
    "iso:country":"RW",
    "wof:name":"Nyagane",
    "wof:placetype":"locality"
},
  "geometry": {"coordinates":[29.5091,-2.3503],"type":"Point"}
}