{
  "type": "Feature",
  "properties": {
    "gn:admin1_code":"13",
    "gn:admin2_code":"45.0",
    "gn:admin3_code":"4512.0",
    "gn:admin4_code":"451202.0",
    "gn:asciiname":"Merezo",
    "gn:country_code":"RW",
    "gn:dem":1843,
    "gn:feature_class":"P",
    "gn:feature_code":"PPLL",
    "gn:name":"Merezo",
    "gn:population":0,
    "gn:timezone":"Africa/Kigali",
    "iso:country":"RW",
    "wof:name":"Merezo",
    "wof:placetype":"locality"
},
  "geometry": {"coordinates":[30.0992,-1.7526],"type":"Point"}
}