{
  "type": "Feature",
  "properties": {
    "gn:admin1_code":"13",
    "gn:admin2_code":"44.0",
    "gn:admin3_code":"4408.0",
    "gn:admin4_code":"440804.0",
    "gn:asciiname":"Kibaya",
    "gn:country_code":"RW",
    "gn:dem":1938,
    "gn:feature_class":"P",
    "gn:feature_code":"PPLL",
    "gn:name":"Kibaya",
    "gn:population":0,
    "gn:timezone":"Africa/Kigali",
    "iso:country":"RW",
    "name:ron_x_preferred":[
        "Kibaya"
    ],
    "wof:name":"Kibaya",
    "wof:placetype":"locality"
},
  "geometry": {"coordinates":[29.7543,-1.3899],"type":"Point"}
}