{
  "type": "Feature",
  "properties": {
    "gn:admin1_code":"11",
    "gn:admin2_code":"53.0",
    "gn:admin3_code":"5308.0",
    "gn:admin4_code":"530802.0",
    "gn:asciiname":"Gakorokombe",
    "gn:country_code":"RW",
    "gn:dem":1681,
    "gn:feature_class":"P",
    "gn:feature_code":"PPLL",
    "gn:name":"Gakorokombe",
    "gn:population":0,
    "gn:timezone":"Africa/Kigali",
    "iso:country":"RW",
    "wof:name":"Gakorokombe",
    "wof:placetype":"locality"
},
  "geometry": {"coordinates":[30.2995,-1.7601],"type":"Point"}
}