{
  "type": "Feature",
  "properties": {
    "gn:admin1_code":"14.0",
    "gn:admin2_code":"32",
    "gn:admin3_code":"3202.0",
    "gn:admin4_code":"320206.0",
    "gn:asciiname":"Rugote",
    "gn:country_code":"RW",
    "gn:dem":1841,
    "gn:feature_class":"P",
    "gn:feature_code":"PPL",
    "gn:name":"Rugote",
    "gn:population":0,
    "gn:timezone":"Africa/Kigali",
    "iso:country":"RW",
    "name:und_x_variant":[
        "Colline Rugoti",
        "Rugoti",
        "Rugote"
    ],
    "wof:name":"Rugote",
    "wof:placetype":"locality"
},
  "geometry": {"coordinates":[29.3785,-1.9246],"type":"Point"}
}