{
  "type": "Feature",
  "properties": {
    "gn:admin1_code":"11.0",
    "gn:admin2_code":"53",
    "gn:admin3_code":"5306.0",
    "gn:admin4_code":"530602.0",
    "gn:asciiname":"Gakenke",
    "gn:country_code":"RW",
    "gn:dem":1519,
    "gn:feature_class":"P",
    "gn:feature_code":"PPLL",
    "gn:name":"Gakenke",
    "gn:population":0,
    "gn:timezone":"Africa/Kigali",
    "iso:country":"RW",
    "name:und_x_variant":[
        "Kakenke",
        "Kakenge",
        "Gakenke"
    ],
    "wof:name":"Gakenke",
    "wof:placetype":"locality"
},
  "geometry": {"coordinates":[30.4316,-1.7976],"type":"Point"}
}