{
  "type": "Feature",
  "properties": {
    "gn:admin1_code":"13",
    "gn:admin2_code":"41.0",
    "gn:admin3_code":"4117.0",
    "gn:admin4_code":"411702.0",
    "gn:asciiname":"Gihinga",
    "gn:country_code":"RW",
    "gn:dem":2144,
    "gn:feature_class":"P",
    "gn:feature_code":"PPL",
    "gn:name":"Gihinga",
    "gn:population":0,
    "gn:timezone":"Africa/Kigali",
    "iso:country":"RW",
    "wof:name":"Gihinga",
    "wof:placetype":"locality"
},
  "geometry": {"coordinates":[29.95472,-1.72018],"type":"Point"}
}