{
  "type": "Feature",
  "properties": {
    "gn:admin1_code":"12",
    "gn:admin2_code":"13.0",
    "gn:admin3_code":"1307.0",
    "gn:admin4_code":"130704.0",
    "gn:asciiname":"Akamabuye",
    "gn:country_code":"RW",
    "gn:dem":1457,
    "gn:feature_class":"P",
    "gn:feature_code":"PPL",
    "gn:name":"Akamabuye",
    "gn:population":0,
    "gn:timezone":"Africa/Kigali",
    "iso:country":"RW",
    "wof:name":"Akamabuye",
    "wof:placetype":"locality"
},
  "geometry": {"coordinates":[30.0568,-1.985],"type":"Point"}
}