{
  "type": "Feature",
  "properties": {
    "gn:admin1_code":"11.0",
    "gn:admin2_code":"51",
    "gn:admin3_code":"5109.0",
    "gn:admin4_code":"510906.0",
    "gn:asciiname":"Rutoma",
    "gn:country_code":"RW",
    "gn:dem":1659,
    "gn:feature_class":"P",
    "gn:feature_code":"PPLL",
    "gn:name":"Rutoma",
    "gn:population":0,
    "gn:timezone":"Africa/Kigali",
    "iso:country":"RW",
    "wof:name":"Rutoma",
    "wof:placetype":"locality"
},
  "geometry": {"coordinates":[30.3189,-1.907],"type":"Point"}
}