{
  "type": "Feature",
  "properties": {
    "gn:admin1_code":"13",
    "gn:admin2_code":"43.0",
    "gn:admin3_code":"4315.0",
    "gn:admin4_code":"431503.0",
    "gn:asciiname":"Kageshi",
    "gn:country_code":"RW",
    "gn:dem":2563,
    "gn:feature_class":"P",
    "gn:feature_code":"PPLL",
    "gn:name":"Kageshi",
    "gn:population":0,
    "gn:timezone":"Africa/Kigali",
    "iso:country":"RW",
    "wof:name":"Kageshi",
    "wof:placetype":"locality"
},
  "geometry": {"coordinates":[29.5291,-1.517],"type":"Point"}
}