{
  "type": "Feature",
  "properties": {
    "gn:admin1_code":"13",
    "gn:admin2_code":"42.0",
    "gn:admin3_code":"4211.0",
    "gn:admin4_code":"421104.0",
    "gn:asciiname":"Ndengamire",
    "gn:country_code":"RW",
    "gn:dem":1625,
    "gn:feature_class":"P",
    "gn:feature_code":"PPLL",
    "gn:name":"Ndengamire",
    "gn:population":0,
    "gn:timezone":"Africa/Kigali",
    "iso:country":"RW",
    "wof:name":"Ndengamire",
    "wof:placetype":"locality"
},
  "geometry": {"coordinates":[29.7987,-1.7092],"type":"Point"}
}