{
  "type": "Feature",
  "properties": {
    "gn:admin1_code":"11",
    "gn:admin2_code":"56.0",
    "gn:admin3_code":"5603.0",
    "gn:admin4_code":"560301.0",
    "gn:asciiname":"Ngara",
    "gn:country_code":"RW",
    "gn:dem":1461,
    "gn:feature_class":"P",
    "gn:feature_code":"PPLL",
    "gn:name":"Ngara",
    "gn:population":0,
    "gn:timezone":"Africa/Kigali",
    "iso:country":"RW",
    "name:ara_x_preferred":[
        "\u0646\u062c\u0627\u0631\u0627"
    ],
    "name:ben_x_preferred":[
        "\u098f\u0982\u0997\u09be\u09b0\u09be"
    ],
    "name:ceb_x_preferred":[
        "Ngara"
    ],
    "name:ell_x_preferred":[
        "\u039d\u03b3\u03ba\u03ac\u03c1\u03b1"
    ],
    "name:fas_x_preferred":[
        "\u0627\u0646\u06af\u0627\u0631\u0627"
    ],
    "name:heb_x_preferred":[
        "\u05e0\u05d2\u05e8\u05d4"
    ],
    "name:hin_x_preferred":[
        "\u090f\u0902\u0917\u093e\u0930\u093e"
    ],
    "name:hun_x_preferred":[
        "Ngara"
    ],
    "name:ind_x_preferred":[
        "Ngara"
    ],
    "name:kor_x_preferred":[
        "\uc751\uac00\ub77c"
    ],
    "name:nor_x_preferred":[
        "Ngara"
    ],
    "name:pol_x_preferred":[
        "Ngara"
    ],
    "name:ron_x_preferred":[
        "Ngara"
    ],
    "name:rus_x_preferred":[
        "\u041d\u0433\u0430\u0440\u0430"
    ],
    "name:swe_x_preferred":[
        "Ngara"
    ],
    "name:tur_x_preferred":[
        "Ngara"
    ],
    "name:ukr_x_preferred":[
        "\u041d\u0433\u0430\u0440\u0430"
    ],
    "name:urd_x_preferred":[
        "\u0627\u0646\u06af\u0627\u0631\u0627"
    ],
    "name:vie_x_preferred":[
        "Ngara"
    ],
    "name:zho_cn_x_preferred":[
        "\u6069\u52a0\u62c9"
    ],
    "name:zho_tw_x_preferred":[
        "\u6069\u52a0\u62c9"
    ],
    "wof:name":"Ngara",
    "wof:placetype":"locality"
},
  "geometry": {"coordinates":[30.449,-2.1678],"type":"Point"}
}