{
  "type": "Feature",
  "properties": {
    "gn:admin1_code":"11",
    "gn:admin2_code":"56.0",
    "gn:admin3_code":"5603.0",
    "gn:admin4_code":"560301.0",
    "gn:asciiname":"Ngara",
    "gn:country_code":"RW",
    "gn:dem":1461,
    "gn:feature_class":"P",
    "gn:feature_code":"PPLL",
    "gn:name":"Ngara",
    "gn:population":0,
    "gn:timezone":"Africa/Kigali",
    "iso:country":"RW",
    "wof:name":"Ngara",
    "wof:placetype":"locality"
},
  "geometry": {"coordinates":[30.449,-2.1678],"type":"Point"}
}