{
  "type": "Feature",
  "properties": {
    "gn:admin1_code":"13",
    "gn:admin2_code":"43.0",
    "gn:admin3_code":"4308.0",
    "gn:admin4_code":"430801.0",
    "gn:asciiname":"Etiru",
    "gn:country_code":"RW",
    "gn:dem":1782,
    "gn:feature_class":"P",
    "gn:feature_code":"PPL",
    "gn:name":"Etiru",
    "gn:population":0,
    "gn:timezone":"Africa/Kigali",
    "iso:country":"RW",
    "wof:name":"Etiru",
    "wof:placetype":"locality"
},
  "geometry": {"coordinates":[29.6559,-1.51],"type":"Point"}
}