{
  "type": "Feature",
  "properties": {
    "gn:admin1_code":"15",
    "gn:admin2_code":"21.0",
    "gn:admin3_code":"2105.0",
    "gn:admin4_code":"210503.0",
    "gn:asciiname":"Mugateke",
    "gn:country_code":"RW",
    "gn:dem":1541,
    "gn:feature_class":"P",
    "gn:feature_code":"PPLL",
    "gn:name":"Mugateke",
    "gn:population":0,
    "gn:timezone":"Africa/Kigali",
    "iso:country":"RW",
    "wof:name":"Mugateke",
    "wof:placetype":"locality"
},
  "geometry": {"coordinates":[29.8241,-2.2832],"type":"Point"}
}