{
  "type": "Feature",
  "properties": {
    "gn:admin1_code":"15",
    "gn:admin2_code":"22.0",
    "gn:admin3_code":"2205.0",
    "gn:admin4_code":"220504.0",
    "gn:asciiname":"Shyombo",
    "gn:country_code":"RW",
    "gn:dem":1602,
    "gn:feature_class":"P",
    "gn:feature_code":"PPLL",
    "gn:name":"Shyombo",
    "gn:population":0,
    "gn:timezone":"Africa/Kigali",
    "iso:country":"RW",
    "wof:name":"Shyombo",
    "wof:placetype":"locality"
},
  "geometry": {"coordinates":[29.7448,-2.7639],"type":"Point"}
}