{
  "type": "Feature",
  "properties": {
    "gn:admin1_code":"14.0",
    "gn:admin2_code":"36",
    "gn:admin3_code":"3604.0",
    "gn:admin4_code":"360405.0",
    "gn:asciiname":"Kamonyi",
    "gn:country_code":"RW",
    "gn:dem":1768,
    "gn:feature_class":"P",
    "gn:feature_code":"PPLL",
    "gn:name":"Kamonyi",
    "gn:population":0,
    "gn:timezone":"Africa/Kigali",
    "iso:country":"RW",
    "wof:name":"Kamonyi",
    "wof:placetype":"locality"
},
  "geometry": {"coordinates":[28.9296,-2.5655],"type":"Point"}
}