{
  "type": "Feature",
  "properties": {
    "gn:admin1_code":"12.0",
    "gn:admin2_code":"12",
    "gn:admin3_code":"1206.0",
    "gn:admin4_code":"120607.0",
    "gn:asciiname":"Jari",
    "gn:country_code":"RW",
    "gn:dem":1923,
    "gn:feature_class":"P",
    "gn:feature_code":"PPL",
    "gn:name":"Jari",
    "gn:population":0,
    "gn:timezone":"Africa/Kigali",
    "iso:country":"RW",
    "name:und_x_variant":[
        "Colline Jari",
        "Jari"
    ],
    "wof:name":"Jari",
    "wof:placetype":"locality"
},
  "geometry": {"coordinates":[30.0207,-1.8987],"type":"Point"}
}