{
  "type": "Feature",
  "properties": {
    "gn:admin1_code":"15.0",
    "gn:admin2_code":"28",
    "gn:admin3_code":"2812.0",
    "gn:admin4_code":"281202.0",
    "gn:asciiname":"Runda",
    "gn:country_code":"RW",
    "gn:dem":1701,
    "gn:feature_class":"P",
    "gn:feature_code":"PPL",
    "gn:name":"Runda",
    "gn:population":0,
    "gn:timezone":"Africa/Kigali",
    "iso:country":"RW",
    "wof:name":"Runda",
    "wof:placetype":"locality"
},
  "geometry": {"coordinates":[29.9445,-1.9555],"type":"Point"}
}