{
  "type": "Feature",
  "properties": {
    "gn:admin1_code":"11.0",
    "gn:admin2_code":"54",
    "gn:admin3_code":"5403.0",
    "gn:admin4_code":"540302.0",
    "gn:asciiname":"Cyinzovu",
    "gn:country_code":"RW",
    "gn:dem":1645,
    "gn:feature_class":"P",
    "gn:feature_code":"PPLL",
    "gn:name":"Cyinzovu",
    "gn:population":0,
    "gn:timezone":"Africa/Kigali",
    "iso:country":"RW",
    "name:und_x_variant":[
        "Tshinzovo",
        "Cyinzovu",
        "Tshinzovu"
    ],
    "wof:name":"Cyinzovu",
    "wof:placetype":"locality"
},
  "geometry": {"coordinates":[30.5626,-2.039],"type":"Point"}
}