{
  "type": "Feature",
  "properties": {
    "gn:admin1_code":"14",
    "gn:admin2_code":"34.0",
    "gn:admin3_code":"3410.0",
    "gn:admin4_code":"341001.0",
    "gn:asciiname":"Gashyushya",
    "gn:country_code":"RW",
    "gn:dem":1509,
    "gn:feature_class":"P",
    "gn:feature_code":"PPL",
    "gn:name":"Gashyushya",
    "gn:population":0,
    "gn:timezone":"Africa/Kigali",
    "iso:country":"RW",
    "wof:name":"Gashyushya",
    "wof:placetype":"locality"
},
  "geometry": {"coordinates":[29.6303,-1.6326],"type":"Point"}
}