{
  "type": "Feature",
  "properties": {
    "gn:admin1_code":"15",
    "gn:admin2_code":"26.0",
    "gn:admin3_code":"2608.0",
    "gn:admin4_code":"260803.0",
    "gn:asciiname":"Kayenzi",
    "gn:country_code":"RW",
    "gn:dem":1586,
    "gn:feature_class":"P",
    "gn:feature_code":"PPLL",
    "gn:name":"Kayenzi",
    "gn:population":0,
    "gn:timezone":"Africa/Kigali",
    "iso:country":"RW",
    "wof:name":"Kayenzi",
    "wof:placetype":"locality"
},
  "geometry": {"coordinates":[29.8597,-2.2052],"type":"Point"}
}