{
  "type": "Feature",
  "properties": {
    "gn:admin1_code":"15.0",
    "gn:admin2_code":"25",
    "gn:admin3_code":"2516.0",
    "gn:admin4_code":"251603.0",
    "gn:asciiname":"Gatovu",
    "gn:country_code":"RW",
    "gn:dem":2141,
    "gn:feature_class":"P",
    "gn:feature_code":"PPL",
    "gn:name":"Gatovu",
    "gn:population":0,
    "gn:timezone":"Africa/Kigali",
    "iso:country":"RW",
    "wof:name":"Gatovu",
    "wof:placetype":"locality"
},
  "geometry": {"coordinates":[29.4973,-2.5167],"type":"Point"}
}