{
  "type": "Feature",
  "properties": {
    "gn:admin1_code":"12",
    "gn:admin2_code":"12.0",
    "gn:admin3_code":"1206.0",
    "gn:admin4_code":"120601.0",
    "gn:asciiname":"Umubanga",
    "gn:country_code":"RW",
    "gn:dem":1427,
    "gn:feature_class":"P",
    "gn:feature_code":"PPL",
    "gn:name":"Umubanga",
    "gn:population":0,
    "gn:timezone":"Africa/Kigali",
    "iso:country":"RW",
    "wof:name":"Umubanga",
    "wof:placetype":"locality"
},
  "geometry": {"coordinates":[30.0433,-1.8988],"type":"Point"}
}