{
  "type": "Feature",
  "properties": {
    "gn:admin1_code":"15",
    "gn:admin2_code":"24.0",
    "gn:admin3_code":"2411.0",
    "gn:admin4_code":"241104.0",
    "gn:asciiname":"Nyabusunzu",
    "gn:country_code":"RW",
    "gn:dem":1543,
    "gn:feature_class":"P",
    "gn:feature_code":"PPL",
    "gn:name":"Nyabusunzu",
    "gn:population":0,
    "gn:timezone":"Africa/Kigali",
    "iso:country":"RW",
    "wof:name":"Nyabusunzu",
    "wof:placetype":"locality"
},
  "geometry": {"coordinates":[29.8057,-2.4739],"type":"Point"}
}