{
  "type": "Feature",
  "properties": {
    "gn:admin1_code":"12.0",
    "gn:admin2_code":"13",
    "gn:admin3_code":"1302.0",
    "gn:admin4_code":"130202.0",
    "gn:asciiname":"Gikondo",
    "gn:country_code":"RW",
    "gn:dem":1450,
    "gn:feature_class":"P",
    "gn:feature_code":"PPL",
    "gn:name":"Gikondo",
    "gn:population":0,
    "gn:timezone":"Africa/Kigali",
    "iso:country":"RW",
    "name:und_x_variant":[
        "Colline Gikondo",
        "Gikondo"
    ],
    "wof:name":"Gikondo",
    "wof:placetype":"locality"
},
  "geometry": {"coordinates":[30.084,-1.97886],"type":"Point"}
}