{
  "type": "Feature",
  "properties": {
    "gn:admin1_code":"13",
    "gn:admin2_code":"41.0",
    "gn:admin3_code":"4113.0",
    "gn:admin4_code":"411301.0",
    "gn:asciiname":"Bikamba",
    "gn:country_code":"RW",
    "gn:dem":1482,
    "gn:feature_class":"P",
    "gn:feature_code":"PPLL",
    "gn:name":"Bikamba",
    "gn:population":0,
    "gn:timezone":"Africa/Kigali",
    "iso:country":"RW",
    "wof:name":"Bikamba",
    "wof:placetype":"locality"
},
  "geometry": {"coordinates":[30.1202,-1.7967],"type":"Point"}
}