{
  "type": "Feature",
  "properties": {
    "gn:admin1_code":"13.0",
    "gn:admin2_code":"42",
    "gn:admin3_code":"4209.0",
    "gn:admin4_code":"420902.0",
    "gn:asciiname":"Jomba",
    "gn:country_code":"RW",
    "gn:dem":1781,
    "gn:feature_class":"P",
    "gn:feature_code":"PPL",
    "gn:name":"Jomba",
    "gn:population":0,
    "gn:timezone":"Africa/Kigali",
    "iso:country":"RW",
    "name:und_x_variant":[
        "Colline Jomba",
        "Jomba"
    ],
    "wof:name":"Jomba",
    "wof:placetype":"locality"
},
  "geometry": {"coordinates":[29.7342,-1.585],"type":"Point"}
}