{
  "type": "Feature",
  "properties": {
    "gn:admin1_code":"14.0",
    "gn:admin2_code":"36",
    "gn:admin3_code":"3604.0",
    "gn:admin4_code":"360405.0",
    "gn:asciiname":"Rango",
    "gn:country_code":"RW",
    "gn:dem":1721,
    "gn:feature_class":"P",
    "gn:feature_code":"PPLL",
    "gn:name":"Rango",
    "gn:population":0,
    "gn:timezone":"Africa/Kigali",
    "iso:country":"RW",
    "name:ceb_x_preferred":[
        "Rango"
    ],
    "name:ces_x_preferred":[
        "Rango"
    ],
    "name:deu_x_preferred":[
        "Rango"
    ],
    "name:epo_x_preferred":[
        "Rango"
    ],
    "name:eus_x_preferred":[
        "Rango"
    ],
    "name:fin_x_preferred":[
        "Rango"
    ],
    "name:fra_x_preferred":[
        "Rango"
    ],
    "name:ita_x_preferred":[
        "Rango"
    ],
    "name:msa_x_preferred":[
        "Rango"
    ],
    "name:nld_x_preferred":[
        "Rango"
    ],
    "name:spa_x_preferred":[
        "Rango"
    ],
    "name:swe_x_preferred":[
        "Rango"
    ],
    "name:und_x_variant":[
        "Colline Rango"
    ],
    "name:uzb_x_preferred":[
        "Rango"
    ],
    "wof:name":"Rango",
    "wof:placetype":"locality"
},
  "geometry": {"coordinates":[28.9256,-2.5845],"type":"Point"}
}