{
  "type": "Feature",
  "properties": {
    "gn:admin1_code":"14.0",
    "gn:admin2_code":"36",
    "gn:admin3_code":"3604.0",
    "gn:admin4_code":"360405.0",
    "gn:asciiname":"Rango",
    "gn:country_code":"RW",
    "gn:dem":1721,
    "gn:feature_class":"P",
    "gn:feature_code":"PPLL",
    "gn:name":"Rango",
    "gn:population":0,
    "gn:timezone":"Africa/Kigali",
    "iso:country":"RW",
    "name:und_x_variant":[
        "Colline Rango",
        "Rango"
    ],
    "wof:name":"Rango",
    "wof:placetype":"locality"
},
  "geometry": {"coordinates":[28.9256,-2.5845],"type":"Point"}
}