{
  "type": "Feature",
  "properties": {
    "gn:admin1_code":"15",
    "gn:admin2_code":"28.0",
    "gn:admin3_code":"2805.0",
    "gn:admin4_code":"280502.0",
    "gn:asciiname":"Kabugondo",
    "gn:country_code":"RW",
    "gn:dem":1407,
    "gn:feature_class":"P",
    "gn:feature_code":"PPLL",
    "gn:name":"Kabugondo",
    "gn:population":0,
    "gn:timezone":"Africa/Kigali",
    "iso:country":"RW",
    "wof:name":"Kabugondo",
    "wof:placetype":"locality"
},
  "geometry": {"coordinates":[29.9553,-2.171],"type":"Point"}
}