{
  "type": "Feature",
  "properties": {
    "gn:admin1_code":"14",
    "gn:admin2_code":"31.0",
    "gn:admin3_code":"3110.0",
    "gn:admin4_code":"311003.0",
    "gn:asciiname":"Gasora",
    "gn:country_code":"RW",
    "gn:dem":2147,
    "gn:feature_class":"P",
    "gn:feature_code":"PPLL",
    "gn:name":"Gasora",
    "gn:population":0,
    "gn:timezone":"Africa/Kigali",
    "iso:country":"RW",
    "wof:name":"Gasora",
    "wof:placetype":"locality"
},
  "geometry": {"coordinates":[29.522,-2.093],"type":"Point"}
}