{
  "type": "Feature",
  "properties": {
    "gn:admin1_code":"14.0",
    "gn:admin2_code":"32",
    "gn:admin3_code":"3206.0",
    "gn:admin4_code":"320606.0",
    "gn:asciiname":"Mwendo",
    "gn:country_code":"RW",
    "gn:dem":2158,
    "gn:feature_class":"P",
    "gn:feature_code":"PPLL",
    "gn:name":"Mwendo",
    "gn:population":0,
    "gn:timezone":"Africa/Kigali",
    "iso:country":"RW",
    "wof:name":"Mwendo",
    "wof:placetype":"locality"
},
  "geometry": {"coordinates":[29.5354,-2.0196],"type":"Point"}
}