{
  "type": "Feature",
  "properties": {
    "gn:admin1_code":"14.0",
    "gn:admin2_code":"36",
    "gn:admin3_code":"3608.0",
    "gn:admin4_code":"360801.0",
    "gn:asciiname":"Njambwe",
    "gn:country_code":"RW",
    "gn:dem":1386,
    "gn:feature_class":"P",
    "gn:feature_code":"PPLL",
    "gn:name":"Njambwe",
    "gn:population":0,
    "gn:timezone":"Africa/Kigali",
    "iso:country":"RW",
    "wof:name":"Njambwe",
    "wof:placetype":"locality"
},
  "geometry": {"coordinates":[28.9783,-2.5941],"type":"Point"}
}