{
  "type": "Feature",
  "properties": {
    "gn:admin1_code":"11.0",
    "gn:admin2_code":"52",
    "gn:admin3_code":"5202.0",
    "gn:admin4_code":"520205.0",
    "gn:asciiname":"Bushara",
    "gn:country_code":"RW",
    "gn:dem":1491,
    "gn:feature_class":"P",
    "gn:feature_code":"PPLL",
    "gn:name":"Bushara",
    "gn:population":0,
    "gn:timezone":"Africa/Kigali",
    "iso:country":"RW",
    "name:und_x_variant":[
        "Colline Bushara",
        "Bushara"
    ],
    "wof:name":"Bushara",
    "wof:placetype":"locality"
},
  "geometry": {"coordinates":[30.1928,-1.3532],"type":"Point"}
}