{
  "type": "Feature",
  "properties": {
    "gn:admin1_code":"14.0",
    "gn:admin2_code":"37",
    "gn:admin3_code":"3705.0",
    "gn:admin4_code":"370501.0",
    "gn:asciiname":"Mpombo",
    "gn:country_code":"RW",
    "gn:dem":1604,
    "gn:feature_class":"P",
    "gn:feature_code":"PPLL",
    "gn:name":"Mpombo",
    "gn:population":0,
    "gn:timezone":"Africa/Kigali",
    "iso:country":"RW",
    "name:swa_x_preferred":[
        "Mpombo"
    ],
    "wof:name":"Mpombo",
    "wof:placetype":"locality"
},
  "geometry": {"coordinates":[29.1214,-2.3549],"type":"Point"}
}