{
  "type": "Feature",
  "properties": {
    "gn:admin1_code":"14",
    "gn:admin2_code":"33.0",
    "gn:admin3_code":"3312.0",
    "gn:admin4_code":"331207.0",
    "gn:asciiname":"Kiroji",
    "gn:country_code":"RW",
    "gn:dem":1592,
    "gn:feature_class":"P",
    "gn:feature_code":"PPLL",
    "gn:name":"Kiroji",
    "gn:population":0,
    "gn:timezone":"Africa/Kigali",
    "iso:country":"RW",
    "wof:name":"Kiroji",
    "wof:placetype":"locality"
},
  "geometry": {"coordinates":[29.2762,-1.697],"type":"Point"}
}