{
  "type": "Feature",
  "properties": {
    "gn:admin1_code":"14",
    "gn:admin2_code":"31.0",
    "gn:admin3_code":"3105.0",
    "gn:admin4_code":"310502.0",
    "gn:asciiname":"Gisunzu",
    "gn:country_code":"RW",
    "gn:dem":1657,
    "gn:feature_class":"P",
    "gn:feature_code":"PPLL",
    "gn:name":"Gisunzu",
    "gn:population":0,
    "gn:timezone":"Africa/Kigali",
    "iso:country":"RW",
    "wof:name":"Gisunzu",
    "wof:placetype":"locality"
},
  "geometry": {"coordinates":[29.3088,-2.1051],"type":"Point"}
}