{
  "type": "Feature",
  "properties": {
    "gn:admin1_code":"13",
    "gn:admin2_code":"42.0",
    "gn:admin3_code":"4215.0",
    "gn:admin4_code":"421505.0",
    "gn:asciiname":"Gihororo",
    "gn:country_code":"RW",
    "gn:dem":1882,
    "gn:feature_class":"P",
    "gn:feature_code":"PPLL",
    "gn:name":"Gihororo",
    "gn:population":0,
    "gn:timezone":"Africa/Kigali",
    "iso:country":"RW",
    "wof:name":"Gihororo",
    "wof:placetype":"locality"
},
  "geometry": {"coordinates":[29.7108,-1.6814],"type":"Point"}
}