{
  "type": "Feature",
  "properties": {
    "gn:admin1_code":"13",
    "gn:admin2_code":"44.0",
    "gn:admin3_code":"4405.0",
    "gn:admin4_code":"440502.0",
    "gn:asciiname":"Kigote",
    "gn:country_code":"RW",
    "gn:dem":2213,
    "gn:feature_class":"P",
    "gn:feature_code":"PPL",
    "gn:name":"Kigote",
    "gn:population":0,
    "gn:timezone":"Africa/Kigali",
    "iso:country":"RW",
    "wof:name":"Kigote",
    "wof:placetype":"locality"
},
  "geometry": {"coordinates":[29.66,-1.4317],"type":"Point"}
}