{
  "type": "Feature",
  "properties": {
    "gn:admin1_code":"15",
    "gn:admin2_code":"28.0",
    "gn:admin3_code":"2805.0",
    "gn:admin4_code":"280503.0",
    "gn:asciiname":"Kansoro",
    "gn:country_code":"RW",
    "gn:dem":1470,
    "gn:feature_class":"P",
    "gn:feature_code":"PPLL",
    "gn:name":"Kansoro",
    "gn:population":0,
    "gn:timezone":"Africa/Kigali",
    "iso:country":"RW",
    "wof:name":"Kansoro",
    "wof:placetype":"locality"
},
  "geometry": {"coordinates":[29.9483,-2.1165],"type":"Point"}
}