{
  "type": "Feature",
  "properties": {
    "gn:admin1_code":"14.0",
    "gn:admin2_code":"32",
    "gn:admin3_code":"3212.0",
    "gn:admin4_code":"321201.0",
    "gn:asciiname":"Kamuramira",
    "gn:country_code":"RW",
    "gn:dem":1892,
    "gn:feature_class":"P",
    "gn:feature_code":"PPLL",
    "gn:name":"Kamuramira",
    "gn:population":0,
    "gn:timezone":"Africa/Kigali",
    "iso:country":"RW",
    "wof:name":"Kamuramira",
    "wof:placetype":"locality"
},
  "geometry": {"coordinates":[29.3818,-1.8846],"type":"Point"}
}