{
  "type": "Feature",
  "properties": {
    "gn:admin1_code":"14",
    "gn:admin2_code":"33.0",
    "gn:admin3_code":"3312.0",
    "gn:admin4_code":"331206.0",
    "gn:asciiname":"Butangi",
    "gn:country_code":"RW",
    "gn:dem":1726,
    "gn:feature_class":"P",
    "gn:feature_code":"PPLL",
    "gn:name":"Butangi",
    "gn:population":0,
    "gn:timezone":"Africa/Kigali",
    "iso:country":"RW",
    "wof:name":"Butangi",
    "wof:placetype":"locality"
},
  "geometry": {"coordinates":[29.2782,-1.7079],"type":"Point"}
}