{
  "type": "Feature",
  "properties": {
    "gn:admin1_code":"14",
    "gn:admin2_code":"33.0",
    "gn:admin3_code":"3311.0",
    "gn:admin4_code":"331101.0",
    "gn:asciiname":"Buhaza",
    "gn:country_code":"RW",
    "gn:dem":1613,
    "gn:feature_class":"P",
    "gn:feature_code":"PPL",
    "gn:name":"Buhaza",
    "gn:population":0,
    "gn:timezone":"Africa/Kigali",
    "iso:country":"RW",
    "wof:name":"Buhaza",
    "wof:placetype":"locality"
},
  "geometry": {"coordinates":[29.2668,-1.6592],"type":"Point"}
}