{
  "type": "Feature",
  "properties": {
    "gn:admin1_code":"15.0",
    "gn:admin2_code":"24",
    "gn:admin3_code":"2402.0",
    "gn:admin4_code":"240201.0",
    "gn:asciiname":"Rwaza",
    "gn:country_code":"RW",
    "gn:dem":1715,
    "gn:feature_class":"P",
    "gn:feature_code":"PPLL",
    "gn:name":"Rwaza",
    "gn:population":0,
    "gn:timezone":"Africa/Kigali",
    "iso:country":"RW",
    "wof:name":"Rwaza",
    "wof:placetype":"locality"
},
  "geometry": {"coordinates":[29.7003,-2.611],"type":"Point"}
}