{
  "type": "Feature",
  "properties": {
    "gn:admin1_code":"15",
    "gn:admin2_code":"26.0",
    "gn:admin3_code":"2609.0",
    "gn:admin4_code":"260906.0",
    "gn:asciiname":"Nyarusange",
    "gn:country_code":"RW",
    "gn:dem":1592,
    "gn:feature_class":"P",
    "gn:feature_code":"PPLL",
    "gn:name":"Nyarusange",
    "gn:population":0,
    "gn:timezone":"Africa/Kigali",
    "iso:country":"RW",
    "wof:name":"Nyarusange",
    "wof:placetype":"locality"
},
  "geometry": {"coordinates":[29.80698,-2.25002],"type":"Point"}
}