{
  "type": "Feature",
  "properties": {
    "gn:admin1_code":"11.0",
    "gn:admin2_code":"53",
    "gn:admin3_code":"5313.0",
    "gn:admin4_code":"531304.0",
    "gn:asciiname":"Gitsimba",
    "gn:country_code":"RW",
    "gn:dem":1414,
    "gn:feature_class":"P",
    "gn:feature_code":"PPLL",
    "gn:name":"Gitsimba",
    "gn:population":0,
    "gn:timezone":"Africa/Kigali",
    "iso:country":"RW",
    "name:und_x_variant":[
        "Colline Gitsimba",
        "Gitsimba"
    ],
    "wof:name":"Gitsimba",
    "wof:placetype":"locality"
},
  "geometry": {"coordinates":[30.3844,-1.6926],"type":"Point"}
}