{
  "type": "Feature",
  "properties": {
    "gn:admin1_code":"13",
    "gn:admin2_code":"43.0",
    "gn:admin3_code":"4307.0",
    "gn:admin4_code":"430701.0",
    "gn:asciiname":"Nyarwayu",
    "gn:country_code":"RW",
    "gn:dem":2585,
    "gn:feature_class":"P",
    "gn:feature_code":"PPLL",
    "gn:name":"Nyarwayu",
    "gn:population":0,
    "gn:timezone":"Africa/Kigali",
    "iso:country":"RW",
    "name:und_x_variant":[
        "Nyawayu"
    ],
    "wof:name":"Nyarwayu",
    "wof:placetype":"locality"
},
  "geometry": {"coordinates":[29.5179,-1.4641],"type":"Point"}
}