{
  "type": "Feature",
  "properties": {
    "gn:admin1_code":"11",
    "gn:admin2_code":"55.0",
    "gn:admin3_code":"5503.0",
    "gn:admin4_code":"550302.0",
    "gn:asciiname":"Kigarama",
    "gn:country_code":"RW",
    "gn:dem":1609,
    "gn:feature_class":"P",
    "gn:feature_code":"PPLL",
    "gn:name":"Kigarama",
    "gn:population":0,
    "gn:timezone":"Africa/Kigali",
    "iso:country":"RW",
    "wof:name":"Kigarama",
    "wof:placetype":"locality"
},
  "geometry": {"coordinates":[30.68934,-2.31765],"type":"Point"}
}