{
  "type": "Feature",
  "properties": {
    "gn:admin1_code":"11",
    "gn:admin2_code":"54.0",
    "gn:admin3_code":"5410.0",
    "gn:admin4_code":"541002.0",
    "gn:asciiname":"Buyonza",
    "gn:country_code":"RW",
    "gn:dem":1570,
    "gn:feature_class":"P",
    "gn:feature_code":"PPLL",
    "gn:name":"Buyonza",
    "gn:population":0,
    "gn:timezone":"Africa/Kigali",
    "iso:country":"RW",
    "wof:name":"Buyonza",
    "wof:placetype":"locality"
},
  "geometry": {"coordinates":[30.512,-1.8035],"type":"Point"}
}