{
  "type": "Feature",
  "properties": {
    "gn:admin1_code":"13",
    "gn:admin2_code":"43.0",
    "gn:admin3_code":"4303.0",
    "gn:admin4_code":"430302.0",
    "gn:asciiname":"Nkurungwe",
    "gn:country_code":"RW",
    "gn:dem":1852,
    "gn:feature_class":"P",
    "gn:feature_code":"PPLL",
    "gn:name":"Nkurungwe",
    "gn:population":0,
    "gn:timezone":"Africa/Kigali",
    "iso:country":"RW",
    "wof:name":"Nkurungwe",
    "wof:placetype":"locality"
},
  "geometry": {"coordinates":[29.7002,-1.5218],"type":"Point"}
}