{
  "type": "Feature",
  "properties": {
    "gn:admin1_code":"15.0",
    "gn:admin2_code":"23",
    "gn:admin3_code":"2307.0",
    "gn:admin4_code":"230701.0",
    "gn:asciiname":"Mashya",
    "gn:country_code":"RW",
    "gn:dem":1835,
    "gn:feature_class":"P",
    "gn:feature_code":"PPLL",
    "gn:name":"Mashya",
    "gn:population":0,
    "gn:timezone":"Africa/Kigali",
    "iso:country":"RW",
    "wof:name":"Mashya",
    "wof:placetype":"locality"
},
  "geometry": {"coordinates":[29.5354,-2.7379],"type":"Point"}
}