{
  "type": "Feature",
  "properties": {
    "gn:admin1_code":"13",
    "gn:admin2_code":"44.0",
    "gn:admin3_code":"4407.0",
    "gn:admin4_code":"440702.0",
    "gn:asciiname":"Musasa",
    "gn:country_code":"RW",
    "gn:dem":1958,
    "gn:feature_class":"P",
    "gn:feature_code":"PPLL",
    "gn:name":"Musasa",
    "gn:population":0,
    "gn:timezone":"Africa/Kigali",
    "iso:country":"RW",
    "name:ceb_x_preferred":[
        "Musasa"
    ],
    "name:swe_x_preferred":[
        "Musasa"
    ],
    "wof:name":"Musasa",
    "wof:placetype":"locality"
},
  "geometry": {"coordinates":[29.7687,-1.4929],"type":"Point"}
}