{
  "type": "Feature",
  "properties": {
    "gn:admin1_code":"11",
    "gn:admin2_code":"57.0",
    "gn:admin3_code":"5703.0",
    "gn:admin4_code":"570302.0",
    "gn:asciiname":"Murambo",
    "gn:country_code":"RW",
    "gn:dem":1385,
    "gn:feature_class":"P",
    "gn:feature_code":"PPLL",
    "gn:name":"Murambo",
    "gn:population":0,
    "gn:timezone":"Africa/Kigali",
    "iso:country":"RW",
    "wof:name":"Murambo",
    "wof:placetype":"locality"
},
  "geometry": {"coordinates":[30.0913,-2.3992],"type":"Point"}
}