{
  "type": "Feature",
  "properties": {
    "gn:admin1_code":"14.0",
    "gn:admin2_code":"32",
    "gn:admin3_code":"3201.0",
    "gn:admin4_code":"320102.0",
    "gn:asciiname":"Rugamba",
    "gn:country_code":"RW",
    "gn:dem":1495,
    "gn:feature_class":"P",
    "gn:feature_code":"PPL",
    "gn:name":"Rugamba",
    "gn:population":0,
    "gn:timezone":"Africa/Kigali",
    "iso:country":"RW",
    "name:und_x_variant":[
        "Colline Rugamba",
        "Rugamba"
    ],
    "wof:name":"Rugamba",
    "wof:placetype":"locality"
},
  "geometry": {"coordinates":[29.2908,-1.879],"type":"Point"}
}