{
  "type": "Feature",
  "properties": {
    "gn:admin1_code":"11",
    "gn:admin2_code":"56.0",
    "gn:admin3_code":"5607.0",
    "gn:admin4_code":"560705.0",
    "gn:asciiname":"Nyagataba",
    "gn:country_code":"RW",
    "gn:dem":1486,
    "gn:feature_class":"P",
    "gn:feature_code":"PPLL",
    "gn:name":"Nyagataba",
    "gn:population":0,
    "gn:timezone":"Africa/Kigali",
    "iso:country":"RW",
    "wof:name":"Nyagataba",
    "wof:placetype":"locality"
},
  "geometry": {"coordinates":[30.5432,-2.2004],"type":"Point"}
}