{
  "type": "Feature",
  "properties": {
    "iso:country":"RW",
    "name:ell_x_preferred":[
        "\u039d\u03b6\u03ad\u03b3\u03ba\u03b1"
    ],
    "name:und_x_variant":[
        "Nseka"
    ],
    "qs:gn_country":"RW",
    "qs:gn_fcode":"PPL",
    "qs:gn_pop":33832,
    "qs:name":"Nzega",
    "qs:name_adm0":"Rwanda",
    "qs:name_adm1":"Province du Sud",
    "qs:photos":0,
    "qs:photos_1k":0,
    "qs:photos_9k":1,
    "qs:photos_9r":1,
    "qs:photos_all":6,
    "qs:photos_sr":0,
    "qs:placetype":"Town",
    "qs:pop_sr":"7",
    "qs:woe_adm0":23424937,
    "wd:wordcount":68,
    "wof:name":"Nzega",
    "wof:placetype":"locality",
    "wof:population":33832
},
  "geometry": {"coordinates":[29.5564,-2.479],"type":"Point"}
}