{
  "type": "Feature",
  "properties": {
    "iso:country":"RW",
    "name:ara_x_preferred":[
        "\u0646\u0632\u064a\u062c\u0627"
    ],
    "name:ben_x_preferred":[
        "\u098f\u099e\u09cd\u099c\u09c7\u0997\u09be"
    ],
    "name:deu_x_preferred":[
        "Nzega"
    ],
    "name:ell_x_preferred":[
        "\u039d\u03b6\u03ad\u03b3\u03ba\u03b1"
    ],
    "name:eng_x_preferred":[
        "Nzega"
    ],
    "name:fas_x_preferred":[
        "\u0646\u0632\u06af\u0627"
    ],
    "name:fra_x_preferred":[
        "Nzega"
    ],
    "name:heb_x_preferred":[
        "\u05e0\u05d6\u05d2\u05d4"
    ],
    "name:hin_x_preferred":[
        "\u090f\u0902\u091c\u093c\u0947\u0917\u093e"
    ],
    "name:hun_x_preferred":[
        "Nzega"
    ],
    "name:ind_x_preferred":[
        "Nzega"
    ],
    "name:ita_x_preferred":[
        "Nzega"
    ],
    "name:jpn_x_preferred":[
        "\u30cc\u30bc\u30ac"
    ],
    "name:kor_x_preferred":[
        "\uc740\uc81c\uac00"
    ],
    "name:nld_x_preferred":[
        "Nzega"
    ],
    "name:pol_x_preferred":[
        "Nzega"
    ],
    "name:por_x_preferred":[
        "Nzega"
    ],
    "name:rus_x_preferred":[
        "\u041d\u0437\u0435\u0433\u0430"
    ],
    "name:spa_x_preferred":[
        "Nzega"
    ],
    "name:swe_x_preferred":[
        "Nzega"
    ],
    "name:tur_x_preferred":[
        "Nzega"
    ],
    "name:ukr_x_preferred":[
        "\u041d\u0437\u0435\u0433\u0430"
    ],
    "name:und_x_variant":[
        "Nseka"
    ],
    "name:urd_x_preferred":[
        "\u0646\u0632\u06cc\u06af\u0627"
    ],
    "name:vie_x_preferred":[
        "Nzega"
    ],
    "name:zho_cn_x_preferred":[
        "\u6069\u6cfd\u52a0"
    ],
    "name:zho_tw_x_preferred":[
        "\u6069\u6fa4\u52a0"
    ],
    "qs:gn_country":"RW",
    "qs:gn_fcode":"PPL",
    "qs:gn_pop":33832,
    "qs:name":"Nzega",
    "qs:name_adm0":"Rwanda",
    "qs:name_adm1":"Province du Sud",
    "qs:photos":0,
    "qs:photos_1k":0,
    "qs:photos_9k":1,
    "qs:photos_9r":1,
    "qs:photos_all":6,
    "qs:photos_sr":0,
    "qs:placetype":"Town",
    "qs:pop_sr":"7",
    "qs:woe_adm0":23424937,
    "wd:wordcount":68,
    "wof:name":"Nzega",
    "wof:placetype":"locality",
    "wof:population":33832
},
  "geometry": {"coordinates":[29.5564,-2.479],"type":"Point"}
}