{
  "type": "Feature",
  "properties": {
    "gn:admin1_code":"13",
    "gn:admin2_code":"43.0",
    "gn:admin3_code":"4315.0",
    "gn:admin4_code":"431502.0",
    "gn:asciiname":"Kibwa",
    "gn:country_code":"RW",
    "gn:dem":2137,
    "gn:feature_class":"P",
    "gn:feature_code":"PPLL",
    "gn:name":"Kibwa",
    "gn:population":0,
    "gn:timezone":"Africa/Kigali",
    "iso:country":"RW",
    "wof:name":"Kibwa",
    "wof:placetype":"locality"
},
  "geometry": {"coordinates":[29.5648,-1.4912],"type":"Point"}
}