{
  "type": "Feature",
  "properties": {
    "gn:admin1_code":"15",
    "gn:admin2_code":"22.0",
    "gn:admin3_code":"2202.0",
    "gn:admin4_code":"220202.0",
    "gn:asciiname":"Nyirakanywero",
    "gn:country_code":"RW",
    "gn:dem":1531,
    "gn:feature_class":"P",
    "gn:feature_code":"PPLL",
    "gn:name":"Nyirakanywero",
    "gn:population":0,
    "gn:timezone":"Africa/Kigali",
    "iso:country":"RW",
    "wof:name":"Nyirakanywero",
    "wof:placetype":"locality"
},
  "geometry": {"coordinates":[29.9136,-2.6186],"type":"Point"}
}