{
  "type": "Feature",
  "properties": {
    "gn:admin1_code":"15",
    "gn:admin2_code":"27.0",
    "gn:admin3_code":"2709.0",
    "gn:admin4_code":"270902.0",
    "gn:asciiname":"Cyiciro",
    "gn:country_code":"RW",
    "gn:dem":1592,
    "gn:feature_class":"P",
    "gn:feature_code":"PPL",
    "gn:name":"Cyiciro",
    "gn:population":0,
    "gn:timezone":"Africa/Kigali",
    "iso:country":"RW",
    "wof:name":"Cyiciro",
    "wof:placetype":"locality"
},
  "geometry": {"coordinates":[29.6449,-2.0605],"type":"Point"}
}