{
  "type": "Feature",
  "properties": {
    "gn:admin1_code":"14.0",
    "gn:admin2_code":"36",
    "gn:admin3_code":"3616.0",
    "gn:admin4_code":"361607.0",
    "gn:asciiname":"Kambabara",
    "gn:country_code":"RW",
    "gn:dem":1807,
    "gn:feature_class":"P",
    "gn:feature_code":"PPLL",
    "gn:name":"Kambabara",
    "gn:population":0,
    "gn:timezone":"Africa/Kigali",
    "iso:country":"RW",
    "wof:name":"Kambabara",
    "wof:placetype":"locality"
},
  "geometry": {"coordinates":[28.9149,-2.5393],"type":"Point"}
}