{
  "type": "Feature",
  "properties": {
    "gn:admin1_code":"14.0",
    "gn:admin2_code":"32",
    "gn:admin3_code":"3201.0",
    "gn:admin4_code":"320101.0",
    "gn:asciiname":"Vugiza",
    "gn:country_code":"RW",
    "gn:dem":1515,
    "gn:feature_class":"P",
    "gn:feature_code":"PPLL",
    "gn:name":"Vugiza",
    "gn:population":0,
    "gn:timezone":"Africa/Kigali",
    "iso:country":"RW",
    "wof:name":"Vugiza",
    "wof:placetype":"locality"
},
  "geometry": {"coordinates":[29.2871,-1.9064],"type":"Point"}
}