{
  "type": "Feature",
  "properties": {
    "gn:admin1_code":"13",
    "gn:admin2_code":"43.0",
    "gn:admin3_code":"4305.0",
    "gn:admin4_code":"430501.0",
    "gn:asciiname":"Ruremera",
    "gn:country_code":"RW",
    "gn:dem":2803,
    "gn:feature_class":"P",
    "gn:feature_code":"PPLL",
    "gn:name":"Ruremera",
    "gn:population":0,
    "gn:timezone":"Africa/Kigali",
    "iso:country":"RW",
    "wof:name":"Ruremera",
    "wof:placetype":"locality"
},
  "geometry": {"coordinates":[29.5199,-1.516],"type":"Point"}
}