{
  "type": "Feature",
  "properties": {
    "gn:admin1_code":"12.0",
    "gn:admin2_code":"12",
    "gn:admin3_code":"1214.0",
    "gn:admin4_code":"121408.0",
    "gn:asciiname":"Gicaca",
    "gn:country_code":"RW",
    "gn:dem":1432,
    "gn:feature_class":"P",
    "gn:feature_code":"PPLL",
    "gn:name":"Gicaca",
    "gn:population":0,
    "gn:timezone":"Africa/Kigali",
    "iso:country":"RW",
    "wof:name":"Gicaca",
    "wof:placetype":"locality"
},
  "geometry": {"coordinates":[30.2485,-1.935],"type":"Point"}
}