{
  "type": "Feature",
  "properties": {
    "gn:admin1_code":"12",
    "gn:admin2_code":"12.0",
    "gn:admin3_code":"1206.0",
    "gn:admin4_code":"120604.0",
    "gn:asciiname":"Buva",
    "gn:country_code":"RW",
    "gn:dem":1783,
    "gn:feature_class":"P",
    "gn:feature_code":"PPLL",
    "gn:name":"Buva",
    "gn:population":0,
    "gn:timezone":"Africa/Kigali",
    "iso:country":"RW",
    "wof:name":"Buva",
    "wof:placetype":"locality"
},
  "geometry": {"coordinates":[30.00008,-1.84356],"type":"Point"}
}