{
  "type": "Feature",
  "properties": {
    "gn:admin1_code":"11",
    "gn:admin2_code":"53.0",
    "gn:admin3_code":"5304.0",
    "gn:admin4_code":"530404.0",
    "gn:asciiname":"Marimba",
    "gn:country_code":"RW",
    "gn:dem":1457,
    "gn:feature_class":"P",
    "gn:feature_code":"PPLL",
    "gn:name":"Marimba",
    "gn:population":0,
    "gn:timezone":"Africa/Kigali",
    "iso:country":"RW",
    "name:ara_x_preferred":[
        "\u0645\u0627\u0631\u064a\u0645\u0628\u0627"
    ],
    "name:bre_x_preferred":[
        "Marimba"
    ],
    "name:bul_x_preferred":[
        "\u041c\u0430\u0440\u0438\u043c\u0431\u0430"
    ],
    "name:cat_x_preferred":[
        "Marimba"
    ],
    "name:ces_x_preferred":[
        "Marimba"
    ],
    "name:dan_x_preferred":[
        "Marimba"
    ],
    "name:deu_x_preferred":[
        "Marimba"
    ],
    "name:ell_x_preferred":[
        "\u039c\u03b1\u03c1\u03af\u03bc\u03c0\u03b1"
    ],
    "name:epo_x_preferred":[
        "Marimbo"
    ],
    "name:est_x_preferred":[
        "Marimbafon"
    ],
    "name:fas_x_preferred":[
        "\u0645\u0627\u0631\u06cc\u0645\u0628\u0627"
    ],
    "name:fin_x_preferred":[
        "Marimba"
    ],
    "name:fra_x_preferred":[
        "Marimba"
    ],
    "name:fry_x_preferred":[
        "Marimba"
    ],
    "name:gle_x_preferred":[
        "Mairimbe"
    ],
    "name:glg_x_preferred":[
        "Marimba"
    ],
    "name:heb_x_preferred":[
        "\u05de\u05e8\u05d9\u05de\u05d1\u05d4"
    ],
    "name:hrv_x_preferred":[
        "Marimba"
    ],
    "name:hun_x_preferred":[
        "Marimba"
    ],
    "name:ita_x_preferred":[
        "Marimba"
    ],
    "name:jpn_x_preferred":[
        "\u30de\u30ea\u30f3\u30d0"
    ],
    "name:kor_x_preferred":[
        "\ub9c8\ub9bc\ubc14"
    ],
    "name:lim_x_preferred":[
        "Marimba"
    ],
    "name:lit_x_preferred":[
        "Marimba"
    ],
    "name:mkd_x_preferred":[
        "\u041c\u0430\u0440\u0438\u043c\u0431\u0430"
    ],
    "name:msa_x_preferred":[
        "Marimba"
    ],
    "name:nld_x_preferred":[
        "Marimba"
    ],
    "name:nor_x_preferred":[
        "Marimba"
    ],
    "name:pol_x_preferred":[
        "Marimba"
    ],
    "name:por_x_preferred":[
        "Marimba"
    ],
    "name:ron_x_preferred":[
        "Marimbafon"
    ],
    "name:rus_x_preferred":[
        "\u041c\u0430\u0440\u0438\u043c\u0431\u0430"
    ],
    "name:slv_x_preferred":[
        "Marimba"
    ],
    "name:spa_x_preferred":[
        "Marimba"
    ],
    "name:srp_x_preferred":[
        "\u041c\u0430\u0440\u0438\u043c\u0431\u0430"
    ],
    "name:swe_x_preferred":[
        "Marimba"
    ],
    "name:tur_x_preferred":[
        "Marimba"
    ],
    "name:ukr_x_preferred":[
        "\u041c\u0430\u0440\u0438\u043c\u0431\u0430"
    ],
    "name:zho_x_preferred":[
        "\u9a6c\u6797\u5df4"
    ],
    "wof:name":"Marimba",
    "wof:placetype":"locality"
},
  "geometry": {"coordinates":[30.3059,-1.5766],"type":"Point"}
}