{
  "type": "Feature",
  "properties": {
    "gn:admin1_code":"11",
    "gn:admin2_code":"53.0",
    "gn:admin3_code":"5304.0",
    "gn:admin4_code":"530404.0",
    "gn:asciiname":"Marimba",
    "gn:country_code":"RW",
    "gn:dem":1457,
    "gn:feature_class":"P",
    "gn:feature_code":"PPLL",
    "gn:name":"Marimba",
    "gn:population":0,
    "gn:timezone":"Africa/Kigali",
    "iso:country":"RW",
    "wof:name":"Marimba",
    "wof:placetype":"locality"
},
  "geometry": {"coordinates":[30.3059,-1.5766],"type":"Point"}
}