{
  "type": "Feature",
  "properties": {
    "gn:admin1_code":"11",
    "gn:admin2_code":"51.0",
    "gn:admin3_code":"5114.0",
    "gn:admin4_code":"511402.0",
    "gn:asciiname":"Mitali",
    "gn:country_code":"RW",
    "gn:dem":1404,
    "gn:feature_class":"P",
    "gn:feature_code":"PPLL",
    "gn:name":"Mitali",
    "gn:population":0,
    "gn:timezone":"Africa/Kigali",
    "iso:country":"RW",
    "wof:name":"Mitali",
    "wof:placetype":"locality"
},
  "geometry": {"coordinates":[30.4043,-2.0614],"type":"Point"}
}