{
  "type": "Feature",
  "properties": {
    "gn:admin1_code":"15",
    "gn:admin2_code":"26.0",
    "gn:admin3_code":"2606.0",
    "gn:admin4_code":"260604.0",
    "gn:asciiname":"Kangoma",
    "gn:country_code":"RW",
    "gn:dem":1612,
    "gn:feature_class":"P",
    "gn:feature_code":"PPLL",
    "gn:name":"Kangoma",
    "gn:population":0,
    "gn:timezone":"Africa/Kigali",
    "iso:country":"RW",
    "wof:name":"Kangoma",
    "wof:placetype":"locality"
},
  "geometry": {"coordinates":[29.8082,-2.1489],"type":"Point"}
}