{
  "type": "Feature",
  "properties": {
    "gn:admin1_code":"12",
    "gn:admin2_code":"12.0",
    "gn:admin3_code":"1203.0",
    "gn:admin4_code":"120305.0",
    "gn:asciiname":"Mukuyi",
    "gn:country_code":"RW",
    "gn:dem":1546,
    "gn:feature_class":"P",
    "gn:feature_code":"PPLL",
    "gn:name":"Mukuyi",
    "gn:population":0,
    "gn:timezone":"Africa/Kigali",
    "iso:country":"RW",
    "wof:name":"Mukuyi",
    "wof:placetype":"locality"
},
  "geometry": {"coordinates":[30.195,-1.8716],"type":"Point"}
}