{
  "type": "Feature",
  "properties": {
    "gn:admin1_code":"12.0",
    "gn:admin2_code":"12",
    "gn:admin3_code":"1205.0",
    "gn:admin4_code":"120503.0",
    "gn:asciiname":"Agatwa",
    "gn:country_code":"RW",
    "gn:dem":1570,
    "gn:feature_class":"P",
    "gn:feature_code":"PPLL",
    "gn:name":"Agatwa",
    "gn:population":0,
    "gn:timezone":"Africa/Kigali",
    "iso:country":"RW",
    "name:und_x_variant":[
        "Agatwi",
        "Agatwa"
    ],
    "wof:name":"Agatwa",
    "wof:placetype":"locality"
},
  "geometry": {"coordinates":[30.0593,-1.8862],"type":"Point"}
}