{
  "type": "Feature",
  "properties": {
    "gn:admin1_code":"15.0",
    "gn:admin2_code":"22",
    "gn:admin3_code":"2213.0",
    "gn:admin4_code":"221301.0",
    "gn:asciiname":"Save",
    "gn:country_code":"RW",
    "gn:dem":1766,
    "gn:feature_class":"P",
    "gn:feature_code":"PPL",
    "gn:name":"Save",
    "gn:population":0,
    "gn:timezone":"Africa/Kigali",
    "iso:country":"RW",
    "name:und_x_variant":[
        "Isavi",
        "Save"
    ],
    "wof:name":"Save",
    "wof:placetype":"locality"
},
  "geometry": {"coordinates":[29.7711,-2.5427],"type":"Point"}
}