{
  "type": "Feature",
  "properties": {
    "gn:admin1_code":"15.0",
    "gn:admin2_code":"22",
    "gn:admin3_code":"2213.0",
    "gn:admin4_code":"221301.0",
    "gn:asciiname":"Save",
    "gn:country_code":"RW",
    "gn:dem":1766,
    "gn:feature_class":"P",
    "gn:feature_code":"PPL",
    "gn:name":"Save",
    "gn:population":0,
    "gn:timezone":"Africa/Kigali",
    "iso:country":"RW",
    "name:ceb_x_preferred":[
        "Save"
    ],
    "name:deu_x_preferred":[
        "Save"
    ],
    "name:fra_x_preferred":[
        "Save"
    ],
    "name:ita_x_preferred":[
        "Save"
    ],
    "name:kor_x_preferred":[
        "\uc0ac\ubca0"
    ],
    "name:kor_x_variant":[
        "\uc138\uc774\ube0c"
    ],
    "name:nld_x_preferred":[
        "Save"
    ],
    "name:pol_x_preferred":[
        "Save"
    ],
    "name:por_x_preferred":[
        "Save"
    ],
    "name:srp_x_preferred":[
        "\u0421\u0430\u0432\u0435"
    ],
    "name:swe_x_preferred":[
        "Save"
    ],
    "name:tur_x_preferred":[
        "Save"
    ],
    "name:und_x_variant":[
        "Isavi"
    ],
    "name:urd_x_preferred":[
        "\u0633\u06cc\u0648"
    ],
    "name:vie_x_preferred":[
        "S\u00f4ng Save"
    ],
    "wof:name":"Save",
    "wof:placetype":"locality"
},
  "geometry": {"coordinates":[29.7711,-2.5427],"type":"Point"}
}