{
  "type": "Feature",
  "properties": {
    "gn:admin1_code":"12",
    "gn:admin2_code":"11.0",
    "gn:admin3_code":"1102.0",
    "gn:admin4_code":"110203.0",
    "gn:asciiname":"Kagaramira",
    "gn:country_code":"RW",
    "gn:dem":1797,
    "gn:feature_class":"P",
    "gn:feature_code":"PPLL",
    "gn:name":"Kagaramira",
    "gn:population":0,
    "gn:timezone":"Africa/Kigali",
    "iso:country":"RW",
    "wof:name":"Kagaramira",
    "wof:placetype":"locality"
},
  "geometry": {"coordinates":[29.9886,-1.8774],"type":"Point"}
}