{
  "type": "Feature",
  "properties": {
    "gn:admin1_code":"11",
    "gn:admin2_code":"56.0",
    "gn:admin3_code":"5606.0",
    "gn:admin4_code":"560601.0",
    "gn:asciiname":"Kukabungo",
    "gn:country_code":"RW",
    "gn:dem":1354,
    "gn:feature_class":"P",
    "gn:feature_code":"PPLL",
    "gn:name":"Kukabungo",
    "gn:population":0,
    "gn:timezone":"Africa/Kigali",
    "iso:country":"RW",
    "wof:name":"Kukabungo",
    "wof:placetype":"locality"
},
  "geometry": {"coordinates":[30.3387,-2.1405],"type":"Point"}
}