{
  "type": "Feature",
  "properties": {
    "gn:admin1_code":"15.0",
    "gn:admin2_code":"23",
    "gn:admin3_code":"2312.0",
    "gn:admin4_code":"231201.0",
    "gn:asciiname":"Gitita",
    "gn:country_code":"RW",
    "gn:dem":2009,
    "gn:feature_class":"P",
    "gn:feature_code":"PPLL",
    "gn:name":"Gitita",
    "gn:population":0,
    "gn:timezone":"Africa/Kigali",
    "iso:country":"RW",
    "wof:name":"Gitita",
    "wof:placetype":"locality"
},
  "geometry": {"coordinates":[29.4893,-2.7315],"type":"Point"}
}