{
  "type": "Feature",
  "properties": {
    "gn:admin1_code":"14.0",
    "gn:admin2_code":"36",
    "gn:admin3_code":"3614.0",
    "gn:admin4_code":"361404.0",
    "gn:asciiname":"Kinanira",
    "gn:country_code":"RW",
    "gn:dem":1964,
    "gn:feature_class":"P",
    "gn:feature_code":"PPLL",
    "gn:name":"Kinanira",
    "gn:population":0,
    "gn:timezone":"Africa/Kigali",
    "iso:country":"RW",
    "wof:name":"Kinanira",
    "wof:placetype":"locality"
},
  "geometry": {"coordinates":[28.9692,-2.5428],"type":"Point"}
}