{
  "type": "Feature",
  "properties": {
    "gn:admin1_code":"13.0",
    "gn:admin2_code":"42",
    "gn:admin3_code":"4212.0",
    "gn:admin4_code":"421203.0",
    "gn:asciiname":"Mutego",
    "gn:country_code":"RW",
    "gn:dem":1576,
    "gn:feature_class":"P",
    "gn:feature_code":"PPLL",
    "gn:name":"Mutego",
    "gn:population":0,
    "gn:timezone":"Africa/Kigali",
    "iso:country":"RW",
    "name:und_x_variant":[
        "Colline Mutego",
        "Mutego"
    ],
    "wof:name":"Mutego",
    "wof:placetype":"locality"
},
  "geometry": {"coordinates":[29.6536,-1.7229],"type":"Point"}
}