{
  "type": "Feature",
  "properties": {
    "gn:admin1_code":"15.0",
    "gn:admin2_code":"21",
    "gn:admin3_code":"2103.0",
    "gn:admin4_code":"210303.0",
    "gn:asciiname":"Rwamagana",
    "gn:country_code":"RW",
    "gn:dem":1749,
    "gn:feature_class":"P",
    "gn:feature_code":"PPLL",
    "gn:name":"Rwamagana",
    "gn:population":0,
    "gn:timezone":"Africa/Kigali",
    "iso:country":"RW",
    "name:cat_x_preferred":[
        "Rwamagana"
    ],
    "name:ceb_x_preferred":[
        "Rwamagana"
    ],
    "name:deu_x_preferred":[
        "Rwamagana"
    ],
    "name:ell_x_preferred":[
        "\u03a1\u03bf\u03c5\u03b1\u03bc\u03b1\u03b3\u03ba\u03ac\u03bd\u03b1"
    ],
    "name:est_x_preferred":[
        "Rwamagana"
    ],
    "name:fra_x_preferred":[
        "Rwamagana"
    ],
    "name:hrv_x_preferred":[
        "Rwamagana"
    ],
    "name:jpn_x_preferred":[
        "\u30eb\u30ef\u30de\u30ac\u30ca"
    ],
    "name:kor_x_preferred":[
        "\ub974\uc640\ub9c8\uac00\ub098"
    ],
    "name:lit_x_preferred":[
        "Rvamagana"
    ],
    "name:mrj_x_preferred":[
        "\u0420\u0432\u0430\u043c\u0430\u0433\u0430\u043d\u0430"
    ],
    "name:nld_x_preferred":[
        "Rwamagana"
    ],
    "name:pol_x_preferred":[
        "Rwamagana"
    ],
    "name:por_x_preferred":[
        "Rwamagana"
    ],
    "name:ron_x_preferred":[
        "Rwamagana"
    ],
    "name:rus_x_preferred":[
        "\u0420\u0432\u0430\u043c\u0430\u0433\u0430\u043d\u0430"
    ],
    "name:tur_x_preferred":[
        "Rwamagana"
    ],
    "name:ukr_x_preferred":[
        "\u0420\u0432\u0430\u043c\u0430\u0433\u0430\u043d\u0430"
    ],
    "name:urd_x_preferred":[
        "\u0631\u0648\u0627\u0645\u0627\u06af\u0627\u0646\u0627"
    ],
    "name:zho_x_preferred":[
        "\u76e7\u74e6\u99ac\u52a0\u7d0d"
    ],
    "wof:name":"Rwamagana",
    "wof:placetype":"locality"
},
  "geometry": {"coordinates":[29.6711,-2.3244],"type":"Point"}
}