{
  "type": "Feature",
  "properties": {
    "gn:admin1_code":"14",
    "gn:admin2_code":"32.0",
    "gn:admin3_code":"3206.0",
    "gn:admin4_code":"320603.0",
    "gn:asciiname":"Rukeli",
    "gn:country_code":"RW",
    "gn:dem":2293,
    "gn:feature_class":"P",
    "gn:feature_code":"PPLL",
    "gn:name":"Rukeli",
    "gn:population":0,
    "gn:timezone":"Africa/Kigali",
    "iso:country":"RW",
    "wof:name":"Rukeli",
    "wof:placetype":"locality"
},
  "geometry": {"coordinates":[29.4786,-2.014],"type":"Point"}
}