{
  "type": "Feature",
  "properties": {
    "gn:admin1_code":"15.0",
    "gn:admin2_code":"25",
    "gn:admin3_code":"2505.0",
    "gn:admin4_code":"250501.0",
    "gn:asciiname":"Bitare",
    "gn:country_code":"RW",
    "gn:dem":1920,
    "gn:feature_class":"P",
    "gn:feature_code":"PPLL",
    "gn:name":"Bitare",
    "gn:population":0,
    "gn:timezone":"Africa/Kigali",
    "iso:country":"RW",
    "wof:name":"Bitare",
    "wof:placetype":"locality"
},
  "geometry": {"coordinates":[29.5025,-2.3351],"type":"Point"}
}