{
  "type": "Feature",
  "properties": {
    "gn:admin1_code":"14",
    "gn:admin2_code":"33.0",
    "gn:admin3_code":"3301.0",
    "gn:admin4_code":"330106.0",
    "gn:asciiname":"Bulingo",
    "gn:country_code":"RW",
    "gn:dem":2408,
    "gn:feature_class":"P",
    "gn:feature_code":"PPLF",
    "gn:name":"Bulingo",
    "gn:population":0,
    "gn:timezone":"Africa/Kigali",
    "iso:country":"RW",
    "wof:name":"Bulingo",
    "wof:placetype":"locality"
},
  "geometry": {"coordinates":[29.3832,-1.5174],"type":"Point"}
}