{
  "type": "Feature",
  "properties": {
    "gn:admin1_code":"14",
    "gn:admin2_code":"33.0",
    "gn:admin3_code":"3302.0",
    "gn:admin4_code":"330201.0",
    "gn:asciiname":"Bukumu",
    "gn:country_code":"RW",
    "gn:dem":2016,
    "gn:feature_class":"P",
    "gn:feature_code":"PPLL",
    "gn:name":"Bukumu",
    "gn:population":0,
    "gn:timezone":"Africa/Kigali",
    "iso:country":"RW",
    "wof:name":"Bukumu",
    "wof:placetype":"locality"
},
  "geometry": {"coordinates":[29.3325,-1.5827],"type":"Point"}
}