{
  "type": "Feature",
  "properties": {
    "gn:admin1_code":"13",
    "gn:admin2_code":"44.0",
    "gn:admin3_code":"4409.0",
    "gn:admin4_code":"440901.0",
    "gn:asciiname":"Mwiko",
    "gn:country_code":"RW",
    "gn:dem":2043,
    "gn:feature_class":"P",
    "gn:feature_code":"PPLL",
    "gn:name":"Mwiko",
    "gn:population":0,
    "gn:timezone":"Africa/Kigali",
    "iso:country":"RW",
    "wof:name":"Mwiko",
    "wof:placetype":"locality"
},
  "geometry": {"coordinates":[29.7364,-1.4375],"type":"Point"}
}