{
  "type": "Feature",
  "properties": {
    "gn:admin1_code":"11",
    "gn:admin2_code":"53.0",
    "gn:admin3_code":"5305.0",
    "gn:admin4_code":"530504.0",
    "gn:asciiname":"Kinyana",
    "gn:country_code":"RW",
    "gn:dem":1819,
    "gn:feature_class":"P",
    "gn:feature_code":"PPLL",
    "gn:name":"Kinyana",
    "gn:population":0,
    "gn:timezone":"Africa/Kigali",
    "iso:country":"RW",
    "wof:name":"Kinyana",
    "wof:placetype":"locality"
},
  "geometry": {"coordinates":[30.2653,-1.6605],"type":"Point"}
}