{
  "type": "Feature",
  "properties": {
    "gn:admin1_code":"15",
    "gn:admin2_code":"27.0",
    "gn:admin3_code":"2701.0",
    "gn:admin4_code":"270105.0",
    "gn:asciiname":"Bishike",
    "gn:country_code":"RW",
    "gn:dem":1825,
    "gn:feature_class":"P",
    "gn:feature_code":"PPL",
    "gn:name":"Bishike",
    "gn:population":0,
    "gn:timezone":"Africa/Kigali",
    "iso:country":"RW",
    "wof:name":"Bishike",
    "wof:placetype":"locality"
},
  "geometry": {"coordinates":[29.7752,-2.0065],"type":"Point"}
}