{
  "type": "Feature",
  "properties": {
    "gn:admin1_code":"15",
    "gn:admin2_code":"28.0",
    "gn:admin3_code":"2811.0",
    "gn:admin4_code":"281102.0",
    "gn:asciiname":"Buguli",
    "gn:country_code":"RW",
    "gn:dem":1775,
    "gn:feature_class":"P",
    "gn:feature_code":"PPL",
    "gn:name":"Buguli",
    "gn:population":0,
    "gn:timezone":"Africa/Kigali",
    "iso:country":"RW",
    "wof:name":"Buguli",
    "wof:placetype":"locality"
},
  "geometry": {"coordinates":[29.9178,-1.9556],"type":"Point"}
}