{
  "type": "Feature",
  "properties": {
    "gn:admin1_code":"13",
    "gn:admin2_code":"42.0",
    "gn:admin3_code":"4209.0",
    "gn:admin4_code":"420902.0",
    "gn:asciiname":"Musekera",
    "gn:country_code":"RW",
    "gn:dem":1946,
    "gn:feature_class":"P",
    "gn:feature_code":"PPL",
    "gn:name":"Musekera",
    "gn:population":0,
    "gn:timezone":"Africa/Kigali",
    "iso:country":"RW",
    "wof:name":"Musekera",
    "wof:placetype":"locality"
},
  "geometry": {"coordinates":[29.7538,-1.5978],"type":"Point"}
}