{
  "type": "Feature",
  "properties": {
    "gn:admin1_code":"15.0",
    "gn:admin2_code":"25",
    "gn:admin3_code":"2509.0",
    "gn:admin4_code":"250904.0",
    "gn:asciiname":"Gakoko",
    "gn:country_code":"RW",
    "gn:dem":2165,
    "gn:feature_class":"P",
    "gn:feature_code":"PPLL",
    "gn:name":"Gakoko",
    "gn:population":0,
    "gn:timezone":"Africa/Kigali",
    "iso:country":"RW",
    "wof:name":"Gakoko",
    "wof:placetype":"locality"
},
  "geometry": {"coordinates":[29.4485,-2.5746],"type":"Point"}
}