{
  "type": "Feature",
  "properties": {
    "gn:admin1_code":"13",
    "gn:admin2_code":"43.0",
    "gn:admin3_code":"4310.0",
    "gn:admin4_code":"431002.0",
    "gn:asciiname":"Gapfuro",
    "gn:country_code":"RW",
    "gn:dem":2100,
    "gn:feature_class":"P",
    "gn:feature_code":"PPLL",
    "gn:name":"Gapfuro",
    "gn:population":0,
    "gn:timezone":"Africa/Kigali",
    "iso:country":"RW",
    "wof:name":"Gapfuro",
    "wof:placetype":"locality"
},
  "geometry": {"coordinates":[29.5859,-1.4724],"type":"Point"}
}