{
  "type": "Feature",
  "properties": {
    "gn:admin1_code":"14",
    "gn:admin2_code":"31.0",
    "gn:admin3_code":"3109.0",
    "gn:admin4_code":"310905.0",
    "gn:asciiname":"Kamuvunyi",
    "gn:country_code":"RW",
    "gn:dem":1636,
    "gn:feature_class":"P",
    "gn:feature_code":"PPLL",
    "gn:name":"Kamuvunyi",
    "gn:population":0,
    "gn:timezone":"Africa/Kigali",
    "iso:country":"RW",
    "wof:name":"Kamuvunyi",
    "wof:placetype":"locality"
},
  "geometry": {"coordinates":[29.4113,-2.0545],"type":"Point"}
}