{
  "type": "Feature",
  "properties": {
    "gn:admin1_code":"11.0",
    "gn:admin2_code":"53",
    "gn:admin3_code":"5308.0",
    "gn:admin4_code":"530805.0",
    "gn:asciiname":"Muhura",
    "gn:country_code":"RW",
    "gn:dem":1844,
    "gn:feature_class":"P",
    "gn:feature_code":"PPL",
    "gn:name":"Muhura",
    "gn:population":0,
    "gn:timezone":"Africa/Kigali",
    "iso:country":"RW",
    "name:und_x_variant":[
        "Colline Muhura",
        "Muhura"
    ],
    "wof:name":"Muhura",
    "wof:placetype":"locality"
},
  "geometry": {"coordinates":[30.266,-1.7324],"type":"Point"}
}