{
  "type": "Feature",
  "properties": {
    "gn:admin1_code":"14.0",
    "gn:admin2_code":"32",
    "gn:admin3_code":"3207.0",
    "gn:admin4_code":"320701.0",
    "gn:asciiname":"Bwiza",
    "gn:country_code":"RW",
    "gn:dem":2550,
    "gn:feature_class":"P",
    "gn:feature_code":"PPLL",
    "gn:name":"Bwiza",
    "gn:population":0,
    "gn:timezone":"Africa/Kigali",
    "iso:country":"RW",
    "wof:name":"Bwiza",
    "wof:placetype":"locality"
},
  "geometry": {"coordinates":[29.4274,-1.866],"type":"Point"}
}