{
  "type": "Feature",
  "properties": {
    "gn:admin1_code":"15",
    "gn:admin2_code":"21.0",
    "gn:admin3_code":"2104.0",
    "gn:admin4_code":"210401.0",
    "gn:asciiname":"Muyebe",
    "gn:country_code":"RW",
    "gn:dem":1482,
    "gn:feature_class":"P",
    "gn:feature_code":"PPLL",
    "gn:name":"Muyebe",
    "gn:population":0,
    "gn:timezone":"Africa/Kigali",
    "iso:country":"RW",
    "wof:name":"Muyebe",
    "wof:placetype":"locality"
},
  "geometry": {"coordinates":[29.9177,-2.3515],"type":"Point"}
}