{
  "type": "Feature",
  "properties": {
    "gn:admin1_code":"13",
    "gn:admin2_code":"42.0",
    "gn:admin3_code":"4216.0",
    "gn:admin4_code":"421602.0",
    "gn:asciiname":"Bukurura",
    "gn:country_code":"RW",
    "gn:dem":1936,
    "gn:feature_class":"P",
    "gn:feature_code":"PPLL",
    "gn:name":"Bukurura",
    "gn:population":0,
    "gn:timezone":"Africa/Kigali",
    "iso:country":"RW",
    "wof:name":"Bukurura",
    "wof:placetype":"locality"
},
  "geometry": {"coordinates":[29.7717,-1.6257],"type":"Point"}
}