{
  "type": "Feature",
  "properties": {
    "gn:admin1_code":"11",
    "gn:admin2_code":"51.0",
    "gn:admin3_code":"5105.0",
    "gn:admin4_code":"510502.0",
    "gn:asciiname":"Kigabiro",
    "gn:country_code":"RW",
    "gn:dem":1536,
    "gn:feature_class":"P",
    "gn:feature_code":"PPL",
    "gn:name":"Kigabiro",
    "gn:population":0,
    "gn:timezone":"Africa/Kigali",
    "iso:country":"RW",
    "wof:name":"Kigabiro",
    "wof:placetype":"locality"
},
  "geometry": {"coordinates":[30.4383,-1.9601],"type":"Point"}
}