{
  "type": "Feature",
  "properties": {
    "gn:admin1_code":"11",
    "gn:admin2_code":"55.0",
    "gn:admin3_code":"5510.0",
    "gn:admin4_code":"551002.0",
    "gn:asciiname":"Nyabimuli",
    "gn:country_code":"RW",
    "gn:dem":1803,
    "gn:feature_class":"P",
    "gn:feature_code":"PPLL",
    "gn:name":"Nyabimuli",
    "gn:population":0,
    "gn:timezone":"Africa/Kigali",
    "iso:country":"RW",
    "wof:name":"Nyabimuli",
    "wof:placetype":"locality"
},
  "geometry": {"coordinates":[30.7393,-2.1458],"type":"Point"}
}