{
  "type": "Feature",
  "properties": {
    "gn:admin1_code":"13",
    "gn:admin2_code":"41.0",
    "gn:admin3_code":"4110.0",
    "gn:admin4_code":"411001.0",
    "gn:asciiname":"Buhira",
    "gn:country_code":"RW",
    "gn:dem":1850,
    "gn:feature_class":"P",
    "gn:feature_code":"PPLL",
    "gn:name":"Buhira",
    "gn:population":0,
    "gn:timezone":"Africa/Kigali",
    "iso:country":"RW",
    "wof:name":"Buhira",
    "wof:placetype":"locality"
},
  "geometry": {"coordinates":[29.9302,-1.7565],"type":"Point"}
}