{
  "type": "Feature",
  "properties": {
    "gn:admin1_code":"13.0",
    "gn:admin2_code":"45",
    "gn:admin3_code":"4504.0",
    "gn:admin4_code":"450405.0",
    "gn:asciiname":"Muture",
    "gn:country_code":"RW",
    "gn:dem":1814,
    "gn:feature_class":"P",
    "gn:feature_code":"PPL",
    "gn:name":"Muture",
    "gn:population":0,
    "gn:timezone":"Africa/Kigali",
    "iso:country":"RW",
    "wof:name":"Muture",
    "wof:placetype":"locality"
},
  "geometry": {"coordinates":[30.02417,-1.48028],"type":"Point"}
}