{
  "type": "Feature",
  "properties": {
    "gn:admin1_code":"11",
    "gn:admin2_code":"51.0",
    "gn:admin3_code":"5106.0",
    "gn:admin4_code":"510608.0",
    "gn:asciiname":"Mwuma",
    "gn:country_code":"RW",
    "gn:dem":1476,
    "gn:feature_class":"P",
    "gn:feature_code":"PPLL",
    "gn:name":"Mwuma",
    "gn:population":0,
    "gn:timezone":"Africa/Kigali",
    "iso:country":"RW",
    "wof:name":"Mwuma",
    "wof:placetype":"locality"
},
  "geometry": {"coordinates":[30.4838,-1.8573],"type":"Point"}
}