{
  "type": "Feature",
  "properties": {
    "gn:admin1_code":"15",
    "gn:admin2_code":"22.0",
    "gn:admin3_code":"2208.0",
    "gn:admin4_code":"220803.0",
    "gn:asciiname":"Nyagahuru",
    "gn:country_code":"RW",
    "gn:dem":1641,
    "gn:feature_class":"P",
    "gn:feature_code":"PPL",
    "gn:name":"Nyagahuru",
    "gn:population":0,
    "gn:timezone":"Africa/Kigali",
    "iso:country":"RW",
    "wof:name":"Nyagahuru",
    "wof:placetype":"locality"
},
  "geometry": {"coordinates":[29.8395,-2.7048],"type":"Point"}
}