{
  "type": "Feature",
  "properties": {
    "gn:admin1_code":"15.0",
    "gn:admin2_code":"23",
    "gn:admin3_code":"2307.0",
    "gn:admin4_code":"230705.0",
    "gn:asciiname":"Kamana",
    "gn:country_code":"RW",
    "gn:dem":1798,
    "gn:feature_class":"P",
    "gn:feature_code":"PPL",
    "gn:name":"Kamana",
    "gn:population":0,
    "gn:timezone":"Africa/Kigali",
    "iso:country":"RW",
    "wof:name":"Kamana",
    "wof:placetype":"locality"
},
  "geometry": {"coordinates":[29.5597,-2.7426],"type":"Point"}
}