{
  "type": "Feature",
  "properties": {
    "gn:admin1_code":"14",
    "gn:admin2_code":"33.0",
    "gn:admin3_code":"3308.0",
    "gn:admin4_code":"330802.0",
    "gn:asciiname":"Kayove",
    "gn:country_code":"RW",
    "gn:dem":2083,
    "gn:feature_class":"P",
    "gn:feature_code":"PPL",
    "gn:name":"Kayove",
    "gn:population":0,
    "gn:timezone":"Africa/Kigali",
    "iso:country":"RW",
    "wof:name":"Kayove",
    "wof:placetype":"locality"
},
  "geometry": {"coordinates":[29.3614,-1.6779],"type":"Point"}
}