{
  "type": "Feature",
  "properties": {
    "gn:admin1_code":"13",
    "gn:admin2_code":"45.0",
    "gn:admin3_code":"4520.0",
    "gn:admin4_code":"452001.0",
    "gn:asciiname":"Kalika",
    "gn:country_code":"RW",
    "gn:dem":1614,
    "gn:feature_class":"P",
    "gn:feature_code":"PPLL",
    "gn:name":"Kalika",
    "gn:population":0,
    "gn:timezone":"Africa/Kigali",
    "iso:country":"RW",
    "wof:name":"Kalika",
    "wof:placetype":"locality"
},
  "geometry": {"coordinates":[30.2063,-1.7622],"type":"Point"}
}