{
  "type": "Feature",
  "properties": {
    "gn:admin1_code":"13",
    "gn:admin2_code":"45.0",
    "gn:admin3_code":"4514.0",
    "gn:admin4_code":"451404.0",
    "gn:asciiname":"Birumba",
    "gn:country_code":"RW",
    "gn:dem":2112,
    "gn:feature_class":"P",
    "gn:feature_code":"PPLL",
    "gn:name":"Birumba",
    "gn:population":0,
    "gn:timezone":"Africa/Kigali",
    "iso:country":"RW",
    "wof:name":"Birumba",
    "wof:placetype":"locality"
},
  "geometry": {"coordinates":[29.9757,-1.5959],"type":"Point"}
}