{
  "type": "Feature",
  "properties": {
    "gn:admin1_code":"14",
    "gn:admin2_code":"35.0",
    "gn:admin3_code":"3510.0",
    "gn:admin4_code":"351002.0",
    "gn:asciiname":"Mpanga",
    "gn:country_code":"RW",
    "gn:dem":1736,
    "gn:feature_class":"P",
    "gn:feature_code":"PPLL",
    "gn:name":"Mpanga",
    "gn:population":0,
    "gn:timezone":"Africa/Kigali",
    "iso:country":"RW",
    "wof:name":"Mpanga",
    "wof:placetype":"locality"
},
  "geometry": {"coordinates":[29.5887,-2.0186],"type":"Point"}
}