{
  "type": "Feature",
  "properties": {
    "gn:admin1_code":"15",
    "gn:admin2_code":"26.0",
    "gn:admin3_code":"2608.0",
    "gn:admin4_code":"260802.0",
    "gn:asciiname":"Malimba",
    "gn:country_code":"RW",
    "gn:dem":1478,
    "gn:feature_class":"P",
    "gn:feature_code":"PPLL",
    "gn:name":"Malimba",
    "gn:population":0,
    "gn:timezone":"Africa/Kigali",
    "iso:country":"RW",
    "name:ceb_x_preferred":[
        "Malimba"
    ],
    "name:fra_x_preferred":[
        "Malimba"
    ],
    "wof:name":"Malimba",
    "wof:placetype":"locality"
},
  "geometry": {"coordinates":[29.8615,-2.2612],"type":"Point"}
}