{
  "type": "Feature",
  "properties": {
    "gn:admin1_code":"15",
    "gn:admin2_code":"21.0",
    "gn:admin3_code":"2102.0",
    "gn:admin4_code":"210201.0",
    "gn:asciiname":"Rushoka",
    "gn:country_code":"RW",
    "gn:dem":1447,
    "gn:feature_class":"P",
    "gn:feature_code":"PPLL",
    "gn:name":"Rushoka",
    "gn:population":0,
    "gn:timezone":"Africa/Kigali",
    "iso:country":"RW",
    "wof:name":"Rushoka",
    "wof:placetype":"locality"
},
  "geometry": {"coordinates":[29.9634,-2.2411],"type":"Point"}
}