{
  "type": "Feature",
  "properties": {
    "gn:admin1_code":"12.0",
    "gn:admin2_code":"12",
    "gn:admin3_code":"1206.0",
    "gn:admin4_code":"120605.0",
    "gn:asciiname":"Nyamabuye",
    "gn:country_code":"RW",
    "gn:dem":1642,
    "gn:feature_class":"P",
    "gn:feature_code":"PPLL",
    "gn:name":"Nyamabuye",
    "gn:population":0,
    "gn:timezone":"Africa/Kigali",
    "iso:country":"RW",
    "wof:name":"Nyamabuye",
    "wof:placetype":"locality"
},
  "geometry": {"coordinates":[30.038,-1.9331],"type":"Point"}
}