{
  "type": "Feature",
  "properties": {
    "gn:admin1_code":"14.0",
    "gn:admin2_code":"37",
    "gn:admin3_code":"3708.0",
    "gn:admin4_code":"370805.0",
    "gn:asciiname":"Kamanu",
    "gn:country_code":"RW",
    "gn:dem":1493,
    "gn:feature_class":"P",
    "gn:feature_code":"PPLL",
    "gn:name":"Kamanu",
    "gn:population":0,
    "gn:timezone":"Africa/Kigali",
    "iso:country":"RW",
    "wof:name":"Kamanu",
    "wof:placetype":"locality"
},
  "geometry": {"coordinates":[29.0201,-2.532],"type":"Point"}
}