{
  "type": "Feature",
  "properties": {
    "gn:admin1_code":"11",
    "gn:admin2_code":"57.0",
    "gn:admin3_code":"5705.0",
    "gn:admin4_code":"570503.0",
    "gn:asciiname":"Kibenga II",
    "gn:country_code":"RW",
    "gn:dem":1431,
    "gn:feature_class":"P",
    "gn:feature_code":"PPLL",
    "gn:name":"Kibenga II",
    "gn:population":0,
    "gn:timezone":"Africa/Kigali",
    "iso:country":"RW",
    "wof:name":"Kibenga II",
    "wof:placetype":"locality"
},
  "geometry": {"coordinates":[30.0967,-2.2135],"type":"Point"}
}