{
  "type": "Feature",
  "properties": {
    "gn:admin1_code":"13",
    "gn:admin2_code":"45.0",
    "gn:admin3_code":"4518.0",
    "gn:admin4_code":"451806.0",
    "gn:asciiname":"Baliza",
    "gn:country_code":"RW",
    "gn:dem":1494,
    "gn:feature_class":"P",
    "gn:feature_code":"PPLL",
    "gn:name":"Baliza",
    "gn:population":0,
    "gn:timezone":"Africa/Kigali",
    "iso:country":"RW",
    "name:bpy_x_preferred":[
        "\u09ac\u09be\u09b2\u09bf\u099c\u09be"
    ],
    "name:deu_x_preferred":[
        "Baliza"
    ],
    "name:epo_x_preferred":[
        "Baliza"
    ],
    "name:fra_x_preferred":[
        "Baliza"
    ],
    "name:hye_x_preferred":[
        "\u0532\u0561\u056c\u056b\u0566\u0561"
    ],
    "name:ita_x_preferred":[
        "Baliza"
    ],
    "name:kat_x_preferred":[
        "\u10d1\u10d0\u10da\u10d8\u10d6\u10d0"
    ],
    "name:kaz_x_preferred":[
        "\u0411\u0430\u043b\u0438\u0437\u0430"
    ],
    "name:mlg_x_preferred":[
        "Baliza"
    ],
    "name:nld_x_preferred":[
        "Baliza"
    ],
    "name:nor_x_preferred":[
        "Baliza"
    ],
    "name:por_x_preferred":[
        "Baliza"
    ],
    "name:ron_x_preferred":[
        "Baliza"
    ],
    "name:rus_x_preferred":[
        "\u0411\u0430\u043b\u0438\u0437\u0430"
    ],
    "name:spa_x_preferred":[
        "Baliza"
    ],
    "name:vie_x_preferred":[
        "Baliza"
    ],
    "name:vol_x_preferred":[
        "Baliza"
    ],
    "name:war_x_preferred":[
        "Baliza"
    ],
    "name:zho_x_preferred":[
        "\u5df4\u5229\u8428"
    ],
    "wof:name":"Baliza",
    "wof:placetype":"locality"
},
  "geometry": {"coordinates":[30.1284,-1.7577],"type":"Point"}
}