{
  "type": "Feature",
  "properties": {
    "gn:admin1_code":"11",
    "gn:admin2_code":"53.0",
    "gn:admin3_code":"5313.0",
    "gn:admin4_code":"531304.0",
    "gn:asciiname":"Kayenzi",
    "gn:country_code":"RW",
    "gn:dem":1566,
    "gn:feature_class":"P",
    "gn:feature_code":"PPLL",
    "gn:name":"Kayenzi",
    "gn:population":0,
    "gn:timezone":"Africa/Kigali",
    "iso:country":"RW",
    "wof:name":"Kayenzi",
    "wof:placetype":"locality"
},
  "geometry": {"coordinates":[30.3742,-1.6796],"type":"Point"}
}