{
  "type": "Feature",
  "properties": {
    "gn:admin1_code":"11",
    "gn:admin2_code":"55.0",
    "gn:admin3_code":"5504.0",
    "gn:admin4_code":"550404.0",
    "gn:asciiname":"Bugarura",
    "gn:country_code":"RW",
    "gn:dem":1623,
    "gn:feature_class":"P",
    "gn:feature_code":"PPLL",
    "gn:name":"Bugarura",
    "gn:population":0,
    "gn:timezone":"Africa/Kigali",
    "iso:country":"RW",
    "wof:name":"Bugarura",
    "wof:placetype":"locality"
},
  "geometry": {"coordinates":[30.7015,-2.2903],"type":"Point"}
}