{
  "type": "Feature",
  "properties": {
    "gn:admin1_code":"14.0",
    "gn:admin2_code":"32",
    "gn:admin3_code":"3209.0",
    "gn:admin4_code":"320902.0",
    "gn:asciiname":"Vumbi",
    "gn:country_code":"RW",
    "gn:dem":1686,
    "gn:feature_class":"P",
    "gn:feature_code":"PPL",
    "gn:name":"Vumbi",
    "gn:population":0,
    "gn:timezone":"Africa/Kigali",
    "iso:country":"RW",
    "wof:name":"Vumbi",
    "wof:placetype":"locality"
},
  "geometry": {"coordinates":[29.2998,-1.8567],"type":"Point"}
}