{
  "type": "Feature",
  "properties": {
    "gn:admin1_code":"14.0",
    "gn:admin2_code":"31",
    "gn:admin3_code":"3108.0",
    "gn:admin4_code":"310803.0",
    "gn:asciiname":"Gisayura",
    "gn:country_code":"RW",
    "gn:dem":2108,
    "gn:feature_class":"P",
    "gn:feature_code":"PPLL",
    "gn:name":"Gisayura",
    "gn:population":0,
    "gn:timezone":"Africa/Kigali",
    "iso:country":"RW",
    "wof:name":"Gisayura",
    "wof:placetype":"locality"
},
  "geometry": {"coordinates":[29.4395,-2.2536],"type":"Point"}
}