{
  "type": "Feature",
  "properties": {
    "gn:admin1_code":"14.0",
    "gn:admin2_code":"37",
    "gn:admin3_code":"3701.0",
    "gn:admin4_code":"370101.0",
    "gn:asciiname":"Gisakura",
    "gn:country_code":"RW",
    "gn:dem":1931,
    "gn:feature_class":"P",
    "gn:feature_code":"PPL",
    "gn:name":"Gisakura",
    "gn:population":0,
    "gn:timezone":"Africa/Kigali",
    "iso:country":"RW",
    "wof:name":"Gisakura",
    "wof:placetype":"locality"
},
  "geometry": {"coordinates":[29.0867,-2.4514],"type":"Point"}
}