{
  "type": "Feature",
  "properties": {
    "gn:admin1_code":"14",
    "gn:admin2_code":"33.0",
    "gn:admin3_code":"3311.0",
    "gn:admin4_code":"331105.0",
    "gn:asciiname":"Buzuta",
    "gn:country_code":"RW",
    "gn:dem":1667,
    "gn:feature_class":"P",
    "gn:feature_code":"PPLL",
    "gn:name":"Buzuta",
    "gn:population":0,
    "gn:timezone":"Africa/Kigali",
    "iso:country":"RW",
    "wof:name":"Buzuta",
    "wof:placetype":"locality"
},
  "geometry": {"coordinates":[29.3028,-1.6591],"type":"Point"}
}