{
  "type": "Feature",
  "properties": {
    "gn:admin1_code":"12.0",
    "gn:admin2_code":"12",
    "gn:admin3_code":"1205.0",
    "gn:admin4_code":"120502.0",
    "gn:asciiname":"Bweramvura",
    "gn:country_code":"RW",
    "gn:dem":1726,
    "gn:feature_class":"P",
    "gn:feature_code":"PPLL",
    "gn:name":"Bweramvura",
    "gn:population":0,
    "gn:timezone":"Africa/Kigali",
    "iso:country":"RW",
    "wof:name":"Bweramvura",
    "wof:placetype":"locality"
},
  "geometry": {"coordinates":[30.0416,-1.8667],"type":"Point"}
}