{
  "type": "Feature",
  "properties": {
    "gn:admin1_code":"15.0",
    "gn:admin2_code":"24",
    "gn:admin3_code":"2404.0",
    "gn:admin4_code":"240407.0",
    "gn:asciiname":"Kigarama",
    "gn:country_code":"RW",
    "gn:dem":1641,
    "gn:feature_class":"P",
    "gn:feature_code":"PPLL",
    "gn:name":"Kigarama",
    "gn:population":0,
    "gn:timezone":"Africa/Kigali",
    "iso:country":"RW",
    "wof:name":"Kigarama",
    "wof:placetype":"locality"
},
  "geometry": {"coordinates":[29.6905,-2.4473],"type":"Point"}
}