{
  "type": "Feature",
  "properties": {
    "gn:admin1_code":"12",
    "gn:admin2_code":"13.0",
    "gn:admin3_code":"1305.0",
    "gn:admin4_code":"130504.0",
    "gn:asciiname":"Kabeza",
    "gn:country_code":"RW",
    "gn:dem":1395,
    "gn:feature_class":"P",
    "gn:feature_code":"PPLL",
    "gn:name":"Kabeza",
    "gn:population":0,
    "gn:timezone":"Africa/Kigali",
    "iso:country":"RW",
    "wof:name":"Kabeza",
    "wof:placetype":"locality"
},
  "geometry": {"coordinates":[30.1292,-1.977],"type":"Point"}
}