{
  "type": "Feature",
  "properties": {
    "gn:admin1_code":"14",
    "gn:admin2_code":"33.0",
    "gn:admin3_code":"3303.0",
    "gn:admin4_code":"330305.0",
    "gn:asciiname":"Makurizo",
    "gn:country_code":"RW",
    "gn:dem":1938,
    "gn:feature_class":"P",
    "gn:feature_code":"PPLL",
    "gn:name":"Makurizo",
    "gn:population":0,
    "gn:timezone":"Africa/Kigali",
    "iso:country":"RW",
    "wof:name":"Makurizo",
    "wof:placetype":"locality"
},
  "geometry": {"coordinates":[29.3384,-1.6555],"type":"Point"}
}