{
  "type": "Feature",
  "properties": {
    "gn:admin1_code":"15",
    "gn:admin2_code":"23.0",
    "gn:admin3_code":"2302.0",
    "gn:admin4_code":"230205.0",
    "gn:asciiname":"Gatwaro",
    "gn:country_code":"RW",
    "gn:dem":1840,
    "gn:feature_class":"P",
    "gn:feature_code":"PPLL",
    "gn:name":"Gatwaro",
    "gn:population":0,
    "gn:timezone":"Africa/Kigali",
    "iso:country":"RW",
    "wof:name":"Gatwaro",
    "wof:placetype":"locality"
},
  "geometry": {"coordinates":[29.5919,-2.7967],"type":"Point"}
}