{
  "type": "Feature",
  "properties": {
    "gn:admin1_code":"15.0",
    "gn:admin2_code":"21",
    "gn:admin3_code":"2106.0",
    "gn:admin4_code":"210604.0",
    "gn:asciiname":"Kabaya",
    "gn:country_code":"RW",
    "gn:dem":1791,
    "gn:feature_class":"P",
    "gn:feature_code":"PPLL",
    "gn:name":"Kabaya",
    "gn:population":0,
    "gn:timezone":"Africa/Kigali",
    "iso:country":"RW",
    "name:jpn_x_preferred":[
        "\u30ab\u30d0\u30e4\u98df\u54c1"
    ],
    "name:kor_x_preferred":[
        "\uac00\ubc14\uc57c \uc2dd\ud488"
    ],
    "wof:name":"Kabaya",
    "wof:placetype":"locality"
},
  "geometry": {"coordinates":[29.7249,-2.2888],"type":"Point"}
}