{
  "type": "Feature",
  "properties": {
    "gn:admin1_code":"13",
    "gn:admin2_code":"43.0",
    "gn:admin3_code":"4312.0",
    "gn:admin4_code":"431202.0",
    "gn:asciiname":"Ntamiziro",
    "gn:country_code":"RW",
    "gn:dem":2046,
    "gn:feature_class":"P",
    "gn:feature_code":"PPL",
    "gn:name":"Ntamiziro",
    "gn:population":0,
    "gn:timezone":"Africa/Kigali",
    "iso:country":"RW",
    "wof:name":"Ntamiziro",
    "wof:placetype":"locality"
},
  "geometry": {"coordinates":[29.6217,-1.4594],"type":"Point"}
}