{
  "type": "Feature",
  "properties": {
    "gn:admin1_code":"15.0",
    "gn:admin2_code":"27",
    "gn:admin3_code":"2703.0",
    "gn:admin4_code":"270302.0",
    "gn:asciiname":"Nyakabanda",
    "gn:country_code":"RW",
    "gn:dem":1575,
    "gn:feature_class":"P",
    "gn:feature_code":"PPL",
    "gn:name":"Nyakabanda",
    "gn:population":0,
    "gn:timezone":"Africa/Kigali",
    "iso:country":"RW",
    "wof:name":"Nyakabanda",
    "wof:placetype":"locality"
},
  "geometry": {"coordinates":[29.6835,-1.8414],"type":"Point"}
}