{
  "type": "Feature",
  "properties": {
    "gn:admin1_code":"12",
    "gn:admin2_code":"11.0",
    "gn:admin3_code":"1105.0",
    "gn:admin4_code":"110501.0",
    "gn:asciiname":"Kankuba",
    "gn:country_code":"RW",
    "gn:dem":1465,
    "gn:feature_class":"P",
    "gn:feature_code":"PPLL",
    "gn:name":"Kankuba",
    "gn:population":0,
    "gn:timezone":"Africa/Kigali",
    "iso:country":"RW",
    "wof:name":"Kankuba",
    "wof:placetype":"locality"
},
  "geometry": {"coordinates":[30.0238,-2.0306],"type":"Point"}
}