{
  "type": "Feature",
  "properties": {
    "gn:admin1_code":"14.0",
    "gn:admin2_code":"36",
    "gn:admin3_code":"3617.0",
    "gn:admin4_code":"361701.0",
    "gn:asciiname":"Ngoma",
    "gn:country_code":"RW",
    "gn:dem":1582,
    "gn:feature_class":"P",
    "gn:feature_code":"PPLL",
    "gn:name":"Ngoma",
    "gn:population":0,
    "gn:timezone":"Africa/Kigali",
    "iso:country":"RW",
    "wof:name":"Ngoma",
    "wof:placetype":"locality"
},
  "geometry": {"coordinates":[28.9565,-2.6682],"type":"Point"}
}