{
  "type": "Feature",
  "properties": {
    "gn:admin1_code":"14.0",
    "gn:admin2_code":"37",
    "gn:admin3_code":"3712.0",
    "gn:admin4_code":"371202.0",
    "gn:asciiname":"Kinunga",
    "gn:country_code":"RW",
    "gn:dem":1615,
    "gn:feature_class":"P",
    "gn:feature_code":"PPLL",
    "gn:name":"Kinunga",
    "gn:population":0,
    "gn:timezone":"Africa/Kigali",
    "iso:country":"RW",
    "name:und_x_variant":[
        "Kinungo",
        "Kinunga"
    ],
    "wof:name":"Kinunga",
    "wof:placetype":"locality"
},
  "geometry": {"coordinates":[29.0304,-2.3486],"type":"Point"}
}