{
  "type": "Feature",
  "properties": {
    "gn:admin1_code":"13",
    "gn:admin2_code":"42.0",
    "gn:admin3_code":"4211.0",
    "gn:admin4_code":"421103.0",
    "gn:asciiname":"Kivuba",
    "gn:country_code":"RW",
    "gn:dem":1672,
    "gn:feature_class":"P",
    "gn:feature_code":"PPLL",
    "gn:name":"Kivuba",
    "gn:population":0,
    "gn:timezone":"Africa/Kigali",
    "iso:country":"RW",
    "wof:name":"Kivuba",
    "wof:placetype":"locality"
},
  "geometry": {"coordinates":[29.788,-1.7523],"type":"Point"}
}