{
  "type": "Feature",
  "properties": {
    "gn:admin1_code":"15",
    "gn:admin2_code":"26.0",
    "gn:admin3_code":"2608.0",
    "gn:admin4_code":"260804.0",
    "gn:asciiname":"Nyarushubi",
    "gn:country_code":"RW",
    "gn:dem":1518,
    "gn:feature_class":"P",
    "gn:feature_code":"PPLL",
    "gn:name":"Nyarushubi",
    "gn:population":0,
    "gn:timezone":"Africa/Kigali",
    "iso:country":"RW",
    "wof:name":"Nyarushubi",
    "wof:placetype":"locality"
},
  "geometry": {"coordinates":[29.84800000000001,-2.2022],"type":"Point"}
}