{
  "type": "Feature",
  "properties": {
    "gn:admin1_code":"14.0",
    "gn:admin2_code":"36",
    "gn:admin3_code":"3606.0",
    "gn:admin4_code":"360605.0",
    "gn:asciiname":"Muhari",
    "gn:country_code":"RW",
    "gn:dem":1539,
    "gn:feature_class":"P",
    "gn:feature_code":"PPL",
    "gn:name":"Muhari",
    "gn:population":0,
    "gn:timezone":"Africa/Kigali",
    "iso:country":"RW",
    "name:und_x_variant":[
        "Colline Muhari",
        "Muhari"
    ],
    "wof:name":"Muhari",
    "wof:placetype":"locality"
},
  "geometry": {"coordinates":[28.9076,-2.4483],"type":"Point"}
}