{
  "type": "Feature",
  "properties": {
    "gn:admin1_code":"14",
    "gn:admin2_code":"31.0",
    "gn:admin3_code":"3112.0",
    "gn:admin4_code":"311208.0",
    "gn:asciiname":"Rutabi",
    "gn:country_code":"RW",
    "gn:dem":2243,
    "gn:feature_class":"P",
    "gn:feature_code":"PPLL",
    "gn:name":"Rutabi",
    "gn:population":0,
    "gn:timezone":"Africa/Kigali",
    "iso:country":"RW",
    "wof:name":"Rutabi",
    "wof:placetype":"locality"
},
  "geometry": {"coordinates":[29.4128,-2.1846],"type":"Point"}
}