{
  "type": "Feature",
  "properties": {
    "gn:admin1_code":"11",
    "gn:admin2_code":"53.0",
    "gn:admin3_code":"5307.0",
    "gn:admin4_code":"530704.0",
    "gn:asciiname":"Umulinga",
    "gn:country_code":"RW",
    "gn:dem":1630,
    "gn:feature_class":"P",
    "gn:feature_code":"PPLL",
    "gn:name":"Umulinga",
    "gn:population":0,
    "gn:timezone":"Africa/Kigali",
    "iso:country":"RW",
    "wof:name":"Umulinga",
    "wof:placetype":"locality"
},
  "geometry": {"coordinates":[30.4156,-1.7684],"type":"Point"}
}