{
  "type": "Feature",
  "properties": {
    "gn:admin1_code":"13",
    "gn:admin2_code":"42.0",
    "gn:admin3_code":"4205.0",
    "gn:admin4_code":"420505.0",
    "gn:asciiname":"Gihanga",
    "gn:country_code":"RW",
    "gn:dem":1788,
    "gn:feature_class":"P",
    "gn:feature_code":"PPLL",
    "gn:name":"Gihanga",
    "gn:population":0,
    "gn:timezone":"Africa/Kigali",
    "iso:country":"RW",
    "name:cat_x_preferred":[
        "Gihanga"
    ],
    "name:pol_x_preferred":[
        "Gihanga"
    ],
    "name:rus_x_preferred":[
        "\u0413\u0438\u0445\u0430\u043d\u0433\u0430"
    ],
    "wof:name":"Gihanga",
    "wof:placetype":"locality"
},
  "geometry": {"coordinates":[29.8397,-1.6617],"type":"Point"}
}