{
  "type": "Feature",
  "properties": {
    "gn:admin1_code":"14.0",
    "gn:admin2_code":"37",
    "gn:admin3_code":"3710.0",
    "gn:admin4_code":"371001.0",
    "gn:asciiname":"Kayenzi",
    "gn:country_code":"RW",
    "gn:dem":1565,
    "gn:feature_class":"P",
    "gn:feature_code":"PPLL",
    "gn:name":"Kayenzi",
    "gn:population":0,
    "gn:timezone":"Africa/Kigali",
    "iso:country":"RW",
    "wof:name":"Kayenzi",
    "wof:placetype":"locality"
},
  "geometry": {"coordinates":[29.2157,-2.2955],"type":"Point"}
}