{
  "type": "Feature",
  "properties": {
    "gn:admin1_code":"11",
    "gn:admin2_code":"56.0",
    "gn:admin3_code":"5611.0",
    "gn:admin4_code":"561105.0",
    "gn:asciiname":"Nyakibande",
    "gn:country_code":"RW",
    "gn:dem":1377,
    "gn:feature_class":"P",
    "gn:feature_code":"PPLL",
    "gn:name":"Nyakibande",
    "gn:population":0,
    "gn:timezone":"Africa/Kigali",
    "iso:country":"RW",
    "wof:name":"Nyakibande",
    "wof:placetype":"locality"
},
  "geometry": {"coordinates":[30.2872,-2.1639],"type":"Point"}
}