{
  "type": "Feature",
  "properties": {
    "gn:admin1_code":"14.0",
    "gn:admin2_code":"32",
    "gn:admin3_code":"3211.0",
    "gn:admin4_code":"321104.0",
    "gn:asciiname":"Ngoma",
    "gn:country_code":"RW",
    "gn:dem":2060,
    "gn:feature_class":"P",
    "gn:feature_code":"PPLL",
    "gn:name":"Ngoma",
    "gn:population":0,
    "gn:timezone":"Africa/Kigali",
    "iso:country":"RW",
    "wof:name":"Ngoma",
    "wof:placetype":"locality"
},
  "geometry": {"coordinates":[29.3662,-1.7621],"type":"Point"}
}