{
  "type": "Feature",
  "properties": {
    "gn:admin1_code":"14.0",
    "gn:admin2_code":"36",
    "gn:admin3_code":"3604.0",
    "gn:admin4_code":"360406.0",
    "gn:asciiname":"Mibilizi",
    "gn:country_code":"RW",
    "gn:dem":1829,
    "gn:feature_class":"P",
    "gn:feature_code":"PPLL",
    "gn:name":"Mibilizi",
    "gn:population":0,
    "gn:timezone":"Africa/Kigali",
    "iso:country":"RW",
    "wof:name":"Mibilizi",
    "wof:placetype":"locality"
},
  "geometry": {"coordinates":[28.9413,-2.5676],"type":"Point"}
}