{
  "type": "Feature",
  "properties": {
    "gn:admin1_code":"14.0",
    "gn:admin2_code":"35",
    "gn:admin3_code":"3508.0",
    "gn:admin4_code":"350801.0",
    "gn:asciiname":"Kihubi",
    "gn:country_code":"RW",
    "gn:dem":2420,
    "gn:feature_class":"P",
    "gn:feature_code":"PPLL",
    "gn:name":"Kihubi",
    "gn:population":0,
    "gn:timezone":"Africa/Kigali",
    "iso:country":"RW",
    "name:und_x_variant":[
        "Kihuri",
        "Kihubi"
    ],
    "wof:name":"Kihubi",
    "wof:placetype":"locality"
},
  "geometry": {"coordinates":[29.4788,-1.7923],"type":"Point"}
}