{
  "type": "Feature",
  "properties": {
    "gn:admin1_code":"14",
    "gn:admin2_code":"31.0",
    "gn:admin3_code":"3113.0",
    "gn:admin4_code":"311304.0",
    "gn:asciiname":"Tuvunasogi",
    "gn:country_code":"RW",
    "gn:dem":2207,
    "gn:feature_class":"P",
    "gn:feature_code":"PPLL",
    "gn:name":"Tuvunasogi",
    "gn:population":0,
    "gn:timezone":"Africa/Kigali",
    "iso:country":"RW",
    "wof:name":"Tuvunasogi",
    "wof:placetype":"locality"
},
  "geometry": {"coordinates":[29.3315,-2.227],"type":"Point"}
}