{
  "type": "Feature",
  "properties": {
    "gn:admin1_code":"13.0",
    "gn:admin2_code":"41",
    "gn:admin3_code":"4117.0",
    "gn:admin4_code":"411704.0",
    "gn:asciiname":"Murambi",
    "gn:country_code":"RW",
    "gn:dem":1795,
    "gn:feature_class":"P",
    "gn:feature_code":"PPLL",
    "gn:name":"Murambi",
    "gn:population":0,
    "gn:timezone":"Africa/Kigali",
    "iso:country":"RW",
    "name:ita_x_preferred":[
        "Murambi"
    ],
    "name:und_x_variant":[
        "Colline Murambi"
    ],
    "wof:name":"Murambi",
    "wof:placetype":"locality"
},
  "geometry": {"coordinates":[29.9359,-1.6796],"type":"Point"}
}