{
  "type": "Feature",
  "properties": {
    "gn:admin1_code":"11",
    "gn:admin2_code":"55.0",
    "gn:admin3_code":"5508.0",
    "gn:admin4_code":"550803.0",
    "gn:asciiname":"Kamurambi",
    "gn:country_code":"RW",
    "gn:dem":1572,
    "gn:feature_class":"P",
    "gn:feature_code":"PPLL",
    "gn:name":"Kamurambi",
    "gn:population":0,
    "gn:timezone":"Africa/Kigali",
    "iso:country":"RW",
    "wof:name":"Kamurambi",
    "wof:placetype":"locality"
},
  "geometry": {"coordinates":[30.6394,-2.3099],"type":"Point"}
}