{
  "type": "Feature",
  "properties": {
    "gn:admin1_code":"13",
    "gn:admin2_code":"44.0",
    "gn:admin3_code":"4405.0",
    "gn:admin4_code":"440505.0",
    "gn:asciiname":"Mutabo",
    "gn:country_code":"RW",
    "gn:dem":1906,
    "gn:feature_class":"P",
    "gn:feature_code":"PPLL",
    "gn:name":"Mutabo",
    "gn:population":0,
    "gn:timezone":"Africa/Kigali",
    "iso:country":"RW",
    "wof:name":"Mutabo",
    "wof:placetype":"locality"
},
  "geometry": {"coordinates":[29.7182,-1.4531],"type":"Point"}
}