{
  "type": "Feature",
  "properties": {
    "gn:admin1_code":"13",
    "gn:admin2_code":"45.0",
    "gn:admin3_code":"4505.0",
    "gn:admin4_code":"450501.0",
    "gn:asciiname":"Nyamirambo",
    "gn:country_code":"RW",
    "gn:dem":1720,
    "gn:feature_class":"P",
    "gn:feature_code":"PPLL",
    "gn:name":"Nyamirambo",
    "gn:population":0,
    "gn:timezone":"Africa/Kigali",
    "iso:country":"RW",
    "name:ita_x_preferred":[
        "Nyamirambo"
    ],
    "wof:name":"Nyamirambo",
    "wof:placetype":"locality"
},
  "geometry": {"coordinates":[30.20300000000001,-1.7519],"type":"Point"}
}