{
  "type": "Feature",
  "properties": {
    "gn:admin1_code":"11.0",
    "gn:admin2_code":"53",
    "gn:admin3_code":"5302.0",
    "gn:admin4_code":"530205.0",
    "gn:asciiname":"Karehe",
    "gn:country_code":"RW",
    "gn:dem":1561,
    "gn:feature_class":"P",
    "gn:feature_code":"PPL",
    "gn:name":"Karehe",
    "gn:population":0,
    "gn:timezone":"Africa/Kigali",
    "iso:country":"RW",
    "wof:name":"Karehe",
    "wof:placetype":"locality"
},
  "geometry": {"coordinates":[30.218,-1.6124],"type":"Point"}
}