{
  "type": "Feature",
  "properties": {
    "gn:admin1_code":"15.0",
    "gn:admin2_code":"25",
    "gn:admin3_code":"2503.0",
    "gn:admin4_code":"250304.0",
    "gn:asciiname":"Nyagisenyi",
    "gn:country_code":"RW",
    "gn:dem":1806,
    "gn:feature_class":"P",
    "gn:feature_code":"PPLL",
    "gn:name":"Nyagisenyi",
    "gn:population":0,
    "gn:timezone":"Africa/Kigali",
    "iso:country":"RW",
    "wof:name":"Nyagisenyi",
    "wof:placetype":"locality"
},
  "geometry": {"coordinates":[29.5813,-2.455],"type":"Point"}
}