{
  "type": "Feature",
  "properties": {
    "gn:admin1_code":"15.0",
    "gn:admin2_code":"24",
    "gn:admin3_code":"2409.0",
    "gn:admin4_code":"240903.0",
    "gn:asciiname":"Matyazo",
    "gn:country_code":"RW",
    "gn:dem":1765,
    "gn:feature_class":"P",
    "gn:feature_code":"PPL",
    "gn:name":"Matyazo",
    "gn:population":0,
    "gn:timezone":"Africa/Kigali",
    "iso:country":"RW",
    "wof:name":"Matyazo",
    "wof:placetype":"locality"
},
  "geometry": {"coordinates":[29.719,-2.5912],"type":"Point"}
}