{
  "type": "Feature",
  "properties": {
    "gn:admin1_code":"13",
    "gn:admin2_code":"42.0",
    "gn:admin3_code":"4214.0",
    "gn:admin4_code":"421402.0",
    "gn:asciiname":"Kiyebe",
    "gn:country_code":"RW",
    "gn:dem":1805,
    "gn:feature_class":"P",
    "gn:feature_code":"PPLL",
    "gn:name":"Kiyebe",
    "gn:population":0,
    "gn:timezone":"Africa/Kigali",
    "iso:country":"RW",
    "wof:name":"Kiyebe",
    "wof:placetype":"locality"
},
  "geometry": {"coordinates":[29.8929,-1.7179],"type":"Point"}
}