{
  "type": "Feature",
  "properties": {
    "gn:admin1_code":"11",
    "gn:admin2_code":"55.0",
    "gn:admin3_code":"5505.0",
    "gn:admin4_code":"550501.0",
    "gn:asciiname":"Mukaziba",
    "gn:country_code":"RW",
    "gn:dem":1571,
    "gn:feature_class":"P",
    "gn:feature_code":"PPLL",
    "gn:name":"Mukaziba",
    "gn:population":0,
    "gn:timezone":"Africa/Kigali",
    "iso:country":"RW",
    "wof:name":"Mukaziba",
    "wof:placetype":"locality"
},
  "geometry": {"coordinates":[30.625,-2.27],"type":"Point"}
}