{
  "type": "Feature",
  "properties": {
    "gn:admin1_code":"15.0",
    "gn:admin2_code":"21",
    "gn:admin3_code":"2108.0",
    "gn:admin4_code":"210802.0",
    "gn:asciiname":"Ruyenzi",
    "gn:country_code":"RW",
    "gn:dem":1561,
    "gn:feature_class":"P",
    "gn:feature_code":"PPL",
    "gn:name":"Ruyenzi",
    "gn:population":0,
    "gn:timezone":"Africa/Kigali",
    "iso:country":"RW",
    "name:und_x_variant":[
        "Colline Ruyenzi",
        "Ruyenzi"
    ],
    "wof:name":"Ruyenzi",
    "wof:placetype":"locality"
},
  "geometry": {"coordinates":[29.8303,-2.4234],"type":"Point"}
}