{
  "type": "Feature",
  "properties": {
    "gn:admin1_code":"14",
    "gn:admin2_code":"33.0",
    "gn:admin3_code":"3307.0",
    "gn:admin4_code":"330706.0",
    "gn:asciiname":"Gahenerezo",
    "gn:country_code":"RW",
    "gn:dem":2214,
    "gn:feature_class":"P",
    "gn:feature_code":"PPL",
    "gn:name":"Gahenerezo",
    "gn:population":0,
    "gn:timezone":"Africa/Kigali",
    "iso:country":"RW",
    "wof:name":"Gahenerezo",
    "wof:placetype":"locality"
},
  "geometry": {"coordinates":[29.3672,-1.6252],"type":"Point"}
}