{
  "type": "Feature",
  "properties": {
    "gn:admin1_code":"14.0",
    "gn:admin2_code":"36",
    "gn:admin3_code":"3612.0",
    "gn:admin4_code":"361203.0",
    "gn:asciiname":"Murama",
    "gn:country_code":"RW",
    "gn:dem":1524,
    "gn:feature_class":"P",
    "gn:feature_code":"PPLL",
    "gn:name":"Murama",
    "gn:population":0,
    "gn:timezone":"Africa/Kigali",
    "iso:country":"RW",
    "wof:name":"Murama",
    "wof:placetype":"locality"
},
  "geometry": {"coordinates":[28.9101,-2.4225],"type":"Point"}
}