{
  "type": "Feature",
  "properties": {
    "gn:admin1_code":"14.0",
    "gn:admin2_code":"37",
    "gn:admin3_code":"3709.0",
    "gn:admin4_code":"370904.0",
    "gn:asciiname":"Gitsimbwe",
    "gn:country_code":"RW",
    "gn:dem":1703,
    "gn:feature_class":"P",
    "gn:feature_code":"PPLL",
    "gn:name":"Gitsimbwe",
    "gn:population":0,
    "gn:timezone":"Africa/Kigali",
    "iso:country":"RW",
    "wof:name":"Gitsimbwe",
    "wof:placetype":"locality"
},
  "geometry": {"coordinates":[29.1957,-2.2352],"type":"Point"}
}