{
  "type": "Feature",
  "properties": {
    "gn:admin1_code":"14.0",
    "gn:admin2_code":"36",
    "gn:admin3_code":"3608.0",
    "gn:admin4_code":"360802.0",
    "gn:asciiname":"Mukibangiro",
    "gn:country_code":"RW",
    "gn:dem":1559,
    "gn:feature_class":"P",
    "gn:feature_code":"PPLL",
    "gn:name":"Mukibangiro",
    "gn:population":0,
    "gn:timezone":"Africa/Kigali",
    "iso:country":"RW",
    "wof:name":"Mukibangiro",
    "wof:placetype":"locality"
},
  "geometry": {"coordinates":[28.9772,-2.6023],"type":"Point"}
}