{
  "type": "Feature",
  "properties": {
    "gn:admin1_code":"13.0",
    "gn:admin2_code":"44",
    "gn:admin3_code":"4416.0",
    "gn:admin4_code":"441603.0",
    "gn:asciiname":"Ruhurura",
    "gn:country_code":"RW",
    "gn:dem":2165,
    "gn:feature_class":"P",
    "gn:feature_code":"PPLL",
    "gn:name":"Ruhurura",
    "gn:population":0,
    "gn:timezone":"Africa/Kigali",
    "iso:country":"RW",
    "name:und_x_variant":[
        "Colline Ruhurura",
        "Ruhurura"
    ],
    "wof:name":"Ruhurura",
    "wof:placetype":"locality"
},
  "geometry": {"coordinates":[29.8504,-1.4692],"type":"Point"}
}