{
  "type": "Feature",
  "properties": {
    "gn:admin1_code":"14.0",
    "gn:admin2_code":"37",
    "gn:admin3_code":"3710.0",
    "gn:admin4_code":"371004.0",
    "gn:asciiname":"Butare",
    "gn:country_code":"RW",
    "gn:dem":1509,
    "gn:feature_class":"P",
    "gn:feature_code":"PPLL",
    "gn:name":"Butare",
    "gn:population":0,
    "gn:timezone":"Africa/Kigali",
    "iso:country":"RW",
    "wof:name":"Butare",
    "wof:placetype":"locality"
},
  "geometry": {"coordinates":[29.1608,-2.283],"type":"Point"}
}