{
  "type": "Feature",
  "properties": {
    "gn:admin1_code":"13",
    "gn:admin2_code":"43.0",
    "gn:admin3_code":"4310.0",
    "gn:admin4_code":"431005.0",
    "gn:asciiname":"Kirerema",
    "gn:country_code":"RW",
    "gn:dem":2052,
    "gn:feature_class":"P",
    "gn:feature_code":"PPLL",
    "gn:name":"Kirerema",
    "gn:population":0,
    "gn:timezone":"Africa/Kigali",
    "iso:country":"RW",
    "wof:name":"Kirerema",
    "wof:placetype":"locality"
},
  "geometry": {"coordinates":[29.5851,-1.482],"type":"Point"}
}