{
  "type": "Feature",
  "properties": {
    "gn:admin1_code":"14",
    "gn:admin2_code":"33.0",
    "gn:admin3_code":"3305.0",
    "gn:admin4_code":"330505.0",
    "gn:asciiname":"Muvebwa",
    "gn:country_code":"RW",
    "gn:dem":2106,
    "gn:feature_class":"P",
    "gn:feature_code":"PPL",
    "gn:name":"Muvebwa",
    "gn:population":0,
    "gn:timezone":"Africa/Kigali",
    "iso:country":"RW",
    "wof:name":"Muvebwa",
    "wof:placetype":"locality"
},
  "geometry": {"coordinates":[29.3865,-1.7137],"type":"Point"}
}