{
  "type": "Feature",
  "properties": {
    "gn:admin1_code":"15",
    "gn:admin2_code":"27.0",
    "gn:admin3_code":"2705.0",
    "gn:admin4_code":"270501.0",
    "gn:asciiname":"Nyarunyinya",
    "gn:country_code":"RW",
    "gn:dem":1867,
    "gn:feature_class":"P",
    "gn:feature_code":"PPLL",
    "gn:name":"Nyarunyinya",
    "gn:population":0,
    "gn:timezone":"Africa/Kigali",
    "iso:country":"RW",
    "wof:name":"Nyarunyinya",
    "wof:placetype":"locality"
},
  "geometry": {"coordinates":[29.6966,-2.08],"type":"Point"}
}