{
  "type": "Feature",
  "properties": {
    "gn:admin1_code":"15",
    "gn:admin2_code":"21.0",
    "gn:admin3_code":"2107.0",
    "gn:admin4_code":"210702.0",
    "gn:asciiname":"Musenyi",
    "gn:country_code":"RW",
    "gn:dem":1492,
    "gn:feature_class":"P",
    "gn:feature_code":"PPLL",
    "gn:name":"Musenyi",
    "gn:population":0,
    "gn:timezone":"Africa/Kigali",
    "iso:country":"RW",
    "name:run_x_preferred":[
        "Musenyi"
    ],
    "wof:name":"Musenyi",
    "wof:placetype":"locality"
},
  "geometry": {"coordinates":[29.8448,-2.3556],"type":"Point"}
}