{
  "type": "Feature",
  "properties": {
    "gn:admin1_code":"13",
    "gn:admin2_code":"41.0",
    "gn:admin3_code":"4105.0",
    "gn:admin4_code":"410501.0",
    "gn:asciiname":"Gihinga",
    "gn:country_code":"RW",
    "gn:dem":1750,
    "gn:feature_class":"P",
    "gn:feature_code":"PPLL",
    "gn:name":"Gihinga",
    "gn:population":0,
    "gn:timezone":"Africa/Kigali",
    "iso:country":"RW",
    "wof:name":"Gihinga",
    "wof:placetype":"locality"
},
  "geometry": {"coordinates":[30.022,-1.7558],"type":"Point"}
}