{
  "type": "Feature",
  "properties": {
    "gn:admin1_code":"15",
    "gn:admin2_code":"28.0",
    "gn:admin3_code":"2803.0",
    "gn:admin4_code":"280306.0",
    "gn:asciiname":"Nyabubare",
    "gn:country_code":"RW",
    "gn:dem":1688,
    "gn:feature_class":"P",
    "gn:feature_code":"PPLL",
    "gn:name":"Nyabubare",
    "gn:population":0,
    "gn:timezone":"Africa/Kigali",
    "iso:country":"RW",
    "wof:name":"Nyabubare",
    "wof:placetype":"locality"
},
  "geometry": {"coordinates":[29.8351,-1.9084],"type":"Point"}
}