{
  "type": "Feature",
  "properties": {
    "gn:admin1_code":"14",
    "gn:admin2_code":"37.0",
    "gn:admin3_code":"3709.0",
    "gn:admin4_code":"370902.0",
    "gn:asciiname":"Remera",
    "gn:country_code":"RW",
    "gn:dem":1824,
    "gn:feature_class":"P",
    "gn:feature_code":"PPLL",
    "gn:name":"Remera",
    "gn:population":0,
    "gn:timezone":"Africa/Kigali",
    "iso:country":"RW",
    "wof:name":"Remera",
    "wof:placetype":"locality"
},
  "geometry": {"coordinates":[29.2504,-2.2414],"type":"Point"}
}