{
  "type": "Feature",
  "properties": {
    "gn:admin1_code":"13",
    "gn:admin2_code":"42.0",
    "gn:admin3_code":"4201.0",
    "gn:admin4_code":"420103.0",
    "gn:asciiname":"Nyagasozi",
    "gn:country_code":"RW",
    "gn:dem":1707,
    "gn:feature_class":"P",
    "gn:feature_code":"PPLL",
    "gn:name":"Nyagasozi",
    "gn:population":0,
    "gn:timezone":"Africa/Kigali",
    "iso:country":"RW",
    "wof:name":"Nyagasozi",
    "wof:placetype":"locality"
},
  "geometry": {"coordinates":[29.6831,-1.6368],"type":"Point"}
}