{
  "type": "Feature",
  "properties": {
    "gn:admin1_code":"14.0",
    "gn:admin2_code":"36",
    "gn:admin3_code":"3606.0",
    "gn:admin4_code":"360604.0",
    "gn:asciiname":"Rukokwa",
    "gn:country_code":"RW",
    "gn:dem":1586,
    "gn:feature_class":"P",
    "gn:feature_code":"PPLL",
    "gn:name":"Rukokwa",
    "gn:population":0,
    "gn:timezone":"Africa/Kigali",
    "iso:country":"RW",
    "wof:name":"Rukokwa",
    "wof:placetype":"locality"
},
  "geometry": {"coordinates":[28.9123,-2.441],"type":"Point"}
}