{
  "type": "Feature",
  "properties": {
    "gn:admin1_code":"11",
    "gn:admin2_code":"51.0",
    "gn:admin3_code":"5104.0",
    "gn:admin4_code":"510405.0",
    "gn:asciiname":"Rukankama",
    "gn:country_code":"RW",
    "gn:dem":1490,
    "gn:feature_class":"P",
    "gn:feature_code":"PPLL",
    "gn:name":"Rukankama",
    "gn:population":0,
    "gn:timezone":"Africa/Kigali",
    "iso:country":"RW",
    "wof:name":"Rukankama",
    "wof:placetype":"locality"
},
  "geometry": {"coordinates":[30.2934,-2.0898],"type":"Point"}
}