{
  "type": "Feature",
  "properties": {
    "gn:admin1_code":"15.0",
    "gn:admin2_code":"25",
    "gn:admin3_code":"2516.0",
    "gn:admin4_code":"251601.0",
    "gn:asciiname":"Kirwa",
    "gn:country_code":"RW",
    "gn:dem":1895,
    "gn:feature_class":"P",
    "gn:feature_code":"PPL",
    "gn:name":"Kirwa",
    "gn:population":0,
    "gn:timezone":"Africa/Kigali",
    "iso:country":"RW",
    "name:deu_x_preferred":[
        "Kirwa"
    ],
    "name:fin_x_preferred":[
        "Kirwa"
    ],
    "wof:name":"Kirwa",
    "wof:placetype":"locality"
},
  "geometry": {"coordinates":[29.5427,-2.5235],"type":"Point"}
}