{
  "type": "Feature",
  "properties": {
    "gn:admin1_code":"14.0",
    "gn:admin2_code":"37",
    "gn:admin3_code":"3708.0",
    "gn:admin4_code":"370803.0",
    "gn:asciiname":"Muhora",
    "gn:country_code":"RW",
    "gn:dem":1457,
    "gn:feature_class":"P",
    "gn:feature_code":"PPLL",
    "gn:name":"Muhora",
    "gn:population":0,
    "gn:timezone":"Africa/Kigali",
    "iso:country":"RW",
    "wof:name":"Muhora",
    "wof:placetype":"locality"
},
  "geometry": {"coordinates":[29.0498,-2.5363],"type":"Point"}
}