{
  "type": "Feature",
  "properties": {
    "gn:admin1_code":"13",
    "gn:admin2_code":"41.0",
    "gn:admin3_code":"4108.0",
    "gn:admin4_code":"410805.0",
    "gn:asciiname":"Buramba",
    "gn:country_code":"RW",
    "gn:dem":1939,
    "gn:feature_class":"P",
    "gn:feature_code":"PPLL",
    "gn:name":"Buramba",
    "gn:population":0,
    "gn:timezone":"Africa/Kigali",
    "iso:country":"RW",
    "wof:name":"Buramba",
    "wof:placetype":"locality"
},
  "geometry": {"coordinates":[30.0488,-1.6356],"type":"Point"}
}