{
  "type": "Feature",
  "properties": {
    "gn:admin1_code":"15",
    "gn:admin2_code":"22.0",
    "gn:admin3_code":"2208.0",
    "gn:admin4_code":"220805.0",
    "gn:asciiname":"Rugeragere",
    "gn:country_code":"RW",
    "gn:dem":1386,
    "gn:feature_class":"P",
    "gn:feature_code":"PPLL",
    "gn:name":"Rugeragere",
    "gn:population":0,
    "gn:timezone":"Africa/Kigali",
    "iso:country":"RW",
    "wof:name":"Rugeragere",
    "wof:placetype":"locality"
},
  "geometry": {"coordinates":[29.7966,-2.7408],"type":"Point"}
}