{
  "type": "Feature",
  "properties": {
    "gn:admin1_code":"11.0",
    "gn:admin2_code":"56",
    "gn:admin3_code":"5614.0",
    "gn:admin4_code":"561403.0",
    "gn:asciiname":"Zaza",
    "gn:country_code":"RW",
    "gn:dem":1425,
    "gn:feature_class":"P",
    "gn:feature_code":"PPL",
    "gn:name":"Zaza",
    "gn:population":0,
    "gn:timezone":"Africa/Kigali",
    "iso:country":"RW",
    "name:bre_x_preferred":[
        "Zaza"
    ],
    "name:cat_x_preferred":[
        "Zaza"
    ],
    "name:ceb_x_preferred":[
        "Zaza"
    ],
    "name:ces_x_preferred":[
        "Zaza"
    ],
    "name:deu_x_preferred":[
        "Zaza"
    ],
    "name:fra_x_preferred":[
        "Zaza"
    ],
    "name:ita_x_preferred":[
        "Zaza"
    ],
    "name:nld_x_preferred":[
        "Zaza"
    ],
    "name:por_x_preferred":[
        "Zaza"
    ],
    "name:rus_x_preferred":[
        "\u0417\u0430\u0437\u0430"
    ],
    "name:swe_x_preferred":[
        "Zaza"
    ],
    "name:ukr_x_preferred":[
        "\u0417\u0430\u0437\u0430"
    ],
    "name:und_x_variant":[
        "Nzaza",
        "Nsaza"
    ],
    "wof:name":"Zaza",
    "wof:placetype":"locality"
},
  "geometry": {"coordinates":[30.42621,-2.16965],"type":"Point"}
}