{
  "type": "Feature",
  "properties": {
    "gn:admin1_code":"14.0",
    "gn:admin2_code":"34",
    "gn:admin3_code":"3406.0",
    "gn:admin4_code":"340601.0",
    "gn:asciiname":"Gatovu",
    "gn:country_code":"RW",
    "gn:dem":2440,
    "gn:feature_class":"P",
    "gn:feature_code":"PPL",
    "gn:name":"Gatovu",
    "gn:population":0,
    "gn:timezone":"Africa/Kigali",
    "iso:country":"RW",
    "name:und_x_variant":[
        "Colline Gatovu",
        "Gatovu"
    ],
    "wof:name":"Gatovu",
    "wof:placetype":"locality"
},
  "geometry": {"coordinates":[29.5548,-1.6047],"type":"Point"}
}