{
  "type": "Feature",
  "properties": {
    "gn:admin1_code":"15.0",
    "gn:admin2_code":"24",
    "gn:admin3_code":"2406.0",
    "gn:admin4_code":"240606.0",
    "gn:asciiname":"Cyarumbo",
    "gn:country_code":"RW",
    "gn:dem":1701,
    "gn:feature_class":"P",
    "gn:feature_code":"PPL",
    "gn:name":"Cyarumbo",
    "gn:population":0,
    "gn:timezone":"Africa/Kigali",
    "iso:country":"RW",
    "wof:name":"Cyarumbo",
    "wof:placetype":"locality"
},
  "geometry": {"coordinates":[29.6704,-2.5438],"type":"Point"}
}