{
  "type": "Feature",
  "properties": {
    "gn:admin1_code":"14",
    "gn:admin2_code":"33.0",
    "gn:admin3_code":"3310.0",
    "gn:admin4_code":"331007.0",
    "gn:asciiname":"Keya",
    "gn:country_code":"RW",
    "gn:dem":1690,
    "gn:feature_class":"P",
    "gn:feature_code":"PPL",
    "gn:name":"Keya",
    "gn:population":0,
    "gn:timezone":"Africa/Kigali",
    "iso:country":"RW",
    "wof:name":"Keya",
    "wof:placetype":"locality"
},
  "geometry": {"coordinates":[29.3117,-1.7067],"type":"Point"}
}