{
  "type": "Feature",
  "properties": {
    "gn:admin1_code":"12",
    "gn:admin2_code":"12.0",
    "gn:admin3_code":"1205.0",
    "gn:admin4_code":"120501.0",
    "gn:asciiname":"Cyeyere",
    "gn:country_code":"RW",
    "gn:dem":1443,
    "gn:feature_class":"P",
    "gn:feature_code":"PPLL",
    "gn:name":"Cyeyere",
    "gn:population":0,
    "gn:timezone":"Africa/Kigali",
    "iso:country":"RW",
    "wof:name":"Cyeyere",
    "wof:placetype":"locality"
},
  "geometry": {"coordinates":[30.0698,-1.8775],"type":"Point"}
}