{
  "type": "Feature",
  "properties": {
    "gn:admin1_code":"15",
    "gn:admin2_code":"26.0",
    "gn:admin3_code":"2605.0",
    "gn:admin4_code":"260501.0",
    "gn:asciiname":"Kabadende",
    "gn:country_code":"RW",
    "gn:dem":1507,
    "gn:feature_class":"P",
    "gn:feature_code":"PPLL",
    "gn:name":"Kabadende",
    "gn:population":0,
    "gn:timezone":"Africa/Kigali",
    "iso:country":"RW",
    "wof:name":"Kabadende",
    "wof:placetype":"locality"
},
  "geometry": {"coordinates":[29.6256,-2.128],"type":"Point"}
}