{
  "type": "Feature",
  "properties": {
    "gn:admin1_code":"15",
    "gn:admin2_code":"28.0",
    "gn:admin3_code":"2811.0",
    "gn:admin4_code":"281103.0",
    "gn:asciiname":"Nyamabuye",
    "gn:country_code":"RW",
    "gn:dem":1784,
    "gn:feature_class":"P",
    "gn:feature_code":"PPLL",
    "gn:name":"Nyamabuye",
    "gn:population":0,
    "gn:timezone":"Africa/Kigali",
    "iso:country":"RW",
    "wof:name":"Nyamabuye",
    "wof:placetype":"locality"
},
  "geometry": {"coordinates":[29.8991,-1.9221],"type":"Point"}
}