{
  "type": "Feature",
  "properties": {
    "gn:admin1_code":"15",
    "gn:admin2_code":"22.0",
    "gn:admin3_code":"2201.0",
    "gn:admin4_code":"220104.0",
    "gn:asciiname":"Buremera",
    "gn:country_code":"RW",
    "gn:dem":1408,
    "gn:feature_class":"P",
    "gn:feature_code":"PPLL",
    "gn:name":"Buremera",
    "gn:population":0,
    "gn:timezone":"Africa/Kigali",
    "iso:country":"RW",
    "wof:name":"Buremera",
    "wof:placetype":"locality"
},
  "geometry": {"coordinates":[29.8975,-2.4508],"type":"Point"}
}