{
  "type": "Feature",
  "properties": {
    "gn:admin1_code":"11",
    "gn:admin2_code":"54.0",
    "gn:admin3_code":"5411.0",
    "gn:admin4_code":"541102.0",
    "gn:asciiname":"Kabarima",
    "gn:country_code":"RW",
    "gn:dem":1488,
    "gn:feature_class":"P",
    "gn:feature_code":"PPLL",
    "gn:name":"Kabarima",
    "gn:population":0,
    "gn:timezone":"Africa/Kigali",
    "iso:country":"RW",
    "wof:name":"Kabarima",
    "wof:placetype":"locality"
},
  "geometry": {"coordinates":[30.4782,-1.982],"type":"Point"}
}