{
  "type": "Feature",
  "properties": {
    "gn:admin1_code":"14.0",
    "gn:admin2_code":"37",
    "gn:admin3_code":"3706.0",
    "gn:admin4_code":"370602.0",
    "gn:asciiname":"Kabanga",
    "gn:country_code":"RW",
    "gn:dem":1761,
    "gn:feature_class":"P",
    "gn:feature_code":"PPLL",
    "gn:name":"Kabanga",
    "gn:population":0,
    "gn:timezone":"Africa/Kigali",
    "iso:country":"RW",
    "wof:name":"Kabanga",
    "wof:placetype":"locality"
},
  "geometry": {"coordinates":[29.1522,-2.3267],"type":"Point"}
}