{
  "type": "Feature",
  "properties": {
    "gn:admin1_code":"13",
    "gn:admin2_code":"41.0",
    "gn:admin3_code":"4110.0",
    "gn:admin4_code":"411003.0",
    "gn:asciiname":"Kibungo",
    "gn:country_code":"RW",
    "gn:dem":1964,
    "gn:feature_class":"P",
    "gn:feature_code":"PPLL",
    "gn:name":"Kibungo",
    "gn:population":0,
    "gn:timezone":"Africa/Kigali",
    "iso:country":"RW",
    "wof:name":"Kibungo",
    "wof:placetype":"locality"
},
  "geometry": {"coordinates":[29.958,-1.7674],"type":"Point"}
}