{
  "type": "Feature",
  "properties": {
    "gn:admin1_code":"13",
    "gn:admin2_code":"41.0",
    "gn:admin3_code":"4110.0",
    "gn:admin4_code":"411003.0",
    "gn:asciiname":"Kibungo",
    "gn:country_code":"RW",
    "gn:dem":1964,
    "gn:feature_class":"P",
    "gn:feature_code":"PPLL",
    "gn:name":"Kibungo",
    "gn:population":0,
    "gn:timezone":"Africa/Kigali",
    "iso:country":"RW",
    "name:ara_x_preferred":[
        "\u0643\u064a\u0628\u0648\u0646\u063a\u0648"
    ],
    "name:ben_x_preferred":[
        "\u0995\u09bf\u09ac\u09c1\u0982\u0997\u09cb"
    ],
    "name:cat_x_preferred":[
        "Kibungo"
    ],
    "name:ceb_x_preferred":[
        "Kibungo"
    ],
    "name:deu_x_preferred":[
        "Kibungo"
    ],
    "name:ell_x_preferred":[
        "\u039a\u03b9\u03bc\u03c0\u03bf\u03cd\u03bd\u03b3\u03ba\u03bf"
    ],
    "name:est_x_preferred":[
        "Kibungo"
    ],
    "name:eus_x_preferred":[
        "Kibungo"
    ],
    "name:fas_x_preferred":[
        "\u06a9\u06cc\u0628\u0648\u0646\u06af\u0648"
    ],
    "name:fra_x_preferred":[
        "Kibungo"
    ],
    "name:hin_x_preferred":[
        "\u0915\u093f\u092c\u0902\u0917\u094b"
    ],
    "name:hrv_x_preferred":[
        "Kibungo"
    ],
    "name:hun_x_preferred":[
        "Kibungo"
    ],
    "name:ind_x_preferred":[
        "Kibungo"
    ],
    "name:ita_x_preferred":[
        "Kibungo"
    ],
    "name:jpn_x_preferred":[
        "\u30ad\u30d6\u30f3\u30b4"
    ],
    "name:kor_x_preferred":[
        "\ud0a4\ubd95\uace0"
    ],
    "name:lit_x_preferred":[
        "Kibungas"
    ],
    "name:mrj_x_preferred":[
        "\u041a\u0438\u0431\u0443\u043d\u0433\u043e"
    ],
    "name:nld_x_preferred":[
        "Kibungo"
    ],
    "name:pol_x_preferred":[
        "Kibungo"
    ],
    "name:por_x_preferred":[
        "Kibungo"
    ],
    "name:ron_x_preferred":[
        "Kibungo"
    ],
    "name:rus_x_preferred":[
        "\u041a\u0438\u0431\u0443\u043d\u0433\u043e"
    ],
    "name:spa_x_preferred":[
        "Kibungo"
    ],
    "name:tur_x_preferred":[
        "Kibungo"
    ],
    "name:ukr_x_preferred":[
        "\u041a\u0456\u0431\u0443\u043d\u0433\u043e"
    ],
    "name:urd_x_preferred":[
        "\u06a9\u06cc\u0628\u0646\u06af\u0648"
    ],
    "name:vie_x_preferred":[
        "Kibungo"
    ],
    "name:zho_x_preferred":[
        "\u57fa\u672c\u53e4"
    ],
    "wof:name":"Kibungo",
    "wof:placetype":"locality"
},
  "geometry": {"coordinates":[29.958,-1.7674],"type":"Point"}
}