{
  "type": "Feature",
  "properties": {
    "gn:admin1_code":"15.0",
    "gn:admin2_code":"24",
    "gn:admin3_code":"2411.0",
    "gn:admin4_code":"241102.0",
    "gn:asciiname":"Gafumba",
    "gn:country_code":"RW",
    "gn:dem":1527,
    "gn:feature_class":"P",
    "gn:feature_code":"PPL",
    "gn:name":"Gafumba",
    "gn:population":0,
    "gn:timezone":"Africa/Kigali",
    "iso:country":"RW",
    "wof:name":"Gafumba",
    "wof:placetype":"locality"
},
  "geometry": {"coordinates":[29.815,-2.4591],"type":"Point"}
}