{
  "type": "Feature",
  "properties": {
    "gn:admin1_code":"13",
    "gn:admin2_code":"42.0",
    "gn:admin3_code":"4218.0",
    "gn:admin4_code":"421801.0",
    "gn:asciiname":"Kebero",
    "gn:country_code":"RW",
    "gn:dem":1784,
    "gn:feature_class":"P",
    "gn:feature_code":"PPLL",
    "gn:name":"Kebero",
    "gn:population":0,
    "gn:timezone":"Africa/Kigali",
    "iso:country":"RW",
    "name:bul_x_preferred":[
        "\u041a\u0435\u0431\u0435\u0440\u043e"
    ],
    "name:fra_x_preferred":[
        "Kebero"
    ],
    "name:spa_x_preferred":[
        "Kebero"
    ],
    "wof:name":"Kebero",
    "wof:placetype":"locality"
},
  "geometry": {"coordinates":[29.6474,-1.6183],"type":"Point"}
}