{
  "type": "Feature",
  "properties": {
    "gn:admin1_code":"11",
    "gn:admin2_code":"56.0",
    "gn:admin3_code":"5607.0",
    "gn:admin4_code":"560701.0",
    "gn:asciiname":"Rukizi",
    "gn:country_code":"RW",
    "gn:dem":1520,
    "gn:feature_class":"P",
    "gn:feature_code":"PPLL",
    "gn:name":"Rukizi",
    "gn:population":0,
    "gn:timezone":"Africa/Kigali",
    "iso:country":"RW",
    "wof:name":"Rukizi",
    "wof:placetype":"locality"
},
  "geometry": {"coordinates":[30.5631,-2.2238],"type":"Point"}
}