{
  "type": "Feature",
  "properties": {
    "gn:admin1_code":"11",
    "gn:admin2_code":"56.0",
    "gn:admin3_code":"5604.0",
    "gn:admin4_code":"560401.0",
    "gn:asciiname":"Birenga",
    "gn:country_code":"RW",
    "gn:dem":1521,
    "gn:feature_class":"P",
    "gn:feature_code":"PPLL",
    "gn:name":"Birenga",
    "gn:population":0,
    "gn:timezone":"Africa/Kigali",
    "iso:country":"RW",
    "wof:name":"Birenga",
    "wof:placetype":"locality"
},
  "geometry": {"coordinates":[30.4934,-2.21092],"type":"Point"}
}