{
  "type": "Feature",
  "properties": {
    "gn:admin1_code":"15",
    "gn:admin2_code":"21.0",
    "gn:admin3_code":"2107.0",
    "gn:admin4_code":"210705.0",
    "gn:asciiname":"Nyagisozi",
    "gn:country_code":"RW",
    "gn:dem":1549,
    "gn:feature_class":"P",
    "gn:feature_code":"PPL",
    "gn:name":"Nyagisozi",
    "gn:population":0,
    "gn:timezone":"Africa/Kigali",
    "iso:country":"RW",
    "wof:name":"Nyagisozi",
    "wof:placetype":"locality"
},
  "geometry": {"coordinates":[29.8721,-2.3464],"type":"Point"}
}