{
  "type": "Feature",
  "properties": {
    "gn:admin1_code":"15",
    "gn:admin2_code":"21.0",
    "gn:admin3_code":"2104.0",
    "gn:admin4_code":"210404.0",
    "gn:asciiname":"Ruteme",
    "gn:country_code":"RW",
    "gn:dem":1523,
    "gn:feature_class":"P",
    "gn:feature_code":"PPL",
    "gn:name":"Ruteme",
    "gn:population":0,
    "gn:timezone":"Africa/Kigali",
    "iso:country":"RW",
    "wof:name":"Ruteme",
    "wof:placetype":"locality"
},
  "geometry": {"coordinates":[29.8469,-2.3969],"type":"Point"}
}