{
  "type": "Feature",
  "properties": {
    "gn:admin1_code":"14",
    "gn:admin2_code":"34.0",
    "gn:admin3_code":"3402.0",
    "gn:admin4_code":"340201.0",
    "gn:asciiname":"Gakarara",
    "gn:country_code":"RW",
    "gn:dem":2462,
    "gn:feature_class":"P",
    "gn:feature_code":"PPL",
    "gn:name":"Gakarara",
    "gn:population":0,
    "gn:timezone":"Africa/Kigali",
    "iso:country":"RW",
    "wof:name":"Gakarara",
    "wof:placetype":"locality"
},
  "geometry": {"coordinates":[29.4548,-1.6125],"type":"Point"}
}