{
  "type": "Feature",
  "properties": {
    "gn:admin1_code":"11",
    "gn:admin2_code":"55.0",
    "gn:admin3_code":"5508.0",
    "gn:admin4_code":"550803.0",
    "gn:asciiname":"Nyagahama",
    "gn:country_code":"RW",
    "gn:dem":1560,
    "gn:feature_class":"P",
    "gn:feature_code":"PPLL",
    "gn:name":"Nyagahama",
    "gn:population":0,
    "gn:timezone":"Africa/Kigali",
    "iso:country":"RW",
    "wof:name":"Nyagahama",
    "wof:placetype":"locality"
},
  "geometry": {"coordinates":[30.6433,-2.2992],"type":"Point"}
}