{
  "type": "Feature",
  "properties": {
    "gn:admin1_code":"15.0",
    "gn:admin2_code":"21",
    "gn:admin3_code":"2101.0",
    "gn:admin4_code":"210105.0",
    "gn:asciiname":"Gako",
    "gn:country_code":"RW",
    "gn:dem":1739,
    "gn:feature_class":"P",
    "gn:feature_code":"PPLL",
    "gn:name":"Gako",
    "gn:population":0,
    "gn:timezone":"Africa/Kigali",
    "iso:country":"RW",
    "wof:name":"Gako",
    "wof:placetype":"locality"
},
  "geometry": {"coordinates":[29.7356,-2.3465],"type":"Point"}
}