{
  "type": "Feature",
  "properties": {
    "gn:admin1_code":"11",
    "gn:admin2_code":"55.0",
    "gn:admin3_code":"5504.0",
    "gn:admin4_code":"550403.0",
    "gn:asciiname":"Ruhanga",
    "gn:country_code":"RW",
    "gn:dem":1630,
    "gn:feature_class":"P",
    "gn:feature_code":"PPLL",
    "gn:name":"Ruhanga",
    "gn:population":0,
    "gn:timezone":"Africa/Kigali",
    "iso:country":"RW",
    "wof:name":"Ruhanga",
    "wof:placetype":"locality"
},
  "geometry": {"coordinates":[30.6879,-2.2538],"type":"Point"}
}