{
  "type": "Feature",
  "properties": {
    "gn:admin1_code":"13.0",
    "gn:admin2_code":"43",
    "gn:admin3_code":"4313.0",
    "gn:admin4_code":"431305.0",
    "gn:asciiname":"Rusayo",
    "gn:country_code":"RW",
    "gn:dem":1795,
    "gn:feature_class":"P",
    "gn:feature_code":"PPLL",
    "gn:name":"Rusayo",
    "gn:population":0,
    "gn:timezone":"Africa/Kigali",
    "iso:country":"RW",
    "name:und_x_variant":[
        "Colline Rusayo",
        "Rusayo"
    ],
    "wof:name":"Rusayo",
    "wof:placetype":"locality"
},
  "geometry": {"coordinates":[29.7178,-1.5605],"type":"Point"}
}