{
  "type": "Feature",
  "properties": {
    "gn:admin1_code":"14.0",
    "gn:admin2_code":"36",
    "gn:admin3_code":"3616.0",
    "gn:admin4_code":"361604.0",
    "gn:asciiname":"Kanoga",
    "gn:country_code":"RW",
    "gn:dem":1863,
    "gn:feature_class":"P",
    "gn:feature_code":"PPLL",
    "gn:name":"Kanoga",
    "gn:population":0,
    "gn:timezone":"Africa/Kigali",
    "iso:country":"RW",
    "wof:name":"Kanoga",
    "wof:placetype":"locality"
},
  "geometry": {"coordinates":[28.9553,-2.5472],"type":"Point"}
}