{
  "type": "Feature",
  "properties": {
    "gn:admin1_code":"11",
    "gn:admin2_code":"54.0",
    "gn:admin3_code":"5403.0",
    "gn:admin4_code":"540304.0",
    "gn:asciiname":"Butobagire",
    "gn:country_code":"RW",
    "gn:dem":1452,
    "gn:feature_class":"P",
    "gn:feature_code":"PPLL",
    "gn:name":"Butobagire",
    "gn:population":0,
    "gn:timezone":"Africa/Kigali",
    "iso:country":"RW",
    "wof:name":"Butobagire",
    "wof:placetype":"locality"
},
  "geometry": {"coordinates":[30.5436,-1.9808],"type":"Point"}
}