{
  "type": "Feature",
  "properties": {
    "gn:admin1_code":"15",
    "gn:admin2_code":"22.0",
    "gn:admin3_code":"2212.0",
    "gn:admin4_code":"221203.0",
    "gn:asciiname":"Rukoko",
    "gn:country_code":"RW",
    "gn:dem":1478,
    "gn:feature_class":"P",
    "gn:feature_code":"PPLL",
    "gn:name":"Rukoko",
    "gn:population":0,
    "gn:timezone":"Africa/Kigali",
    "iso:country":"RW",
    "wof:name":"Rukoko",
    "wof:placetype":"locality"
},
  "geometry": {"coordinates":[29.7358,-2.8064],"type":"Point"}
}