{
  "type": "Feature",
  "properties": {
    "gn:admin1_code":"13",
    "gn:admin2_code":"42.0",
    "gn:admin3_code":"4210.0",
    "gn:admin4_code":"421003.0",
    "gn:asciiname":"Gihita",
    "gn:country_code":"RW",
    "gn:dem":1804,
    "gn:feature_class":"P",
    "gn:feature_code":"PPL",
    "gn:name":"Gihita",
    "gn:population":0,
    "gn:timezone":"Africa/Kigali",
    "iso:country":"RW",
    "wof:name":"Gihita",
    "wof:placetype":"locality"
},
  "geometry": {"coordinates":[29.7651,-1.7098],"type":"Point"}
}