{
  "type": "Feature",
  "properties": {
    "gn:admin1_code":"15.0",
    "gn:admin2_code":"25",
    "gn:admin3_code":"2513.0",
    "gn:admin4_code":"251306.0",
    "gn:asciiname":"Nyaruhura",
    "gn:country_code":"RW",
    "gn:dem":2169,
    "gn:feature_class":"P",
    "gn:feature_code":"PPLL",
    "gn:name":"Nyaruhura",
    "gn:population":0,
    "gn:timezone":"Africa/Kigali",
    "iso:country":"RW",
    "wof:name":"Nyaruhura",
    "wof:placetype":"locality"
},
  "geometry": {"coordinates":[29.4722,-2.3997],"type":"Point"}
}