{
  "type": "Feature",
  "properties": {
    "gn:admin1_code":"15.0",
    "gn:admin2_code":"24",
    "gn:admin3_code":"2412.0",
    "gn:admin4_code":"241207.0",
    "gn:asciiname":"Shyunga",
    "gn:country_code":"RW",
    "gn:dem":1683,
    "gn:feature_class":"P",
    "gn:feature_code":"PPLL",
    "gn:name":"Shyunga",
    "gn:population":0,
    "gn:timezone":"Africa/Kigali",
    "iso:country":"RW",
    "wof:name":"Shyunga",
    "wof:placetype":"locality"
},
  "geometry": {"coordinates":[29.7366,-2.444],"type":"Point"}
}