{
  "type": "Feature",
  "properties": {
    "gn:admin1_code":"15",
    "gn:admin2_code":"26.0",
    "gn:admin3_code":"2601.0",
    "gn:admin4_code":"260102.0",
    "gn:asciiname":"Rwezamenyo",
    "gn:country_code":"RW",
    "gn:dem":1687,
    "gn:feature_class":"P",
    "gn:feature_code":"PPLL",
    "gn:name":"Rwezamenyo",
    "gn:population":0,
    "gn:timezone":"Africa/Kigali",
    "iso:country":"RW",
    "wof:name":"Rwezamenyo",
    "wof:placetype":"locality"
},
  "geometry": {"coordinates":[29.7355,-2.2295],"type":"Point"}
}