{
  "type": "Feature",
  "properties": {
    "gn:admin1_code":"11",
    "gn:admin2_code":"54.0",
    "gn:admin3_code":"5407.0",
    "gn:admin4_code":"540704.0",
    "gn:asciiname":"Murehe",
    "gn:country_code":"RW",
    "gn:dem":1510,
    "gn:feature_class":"P",
    "gn:feature_code":"PPLL",
    "gn:name":"Murehe",
    "gn:population":0,
    "gn:timezone":"Africa/Kigali",
    "iso:country":"RW",
    "name:run_x_preferred":[
        "Murehe"
    ],
    "wof:name":"Murehe",
    "wof:placetype":"locality"
},
  "geometry": {"coordinates":[30.53694,-1.8755],"type":"Point"}
}