{
  "type": "Feature",
  "properties": {
    "gn:admin1_code":"15",
    "gn:admin2_code":"23.0",
    "gn:admin3_code":"2309.0",
    "gn:admin4_code":"230906.0",
    "gn:asciiname":"Kibangu",
    "gn:country_code":"RW",
    "gn:dem":1714,
    "gn:feature_class":"P",
    "gn:feature_code":"PPLL",
    "gn:name":"Kibangu",
    "gn:population":0,
    "gn:timezone":"Africa/Kigali",
    "iso:country":"RW",
    "wof:name":"Kibangu",
    "wof:placetype":"locality"
},
  "geometry": {"coordinates":[29.6574,-2.7601],"type":"Point"}
}