{
  "type": "Feature",
  "properties": {
    "gn:admin1_code":"14.0",
    "gn:admin2_code":"34",
    "gn:admin3_code":"3408.0",
    "gn:admin4_code":"340802.0",
    "gn:asciiname":"Nyamugeyo",
    "gn:country_code":"RW",
    "gn:dem":2293,
    "gn:feature_class":"P",
    "gn:feature_code":"PPLL",
    "gn:name":"Nyamugeyo",
    "gn:population":0,
    "gn:timezone":"Africa/Kigali",
    "iso:country":"RW",
    "name:und_x_variant":[
        "Colline Nyamugeyo",
        "Nyamugeyo"
    ],
    "wof:name":"Nyamugeyo",
    "wof:placetype":"locality"
},
  "geometry": {"coordinates":[29.521,-1.7367],"type":"Point"}
}