{
  "type": "Feature",
  "properties": {
    "gn:admin1_code":"13",
    "gn:admin2_code":"44.0",
    "gn:admin3_code":"4401.0",
    "gn:admin4_code":"440104.0",
    "gn:asciiname":"Muhura",
    "gn:country_code":"RW",
    "gn:dem":2305,
    "gn:feature_class":"P",
    "gn:feature_code":"PPLL",
    "gn:name":"Muhura",
    "gn:population":0,
    "gn:timezone":"Africa/Kigali",
    "iso:country":"RW",
    "wof:name":"Muhura",
    "wof:placetype":"locality"
},
  "geometry": {"coordinates":[29.958,-1.5113],"type":"Point"}
}