{
  "type": "Feature",
  "properties": {
    "gn:admin1_code":"13.0",
    "gn:admin2_code":"42",
    "gn:admin3_code":"4209.0",
    "gn:admin4_code":"420902.0",
    "gn:asciiname":"Bushoka",
    "gn:country_code":"RW",
    "gn:dem":1939,
    "gn:feature_class":"P",
    "gn:feature_code":"PPLL",
    "gn:name":"Bushoka",
    "gn:population":0,
    "gn:timezone":"Africa/Kigali",
    "iso:country":"RW",
    "name:und_x_variant":[
        "Colline Bushoka",
        "Bushoka"
    ],
    "wof:name":"Bushoka",
    "wof:placetype":"locality"
},
  "geometry": {"coordinates":[29.7448,-1.5963],"type":"Point"}
}