{
  "type": "Feature",
  "properties": {
    "gn:admin1_code":"11",
    "gn:admin2_code":"56.0",
    "gn:admin3_code":"5604.0",
    "gn:admin4_code":"560402.0",
    "gn:asciiname":"Gahulire",
    "gn:country_code":"RW",
    "gn:dem":1569,
    "gn:feature_class":"P",
    "gn:feature_code":"PPLL",
    "gn:name":"Gahulire",
    "gn:population":0,
    "gn:timezone":"Africa/Kigali",
    "iso:country":"RW",
    "wof:name":"Gahulire",
    "wof:placetype":"locality"
},
  "geometry": {"coordinates":[30.5278,-2.2058],"type":"Point"}
}