{
  "type": "Feature",
  "properties": {
    "gn:admin1_code":"13",
    "gn:admin2_code":"43.0",
    "gn:admin3_code":"4311.0",
    "gn:admin4_code":"431103.0",
    "gn:asciiname":"Nkurura",
    "gn:country_code":"RW",
    "gn:dem":2004,
    "gn:feature_class":"P",
    "gn:feature_code":"PPLL",
    "gn:name":"Nkurura",
    "gn:population":0,
    "gn:timezone":"Africa/Kigali",
    "iso:country":"RW",
    "wof:name":"Nkurura",
    "wof:placetype":"locality"
},
  "geometry": {"coordinates":[29.5895,-1.5756],"type":"Point"}
}