{
  "type": "Feature",
  "properties": {
    "gn:admin1_code":"13",
    "gn:admin2_code":"45.0",
    "gn:admin3_code":"4517.0",
    "gn:admin4_code":"451702.0",
    "gn:asciiname":"Karwoga",
    "gn:country_code":"RW",
    "gn:dem":1910,
    "gn:feature_class":"P",
    "gn:feature_code":"PPLL",
    "gn:name":"Karwoga",
    "gn:population":0,
    "gn:timezone":"Africa/Kigali",
    "iso:country":"RW",
    "wof:name":"Karwoga",
    "wof:placetype":"locality"
},
  "geometry": {"coordinates":[30.1079,-1.4721],"type":"Point"}
}