{
  "type": "Feature",
  "properties": {
    "gn:admin1_code":"11",
    "gn:admin2_code":"57.0",
    "gn:admin3_code":"5712.0",
    "gn:admin4_code":"571201.0",
    "gn:asciiname":"Kalilisi",
    "gn:country_code":"RW",
    "gn:dem":1375,
    "gn:feature_class":"P",
    "gn:feature_code":"PPLL",
    "gn:name":"Kalilisi",
    "gn:population":0,
    "gn:timezone":"Africa/Kigali",
    "iso:country":"RW",
    "wof:name":"Kalilisi",
    "wof:placetype":"locality"
},
  "geometry": {"coordinates":[30.18654,-2.18468],"type":"Point"}
}