{
  "type": "Feature",
  "properties": {
    "gn:admin1_code":"15.0",
    "gn:admin2_code":"26",
    "gn:admin3_code":"2603.0",
    "gn:admin4_code":"260302.0",
    "gn:asciiname":"Karambi",
    "gn:country_code":"RW",
    "gn:dem":1719,
    "gn:feature_class":"P",
    "gn:feature_code":"PPL",
    "gn:name":"Karambi",
    "gn:population":0,
    "gn:timezone":"Africa/Kigali",
    "iso:country":"RW",
    "name:und_x_variant":[
        "Colline Karambi",
        "Karambi"
    ],
    "wof:name":"Karambi",
    "wof:placetype":"locality"
},
  "geometry": {"coordinates":[29.64978,-2.22887],"type":"Point"}
}