{
  "type": "Feature",
  "properties": {
    "gn:admin1_code":"15.0",
    "gn:admin2_code":"21",
    "gn:admin3_code":"2106.0",
    "gn:admin4_code":"210606.0",
    "gn:asciiname":"Kigarama",
    "gn:country_code":"RW",
    "gn:dem":1698,
    "gn:feature_class":"P",
    "gn:feature_code":"PPLL",
    "gn:name":"Kigarama",
    "gn:population":0,
    "gn:timezone":"Africa/Kigali",
    "iso:country":"RW",
    "wof:name":"Kigarama",
    "wof:placetype":"locality"
},
  "geometry": {"coordinates":[29.7119,-2.2845],"type":"Point"}
}