{
  "type": "Feature",
  "properties": {
    "gn:admin1_code":"12",
    "gn:admin2_code":"12.0",
    "gn:admin3_code":"1211.0",
    "gn:admin4_code":"121103.0",
    "gn:asciiname":"Gishure",
    "gn:country_code":"RW",
    "gn:dem":1460,
    "gn:feature_class":"P",
    "gn:feature_code":"PPLL",
    "gn:name":"Gishure",
    "gn:population":0,
    "gn:timezone":"Africa/Kigali",
    "iso:country":"RW",
    "wof:name":"Gishure",
    "wof:placetype":"locality"
},
  "geometry": {"coordinates":[30.1849,-1.9288],"type":"Point"}
}