{
  "type": "Feature",
  "properties": {
    "gn:admin1_code":"14",
    "gn:admin2_code":"34.0",
    "gn:admin3_code":"3410.0",
    "gn:admin4_code":"341003.0",
    "gn:asciiname":"Ngororero",
    "gn:country_code":"RW",
    "gn:dem":1774,
    "gn:feature_class":"P",
    "gn:feature_code":"PPLL",
    "gn:name":"Ngororero",
    "gn:population":0,
    "gn:timezone":"Africa/Kigali",
    "iso:country":"RW",
    "name:bul_x_preferred":[
        "\u041d\u0433\u043e\u0440\u043e\u0440\u0435\u0440\u043e"
    ],
    "name:ceb_x_preferred":[
        "Ngororero"
    ],
    "name:fra_x_preferred":[
        "Ngororero"
    ],
    "name:ita_x_preferred":[
        "Ngororero"
    ],
    "name:zho_x_preferred":[
        "\u6069\u6208\u7f85\u96f7\u7f85"
    ],
    "wof:name":"Ngororero",
    "wof:placetype":"locality"
},
  "geometry": {"coordinates":[29.6196,-1.6458],"type":"Point"}
}