{
  "type": "Feature",
  "properties": {
    "gn:admin1_code":"14",
    "gn:admin2_code":"33.0",
    "gn:admin3_code":"3302.0",
    "gn:admin4_code":"330204.0",
    "gn:asciiname":"Cyanika",
    "gn:country_code":"RW",
    "gn:dem":1929,
    "gn:feature_class":"P",
    "gn:feature_code":"PPLL",
    "gn:name":"Cyanika",
    "gn:population":0,
    "gn:timezone":"Africa/Kigali",
    "iso:country":"RW",
    "wof:name":"Cyanika",
    "wof:placetype":"locality"
},
  "geometry": {"coordinates":[29.3124,-1.5998],"type":"Point"}
}