{
  "type": "Feature",
  "properties": {
    "gn:admin1_code":"14.0",
    "gn:admin2_code":"35",
    "gn:admin3_code":"3503.0",
    "gn:admin4_code":"350306.0",
    "gn:asciiname":"Nyabihu",
    "gn:cc2":"RW",
    "gn:country_code":"RW",
    "gn:dem":2221,
    "gn:feature_class":"P",
    "gn:feature_code":"PPLL",
    "gn:name":"Nyabihu",
    "gn:population":0,
    "gn:timezone":"Africa/Kigali",
    "iso:country":"RW",
    "name:und_x_variant":[
        "Colline Nyabihu",
        "Nyabihu"
    ],
    "wof:name":"Nyabihu",
    "wof:placetype":"locality"
},
  "geometry": {"coordinates":[29.58333,-1.78333],"type":"Point"}
}