{
  "type": "Feature",
  "properties": {
    "gn:admin1_code":"15",
    "gn:admin2_code":"27.0",
    "gn:admin3_code":"2712.0",
    "gn:admin4_code":"271201.0",
    "gn:asciiname":"Mbali",
    "gn:country_code":"RW",
    "gn:dem":1887,
    "gn:feature_class":"P",
    "gn:feature_code":"PPL",
    "gn:name":"Mbali",
    "gn:population":0,
    "gn:timezone":"Africa/Kigali",
    "iso:country":"RW",
    "wof:name":"Mbali",
    "wof:placetype":"locality"
},
  "geometry": {"coordinates":[29.769,-2.1091],"type":"Point"}
}