{
  "type": "Feature",
  "properties": {
    "gn:admin1_code":"15",
    "gn:admin2_code":"27.0",
    "gn:admin3_code":"2712.0",
    "gn:admin4_code":"271204.0",
    "gn:asciiname":"Cyakabili",
    "gn:country_code":"RW",
    "gn:dem":1858,
    "gn:feature_class":"P",
    "gn:feature_code":"PPLL",
    "gn:name":"Cyakabili",
    "gn:population":0,
    "gn:timezone":"Africa/Kigali",
    "iso:country":"RW",
    "wof:name":"Cyakabili",
    "wof:placetype":"locality"
},
  "geometry": {"coordinates":[29.788,-2.0699],"type":"Point"}
}