{
  "type": "Feature",
  "properties": {
    "gn:admin1_code":"14.0",
    "gn:admin2_code":"36",
    "gn:admin3_code":"3615.0",
    "gn:admin4_code":"361506.0",
    "gn:asciiname":"Nyabintare",
    "gn:country_code":"RW",
    "gn:dem":1459,
    "gn:feature_class":"P",
    "gn:feature_code":"PPLL",
    "gn:name":"Nyabintare",
    "gn:population":0,
    "gn:timezone":"Africa/Kigali",
    "iso:country":"RW",
    "wof:name":"Nyabintare",
    "wof:placetype":"locality"
},
  "geometry": {"coordinates":[29.0569,-2.5418],"type":"Point"}
}