{
  "type": "Feature",
  "properties": {
    "gn:admin1_code":"11",
    "gn:admin2_code":"57.0",
    "gn:admin3_code":"5703.0",
    "gn:admin4_code":"570302.0",
    "gn:asciiname":"Karenge",
    "gn:country_code":"RW",
    "gn:dem":1395,
    "gn:feature_class":"P",
    "gn:feature_code":"PPLL",
    "gn:name":"Karenge",
    "gn:population":0,
    "gn:timezone":"Africa/Kigali",
    "iso:country":"RW",
    "wof:name":"Karenge",
    "wof:placetype":"locality"
},
  "geometry": {"coordinates":[30.1197,-2.4058],"type":"Point"}
}