{
  "type": "Feature",
  "properties": {
    "gn:admin1_code":"11",
    "gn:admin2_code":"53.0",
    "gn:admin3_code":"5313.0",
    "gn:admin4_code":"531303.0",
    "gn:asciiname":"Rugarama",
    "gn:country_code":"RW",
    "gn:dem":1382,
    "gn:feature_class":"P",
    "gn:feature_code":"PPLL",
    "gn:name":"Rugarama",
    "gn:population":0,
    "gn:timezone":"Africa/Kigali",
    "iso:country":"RW",
    "wof:name":"Rugarama",
    "wof:placetype":"locality"
},
  "geometry": {"coordinates":[30.43022,-1.69901],"type":"Point"}
}