{
  "type": "Feature",
  "properties": {
    "gn:admin1_code":"13",
    "gn:admin2_code":"45.0",
    "gn:admin3_code":"4506.0",
    "gn:admin4_code":"450603.0",
    "gn:asciiname":"Gatobotobo",
    "gn:country_code":"RW",
    "gn:dem":2002,
    "gn:feature_class":"P",
    "gn:feature_code":"PPLL",
    "gn:name":"Gatobotobo",
    "gn:population":0,
    "gn:timezone":"Africa/Kigali",
    "iso:country":"RW",
    "wof:name":"Gatobotobo",
    "wof:placetype":"locality"
},
  "geometry": {"coordinates":[30.0864,-1.6527],"type":"Point"}
}