{
  "type": "Feature",
  "properties": {
    "gn:admin1_code":"14",
    "gn:admin2_code":"31.0",
    "gn:admin3_code":"3109.0",
    "gn:admin4_code":"310908.0",
    "gn:asciiname":"Rwimpongo",
    "gn:country_code":"RW",
    "gn:dem":1642,
    "gn:feature_class":"P",
    "gn:feature_code":"PPLL",
    "gn:name":"Rwimpongo",
    "gn:population":0,
    "gn:timezone":"Africa/Kigali",
    "iso:country":"RW",
    "wof:name":"Rwimpongo",
    "wof:placetype":"locality"
},
  "geometry": {"coordinates":[29.4105,-2.0731],"type":"Point"}
}