{
  "type": "Feature",
  "properties": {
    "gn:admin1_code":"14.0",
    "gn:admin2_code":"37",
    "gn:admin3_code":"3703.0",
    "gn:admin4_code":"370301.0",
    "gn:asciiname":"Bisumo",
    "gn:country_code":"RW",
    "gn:dem":2109,
    "gn:feature_class":"P",
    "gn:feature_code":"PPLL",
    "gn:name":"Bisumo",
    "gn:population":0,
    "gn:timezone":"Africa/Kigali",
    "iso:country":"RW",
    "wof:name":"Bisumo",
    "wof:placetype":"locality"
},
  "geometry": {"coordinates":[29.2444,-2.3976],"type":"Point"}
}