{
  "type": "Feature",
  "properties": {
    "gn:admin1_code":"14.0",
    "gn:admin2_code":"32",
    "gn:admin3_code":"3208.0",
    "gn:admin4_code":"320802.0",
    "gn:asciiname":"Gitovu",
    "gn:country_code":"RW",
    "gn:dem":1649,
    "gn:feature_class":"P",
    "gn:feature_code":"PPL",
    "gn:name":"Gitovu",
    "gn:population":0,
    "gn:timezone":"Africa/Kigali",
    "iso:country":"RW",
    "wof:name":"Gitovu",
    "wof:placetype":"locality"
},
  "geometry": {"coordinates":[29.3479,-1.9295],"type":"Point"}
}