{
  "type": "Feature",
  "properties": {
    "gn:admin1_code":"15.0",
    "gn:admin2_code":"25",
    "gn:admin3_code":"2509.0",
    "gn:admin4_code":"250903.0",
    "gn:asciiname":"Uwurunazi",
    "gn:country_code":"RW",
    "gn:dem":2254,
    "gn:feature_class":"P",
    "gn:feature_code":"PPLL",
    "gn:name":"Uwurunazi",
    "gn:population":0,
    "gn:timezone":"Africa/Kigali",
    "iso:country":"RW",
    "wof:name":"Uwurunazi",
    "wof:placetype":"locality"
},
  "geometry": {"coordinates":[29.4467,-2.5301],"type":"Point"}
}