{
  "type": "Feature",
  "properties": {
    "gn:admin1_code":"15",
    "gn:admin2_code":"26.0",
    "gn:admin3_code":"2604.0",
    "gn:admin4_code":"260403.0",
    "gn:asciiname":"Mukoma",
    "gn:country_code":"RW",
    "gn:dem":1417,
    "gn:feature_class":"P",
    "gn:feature_code":"PPL",
    "gn:name":"Mukoma",
    "gn:population":0,
    "gn:timezone":"Africa/Kigali",
    "iso:country":"RW",
    "wof:name":"Mukoma",
    "wof:placetype":"locality"
},
  "geometry": {"coordinates":[29.9401,-2.1958],"type":"Point"}
}