{
  "type": "Feature",
  "properties": {
    "gn:admin1_code":"15.0",
    "gn:admin2_code":"26",
    "gn:admin3_code":"2609.0",
    "gn:admin4_code":"260907.0",
    "gn:asciiname":"Bumbogo",
    "gn:country_code":"RW",
    "gn:dem":1667,
    "gn:feature_class":"P",
    "gn:feature_code":"PPLL",
    "gn:name":"Bumbogo",
    "gn:population":0,
    "gn:timezone":"Africa/Kigali",
    "iso:country":"RW",
    "wof:name":"Bumbogo",
    "wof:placetype":"locality"
},
  "geometry": {"coordinates":[29.76667,-2.24994],"type":"Point"}
}