{
  "type": "Feature",
  "properties": {
    "gn:admin1_code":"12",
    "gn:admin2_code":"12.0",
    "gn:admin3_code":"1215.0",
    "gn:admin4_code":"121505.0",
    "gn:asciiname":"Rwanyanza",
    "gn:country_code":"RW",
    "gn:dem":1553,
    "gn:feature_class":"P",
    "gn:feature_code":"PPLL",
    "gn:name":"Rwanyanza",
    "gn:population":0,
    "gn:timezone":"Africa/Kigali",
    "iso:country":"RW",
    "wof:name":"Rwanyanza",
    "wof:placetype":"locality"
},
  "geometry": {"coordinates":[30.165,-1.8273],"type":"Point"}
}