{
  "type": "Feature",
  "properties": {
    "gn:admin1_code":"13",
    "gn:admin2_code":"42.0",
    "gn:admin3_code":"4202.0",
    "gn:admin4_code":"420204.0",
    "gn:asciiname":"Gitaba",
    "gn:country_code":"RW",
    "gn:dem":1940,
    "gn:feature_class":"P",
    "gn:feature_code":"PPL",
    "gn:name":"Gitaba",
    "gn:population":0,
    "gn:timezone":"Africa/Kigali",
    "iso:country":"RW",
    "wof:name":"Gitaba",
    "wof:placetype":"locality"
},
  "geometry": {"coordinates":[29.8321,-1.7696],"type":"Point"}
}