{
  "type": "Feature",
  "properties": {
    "gn:admin1_code":"14",
    "gn:admin2_code":"35.0",
    "gn:admin3_code":"3510.0",
    "gn:admin4_code":"351001.0",
    "gn:asciiname":"Kibande",
    "gn:country_code":"RW",
    "gn:dem":1687,
    "gn:feature_class":"P",
    "gn:feature_code":"PPLL",
    "gn:name":"Kibande",
    "gn:population":0,
    "gn:timezone":"Africa/Kigali",
    "iso:country":"RW",
    "wof:name":"Kibande",
    "wof:placetype":"locality"
},
  "geometry": {"coordinates":[29.61517000000001,-1.99984],"type":"Point"}
}