{
  "type": "Feature",
  "properties": {
    "gn:admin1_code":"11",
    "gn:admin2_code":"51.0",
    "gn:admin3_code":"5106.0",
    "gn:admin4_code":"510605.0",
    "gn:asciiname":"Buhanya",
    "gn:country_code":"RW",
    "gn:dem":1549,
    "gn:feature_class":"P",
    "gn:feature_code":"PPLL",
    "gn:name":"Buhanya",
    "gn:population":0,
    "gn:timezone":"Africa/Kigali",
    "iso:country":"RW",
    "wof:name":"Buhanya",
    "wof:placetype":"locality"
},
  "geometry": {"coordinates":[30.4816,-1.8727],"type":"Point"}
}