{
  "type": "Feature",
  "properties": {
    "gn:admin1_code":"14",
    "gn:admin2_code":"34.0",
    "gn:admin3_code":"3407.0",
    "gn:admin4_code":"340702.0",
    "gn:asciiname":"Hesha",
    "gn:country_code":"RW",
    "gn:dem":2429,
    "gn:feature_class":"P",
    "gn:feature_code":"PPLL",
    "gn:name":"Hesha",
    "gn:population":0,
    "gn:timezone":"Africa/Kigali",
    "iso:country":"RW",
    "name:und_x_variant":[
        "Hasha"
    ],
    "wof:name":"Hesha",
    "wof:placetype":"locality"
},
  "geometry": {"coordinates":[29.4913,-1.6132],"type":"Point"}
}