{
  "type": "Feature",
  "properties": {
    "gn:admin1_code":"14.0",
    "gn:admin2_code":"37",
    "gn:admin3_code":"3710.0",
    "gn:admin4_code":"371004.0",
    "gn:asciiname":"Muramba",
    "gn:country_code":"RW",
    "gn:dem":1597,
    "gn:feature_class":"P",
    "gn:feature_code":"PPL",
    "gn:name":"Muramba",
    "gn:population":0,
    "gn:timezone":"Africa/Kigali",
    "iso:country":"RW",
    "name:und_x_variant":[
        "Colline Muramba",
        "Muramba"
    ],
    "wof:name":"Muramba",
    "wof:placetype":"locality"
},
  "geometry": {"coordinates":[29.1845,-2.2846],"type":"Point"}
}