{
  "type": "Feature",
  "properties": {
    "gn:admin1_code":"14.0",
    "gn:admin2_code":"34",
    "gn:admin3_code":"3411.0",
    "gn:admin4_code":"341101.0",
    "gn:asciiname":"Mburabuturo",
    "gn:country_code":"RW",
    "gn:dem":2101,
    "gn:feature_class":"P",
    "gn:feature_code":"PPL",
    "gn:name":"Mburabuturo",
    "gn:population":0,
    "gn:timezone":"Africa/Kigali",
    "iso:country":"RW",
    "name:und_x_variant":[
        "Bulabuturo",
        "Mburabuturo"
    ],
    "wof:name":"Mburabuturo",
    "wof:placetype":"locality"
},
  "geometry": {"coordinates":[29.5877,-1.6211],"type":"Point"}
}