{
  "type": "Feature",
  "properties": {
    "gn:admin1_code":"11",
    "gn:admin2_code":"51.0",
    "gn:admin3_code":"5109.0",
    "gn:admin4_code":"510904.0",
    "gn:asciiname":"Musha Ya Ruguru Yose",
    "gn:country_code":"RW",
    "gn:dem":1619,
    "gn:feature_class":"P",
    "gn:feature_code":"PPL",
    "gn:name":"Musha Ya Ruguru Yose",
    "gn:population":0,
    "gn:timezone":"Africa/Kigali",
    "iso:country":"RW",
    "wof:name":"Musha Ya Ruguru Yose",
    "wof:placetype":"locality"
},
  "geometry": {"coordinates":[30.3459,-1.9436],"type":"Point"}
}