{
  "type": "Feature",
  "properties": {
    "gn:admin1_code":"15.0",
    "gn:admin2_code":"25",
    "gn:admin3_code":"2515.0",
    "gn:admin4_code":"251501.0",
    "gn:asciiname":"Buhanzi",
    "gn:country_code":"RW",
    "gn:dem":1982,
    "gn:feature_class":"P",
    "gn:feature_code":"PPLL",
    "gn:name":"Buhanzi",
    "gn:population":0,
    "gn:timezone":"Africa/Kigali",
    "iso:country":"RW",
    "wof:name":"Buhanzi",
    "wof:placetype":"locality"
},
  "geometry": {"coordinates":[29.4221,-2.3258],"type":"Point"}
}