{
  "type": "Feature",
  "properties": {
    "gn:admin1_code":"13",
    "gn:admin2_code":"44.0",
    "gn:admin3_code":"4401.0",
    "gn:admin4_code":"440103.0",
    "gn:asciiname":"Mudugali",
    "gn:country_code":"RW",
    "gn:dem":2351,
    "gn:feature_class":"P",
    "gn:feature_code":"PPLL",
    "gn:name":"Mudugali",
    "gn:population":0,
    "gn:timezone":"Africa/Kigali",
    "iso:country":"RW",
    "wof:name":"Mudugali",
    "wof:placetype":"locality"
},
  "geometry": {"coordinates":[29.96109,-1.48314],"type":"Point"}
}