{
  "type": "Feature",
  "properties": {
    "gn:admin1_code":"14.0",
    "gn:admin2_code":"36",
    "gn:admin3_code":"3617.0",
    "gn:admin4_code":"361703.0",
    "gn:asciiname":"Nyagasozi",
    "gn:country_code":"RW",
    "gn:dem":1671,
    "gn:feature_class":"P",
    "gn:feature_code":"PPLL",
    "gn:name":"Nyagasozi",
    "gn:population":0,
    "gn:timezone":"Africa/Kigali",
    "iso:country":"RW",
    "wof:name":"Nyagasozi",
    "wof:placetype":"locality"
},
  "geometry": {"coordinates":[28.9413,-2.6581],"type":"Point"}
}