{
  "type": "Feature",
  "properties": {
    "gn:admin1_code":"11",
    "gn:admin2_code":"56.0",
    "gn:admin3_code":"5611.0",
    "gn:admin4_code":"561105.0",
    "gn:asciiname":"Ibare",
    "gn:country_code":"RW",
    "gn:dem":1388,
    "gn:feature_class":"P",
    "gn:feature_code":"PPLL",
    "gn:name":"Ibare",
    "gn:population":0,
    "gn:timezone":"Africa/Kigali",
    "iso:country":"RW",
    "wof:name":"Ibare",
    "wof:placetype":"locality"
},
  "geometry": {"coordinates":[30.2848,-2.166],"type":"Point"}
}