{
  "type": "Feature",
  "properties": {
    "gn:admin1_code":"13",
    "gn:admin2_code":"41.0",
    "gn:admin3_code":"4108.0",
    "gn:admin4_code":"410802.0",
    "gn:asciiname":"Rubona",
    "gn:country_code":"RW",
    "gn:dem":2065,
    "gn:feature_class":"P",
    "gn:feature_code":"PPL",
    "gn:name":"Rubona",
    "gn:population":0,
    "gn:timezone":"Africa/Kigali",
    "iso:country":"RW",
    "name:ceb_x_preferred":[
        "Rubona"
    ],
    "name:swe_x_preferred":[
        "Rubona"
    ],
    "wof:name":"Rubona",
    "wof:placetype":"locality"
},
  "geometry": {"coordinates":[30.0488,-1.6227],"type":"Point"}
}