{
  "type": "Feature",
  "properties": {
    "gn:admin1_code":"14.0",
    "gn:admin2_code":"37",
    "gn:admin3_code":"3706.0",
    "gn:admin4_code":"370602.0",
    "gn:asciiname":"Gisura",
    "gn:country_code":"RW",
    "gn:dem":1632,
    "gn:feature_class":"P",
    "gn:feature_code":"PPLL",
    "gn:name":"Gisura",
    "gn:population":0,
    "gn:timezone":"Africa/Kigali",
    "iso:country":"RW",
    "wof:name":"Gisura",
    "wof:placetype":"locality"
},
  "geometry": {"coordinates":[29.1602,-2.3235],"type":"Point"}
}