{
  "type": "Feature",
  "properties": {
    "gn:admin1_code":"15.0",
    "gn:admin2_code":"24",
    "gn:admin3_code":"2408.0",
    "gn:admin4_code":"240801.0",
    "gn:asciiname":"Mubumbano",
    "gn:country_code":"RW",
    "gn:dem":1772,
    "gn:feature_class":"P",
    "gn:feature_code":"PPL",
    "gn:name":"Mubumbano",
    "gn:population":0,
    "gn:timezone":"Africa/Kigali",
    "iso:country":"RW",
    "name:und_x_variant":[
        "Colline Mubumbano",
        "Mubumbano"
    ],
    "wof:name":"Mubumbano",
    "wof:placetype":"locality"
},
  "geometry": {"coordinates":[29.7244,-2.6581],"type":"Point"}
}