{
  "type": "Feature",
  "properties": {
    "gn:admin1_code":"15",
    "gn:admin2_code":"22.0",
    "gn:admin3_code":"2212.0",
    "gn:admin4_code":"221204.0",
    "gn:asciiname":"Umukubo",
    "gn:country_code":"RW",
    "gn:dem":1570,
    "gn:feature_class":"P",
    "gn:feature_code":"PPLL",
    "gn:name":"Umukubo",
    "gn:population":0,
    "gn:timezone":"Africa/Kigali",
    "iso:country":"RW",
    "wof:name":"Umukubo",
    "wof:placetype":"locality"
},
  "geometry": {"coordinates":[29.7611,-2.7685],"type":"Point"}
}