{
  "type": "Feature",
  "properties": {
    "gn:admin1_code":"13",
    "gn:admin2_code":"43.0",
    "gn:admin3_code":"4303.0",
    "gn:admin4_code":"430304.0",
    "gn:asciiname":"Karwasa",
    "gn:country_code":"RW",
    "gn:dem":1845,
    "gn:feature_class":"P",
    "gn:feature_code":"PPL",
    "gn:name":"Karwasa",
    "gn:population":0,
    "gn:timezone":"Africa/Kigali",
    "iso:country":"RW",
    "wof:name":"Karwasa",
    "wof:placetype":"locality"
},
  "geometry": {"coordinates":[29.6831,-1.4861],"type":"Point"}
}