{
  "type": "Feature",
  "properties": {
    "gn:admin1_code":"13",
    "gn:admin2_code":"41.0",
    "gn:admin3_code":"4102.0",
    "gn:admin4_code":"410201.0",
    "gn:asciiname":"Cyerere",
    "gn:country_code":"RW",
    "gn:dem":1509,
    "gn:feature_class":"P",
    "gn:feature_code":"PPLL",
    "gn:name":"Cyerere",
    "gn:population":0,
    "gn:timezone":"Africa/Kigali",
    "iso:country":"RW",
    "wof:name":"Cyerere",
    "wof:placetype":"locality"
},
  "geometry": {"coordinates":[30.0775,-1.7399],"type":"Point"}
}