{
  "type": "Feature",
  "properties": {
    "gn:admin1_code":"11.0",
    "gn:admin2_code":"52",
    "gn:admin3_code":"5208.0",
    "gn:admin4_code":"520804.0",
    "gn:asciiname":"Mukama",
    "gn:country_code":"RW",
    "gn:dem":1422,
    "gn:feature_class":"P",
    "gn:feature_code":"PPLL",
    "gn:name":"Mukama",
    "gn:population":0,
    "gn:timezone":"Africa/Kigali",
    "iso:country":"RW",
    "wof:name":"Mukama",
    "wof:placetype":"locality"
},
  "geometry": {"coordinates":[30.2072,-1.4342],"type":"Point"}
}