{
  "type": "Feature",
  "properties": {
    "gn:admin1_code":"14.0",
    "gn:admin2_code":"37",
    "gn:admin3_code":"3705.0",
    "gn:admin4_code":"370504.0",
    "gn:asciiname":"Nyamakara",
    "gn:country_code":"RW",
    "gn:dem":1671,
    "gn:feature_class":"P",
    "gn:feature_code":"PPLL",
    "gn:name":"Nyamakara",
    "gn:population":0,
    "gn:timezone":"Africa/Kigali",
    "iso:country":"RW",
    "wof:name":"Nyamakara",
    "wof:placetype":"locality"
},
  "geometry": {"coordinates":[29.1025,-2.3748],"type":"Point"}
}