{
  "type": "Feature",
  "properties": {
    "gn:admin1_code":"14",
    "gn:admin2_code":"33.0",
    "gn:admin3_code":"3301.0",
    "gn:admin4_code":"330102.0",
    "gn:asciiname":"Kinyamuhanga",
    "gn:country_code":"RW",
    "gn:dem":2513,
    "gn:feature_class":"P",
    "gn:feature_code":"PPLF",
    "gn:name":"Kinyamuhanga",
    "gn:population":0,
    "gn:timezone":"Africa/Kigali",
    "iso:country":"RW",
    "wof:name":"Kinyamuhanga",
    "wof:placetype":"locality"
},
  "geometry": {"coordinates":[29.3909,-1.5188],"type":"Point"}
}