{
  "type": "Feature",
  "properties": {
    "gn:admin1_code":"11",
    "gn:admin2_code":"53.0",
    "gn:admin3_code":"5312.0",
    "gn:admin4_code":"531205.0",
    "gn:asciiname":"Rutagara",
    "gn:country_code":"RW",
    "gn:dem":1656,
    "gn:feature_class":"P",
    "gn:feature_code":"PPLL",
    "gn:name":"Rutagara",
    "gn:population":0,
    "gn:timezone":"Africa/Kigali",
    "iso:country":"RW",
    "wof:name":"Rutagara",
    "wof:placetype":"locality"
},
  "geometry": {"coordinates":[30.3301,-1.7124],"type":"Point"}
}