{
  "type": "Feature",
  "properties": {
    "gn:admin1_code":"11.0",
    "gn:admin2_code":"52",
    "gn:admin3_code":"5209.0",
    "gn:admin4_code":"520906.0",
    "gn:asciiname":"Bihinga",
    "gn:country_code":"RW",
    "gn:dem":1378,
    "gn:feature_class":"P",
    "gn:feature_code":"PPL",
    "gn:name":"Bihinga",
    "gn:population":0,
    "gn:timezone":"Africa/Kigali",
    "iso:country":"RW",
    "wof:name":"Bihinga",
    "wof:placetype":"locality"
},
  "geometry": {"coordinates":[30.3531,-1.1141],"type":"Point"}
}