{
  "type": "Feature",
  "properties": {
    "gn:admin1_code":"11",
    "gn:admin2_code":"51.0",
    "gn:admin3_code":"5110.0",
    "gn:admin4_code":"511002.0",
    "gn:asciiname":"Gishaka",
    "gn:country_code":"RW",
    "gn:dem":1543,
    "gn:feature_class":"P",
    "gn:feature_code":"PPLL",
    "gn:name":"Gishaka",
    "gn:population":0,
    "gn:timezone":"Africa/Kigali",
    "iso:country":"RW",
    "wof:name":"Gishaka",
    "wof:placetype":"locality"
},
  "geometry": {"coordinates":[30.2663,-2.0271],"type":"Point"}
}