{
  "type": "Feature",
  "properties": {
    "gn:admin1_code":"11",
    "gn:admin2_code":"52.0",
    "gn:admin3_code":"5208.0",
    "gn:admin4_code":"520806.0",
    "gn:asciiname":"Bukire",
    "gn:country_code":"RW",
    "gn:dem":1405,
    "gn:feature_class":"P",
    "gn:feature_code":"PPLL",
    "gn:name":"Bukire",
    "gn:population":0,
    "gn:timezone":"Africa/Kigali",
    "iso:country":"RW",
    "wof:name":"Bukire",
    "wof:placetype":"locality"
},
  "geometry": {"coordinates":[30.2293,-1.4316],"type":"Point"}
}