{
  "type": "Feature",
  "properties": {
    "gn:admin1_code":"15",
    "gn:admin2_code":"27.0",
    "gn:admin3_code":"2705.0",
    "gn:admin4_code":"270502.0",
    "gn:asciiname":"Nyamyumba",
    "gn:country_code":"RW",
    "gn:dem":1854,
    "gn:feature_class":"P",
    "gn:feature_code":"PPL",
    "gn:name":"Nyamyumba",
    "gn:population":0,
    "gn:timezone":"Africa/Kigali",
    "iso:country":"RW",
    "wof:name":"Nyamyumba",
    "wof:placetype":"locality"
},
  "geometry": {"coordinates":[29.7206,-2.0695],"type":"Point"}
}