{
  "type": "Feature",
  "properties": {
    "gn:admin1_code":"15.0",
    "gn:admin2_code":"22",
    "gn:admin3_code":"2201.0",
    "gn:admin4_code":"220103.0",
    "gn:asciiname":"Mugusa",
    "gn:country_code":"RW",
    "gn:dem":1515,
    "gn:feature_class":"P",
    "gn:feature_code":"PPL",
    "gn:name":"Mugusa",
    "gn:population":0,
    "gn:timezone":"Africa/Kigali",
    "iso:country":"RW",
    "name:und_x_variant":[
        "Mont Mugusa",
        "Mugusa"
    ],
    "wof:name":"Mugusa",
    "wof:placetype":"locality"
},
  "geometry": {"coordinates":[29.8564,-2.48122],"type":"Point"}
}