{
  "type": "Feature",
  "properties": {
    "gn:admin1_code":"15.0",
    "gn:admin2_code":"25",
    "gn:admin3_code":"2512.0",
    "gn:admin4_code":"251205.0",
    "gn:asciiname":"Mburabuturo",
    "gn:country_code":"RW",
    "gn:dem":1527,
    "gn:feature_class":"P",
    "gn:feature_code":"PPLL",
    "gn:name":"Mburabuturo",
    "gn:population":0,
    "gn:timezone":"Africa/Kigali",
    "iso:country":"RW",
    "wof:name":"Mburabuturo",
    "wof:placetype":"locality"
},
  "geometry": {"coordinates":[29.5888,-2.2524],"type":"Point"}
}