{
  "type": "Feature",
  "properties": {
    "gn:admin1_code":"14",
    "gn:admin2_code":"34.0",
    "gn:admin3_code":"3411.0",
    "gn:admin4_code":"341106.0",
    "gn:asciiname":"Kazenzo",
    "gn:country_code":"RW",
    "gn:dem":2046,
    "gn:feature_class":"P",
    "gn:feature_code":"PPLL",
    "gn:name":"Kazenzo",
    "gn:population":0,
    "gn:timezone":"Africa/Kigali",
    "iso:country":"RW",
    "name:und_x_variant":[
        "Kazenze"
    ],
    "wof:name":"Kazenzo",
    "wof:placetype":"locality"
},
  "geometry": {"coordinates":[29.58,-1.6699],"type":"Point"}
}