{
  "type": "Feature",
  "properties": {
    "gn:admin1_code":"14.0",
    "gn:admin2_code":"36",
    "gn:admin3_code":"3609.0",
    "gn:admin4_code":"360902.0",
    "gn:asciiname":"Burunga",
    "gn:country_code":"RW",
    "gn:dem":1679,
    "gn:feature_class":"P",
    "gn:feature_code":"PPLL",
    "gn:name":"Burunga",
    "gn:population":0,
    "gn:timezone":"Africa/Kigali",
    "iso:country":"RW",
    "wof:name":"Burunga",
    "wof:placetype":"locality"
},
  "geometry": {"coordinates":[28.9161,-2.4791],"type":"Point"}
}