{
  "type": "Feature",
  "properties": {
    "gn:admin1_code":"11",
    "gn:admin2_code":"53.0",
    "gn:admin3_code":"5310.0",
    "gn:admin4_code":"531005.0",
    "gn:asciiname":"Burambira",
    "gn:country_code":"RW",
    "gn:dem":1407,
    "gn:feature_class":"P",
    "gn:feature_code":"PPLL",
    "gn:name":"Burambira",
    "gn:population":0,
    "gn:timezone":"Africa/Kigali",
    "iso:country":"RW",
    "wof:name":"Burambira",
    "wof:placetype":"locality"
},
  "geometry": {"coordinates":[30.2471,-1.5191],"type":"Point"}
}