{
  "type": "Feature",
  "properties": {
    "gn:admin1_code":"11",
    "gn:admin2_code":"55.0",
    "gn:admin3_code":"5504.0",
    "gn:admin4_code":"550402.0",
    "gn:asciiname":"Nyagisozi",
    "gn:country_code":"RW",
    "gn:dem":1518,
    "gn:feature_class":"P",
    "gn:feature_code":"PPLL",
    "gn:name":"Nyagisozi",
    "gn:population":0,
    "gn:timezone":"Africa/Kigali",
    "iso:country":"RW",
    "wof:name":"Nyagisozi",
    "wof:placetype":"locality"
},
  "geometry": {"coordinates":[30.7112,-2.229],"type":"Point"}
}