{
  "type": "Feature",
  "properties": {
    "gn:admin1_code":"11",
    "gn:admin2_code":"55.0",
    "gn:admin3_code":"5502.0",
    "gn:admin4_code":"550204.0",
    "gn:asciiname":"Nyamiryango",
    "gn:country_code":"RW",
    "gn:dem":1507,
    "gn:feature_class":"P",
    "gn:feature_code":"PPLL",
    "gn:name":"Nyamiryango",
    "gn:population":0,
    "gn:timezone":"Africa/Kigali",
    "iso:country":"RW",
    "wof:name":"Nyamiryango",
    "wof:placetype":"locality"
},
  "geometry": {"coordinates":[30.5919,-2.2814],"type":"Point"}
}