{
  "type": "Feature",
  "properties": {
    "gn:admin1_code":"13.0",
    "gn:admin2_code":"44",
    "gn:admin3_code":"4414.0",
    "gn:admin4_code":"441404.0",
    "gn:asciiname":"Ngoma",
    "gn:country_code":"RW",
    "gn:dem":2181,
    "gn:feature_class":"P",
    "gn:feature_code":"PPLL",
    "gn:name":"Ngoma",
    "gn:population":0,
    "gn:timezone":"Africa/Kigali",
    "iso:country":"RW",
    "name:und_x_variant":[
        "Colline Ngoma",
        "Ngoma"
    ],
    "wof:name":"Ngoma",
    "wof:placetype":"locality"
},
  "geometry": {"coordinates":[29.79906,-1.54307],"type":"Point"}
}