{
  "type": "Feature",
  "properties": {
    "gn:admin1_code":"13",
    "gn:admin2_code":"41.0",
    "gn:admin3_code":"4104.0",
    "gn:admin4_code":"410407.0",
    "gn:asciiname":"Bunyana",
    "gn:country_code":"RW",
    "gn:dem":1651,
    "gn:feature_class":"P",
    "gn:feature_code":"PPLL",
    "gn:name":"Bunyana",
    "gn:population":0,
    "gn:timezone":"Africa/Kigali",
    "iso:country":"RW",
    "wof:name":"Bunyana",
    "wof:placetype":"locality"
},
  "geometry": {"coordinates":[30.0533,-1.7011],"type":"Point"}
}