{
  "type": "Feature",
  "properties": {
    "gn:admin1_code":"11.0",
    "gn:admin2_code":"52",
    "gn:admin3_code":"5212.0",
    "gn:admin4_code":"521209.0",
    "gn:asciiname":"Rwempasha",
    "gn:country_code":"RW",
    "gn:dem":1438,
    "gn:feature_class":"P",
    "gn:feature_code":"PPL",
    "gn:name":"Rwempasha",
    "gn:population":0,
    "gn:timezone":"Africa/Kigali",
    "iso:country":"RW",
    "name:und_x_variant":[
        "Rwemhasha",
        "Rwempasha"
    ],
    "wof:name":"Rwempasha",
    "wof:placetype":"locality"
},
  "geometry": {"coordinates":[30.2983,-1.2128],"type":"Point"}
}