{
  "type": "Feature",
  "properties": {
    "gn:admin1_code":"14.0",
    "gn:admin2_code":"37",
    "gn:admin3_code":"3710.0",
    "gn:admin4_code":"371004.0",
    "gn:asciiname":"Hanika",
    "gn:country_code":"RW",
    "gn:dem":1585,
    "gn:feature_class":"P",
    "gn:feature_code":"PPL",
    "gn:name":"Hanika",
    "gn:population":0,
    "gn:timezone":"Africa/Kigali",
    "iso:country":"RW",
    "wof:name":"Hanika",
    "wof:placetype":"locality"
},
  "geometry": {"coordinates":[29.1881,-2.2889],"type":"Point"}
}