{
  "type": "Feature",
  "properties": {
    "gn:admin1_code":"15.0",
    "gn:admin2_code":"25",
    "gn:admin3_code":"2514.0",
    "gn:admin4_code":"251402.0",
    "gn:asciiname":"Nyagisumo",
    "gn:country_code":"RW",
    "gn:dem":1977,
    "gn:feature_class":"P",
    "gn:feature_code":"PPLL",
    "gn:name":"Nyagisumo",
    "gn:population":0,
    "gn:timezone":"Africa/Kigali",
    "iso:country":"RW",
    "wof:name":"Nyagisumo",
    "wof:placetype":"locality"
},
  "geometry": {"coordinates":[29.4577,-2.3281],"type":"Point"}
}