{
  "type": "Feature",
  "properties": {
    "gn:admin1_code":"11",
    "gn:admin2_code":"51.0",
    "gn:admin3_code":"5111.0",
    "gn:admin4_code":"511101.0",
    "gn:asciiname":"Karama",
    "gn:country_code":"RW",
    "gn:dem":1416,
    "gn:feature_class":"P",
    "gn:feature_code":"PPLL",
    "gn:name":"Karama",
    "gn:population":0,
    "gn:timezone":"Africa/Kigali",
    "iso:country":"RW",
    "name:ceb_x_preferred":[
        "Karama"
    ],
    "name:fra_x_preferred":[
        "Karama"
    ],
    "name:ita_x_preferred":[
        "Karama"
    ],
    "name:swe_x_preferred":[
        "Karama"
    ],
    "wof:name":"Karama",
    "wof:placetype":"locality"
},
  "geometry": {"coordinates":[30.3465,-1.9867],"type":"Point"}
}