{
  "type": "Feature",
  "properties": {
    "gn:admin1_code":"13",
    "gn:asciiname":"Muhondo",
    "gn:country_code":"RW",
    "gn:dem":1820,
    "gn:feature_class":"P",
    "gn:feature_code":"PPLL",
    "gn:name":"Muhondo",
    "gn:population":0,
    "gn:timezone":"Africa/Kigali",
    "iso:country":"RW",
    "wof:name":"Muhondo",
    "wof:placetype":"locality"
},
  "geometry": {"coordinates":[29.9909,-1.4492],"type":"Point"}
}