{
  "type": "Feature",
  "properties": {
    "gn:admin1_code":"13",
    "gn:admin2_code":"44.0",
    "gn:admin3_code":"4417.0",
    "gn:admin4_code":"441703.0",
    "gn:asciiname":"Ruconsho",
    "gn:country_code":"RW",
    "gn:dem":2261,
    "gn:feature_class":"P",
    "gn:feature_code":"PPLL",
    "gn:name":"Ruconsho",
    "gn:population":0,
    "gn:timezone":"Africa/Kigali",
    "iso:country":"RW",
    "wof:name":"Ruconsho",
    "wof:placetype":"locality"
},
  "geometry": {"coordinates":[29.8742,-1.52152],"type":"Point"}
}