{
  "type": "Feature",
  "properties": {
    "gn:admin1_code":"15.0",
    "gn:admin2_code":"25",
    "gn:admin3_code":"2502.0",
    "gn:admin4_code":"250204.0",
    "gn:asciiname":"Gikomero",
    "gn:country_code":"RW",
    "gn:dem":1800,
    "gn:feature_class":"P",
    "gn:feature_code":"PPLL",
    "gn:name":"Gikomero",
    "gn:population":0,
    "gn:timezone":"Africa/Kigali",
    "iso:country":"RW",
    "wof:name":"Gikomero",
    "wof:placetype":"locality"
},
  "geometry": {"coordinates":[29.6154,-2.4486],"type":"Point"}
}