{
  "type": "Feature",
  "properties": {
    "gn:admin1_code":"14.0",
    "gn:admin2_code":"37",
    "gn:admin3_code":"3713.0",
    "gn:admin4_code":"371302.0",
    "gn:asciiname":"Gashihe",
    "gn:country_code":"RW",
    "gn:dem":1674,
    "gn:feature_class":"P",
    "gn:feature_code":"PPLL",
    "gn:name":"Gashihe",
    "gn:population":0,
    "gn:timezone":"Africa/Kigali",
    "iso:country":"RW",
    "wof:name":"Gashihe",
    "wof:placetype":"locality"
},
  "geometry": {"coordinates":[29.1711,-2.4074],"type":"Point"}
}