{
  "type": "Feature",
  "properties": {
    "gn:admin1_code":"11",
    "gn:admin2_code":"57.0",
    "gn:admin3_code":"5701.0",
    "gn:admin4_code":"570101.0",
    "gn:asciiname":"Buhoro",
    "gn:country_code":"RW",
    "gn:dem":1368,
    "gn:feature_class":"P",
    "gn:feature_code":"PPLL",
    "gn:name":"Buhoro",
    "gn:population":0,
    "gn:timezone":"Africa/Kigali",
    "iso:country":"RW",
    "wof:name":"Buhoro",
    "wof:placetype":"locality"
},
  "geometry": {"coordinates":[30.2425,-2.1987],"type":"Point"}
}