{
  "type": "Feature",
  "properties": {
    "gn:admin1_code":"15.0",
    "gn:admin2_code":"27",
    "gn:admin3_code":"2701.0",
    "gn:admin4_code":"270103.0",
    "gn:asciiname":"Gisari",
    "gn:country_code":"RW",
    "gn:dem":1918,
    "gn:feature_class":"P",
    "gn:feature_code":"PPLL",
    "gn:name":"Gisari",
    "gn:population":0,
    "gn:timezone":"Africa/Kigali",
    "iso:country":"RW",
    "wof:name":"Gisari",
    "wof:placetype":"locality"
},
  "geometry": {"coordinates":[29.789,-2.0516],"type":"Point"}
}