{
  "type": "Feature",
  "properties": {
    "gn:admin1_code":"11",
    "gn:admin2_code":"55.0",
    "gn:admin3_code":"5507.0",
    "gn:admin4_code":"550705.0",
    "gn:asciiname":"Rukumbo",
    "gn:country_code":"RW",
    "gn:dem":1311,
    "gn:feature_class":"P",
    "gn:feature_code":"PPL",
    "gn:name":"Rukumbo",
    "gn:population":0,
    "gn:timezone":"Africa/Kigali",
    "iso:country":"RW",
    "wof:name":"Rukumbo",
    "wof:placetype":"locality"
},
  "geometry": {"coordinates":[30.8424,-2.1078],"type":"Point"}
}