{
  "type": "Feature",
  "properties": {
    "gn:admin1_code":"15",
    "gn:admin2_code":"23.0",
    "gn:admin3_code":"2311.0",
    "gn:admin4_code":"231102.0",
    "gn:asciiname":"Bwerankori",
    "gn:country_code":"RW",
    "gn:dem":1750,
    "gn:feature_class":"P",
    "gn:feature_code":"PPL",
    "gn:name":"Bwerankori",
    "gn:population":0,
    "gn:timezone":"Africa/Kigali",
    "iso:country":"RW",
    "wof:name":"Bwerankori",
    "wof:placetype":"locality"
},
  "geometry": {"coordinates":[29.6373,-2.7605],"type":"Point"}
}