{
  "type": "Feature",
  "properties": {
    "gn:admin1_code":"15.0",
    "gn:admin2_code":"25",
    "gn:admin3_code":"2516.0",
    "gn:admin4_code":"251602.0",
    "gn:asciiname":"Bivumu",
    "gn:country_code":"RW",
    "gn:dem":2204,
    "gn:feature_class":"P",
    "gn:feature_code":"PPLL",
    "gn:name":"Bivumu",
    "gn:population":0,
    "gn:timezone":"Africa/Kigali",
    "iso:country":"RW",
    "wof:name":"Bivumu",
    "wof:placetype":"locality"
},
  "geometry": {"coordinates":[29.4897,-2.507],"type":"Point"}
}