{
  "type": "Feature",
  "properties": {
    "gn:admin1_code":"14.0",
    "gn:admin2_code":"36",
    "gn:admin3_code":"3606.0",
    "gn:admin4_code":"360606.0",
    "gn:asciiname":"Gasharu",
    "gn:country_code":"RW",
    "gn:dem":1631,
    "gn:feature_class":"P",
    "gn:feature_code":"PPLL",
    "gn:name":"Gasharu",
    "gn:population":0,
    "gn:timezone":"Africa/Kigali",
    "iso:country":"RW",
    "wof:name":"Gasharu",
    "wof:placetype":"locality"
},
  "geometry": {"coordinates":[28.9316,-2.4483],"type":"Point"}
}