{
  "type": "Feature",
  "properties": {
    "gn:admin1_code":"15",
    "gn:admin2_code":"21.0",
    "gn:admin3_code":"2105.0",
    "gn:admin4_code":"210505.0",
    "gn:asciiname":"Nyarukurazo",
    "gn:country_code":"RW",
    "gn:dem":1441,
    "gn:feature_class":"P",
    "gn:feature_code":"PPLL",
    "gn:name":"Nyarukurazo",
    "gn:population":0,
    "gn:timezone":"Africa/Kigali",
    "iso:country":"RW",
    "name:und_x_variant":[
        "Nyarukuraze"
    ],
    "wof:name":"Nyarukurazo",
    "wof:placetype":"locality"
},
  "geometry": {"coordinates":[29.8966,-2.2869],"type":"Point"}
}