{
  "type": "Feature",
  "properties": {
    "gn:admin1_code":"15.0",
    "gn:admin2_code":"25",
    "gn:admin3_code":"2506.0",
    "gn:admin4_code":"250605.0",
    "gn:asciiname":"Nyarusange",
    "gn:country_code":"RW",
    "gn:dem":1903,
    "gn:feature_class":"P",
    "gn:feature_code":"PPLL",
    "gn:name":"Nyarusange",
    "gn:population":0,
    "gn:timezone":"Africa/Kigali",
    "iso:country":"RW",
    "wof:name":"Nyarusange",
    "wof:placetype":"locality"
},
  "geometry": {"coordinates":[29.5834,-2.5462],"type":"Point"}
}