{
  "type": "Feature",
  "properties": {
    "gn:admin1_code":"13",
    "gn:admin2_code":"41.0",
    "gn:admin3_code":"4110.0",
    "gn:admin4_code":"411001.0",
    "gn:asciiname":"Muhora",
    "gn:country_code":"RW",
    "gn:dem":1809,
    "gn:feature_class":"P",
    "gn:feature_code":"PPLL",
    "gn:name":"Muhora",
    "gn:population":0,
    "gn:timezone":"Africa/Kigali",
    "iso:country":"RW",
    "wof:name":"Muhora",
    "wof:placetype":"locality"
},
  "geometry": {"coordinates":[29.9434,-1.746],"type":"Point"}
}