{
  "type": "Feature",
  "properties": {
    "gn:admin1_code":"13",
    "gn:admin2_code":"45.0",
    "gn:admin3_code":"4517.0",
    "gn:admin4_code":"451701.0",
    "gn:asciiname":"Rubyiro",
    "gn:country_code":"RW",
    "gn:dem":1994,
    "gn:feature_class":"P",
    "gn:feature_code":"PPLL",
    "gn:name":"Rubyiro",
    "gn:population":0,
    "gn:timezone":"Africa/Kigali",
    "iso:country":"RW",
    "name:und_x_variant":[
        "Rubyira"
    ],
    "wof:name":"Rubyiro",
    "wof:placetype":"locality"
},
  "geometry": {"coordinates":[30.139,-1.5057],"type":"Point"}
}