{
  "type": "Feature",
  "properties": {
    "gn:admin1_code":"11",
    "gn:admin2_code":"55.0",
    "gn:admin3_code":"5503.0",
    "gn:admin4_code":"550301.0",
    "gn:asciiname":"Cyanya",
    "gn:country_code":"RW",
    "gn:dem":1827,
    "gn:feature_class":"P",
    "gn:feature_code":"PPLL",
    "gn:name":"Cyanya",
    "gn:population":0,
    "gn:timezone":"Africa/Kigali",
    "iso:country":"RW",
    "wof:name":"Cyanya",
    "wof:placetype":"locality"
},
  "geometry": {"coordinates":[30.6479,-2.3431],"type":"Point"}
}