{
  "type": "Feature",
  "properties": {
    "gn:admin1_code":"14",
    "gn:admin2_code":"31.0",
    "gn:admin3_code":"3106.0",
    "gn:admin4_code":"310601.0",
    "gn:asciiname":"Bugarama",
    "gn:country_code":"RW",
    "gn:dem":1737,
    "gn:feature_class":"P",
    "gn:feature_code":"PPLL",
    "gn:name":"Bugarama",
    "gn:population":0,
    "gn:timezone":"Africa/Kigali",
    "iso:country":"RW",
    "name:cat_x_preferred":[
        "Bugarama"
    ],
    "name:deu_x_preferred":[
        "Bugarama"
    ],
    "name:est_x_preferred":[
        "Bugarama"
    ],
    "name:ita_x_preferred":[
        "Bugarama"
    ],
    "name:pol_x_preferred":[
        "Bugarama"
    ],
    "wof:name":"Bugarama",
    "wof:placetype":"locality"
},
  "geometry": {"coordinates":[29.5841,-2.1435],"type":"Point"}
}