{
  "type": "Feature",
  "properties": {
    "gn:admin1_code":"13.0",
    "gn:admin2_code":"43",
    "gn:admin3_code":"4314.0",
    "gn:admin4_code":"431403.0",
    "gn:asciiname":"Kiganda",
    "gn:country_code":"RW",
    "gn:dem":1790,
    "gn:feature_class":"P",
    "gn:feature_code":"PPLL",
    "gn:name":"Kiganda",
    "gn:population":0,
    "gn:timezone":"Africa/Kigali",
    "iso:country":"RW",
    "name:und_x_variant":[
        "Colline Kiganda",
        "Kiganda"
    ],
    "wof:name":"Kiganda",
    "wof:placetype":"locality"
},
  "geometry": {"coordinates":[29.6747,-1.567],"type":"Point"}
}