{
  "type": "Feature",
  "properties": {
    "gn:admin1_code":"11",
    "gn:admin2_code":"53.0",
    "gn:admin3_code":"5302.0",
    "gn:admin4_code":"530201.0",
    "gn:asciiname":"Nyabukingi",
    "gn:country_code":"RW",
    "gn:dem":1783,
    "gn:feature_class":"P",
    "gn:feature_code":"PPL",
    "gn:name":"Nyabukingi",
    "gn:population":0,
    "gn:timezone":"Africa/Kigali",
    "iso:country":"RW",
    "wof:name":"Nyabukingi",
    "wof:placetype":"locality"
},
  "geometry": {"coordinates":[30.2366,-1.5789],"type":"Point"}
}