{
  "type": "Feature",
  "properties": {
    "gn:admin1_code":"15.0",
    "gn:admin2_code":"26",
    "gn:admin3_code":"2607.0",
    "gn:admin4_code":"260707.0",
    "gn:asciiname":"Mutara",
    "gn:country_code":"RW",
    "gn:dem":1603,
    "gn:feature_class":"P",
    "gn:feature_code":"PPLL",
    "gn:name":"Mutara",
    "gn:population":0,
    "gn:timezone":"Africa/Kigali",
    "iso:country":"RW",
    "name:ceb_x_preferred":[
        "Mutara"
    ],
    "name:swe_x_preferred":[
        "Mutara"
    ],
    "wof:name":"Mutara",
    "wof:placetype":"locality"
},
  "geometry": {"coordinates":[29.64756,-2.1421],"type":"Point"}
}