{
  "type": "Feature",
  "properties": {
    "gn:admin1_code":"13",
    "gn:admin2_code":"43.0",
    "gn:admin3_code":"4314.0",
    "gn:admin4_code":"431401.0",
    "gn:asciiname":"Nyarubuye",
    "gn:country_code":"RW",
    "gn:dem":1656,
    "gn:feature_class":"P",
    "gn:feature_code":"PPLL",
    "gn:name":"Nyarubuye",
    "gn:population":0,
    "gn:timezone":"Africa/Kigali",
    "iso:country":"RW",
    "name:ita_x_preferred":[
        "Nyarubuye"
    ],
    "wof:name":"Nyarubuye",
    "wof:placetype":"locality"
},
  "geometry": {"coordinates":[29.6575,-1.5734],"type":"Point"}
}