{
  "type": "Feature",
  "properties": {
    "gn:admin1_code":"15.0",
    "gn:admin2_code":"25",
    "gn:admin3_code":"2508.0",
    "gn:admin4_code":"250801.0",
    "gn:asciiname":"Kamurwa",
    "gn:country_code":"RW",
    "gn:dem":1764,
    "gn:feature_class":"P",
    "gn:feature_code":"PPLL",
    "gn:name":"Kamurwa",
    "gn:population":0,
    "gn:timezone":"Africa/Kigali",
    "iso:country":"RW",
    "wof:name":"Kamurwa",
    "wof:placetype":"locality"
},
  "geometry": {"coordinates":[29.5614,-2.387],"type":"Point"}
}