{
  "type": "Feature",
  "properties": {
    "gn:admin1_code":"13.0",
    "gn:admin2_code":"44",
    "gn:admin3_code":"4416.0",
    "gn:admin4_code":"441603.0",
    "gn:asciiname":"Ruhanga",
    "gn:country_code":"RW",
    "gn:dem":2175,
    "gn:feature_class":"P",
    "gn:feature_code":"PPLL",
    "gn:name":"Ruhanga",
    "gn:population":0,
    "gn:timezone":"Africa/Kigali",
    "iso:country":"RW",
    "name:ita_x_preferred":[
        "Ruhanga"
    ],
    "wof:name":"Ruhanga",
    "wof:placetype":"locality"
},
  "geometry": {"coordinates":[29.8418,-1.4525],"type":"Point"}
}