{
  "type": "Feature",
  "properties": {
    "gn:admin1_code":"14",
    "gn:admin2_code":"33.0",
    "gn:admin3_code":"3311.0",
    "gn:admin4_code":"331103.0",
    "gn:asciiname":"Ngugo",
    "gn:country_code":"RW",
    "gn:dem":1608,
    "gn:feature_class":"P",
    "gn:feature_code":"PPL",
    "gn:name":"Ngugo",
    "gn:population":0,
    "gn:timezone":"Africa/Kigali",
    "iso:country":"RW",
    "wof:name":"Ngugo",
    "wof:placetype":"locality"
},
  "geometry": {"coordinates":[29.27,-1.6613],"type":"Point"}
}