{
  "type": "Feature",
  "properties": {
    "gn:admin1_code":"11",
    "gn:admin2_code":"54.0",
    "gn:admin3_code":"5404.0",
    "gn:admin4_code":"540403.0",
    "gn:asciiname":"Mburabuturo",
    "gn:country_code":"RW",
    "gn:dem":1479,
    "gn:feature_class":"P",
    "gn:feature_code":"PPLL",
    "gn:name":"Mburabuturo",
    "gn:population":0,
    "gn:timezone":"Africa/Kigali",
    "iso:country":"RW",
    "wof:name":"Mburabuturo",
    "wof:placetype":"locality"
},
  "geometry": {"coordinates":[30.4633,-1.9083],"type":"Point"}
}