{
  "type": "Feature",
  "properties": {
    "gn:admin1_code":"13",
    "gn:admin2_code":"44.0",
    "gn:admin3_code":"4411.0",
    "gn:admin4_code":"441103.0",
    "gn:asciiname":"Rusasa",
    "gn:country_code":"RW",
    "gn:dem":2123,
    "gn:feature_class":"P",
    "gn:feature_code":"PPLL",
    "gn:name":"Rusasa",
    "gn:population":0,
    "gn:timezone":"Africa/Kigali",
    "iso:country":"RW",
    "wof:name":"Rusasa",
    "wof:placetype":"locality"
},
  "geometry": {"coordinates":[29.871,-1.4514],"type":"Point"}
}