{
  "type": "Feature",
  "properties": {
    "gn:admin1_code":"11",
    "gn:admin2_code":"55.0",
    "gn:admin3_code":"5503.0",
    "gn:admin4_code":"550303.0",
    "gn:asciiname":"Kimesho",
    "gn:country_code":"RW",
    "gn:dem":1435,
    "gn:feature_class":"P",
    "gn:feature_code":"PPLL",
    "gn:name":"Kimesho",
    "gn:population":0,
    "gn:timezone":"Africa/Kigali",
    "iso:country":"RW",
    "wof:name":"Kimesho",
    "wof:placetype":"locality"
},
  "geometry": {"coordinates":[30.7078,-2.3396],"type":"Point"}
}