{
  "type": "Feature",
  "properties": {
    "gn:admin1_code":"15",
    "gn:admin2_code":"26.0",
    "gn:admin3_code":"2604.0",
    "gn:admin4_code":"260402.0",
    "gn:asciiname":"Kakirenzi",
    "gn:country_code":"RW",
    "gn:dem":1513,
    "gn:feature_class":"P",
    "gn:feature_code":"PPLL",
    "gn:name":"Kakirenzi",
    "gn:population":0,
    "gn:timezone":"Africa/Kigali",
    "iso:country":"RW",
    "wof:name":"Kakirenzi",
    "wof:placetype":"locality"
},
  "geometry": {"coordinates":[29.916,-2.1516],"type":"Point"}
}