{
  "type": "Feature",
  "properties": {
    "gn:admin1_code":"15",
    "gn:admin2_code":"27.0",
    "gn:admin3_code":"2701.0",
    "gn:admin4_code":"270102.0",
    "gn:asciiname":"Shyanda",
    "gn:country_code":"RW",
    "gn:dem":1721,
    "gn:feature_class":"P",
    "gn:feature_code":"PPLL",
    "gn:name":"Shyanda",
    "gn:population":0,
    "gn:timezone":"Africa/Kigali",
    "iso:country":"RW",
    "wof:name":"Shyanda",
    "wof:placetype":"locality"
},
  "geometry": {"coordinates":[29.78283,-1.97984],"type":"Point"}
}