{
  "type": "Feature",
  "properties": {
    "gn:admin1_code":"15",
    "gn:admin2_code":"26.0",
    "gn:admin3_code":"2609.0",
    "gn:admin4_code":"260903.0",
    "gn:asciiname":"Gikumba",
    "gn:country_code":"RW",
    "gn:dem":1535,
    "gn:feature_class":"P",
    "gn:feature_code":"PPLL",
    "gn:name":"Gikumba",
    "gn:population":0,
    "gn:timezone":"Africa/Kigali",
    "iso:country":"RW",
    "wof:name":"Gikumba",
    "wof:placetype":"locality"
},
  "geometry": {"coordinates":[29.835,-2.2155],"type":"Point"}
}