{
  "type": "Feature",
  "properties": {
    "gn:admin1_code":"14.0",
    "gn:admin2_code":"34",
    "gn:admin3_code":"3401.0",
    "gn:admin4_code":"340104.0",
    "gn:asciiname":"Kora",
    "gn:country_code":"RW",
    "gn:dem":2474,
    "gn:feature_class":"P",
    "gn:feature_code":"PPL",
    "gn:name":"Kora",
    "gn:population":0,
    "gn:timezone":"Africa/Kigali",
    "iso:country":"RW",
    "name:ben_x_preferred":[
        "\u0995\u09cb\u09b0\u09be"
    ],
    "name:bre_x_preferred":[
        "Kora"
    ],
    "name:bul_x_preferred":[
        "\u041a\u043e\u0440\u0430"
    ],
    "name:cat_x_preferred":[
        "Kora"
    ],
    "name:ceb_x_preferred":[
        "Kora"
    ],
    "name:chv_x_preferred":[
        "\u041a\u043e\u0440\u0430"
    ],
    "name:deu_x_preferred":[
        "Kora"
    ],
    "name:fra_x_preferred":[
        "Kora"
    ],
    "name:hrv_x_preferred":[
        "Kora"
    ],
    "name:ita_x_preferred":[
        "Kora"
    ],
    "name:nld_x_preferred":[
        "Kora"
    ],
    "name:pol_x_preferred":[
        "Kora"
    ],
    "name:por_x_preferred":[
        "Kora"
    ],
    "name:rus_x_preferred":[
        "\u041a\u043e\u0440\u0430"
    ],
    "name:spa_x_preferred":[
        "Kora"
    ],
    "name:srp_x_preferred":[
        "\u041a\u043e\u0440\u0430"
    ],
    "name:swe_x_preferred":[
        "Kora"
    ],
    "name:ukr_x_preferred":[
        "\u041a\u043e\u0440\u0430"
    ],
    "wof:name":"Kora",
    "wof:placetype":"locality"
},
  "geometry": {"coordinates":[29.445,-1.6101],"type":"Point"}
}