{
  "type": "Feature",
  "properties": {
    "gn:admin1_code":"15",
    "gn:admin2_code":"22.0",
    "gn:admin3_code":"2202.0",
    "gn:admin4_code":"220204.0",
    "gn:asciiname":"Gateketeke",
    "gn:country_code":"RW",
    "gn:dem":1377,
    "gn:feature_class":"P",
    "gn:feature_code":"PPLL",
    "gn:name":"Gateketeke",
    "gn:population":0,
    "gn:timezone":"Africa/Kigali",
    "iso:country":"RW",
    "wof:name":"Gateketeke",
    "wof:placetype":"locality"
},
  "geometry": {"coordinates":[29.9021,-2.5595],"type":"Point"}
}