{
  "type": "Feature",
  "properties": {
    "gn:admin1_code":"15.0",
    "gn:admin2_code":"25",
    "gn:admin3_code":"2515.0",
    "gn:admin4_code":"251503.0",
    "gn:asciiname":"Tubuye",
    "gn:country_code":"RW",
    "gn:dem":2299,
    "gn:feature_class":"P",
    "gn:feature_code":"PPL",
    "gn:name":"Tubuye",
    "gn:population":0,
    "gn:timezone":"Africa/Kigali",
    "iso:country":"RW",
    "wof:name":"Tubuye",
    "wof:placetype":"locality"
},
  "geometry": {"coordinates":[29.3968,-2.3359],"type":"Point"}
}