{
  "type": "Feature",
  "properties": {
    "gn:admin1_code":"15",
    "gn:admin2_code":"26.0",
    "gn:admin3_code":"2607.0",
    "gn:admin4_code":"260706.0",
    "gn:asciiname":"Kavumu",
    "gn:country_code":"RW",
    "gn:dem":1709,
    "gn:feature_class":"P",
    "gn:feature_code":"PPLL",
    "gn:name":"Kavumu",
    "gn:population":0,
    "gn:timezone":"Africa/Kigali",
    "iso:country":"RW",
    "wof:name":"Kavumu",
    "wof:placetype":"locality"
},
  "geometry": {"coordinates":[29.649,-2.1223],"type":"Point"}
}