{
  "type": "Feature",
  "properties": {
    "gn:admin1_code":"14.0",
    "gn:admin2_code":"37",
    "gn:admin3_code":"3714.0",
    "gn:admin4_code":"371403.0",
    "gn:asciiname":"Kanyovu",
    "gn:country_code":"RW",
    "gn:dem":1882,
    "gn:feature_class":"P",
    "gn:feature_code":"PPLL",
    "gn:name":"Kanyovu",
    "gn:population":0,
    "gn:timezone":"Africa/Kigali",
    "iso:country":"RW",
    "wof:name":"Kanyovu",
    "wof:placetype":"locality"
},
  "geometry": {"coordinates":[28.9941,-2.4821],"type":"Point"}
}