{
  "type": "Feature",
  "properties": {
    "gn:admin1_code":"13",
    "gn:admin2_code":"43.0",
    "gn:admin3_code":"4306.0",
    "gn:admin4_code":"430603.0",
    "gn:asciiname":"Ndorahe",
    "gn:country_code":"RW",
    "gn:dem":2061,
    "gn:feature_class":"P",
    "gn:feature_code":"PPLL",
    "gn:name":"Ndorahe",
    "gn:population":0,
    "gn:timezone":"Africa/Kigali",
    "iso:country":"RW",
    "wof:name":"Ndorahe",
    "wof:placetype":"locality"
},
  "geometry": {"coordinates":[29.58,-1.50111],"type":"Point"}
}