{
  "type": "Feature",
  "properties": {
    "gn:admin1_code":"15.0",
    "gn:admin2_code":"23",
    "gn:admin3_code":"2307.0",
    "gn:admin4_code":"230703.0",
    "gn:asciiname":"Kagera",
    "gn:country_code":"RW",
    "gn:dem":1814,
    "gn:feature_class":"P",
    "gn:feature_code":"PPLL",
    "gn:name":"Kagera",
    "gn:population":0,
    "gn:timezone":"Africa/Kigali",
    "iso:country":"RW",
    "wof:name":"Kagera",
    "wof:placetype":"locality"
},
  "geometry": {"coordinates":[29.5592,-2.7187],"type":"Point"}
}