{
  "type": "Feature",
  "properties": {
    "gn:admin1_code":"12",
    "gn:asciiname":"Karambo",
    "gn:country_code":"RW",
    "gn:dem":1616,
    "gn:feature_class":"P",
    "gn:feature_code":"PPLL",
    "gn:name":"Karambo",
    "gn:population":0,
    "gn:timezone":"Africa/Kigali",
    "iso:country":"RW",
    "wof:name":"Karambo",
    "wof:placetype":"locality"
},
  "geometry": {"coordinates":[30.0277,-1.8537],"type":"Point"}
}