{
  "type": "Feature",
  "properties": {
    "gn:admin1_code":"14",
    "gn:admin2_code":"33.0",
    "gn:admin3_code":"3306.0",
    "gn:admin4_code":"330605.0",
    "gn:asciiname":"Nyamirango",
    "gn:country_code":"RW",
    "gn:dem":2322,
    "gn:feature_class":"P",
    "gn:feature_code":"PPLL",
    "gn:name":"Nyamirango",
    "gn:population":0,
    "gn:timezone":"Africa/Kigali",
    "iso:country":"RW",
    "wof:name":"Nyamirango",
    "wof:placetype":"locality"
},
  "geometry": {"coordinates":[29.3871,-1.6518],"type":"Point"}
}