{
  "type": "Feature",
  "properties": {
    "iso:country":"RW",
    "qs:gn_pop":0,
    "qs:name":"Mwufe",
    "qs:name_adm0":"Rwanda",
    "qs:name_adm1":"Province de l'Ouest",
    "qs:photos":27,
    "qs:photos_1k":5,
    "qs:photos_9k":1,
    "qs:photos_9r":2,
    "qs:photos_all":27,
    "qs:photos_sr":2,
    "qs:placetype":"Town",
    "qs:pop_sr":"0",
    "qs:woe_adm0":23424937,
    "wof:name":"Mwufe",
    "wof:placetype":"locality"
},
  "geometry": {"coordinates":[29.30397,-1.768517],"type":"Point"}
}