{
  "type": "Feature",
  "properties": {
    "gn:admin1_code":"11",
    "gn:admin2_code":"55.0",
    "gn:admin3_code":"5506.0",
    "gn:admin4_code":"550602.0",
    "gn:asciiname":"Paysannat M",
    "gn:country_code":"RW",
    "gn:dem":1328,
    "gn:feature_class":"P",
    "gn:feature_code":"PPLL",
    "gn:name":"Paysannat M",
    "gn:population":0,
    "gn:timezone":"Africa/Kigali",
    "iso:country":"RW",
    "wof:name":"Paysannat M",
    "wof:placetype":"locality"
},
  "geometry": {"coordinates":[30.8105,-2.2708],"type":"Point"}
}