{
  "type": "Feature",
  "properties": {
    "gn:admin1_code":"15",
    "gn:admin2_code":"22.0",
    "gn:admin3_code":"2210.0",
    "gn:admin4_code":"221003.0",
    "gn:asciiname":"Nyesonga",
    "gn:country_code":"RW",
    "gn:dem":1624,
    "gn:feature_class":"P",
    "gn:feature_code":"PPLL",
    "gn:name":"Nyesonga",
    "gn:population":0,
    "gn:timezone":"Africa/Kigali",
    "iso:country":"RW",
    "wof:name":"Nyesonga",
    "wof:placetype":"locality"
},
  "geometry": {"coordinates":[29.82479,-2.53845],"type":"Point"}
}