{
  "type": "Feature",
  "properties": {
    "gn:admin1_code":"15",
    "gn:asciiname":"Nyamagana",
    "gn:country_code":"RW",
    "gn:dem":1512,
    "gn:feature_class":"P",
    "gn:feature_code":"PPLL",
    "gn:name":"Nyamagana",
    "gn:population":0,
    "gn:timezone":"Africa/Kigali",
    "iso:country":"RW",
    "wof:name":"Nyamagana",
    "wof:placetype":"locality"
},
  "geometry": {"coordinates":[29.60567,-2.18464],"type":"Point"}
}