{
  "type": "Feature",
  "properties": {
    "gn:admin1_code":"15",
    "gn:admin2_code":"22.0",
    "gn:admin3_code":"2206.0",
    "gn:admin4_code":"220603.0",
    "gn:asciiname":"Mashenyi",
    "gn:country_code":"RW",
    "gn:dem":1496,
    "gn:feature_class":"P",
    "gn:feature_code":"PPL",
    "gn:name":"Mashenyi",
    "gn:population":0,
    "gn:timezone":"Africa/Kigali",
    "iso:country":"RW",
    "wof:name":"Mashenyi",
    "wof:placetype":"locality"
},
  "geometry": {"coordinates":[29.9246,-2.4617],"type":"Point"}
}