{
  "type": "Feature",
  "properties": {
    "gn:admin1_code":"13",
    "gn:admin2_code":"41.0",
    "gn:admin3_code":"4107.0",
    "gn:admin4_code":"410701.0",
    "gn:asciiname":"Kinihira",
    "gn:country_code":"RW",
    "gn:dem":1794,
    "gn:feature_class":"P",
    "gn:feature_code":"PPL",
    "gn:name":"Kinihira",
    "gn:population":0,
    "gn:timezone":"Africa/Kigali",
    "iso:country":"RW",
    "wof:name":"Kinihira",
    "wof:placetype":"locality"
},
  "geometry": {"coordinates":[29.9539,-1.6663],"type":"Point"}
}