{
  "type": "Feature",
  "properties": {
    "gn:admin1_code":"15.0",
    "gn:admin2_code":"25",
    "gn:admin3_code":"2501.0",
    "gn:admin4_code":"250103.0",
    "gn:asciiname":"Ruronzi",
    "gn:country_code":"RW",
    "gn:dem":2105,
    "gn:feature_class":"P",
    "gn:feature_code":"PPL",
    "gn:name":"Ruronzi",
    "gn:population":0,
    "gn:timezone":"Africa/Kigali",
    "iso:country":"RW",
    "wof:name":"Ruronzi",
    "wof:placetype":"locality"
},
  "geometry": {"coordinates":[29.4286,-2.4023],"type":"Point"}
}