{
  "type": "Feature",
  "properties": {
    "gn:admin1_code":"13",
    "gn:admin2_code":"45.0",
    "gn:admin3_code":"4519.0",
    "gn:admin4_code":"451903.0",
    "gn:asciiname":"Kagasha",
    "gn:country_code":"RW",
    "gn:dem":1779,
    "gn:feature_class":"P",
    "gn:feature_code":"PPLL",
    "gn:name":"Kagasha",
    "gn:population":0,
    "gn:timezone":"Africa/Kigali",
    "iso:country":"RW",
    "wof:name":"Kagasha",
    "wof:placetype":"locality"
},
  "geometry": {"coordinates":[30.1722,-1.6238],"type":"Point"}
}