{
  "type": "Feature",
  "properties": {
    "gn:admin1_code":"15",
    "gn:admin2_code":"22.0",
    "gn:admin3_code":"2208.0",
    "gn:admin4_code":"220803.0",
    "gn:asciiname":"Mushongi",
    "gn:country_code":"RW",
    "gn:dem":1623,
    "gn:feature_class":"P",
    "gn:feature_code":"PPLL",
    "gn:name":"Mushongi",
    "gn:population":0,
    "gn:timezone":"Africa/Kigali",
    "iso:country":"RW",
    "wof:name":"Mushongi",
    "wof:placetype":"locality"
},
  "geometry": {"coordinates":[29.837,-2.7218],"type":"Point"}
}