{
  "type": "Feature",
  "properties": {
    "gn:admin1_code":"11",
    "gn:admin2_code":"55.0",
    "gn:admin3_code":"5510.0",
    "gn:admin4_code":"551003.0",
    "gn:asciiname":"Gitazi",
    "gn:country_code":"RW",
    "gn:dem":1699,
    "gn:feature_class":"P",
    "gn:feature_code":"PPLL",
    "gn:name":"Gitazi",
    "gn:population":0,
    "gn:timezone":"Africa/Kigali",
    "iso:country":"RW",
    "wof:name":"Gitazi",
    "wof:placetype":"locality"
},
  "geometry": {"coordinates":[30.6881,-2.139],"type":"Point"}
}