{
  "type": "Feature",
  "properties": {
    "gn:admin1_code":"13",
    "gn:admin2_code":"43.0",
    "gn:admin3_code":"4307.0",
    "gn:admin4_code":"430702.0",
    "gn:asciiname":"Bisate I",
    "gn:country_code":"RW",
    "gn:dem":2435,
    "gn:feature_class":"P",
    "gn:feature_code":"PPLL",
    "gn:name":"Bisate I",
    "gn:population":0,
    "gn:timezone":"Africa/Kigali",
    "iso:country":"RW",
    "wof:name":"Bisate I",
    "wof:placetype":"locality"
},
  "geometry": {"coordinates":[29.5378,-1.4491],"type":"Point"}
}