{
  "type": "Feature",
  "properties": {
    "gn:admin1_code":"14",
    "gn:admin2_code":"33.0",
    "gn:admin3_code":"3309.0",
    "gn:admin4_code":"330903.0",
    "gn:asciiname":"Burevu",
    "gn:country_code":"RW",
    "gn:dem":1797,
    "gn:feature_class":"P",
    "gn:feature_code":"PPLL",
    "gn:name":"Burevu",
    "gn:population":0,
    "gn:timezone":"Africa/Kigali",
    "iso:country":"RW",
    "wof:name":"Burevu",
    "wof:placetype":"locality"
},
  "geometry": {"coordinates":[29.3062,-1.7356],"type":"Point"}
}