{
  "type": "Feature",
  "properties": {
    "gn:admin1_code":"13",
    "gn:admin2_code":"45.0",
    "gn:admin3_code":"4507.0",
    "gn:admin4_code":"450702.0",
    "gn:asciiname":"Kamabare",
    "gn:country_code":"RW",
    "gn:dem":1946,
    "gn:feature_class":"P",
    "gn:feature_code":"PPLL",
    "gn:name":"Kamabare",
    "gn:population":0,
    "gn:timezone":"Africa/Kigali",
    "iso:country":"RW",
    "wof:name":"Kamabare",
    "wof:placetype":"locality"
},
  "geometry": {"coordinates":[30.0647,-1.4033],"type":"Point"}
}