{
  "type": "Feature",
  "properties": {
    "gn:admin1_code":"15",
    "gn:admin2_code":"22.0",
    "gn:admin3_code":"2211.0",
    "gn:admin4_code":"221104.0",
    "gn:asciiname":"Rugara",
    "gn:country_code":"RW",
    "gn:dem":1680,
    "gn:feature_class":"P",
    "gn:feature_code":"PPLL",
    "gn:name":"Rugara",
    "gn:population":0,
    "gn:timezone":"Africa/Kigali",
    "iso:country":"RW",
    "wof:name":"Rugara",
    "wof:placetype":"locality"
},
  "geometry": {"coordinates":[29.8133,-2.6076],"type":"Point"}
}