{
  "type": "Feature",
  "properties": {
    "gn:admin1_code":"11",
    "gn:admin2_code":"57.0",
    "gn:admin3_code":"5710.0",
    "gn:admin4_code":"571001.0",
    "gn:asciiname":"Nyarugati",
    "gn:country_code":"RW",
    "gn:dem":1422,
    "gn:feature_class":"P",
    "gn:feature_code":"PPLL",
    "gn:name":"Nyarugati",
    "gn:population":0,
    "gn:timezone":"Africa/Kigali",
    "iso:country":"RW",
    "wof:name":"Nyarugati",
    "wof:placetype":"locality"
},
  "geometry": {"coordinates":[30.067,-2.1607],"type":"Point"}
}