{
  "type": "Feature",
  "properties": {
    "gn:admin1_code":"13",
    "gn:admin2_code":"45.0",
    "gn:admin3_code":"4515.0",
    "gn:admin4_code":"451501.0",
    "gn:asciiname":"Bugerero",
    "gn:country_code":"RW",
    "gn:dem":1889,
    "gn:feature_class":"P",
    "gn:feature_code":"PPL",
    "gn:name":"Bugerero",
    "gn:population":0,
    "gn:timezone":"Africa/Kigali",
    "iso:country":"RW",
    "wof:name":"Bugerero",
    "wof:placetype":"locality"
},
  "geometry": {"coordinates":[29.9943,-1.47887],"type":"Point"}
}