{
  "type": "Feature",
  "properties": {
    "gn:admin1_code":"15.0",
    "gn:admin2_code":"23",
    "gn:admin3_code":"2313.0",
    "gn:admin4_code":"231301.0",
    "gn:asciiname":"Bukoro",
    "gn:country_code":"RW",
    "gn:dem":1932,
    "gn:feature_class":"P",
    "gn:feature_code":"PPLL",
    "gn:name":"Bukoro",
    "gn:population":0,
    "gn:timezone":"Africa/Kigali",
    "iso:country":"RW",
    "wof:name":"Bukoro",
    "wof:placetype":"locality"
},
  "geometry": {"coordinates":[29.5176,-2.6004],"type":"Point"}
}