{
  "type": "Feature",
  "properties": {
    "gn:admin1_code":"11",
    "gn:admin2_code":"53.0",
    "gn:admin3_code":"5313.0",
    "gn:admin4_code":"531301.0",
    "gn:asciiname":"Rubiha",
    "gn:country_code":"RW",
    "gn:dem":1426,
    "gn:feature_class":"P",
    "gn:feature_code":"PPLL",
    "gn:name":"Rubiha",
    "gn:population":0,
    "gn:timezone":"Africa/Kigali",
    "iso:country":"RW",
    "wof:name":"Rubiha",
    "wof:placetype":"locality"
},
  "geometry": {"coordinates":[30.3905,-1.726],"type":"Point"}
}