{
  "type": "Feature",
  "properties": {
    "gn:admin1_code":"15",
    "gn:admin2_code":"28.0",
    "gn:admin3_code":"2810.0",
    "gn:admin4_code":"281001.0",
    "gn:asciiname":"Kinyambi",
    "gn:country_code":"RW",
    "gn:dem":1607,
    "gn:feature_class":"P",
    "gn:feature_code":"PPLL",
    "gn:name":"Kinyambi",
    "gn:population":0,
    "gn:timezone":"Africa/Kigali",
    "iso:country":"RW",
    "wof:name":"Kinyambi",
    "wof:placetype":"locality"
},
  "geometry": {"coordinates":[29.9314,-2.0133],"type":"Point"}
}