{
  "type": "Feature",
  "properties": {
    "gn:admin1_code":"13",
    "gn:admin2_code":"44.0",
    "gn:admin3_code":"4411.0",
    "gn:admin4_code":"441104.0",
    "gn:asciiname":"Mushunga",
    "gn:country_code":"RW",
    "gn:dem":2189,
    "gn:feature_class":"P",
    "gn:feature_code":"PPLL",
    "gn:name":"Mushunga",
    "gn:population":0,
    "gn:timezone":"Africa/Kigali",
    "iso:country":"RW",
    "wof:name":"Mushunga",
    "wof:placetype":"locality"
},
  "geometry": {"coordinates":[29.9458,-1.4711],"type":"Point"}
}