{
  "type": "Feature",
  "properties": {
    "gn:admin1_code":"15.0",
    "gn:admin2_code":"26",
    "gn:admin3_code":"2603.0",
    "gn:admin4_code":"260302.0",
    "gn:asciiname":"Mbuye",
    "gn:country_code":"RW",
    "gn:dem":1750,
    "gn:feature_class":"P",
    "gn:feature_code":"PPLL",
    "gn:name":"Mbuye",
    "gn:population":0,
    "gn:timezone":"Africa/Kigali",
    "iso:country":"RW",
    "name:und_x_variant":[
        "Colline Mbuye",
        "Mbuye"
    ],
    "wof:name":"Mbuye",
    "wof:placetype":"locality"
},
  "geometry": {"coordinates":[29.6544,-2.2344],"type":"Point"}
}