{
  "type": "Feature",
  "properties": {
    "gn:admin1_code":"14",
    "gn:admin2_code":"37.0",
    "gn:admin3_code":"3711.0",
    "gn:admin4_code":"371102.0",
    "gn:asciiname":"Kigara",
    "gn:country_code":"RW",
    "gn:dem":1725,
    "gn:feature_class":"P",
    "gn:feature_code":"PPL",
    "gn:name":"Kigara",
    "gn:population":0,
    "gn:timezone":"Africa/Kigali",
    "iso:country":"RW",
    "wof:name":"Kigara",
    "wof:placetype":"locality"
},
  "geometry": {"coordinates":[29.27115,-2.21685],"type":"Point"}
}