{
  "type": "Feature",
  "properties": {
    "gn:admin1_code":"15",
    "gn:admin2_code":"27.0",
    "gn:admin3_code":"2710.0",
    "gn:admin4_code":"271004.0",
    "gn:asciiname":"Mbuye",
    "gn:country_code":"RW",
    "gn:dem":1383,
    "gn:feature_class":"P",
    "gn:feature_code":"PPL",
    "gn:name":"Mbuye",
    "gn:population":0,
    "gn:timezone":"Africa/Kigali",
    "iso:country":"RW",
    "wof:name":"Mbuye",
    "wof:placetype":"locality"
},
  "geometry": {"coordinates":[29.7704,-1.8091],"type":"Point"}
}