{
  "type": "Feature",
  "properties": {
    "gn:admin1_code":"14.0",
    "gn:admin2_code":"34",
    "gn:admin3_code":"3410.0",
    "gn:admin4_code":"341001.0",
    "gn:asciiname":"Nyamutera",
    "gn:country_code":"RW",
    "gn:dem":1552,
    "gn:feature_class":"P",
    "gn:feature_code":"PPL",
    "gn:name":"Nyamutera",
    "gn:population":0,
    "gn:timezone":"Africa/Kigali",
    "iso:country":"RW",
    "wof:name":"Nyamutera",
    "wof:placetype":"locality"
},
  "geometry": {"coordinates":[29.627,-1.6288],"type":"Point"}
}