{
  "type": "Feature",
  "properties": {
    "gn:admin1_code":"15",
    "gn:admin2_code":"22.0",
    "gn:admin3_code":"2210.0",
    "gn:admin4_code":"221003.0",
    "gn:asciiname":"Cyarukobora",
    "gn:country_code":"RW",
    "gn:dem":1654,
    "gn:feature_class":"P",
    "gn:feature_code":"PPL",
    "gn:name":"Cyarukobora",
    "gn:population":0,
    "gn:timezone":"Africa/Kigali",
    "iso:country":"RW",
    "wof:name":"Cyarukobora",
    "wof:placetype":"locality"
},
  "geometry": {"coordinates":[29.8101,-2.5397],"type":"Point"}
}