{
  "type": "Feature",
  "properties": {
    "gn:admin1_code":"14.0",
    "gn:admin2_code":"32",
    "gn:admin3_code":"3201.0",
    "gn:admin4_code":"320101.0",
    "gn:asciiname":"Rwimbogo",
    "gn:country_code":"RW",
    "gn:dem":1470,
    "gn:feature_class":"P",
    "gn:feature_code":"PPL",
    "gn:name":"Rwimbogo",
    "gn:population":0,
    "gn:timezone":"Africa/Kigali",
    "iso:country":"RW",
    "wof:name":"Rwimbogo",
    "wof:placetype":"locality"
},
  "geometry": {"coordinates":[29.2854,-1.8837],"type":"Point"}
}