{
  "type": "Feature",
  "properties": {
    "gn:admin1_code":"15.0",
    "gn:admin2_code":"25",
    "gn:admin3_code":"2507.0",
    "gn:admin4_code":"250702.0",
    "gn:asciiname":"Bweramana",
    "gn:country_code":"RW",
    "gn:dem":1774,
    "gn:feature_class":"P",
    "gn:feature_code":"PPLL",
    "gn:name":"Bweramana",
    "gn:population":0,
    "gn:timezone":"Africa/Kigali",
    "iso:country":"RW",
    "wof:name":"Bweramana",
    "wof:placetype":"locality"
},
  "geometry": {"coordinates":[29.5675,-2.4332],"type":"Point"}
}