{
  "type": "Feature",
  "properties": {
    "gn:admin1_code":"13",
    "gn:admin2_code":"41.0",
    "gn:admin3_code":"4109.0",
    "gn:admin4_code":"410903.0",
    "gn:asciiname":"Gahama",
    "gn:country_code":"RW",
    "gn:dem":1579,
    "gn:feature_class":"P",
    "gn:feature_code":"PPLL",
    "gn:name":"Gahama",
    "gn:population":0,
    "gn:timezone":"Africa/Kigali",
    "iso:country":"RW",
    "wof:name":"Gahama",
    "wof:placetype":"locality"
},
  "geometry": {"coordinates":[30.0624,-1.7875],"type":"Point"}
}