{
  "type": "Feature",
  "properties": {
    "gn:admin1_code":"14.0",
    "gn:admin2_code":"37",
    "gn:admin3_code":"3712.0",
    "gn:admin4_code":"371203.0",
    "gn:asciiname":"Muyange",
    "gn:country_code":"RW",
    "gn:dem":1502,
    "gn:feature_class":"P",
    "gn:feature_code":"PPLL",
    "gn:name":"Muyange",
    "gn:population":0,
    "gn:timezone":"Africa/Kigali",
    "iso:country":"RW",
    "wof:name":"Muyange",
    "wof:placetype":"locality"
},
  "geometry": {"coordinates":[29.0037,-2.3704],"type":"Point"}
}