{
  "type": "Feature",
  "properties": {
    "gn:admin1_code":"15.0",
    "gn:admin2_code":"25",
    "gn:admin3_code":"2511.0",
    "gn:admin4_code":"251104.0",
    "gn:asciiname":"Gakurwe",
    "gn:country_code":"RW",
    "gn:dem":2095,
    "gn:feature_class":"P",
    "gn:feature_code":"PPLL",
    "gn:name":"Gakurwe",
    "gn:population":0,
    "gn:timezone":"Africa/Kigali",
    "iso:country":"RW",
    "wof:name":"Gakurwe",
    "wof:placetype":"locality"
},
  "geometry": {"coordinates":[29.5033,-2.2921],"type":"Point"}
}