{
  "type": "Feature",
  "properties": {
    "gn:admin1_code":"13",
    "gn:admin2_code":"43.0",
    "gn:admin3_code":"4314.0",
    "gn:admin4_code":"431404.0",
    "gn:asciiname":"Gakenke",
    "gn:country_code":"RW",
    "gn:dem":1683,
    "gn:feature_class":"P",
    "gn:feature_code":"PPLL",
    "gn:name":"Gakenke",
    "gn:population":0,
    "gn:timezone":"Africa/Kigali",
    "iso:country":"RW",
    "wof:name":"Gakenke",
    "wof:placetype":"locality"
},
  "geometry": {"coordinates":[29.6474,-1.5579],"type":"Point"}
}