{
  "type": "Feature",
  "properties": {
    "gn:admin1_code":"14.0",
    "gn:admin2_code":"32",
    "gn:admin3_code":"3211.0",
    "gn:admin4_code":"321105.0",
    "gn:asciiname":"Rwangambuto",
    "gn:country_code":"RW",
    "gn:dem":1920,
    "gn:feature_class":"P",
    "gn:feature_code":"PPLL",
    "gn:name":"Rwangambuto",
    "gn:population":0,
    "gn:timezone":"Africa/Kigali",
    "iso:country":"RW",
    "wof:name":"Rwangambuto",
    "wof:placetype":"locality"
},
  "geometry": {"coordinates":[29.3279,-1.753],"type":"Point"}
}