{
  "type": "Feature",
  "properties": {
    "gn:admin1_code":"15",
    "gn:admin2_code":"26.0",
    "gn:admin3_code":"2609.0",
    "gn:admin4_code":"260905.0",
    "gn:asciiname":"Rwinkuba",
    "gn:country_code":"RW",
    "gn:dem":1604,
    "gn:feature_class":"P",
    "gn:feature_code":"PPLL",
    "gn:name":"Rwinkuba",
    "gn:population":0,
    "gn:timezone":"Africa/Kigali",
    "iso:country":"RW",
    "wof:name":"Rwinkuba",
    "wof:placetype":"locality"
},
  "geometry": {"coordinates":[29.8081,-2.2408],"type":"Point"}
}