{
  "type": "Feature",
  "properties": {
    "gn:admin1_code":"15.0",
    "gn:admin2_code":"23",
    "gn:admin3_code":"2314.0",
    "gn:admin4_code":"231402.0",
    "gn:asciiname":"Kiramutse",
    "gn:country_code":"RW",
    "gn:dem":1846,
    "gn:feature_class":"P",
    "gn:feature_code":"PPLL",
    "gn:name":"Kiramutse",
    "gn:population":0,
    "gn:timezone":"Africa/Kigali",
    "iso:country":"RW",
    "wof:name":"Kiramutse",
    "wof:placetype":"locality"
},
  "geometry": {"coordinates":[29.6113,-2.6917],"type":"Point"}
}