{
  "type": "Feature",
  "properties": {
    "gn:admin1_code":"15",
    "gn:admin2_code":"27.0",
    "gn:admin3_code":"2704.0",
    "gn:admin4_code":"270405.0",
    "gn:asciiname":"Rukeli",
    "gn:country_code":"RW",
    "gn:dem":1419,
    "gn:feature_class":"P",
    "gn:feature_code":"PPL",
    "gn:name":"Rukeli",
    "gn:population":0,
    "gn:timezone":"Africa/Kigali",
    "iso:country":"RW",
    "wof:name":"Rukeli",
    "wof:placetype":"locality"
},
  "geometry": {"coordinates":[29.7932,-1.8493],"type":"Point"}
}