{
  "type": "Feature",
  "properties": {
    "gn:admin1_code":"15",
    "gn:admin2_code":"21.0",
    "gn:admin3_code":"2104.0",
    "gn:admin4_code":"210401.0",
    "gn:asciiname":"Cyeru",
    "gn:country_code":"RW",
    "gn:dem":1505,
    "gn:feature_class":"P",
    "gn:feature_code":"PPLL",
    "gn:name":"Cyeru",
    "gn:population":0,
    "gn:timezone":"Africa/Kigali",
    "iso:country":"RW",
    "wof:name":"Cyeru",
    "wof:placetype":"locality"
},
  "geometry": {"coordinates":[29.8984,-2.3646],"type":"Point"}
}