{
  "type": "Feature",
  "properties": {
    "gn:admin1_code":"14",
    "gn:admin2_code":"31.0",
    "gn:admin3_code":"3111.0",
    "gn:admin4_code":"311101.0",
    "gn:asciiname":"Muremure",
    "gn:country_code":"RW",
    "gn:dem":1769,
    "gn:feature_class":"P",
    "gn:feature_code":"PPLL",
    "gn:name":"Muremure",
    "gn:population":0,
    "gn:timezone":"Africa/Kigali",
    "iso:country":"RW",
    "wof:name":"Muremure",
    "wof:placetype":"locality"
},
  "geometry": {"coordinates":[29.4769,-2.2388],"type":"Point"}
}