{
  "type": "Feature",
  "properties": {
    "gn:admin1_code":"14",
    "gn:admin2_code":"31.0",
    "gn:admin3_code":"3104.0",
    "gn:admin4_code":"310401.0",
    "gn:asciiname":"Gasharu",
    "gn:country_code":"RW",
    "gn:dem":2049,
    "gn:feature_class":"P",
    "gn:feature_code":"PPLL",
    "gn:name":"Gasharu",
    "gn:population":0,
    "gn:timezone":"Africa/Kigali",
    "iso:country":"RW",
    "wof:name":"Gasharu",
    "wof:placetype":"locality"
},
  "geometry": {"coordinates":[29.4305,-2.1364],"type":"Point"}
}