{
  "type": "Feature",
  "properties": {
    "gn:admin1_code":"14.0",
    "gn:admin2_code":"37",
    "gn:admin3_code":"3709.0",
    "gn:admin4_code":"370901.0",
    "gn:asciiname":"Mutongo",
    "gn:country_code":"RW",
    "gn:dem":1489,
    "gn:feature_class":"P",
    "gn:feature_code":"PPLL",
    "gn:name":"Mutongo",
    "gn:population":0,
    "gn:timezone":"Africa/Kigali",
    "iso:country":"RW",
    "name:und_x_variant":[
        "Colline Mutongo",
        "Mutongo"
    ],
    "wof:name":"Mutongo",
    "wof:placetype":"locality"
},
  "geometry": {"coordinates":[29.2109,-2.2848],"type":"Point"}
}