{
  "type": "Feature",
  "properties": {
    "gn:admin1_code":"11",
    "gn:admin2_code":"56.0",
    "gn:admin3_code":"5602.0",
    "gn:admin4_code":"560204.0",
    "gn:asciiname":"Akabande",
    "gn:country_code":"RW",
    "gn:dem":1437,
    "gn:feature_class":"P",
    "gn:feature_code":"PPLL",
    "gn:name":"Akabande",
    "gn:population":0,
    "gn:timezone":"Africa/Kigali",
    "iso:country":"RW",
    "wof:name":"Akabande",
    "wof:placetype":"locality"
},
  "geometry": {"coordinates":[30.3964,-2.2911],"type":"Point"}
}