{
  "type": "Feature",
  "properties": {
    "gn:admin1_code":"11",
    "gn:admin2_code":"56.0",
    "gn:admin3_code":"5609.0",
    "gn:admin4_code":"560902.0",
    "gn:asciiname":"Kabare I",
    "gn:country_code":"RW",
    "gn:dem":1647,
    "gn:feature_class":"P",
    "gn:feature_code":"PPLL",
    "gn:name":"Kabare I",
    "gn:population":0,
    "gn:timezone":"Africa/Kigali",
    "iso:country":"RW",
    "wof:name":"Kabare I",
    "wof:placetype":"locality"
},
  "geometry": {"coordinates":[30.5568,-2.1009],"type":"Point"}
}