{
  "type": "Feature",
  "properties": {
    "gn:admin1_code":"14",
    "gn:admin2_code":"31.0",
    "gn:admin3_code":"3102.0",
    "gn:admin4_code":"310202.0",
    "gn:asciiname":"Bugeni",
    "gn:country_code":"RW",
    "gn:dem":1808,
    "gn:feature_class":"P",
    "gn:feature_code":"PPLL",
    "gn:name":"Bugeni",
    "gn:population":0,
    "gn:timezone":"Africa/Kigali",
    "iso:country":"RW",
    "wof:name":"Bugeni",
    "wof:placetype":"locality"
},
  "geometry": {"coordinates":[29.5425,-2.0987],"type":"Point"}
}