{
  "type": "Feature",
  "properties": {
    "gn:admin1_code":"13.0",
    "gn:admin2_code":"41",
    "gn:admin3_code":"4107.0",
    "gn:admin4_code":"410703.0",
    "gn:asciiname":"Karama",
    "gn:country_code":"RW",
    "gn:dem":1838,
    "gn:feature_class":"P",
    "gn:feature_code":"PPLL",
    "gn:name":"Karama",
    "gn:population":0,
    "gn:timezone":"Africa/Kigali",
    "iso:country":"RW",
    "name:ceb_x_preferred":[
        "Karama"
    ],
    "name:fra_x_preferred":[
        "Karama"
    ],
    "name:ita_x_preferred":[
        "Karama"
    ],
    "name:swe_x_preferred":[
        "Karama"
    ],
    "name:und_x_variant":[
        "Colline Karama"
    ],
    "wof:name":"Karama",
    "wof:placetype":"locality"
},
  "geometry": {"coordinates":[29.9282,-1.6585],"type":"Point"}
}