{
  "type": "Feature",
  "properties": {
    "gn:admin1_code":"14.0",
    "gn:admin2_code":"36",
    "gn:admin3_code":"3606.0",
    "gn:admin4_code":"360605.0",
    "gn:asciiname":"Kannyogo",
    "gn:country_code":"RW",
    "gn:dem":1588,
    "gn:feature_class":"P",
    "gn:feature_code":"PPL",
    "gn:name":"Kannyogo",
    "gn:population":0,
    "gn:timezone":"Africa/Kigali",
    "iso:country":"RW",
    "wof:name":"Kannyogo",
    "wof:placetype":"locality"
},
  "geometry": {"coordinates":[28.9073,-2.4661],"type":"Point"}
}