{
  "type": "Feature",
  "properties": {
    "gn:admin1_code":"14",
    "gn:admin2_code":"34.0",
    "gn:admin3_code":"3404.0",
    "gn:admin4_code":"340402.0",
    "gn:asciiname":"Cyamvumba",
    "gn:country_code":"RW",
    "gn:dem":2569,
    "gn:feature_class":"P",
    "gn:feature_code":"PPLF",
    "gn:name":"Cyamvumba",
    "gn:population":0,
    "gn:timezone":"Africa/Kigali",
    "iso:country":"RW",
    "wof:name":"Cyamvumba",
    "wof:placetype":"locality"
},
  "geometry": {"coordinates":[29.4125,-1.5709],"type":"Point"}
}