{
  "type": "Feature",
  "properties": {
    "gn:admin1_code":"13",
    "gn:admin2_code":"45.0",
    "gn:admin3_code":"4504.0",
    "gn:admin4_code":"450405.0",
    "gn:asciiname":"Maya",
    "gn:country_code":"RW",
    "gn:dem":2025,
    "gn:feature_class":"P",
    "gn:feature_code":"PPLL",
    "gn:name":"Maya",
    "gn:population":0,
    "gn:timezone":"Africa/Kigali",
    "iso:country":"RW",
    "wof:name":"Maya",
    "wof:placetype":"locality"
},
  "geometry": {"coordinates":[30.0236,-1.4909],"type":"Point"}
}