{
  "type": "Feature",
  "properties": {
    "gn:admin1_code":"11.0",
    "gn:admin2_code":"56",
    "gn:admin3_code":"5601.0",
    "gn:admin4_code":"560102.0",
    "gn:asciiname":"Gisera",
    "gn:country_code":"RW",
    "gn:dem":1439,
    "gn:feature_class":"P",
    "gn:feature_code":"PPLL",
    "gn:name":"Gisera",
    "gn:population":0,
    "gn:timezone":"Africa/Kigali",
    "iso:country":"RW",
    "wof:name":"Gisera",
    "wof:placetype":"locality"
},
  "geometry": {"coordinates":[30.47806,-2.15056],"type":"Point"}
}