{
  "type": "Feature",
  "properties": {
    "gn:admin1_code":"13",
    "gn:admin2_code":"45.0",
    "gn:admin3_code":"4509.0",
    "gn:admin4_code":"450903.0",
    "gn:asciiname":"Mutonga",
    "gn:country_code":"RW",
    "gn:dem":2061,
    "gn:feature_class":"P",
    "gn:feature_code":"PPLL",
    "gn:name":"Mutonga",
    "gn:population":0,
    "gn:timezone":"Africa/Kigali",
    "iso:country":"RW",
    "wof:name":"Mutonga",
    "wof:placetype":"locality"
},
  "geometry": {"coordinates":[29.9661,-1.5957],"type":"Point"}
}