{
  "type": "Feature",
  "properties": {
    "gn:admin1_code":"11",
    "gn:admin2_code":"54.0",
    "gn:admin3_code":"5411.0",
    "gn:admin4_code":"541104.0",
    "gn:asciiname":"Abiyahuzi",
    "gn:country_code":"RW",
    "gn:dem":1472,
    "gn:feature_class":"P",
    "gn:feature_code":"PPLL",
    "gn:name":"Abiyahuzi",
    "gn:population":0,
    "gn:timezone":"Africa/Kigali",
    "iso:country":"RW",
    "wof:name":"Abiyahuzi",
    "wof:placetype":"locality"
},
  "geometry": {"coordinates":[30.5063,-2.0143],"type":"Point"}
}