{
  "type": "Feature",
  "properties": {
    "gn:admin1_code":"13",
    "gn:admin2_code":"41.0",
    "gn:admin3_code":"4107.0",
    "gn:admin4_code":"410702.0",
    "gn:asciiname":"Bwishya",
    "gn:country_code":"RW",
    "gn:dem":1790,
    "gn:feature_class":"P",
    "gn:feature_code":"PPLL",
    "gn:name":"Bwishya",
    "gn:population":0,
    "gn:timezone":"Africa/Kigali",
    "iso:country":"RW",
    "wof:name":"Bwishya",
    "wof:placetype":"locality"
},
  "geometry": {"coordinates":[29.9739,-1.6664],"type":"Point"}
}