{
  "type": "Feature",
  "properties": {
    "gn:admin1_code":"13",
    "gn:admin2_code":"41.0",
    "gn:admin3_code":"4113.0",
    "gn:admin4_code":"411302.0",
    "gn:asciiname":"Cyiri",
    "gn:country_code":"RW",
    "gn:dem":1627,
    "gn:feature_class":"P",
    "gn:feature_code":"PPLL",
    "gn:name":"Cyiri",
    "gn:population":0,
    "gn:timezone":"Africa/Kigali",
    "iso:country":"RW",
    "wof:name":"Cyiri",
    "wof:placetype":"locality"
},
  "geometry": {"coordinates":[30.0556,-1.7591],"type":"Point"}
}