{
  "type": "Feature",
  "properties": {
    "gn:admin1_code":"13",
    "gn:admin2_code":"42.0",
    "gn:admin3_code":"4205.0",
    "gn:admin4_code":"420503.0",
    "gn:asciiname":"Muhendu",
    "gn:country_code":"RW",
    "gn:dem":2150,
    "gn:feature_class":"P",
    "gn:feature_code":"PPLL",
    "gn:name":"Muhendu",
    "gn:population":0,
    "gn:timezone":"Africa/Kigali",
    "iso:country":"RW",
    "wof:name":"Muhendu",
    "wof:placetype":"locality"
},
  "geometry": {"coordinates":[29.8504,-1.6161],"type":"Point"}
}