{
  "type": "Feature",
  "properties": {
    "gn:admin1_code":"13.0",
    "gn:admin2_code":"43",
    "gn:admin3_code":"4305.0",
    "gn:admin4_code":"430502.0",
    "gn:asciiname":"Mararo",
    "gn:country_code":"RW",
    "gn:dem":2219,
    "gn:feature_class":"P",
    "gn:feature_code":"PPLL",
    "gn:name":"Mararo",
    "gn:population":0,
    "gn:timezone":"Africa/Kigali",
    "iso:country":"RW",
    "name:und_x_variant":[
        "Colline Mararo",
        "Mararo"
    ],
    "wof:name":"Mararo",
    "wof:placetype":"locality"
},
  "geometry": {"coordinates":[29.55,-1.55],"type":"Point"}
}