{
  "type": "Feature",
  "properties": {
    "gn:admin1_code":"14.0",
    "gn:admin2_code":"36",
    "gn:admin3_code":"3614.0",
    "gn:admin4_code":"361404.0",
    "gn:asciiname":"Gako",
    "gn:country_code":"RW",
    "gn:dem":1960,
    "gn:feature_class":"P",
    "gn:feature_code":"PPLL",
    "gn:name":"Gako",
    "gn:population":0,
    "gn:timezone":"Africa/Kigali",
    "iso:country":"RW",
    "wof:name":"Gako",
    "wof:placetype":"locality"
},
  "geometry": {"coordinates":[28.9637,-2.5382],"type":"Point"}
}