{
  "type": "Feature",
  "properties": {
    "gn:admin1_code":"13",
    "gn:admin2_code":"41.0",
    "gn:admin3_code":"4105.0",
    "gn:admin4_code":"410503.0",
    "gn:asciiname":"Gasekabuye",
    "gn:country_code":"RW",
    "gn:dem":1800,
    "gn:feature_class":"P",
    "gn:feature_code":"PPLL",
    "gn:name":"Gasekabuye",
    "gn:population":0,
    "gn:timezone":"Africa/Kigali",
    "iso:country":"RW",
    "wof:name":"Gasekabuye",
    "wof:placetype":"locality"
},
  "geometry": {"coordinates":[30.0106,-1.7825],"type":"Point"}
}