{
  "type": "Feature",
  "properties": {
    "gn:admin1_code":"15.0",
    "gn:admin2_code":"22",
    "gn:admin3_code":"2202.0",
    "gn:admin4_code":"220204.0",
    "gn:asciiname":"Nyeranzi",
    "gn:country_code":"RW",
    "gn:dem":1512,
    "gn:feature_class":"P",
    "gn:feature_code":"PPLL",
    "gn:name":"Nyeranzi",
    "gn:population":0,
    "gn:timezone":"Africa/Kigali",
    "iso:country":"RW",
    "wof:name":"Nyeranzi",
    "wof:placetype":"locality"
},
  "geometry": {"coordinates":[29.88098,-2.5568],"type":"Point"}
}