{
  "type": "Feature",
  "properties": {
    "gn:admin1_code":"13",
    "gn:admin2_code":"43.0",
    "gn:admin3_code":"4307.0",
    "gn:admin4_code":"430701.0",
    "gn:asciiname":"Gisasa",
    "gn:country_code":"RW",
    "gn:dem":2614,
    "gn:feature_class":"P",
    "gn:feature_code":"PPL",
    "gn:name":"Gisasa",
    "gn:population":0,
    "gn:timezone":"Africa/Kigali",
    "iso:country":"RW",
    "wof:name":"Gisasa",
    "wof:placetype":"locality"
},
  "geometry": {"coordinates":[29.5107,-1.4513],"type":"Point"}
}