{
  "type": "Feature",
  "properties": {
    "gn:admin1_code":"14",
    "gn:admin2_code":"34.0",
    "gn:admin3_code":"3412.0",
    "gn:admin4_code":"341201.0",
    "gn:asciiname":"Cyarwa",
    "gn:country_code":"RW",
    "gn:dem":1891,
    "gn:feature_class":"P",
    "gn:feature_code":"PPLL",
    "gn:name":"Cyarwa",
    "gn:population":0,
    "gn:timezone":"Africa/Kigali",
    "iso:country":"RW",
    "wof:name":"Cyarwa",
    "wof:placetype":"locality"
},
  "geometry": {"coordinates":[29.61767,-1.69357],"type":"Point"}
}