{
  "type": "Feature",
  "properties": {
    "gn:admin1_code":"13.0",
    "gn:admin2_code":"43",
    "gn:admin3_code":"4310.0",
    "gn:admin4_code":"431005.0",
    "gn:asciiname":"Musanze",
    "gn:country_code":"RW",
    "gn:dem":1951,
    "gn:feature_class":"P",
    "gn:feature_code":"PPLL",
    "gn:name":"Musanze",
    "gn:population":0,
    "gn:timezone":"Africa/Kigali",
    "iso:country":"RW",
    "name:und_x_variant":[
        "Colline Musanze",
        "Musanze"
    ],
    "wof:name":"Musanze",
    "wof:placetype":"locality"
},
  "geometry": {"coordinates":[29.5984,-1.4915],"type":"Point"}
}