{
  "type": "Feature",
  "properties": {
    "gn:admin1_code":"12",
    "gn:admin2_code":"11.0",
    "gn:admin3_code":"1105.0",
    "gn:admin4_code":"110505.0",
    "gn:asciiname":"Nyarufunzo",
    "gn:country_code":"RW",
    "gn:dem":1408,
    "gn:feature_class":"P",
    "gn:feature_code":"PPLL",
    "gn:name":"Nyarufunzo",
    "gn:population":0,
    "gn:timezone":"Africa/Kigali",
    "iso:country":"RW",
    "wof:name":"Nyarufunzo",
    "wof:placetype":"locality"
},
  "geometry": {"coordinates":[30.044,-2.0155],"type":"Point"}
}