{
  "type": "Feature",
  "properties": {
    "gn:admin1_code":"12.0",
    "gn:admin2_code":"12",
    "gn:admin3_code":"1214.0",
    "gn:admin4_code":"121403.0",
    "gn:asciiname":"Rusororo",
    "gn:country_code":"RW",
    "gn:dem":1465,
    "gn:feature_class":"P",
    "gn:feature_code":"PPL",
    "gn:name":"Rusororo",
    "gn:population":0,
    "gn:timezone":"Africa/Kigali",
    "iso:country":"RW",
    "wof:name":"Rusororo",
    "wof:placetype":"locality"
},
  "geometry": {"coordinates":[30.22306,-1.97389],"type":"Point"}
}