{
  "type": "Feature",
  "properties": {
    "gn:admin1_code":"14",
    "gn:admin2_code":"34.0",
    "gn:admin3_code":"3411.0",
    "gn:admin4_code":"341105.0",
    "gn:asciiname":"Kazigo",
    "gn:country_code":"RW",
    "gn:dem":2029,
    "gn:feature_class":"P",
    "gn:feature_code":"PPLL",
    "gn:name":"Kazigo",
    "gn:population":0,
    "gn:timezone":"Africa/Kigali",
    "iso:country":"RW",
    "wof:name":"Kazigo",
    "wof:placetype":"locality"
},
  "geometry": {"coordinates":[29.5983,-1.6659],"type":"Point"}
}