{
  "type": "Feature",
  "properties": {
    "gn:admin1_code":"11",
    "gn:admin2_code":"53.0",
    "gn:admin3_code":"5306.0",
    "gn:admin4_code":"530602.0",
    "gn:asciiname":"Nyakagarama",
    "gn:country_code":"RW",
    "gn:dem":1501,
    "gn:feature_class":"P",
    "gn:feature_code":"PPLL",
    "gn:name":"Nyakagarama",
    "gn:population":0,
    "gn:timezone":"Africa/Kigali",
    "iso:country":"RW",
    "wof:name":"Nyakagarama",
    "wof:placetype":"locality"
},
  "geometry": {"coordinates":[30.4366,-1.8052],"type":"Point"}
}