{
  "type": "Feature",
  "properties": {
    "gn:admin1_code":"15.0",
    "gn:admin2_code":"23",
    "gn:admin3_code":"2306.0",
    "gn:admin4_code":"230603.0",
    "gn:asciiname":"Samiyonga",
    "gn:country_code":"RW",
    "gn:dem":2015,
    "gn:feature_class":"P",
    "gn:feature_code":"PPLL",
    "gn:name":"Samiyonga",
    "gn:population":0,
    "gn:timezone":"Africa/Kigali",
    "iso:country":"RW",
    "wof:name":"Samiyonga",
    "wof:placetype":"locality"
},
  "geometry": {"coordinates":[29.4558,-2.6699],"type":"Point"}
}