{
  "type": "Feature",
  "properties": {
    "gn:admin1_code":"11",
    "gn:admin2_code":"56.0",
    "gn:admin3_code":"5604.0",
    "gn:admin4_code":"560403.0",
    "gn:asciiname":"Kabimba",
    "gn:country_code":"RW",
    "gn:dem":1639,
    "gn:feature_class":"P",
    "gn:feature_code":"PPLL",
    "gn:name":"Kabimba",
    "gn:population":0,
    "gn:timezone":"Africa/Kigali",
    "iso:country":"RW",
    "wof:name":"Kabimba",
    "wof:placetype":"locality"
},
  "geometry": {"coordinates":[30.5209,-2.1767],"type":"Point"}
}