{
  "type": "Feature",
  "properties": {
    "gn:admin1_code":"13",
    "gn:admin2_code":"43.0",
    "gn:admin3_code":"4303.0",
    "gn:admin4_code":"430302.0",
    "gn:asciiname":"Shashi",
    "gn:country_code":"RW",
    "gn:dem":1833,
    "gn:feature_class":"P",
    "gn:feature_code":"PPLL",
    "gn:name":"Shashi",
    "gn:population":0,
    "gn:timezone":"Africa/Kigali",
    "iso:country":"RW",
    "name:ceb_x_preferred":[
        "Shashi"
    ],
    "name:fra_x_preferred":[
        "Shashi"
    ],
    "name:swe_x_preferred":[
        "Shashi"
    ],
    "wof:name":"Shashi",
    "wof:placetype":"locality"
},
  "geometry": {"coordinates":[29.7151,-1.5013],"type":"Point"}
}