{
  "type": "Feature",
  "properties": {
    "gn:admin1_code":"13",
    "gn:admin2_code":"42.0",
    "gn:admin3_code":"4208.0",
    "gn:admin4_code":"420803.0",
    "gn:asciiname":"Soha",
    "gn:country_code":"RW",
    "gn:dem":1781,
    "gn:feature_class":"P",
    "gn:feature_code":"PPLL",
    "gn:name":"Soha",
    "gn:population":0,
    "gn:timezone":"Africa/Kigali",
    "iso:country":"RW",
    "name:fas_x_preferred":[
        "\u0633\u0647\u0627"
    ],
    "name:urd_x_preferred":[
        "\u0633\u0648\u06c1\u0627"
    ],
    "wof:name":"Soha",
    "wof:placetype":"locality"
},
  "geometry": {"coordinates":[29.8086,-1.6302],"type":"Point"}
}