{
  "type": "Feature",
  "properties": {
    "gn:admin1_code":"15",
    "gn:admin2_code":"28.0",
    "gn:admin3_code":"2806.0",
    "gn:admin4_code":"280602.0",
    "gn:asciiname":"Giheta",
    "gn:country_code":"RW",
    "gn:dem":1660,
    "gn:feature_class":"P",
    "gn:feature_code":"PPLL",
    "gn:name":"Giheta",
    "gn:population":0,
    "gn:timezone":"Africa/Kigali",
    "iso:country":"RW",
    "wof:name":"Giheta",
    "wof:placetype":"locality"
},
  "geometry": {"coordinates":[29.84255,-2.06958],"type":"Point"}
}