{
  "type": "Feature",
  "properties": {
    "gn:admin1_code":"14.0",
    "gn:admin2_code":"32",
    "gn:admin3_code":"3204.0",
    "gn:admin4_code":"320403.0",
    "gn:asciiname":"Burango",
    "gn:country_code":"RW",
    "gn:dem":1791,
    "gn:feature_class":"P",
    "gn:feature_code":"PPLL",
    "gn:name":"Burango",
    "gn:population":0,
    "gn:timezone":"Africa/Kigali",
    "iso:country":"RW",
    "wof:name":"Burango",
    "wof:placetype":"locality"
},
  "geometry": {"coordinates":[29.3027,-1.7843],"type":"Point"}
}