{
  "type": "Feature",
  "properties": {
    "gn:admin1_code":"11",
    "gn:admin2_code":"51.0",
    "gn:admin3_code":"5107.0",
    "gn:admin4_code":"510702.0",
    "gn:asciiname":"Kabuye",
    "gn:country_code":"RW",
    "gn:dem":1530,
    "gn:feature_class":"P",
    "gn:feature_code":"PPLL",
    "gn:name":"Kabuye",
    "gn:population":0,
    "gn:timezone":"Africa/Kigali",
    "iso:country":"RW",
    "wof:name":"Kabuye",
    "wof:placetype":"locality"
},
  "geometry": {"coordinates":[30.443,-2.0487],"type":"Point"}
}