{
  "type": "Feature",
  "properties": {
    "gn:admin1_code":"11",
    "gn:admin2_code":"56.0",
    "gn:admin3_code":"5607.0",
    "gn:admin4_code":"560705.0",
    "gn:asciiname":"Kabahushi",
    "gn:country_code":"RW",
    "gn:dem":1591,
    "gn:feature_class":"P",
    "gn:feature_code":"PPL",
    "gn:name":"Kabahushi",
    "gn:population":0,
    "gn:timezone":"Africa/Kigali",
    "iso:country":"RW",
    "wof:name":"Kabahushi",
    "wof:placetype":"locality"
},
  "geometry": {"coordinates":[30.5416,-2.2338],"type":"Point"}
}