{
  "type": "Feature",
  "properties": {
    "gn:admin1_code":"14.0",
    "gn:admin2_code":"36",
    "gn:admin3_code":"3617.0",
    "gn:admin4_code":"361705.0",
    "gn:asciiname":"Kabuyange",
    "gn:country_code":"RW",
    "gn:dem":1363,
    "gn:feature_class":"P",
    "gn:feature_code":"PPLL",
    "gn:name":"Kabuyange",
    "gn:population":0,
    "gn:timezone":"Africa/Kigali",
    "iso:country":"RW",
    "wof:name":"Kabuyange",
    "wof:placetype":"locality"
},
  "geometry": {"coordinates":[28.9704,-2.6452],"type":"Point"}
}