{
  "type": "Feature",
  "properties": {
    "gn:admin1_code":"11",
    "gn:admin2_code":"51.0",
    "gn:admin3_code":"5106.0",
    "gn:admin4_code":"510601.0",
    "gn:asciiname":"Gatobotobo",
    "gn:country_code":"RW",
    "gn:dem":1467,
    "gn:feature_class":"P",
    "gn:feature_code":"PPLL",
    "gn:name":"Gatobotobo",
    "gn:population":0,
    "gn:timezone":"Africa/Kigali",
    "iso:country":"RW",
    "wof:name":"Gatobotobo",
    "wof:placetype":"locality"
},
  "geometry": {"coordinates":[30.4374,-1.8663],"type":"Point"}
}