{
  "type": "Feature",
  "properties": {
    "gn:admin1_code":"13",
    "gn:admin2_code":"42.0",
    "gn:admin3_code":"4215.0",
    "gn:admin4_code":"421504.0",
    "gn:asciiname":"Gitabi",
    "gn:country_code":"RW",
    "gn:dem":2010,
    "gn:feature_class":"P",
    "gn:feature_code":"PPLL",
    "gn:name":"Gitabi",
    "gn:population":0,
    "gn:timezone":"Africa/Kigali",
    "iso:country":"RW",
    "name:run_x_preferred":[
        "Gitabi"
    ],
    "wof:name":"Gitabi",
    "wof:placetype":"locality"
},
  "geometry": {"coordinates":[29.7267,-1.7195],"type":"Point"}
}