{
  "type": "Feature",
  "properties": {
    "gn:admin1_code":"13",
    "gn:admin2_code":"43.0",
    "gn:admin3_code":"4307.0",
    "gn:admin4_code":"430704.0",
    "gn:asciiname":"Ryango",
    "gn:country_code":"RW",
    "gn:dem":2505,
    "gn:feature_class":"P",
    "gn:feature_code":"PPLL",
    "gn:name":"Ryango",
    "gn:population":0,
    "gn:timezone":"Africa/Kigali",
    "iso:country":"RW",
    "wof:name":"Ryango",
    "wof:placetype":"locality"
},
  "geometry": {"coordinates":[29.5821,-1.4184],"type":"Point"}
}