{
  "type": "Feature",
  "properties": {
    "gn:admin1_code":"15",
    "gn:admin2_code":"24.0",
    "gn:admin3_code":"2408.0",
    "gn:admin4_code":"240804.0",
    "gn:asciiname":"Agakera",
    "gn:country_code":"RW",
    "gn:dem":1666,
    "gn:feature_class":"P",
    "gn:feature_code":"PPLL",
    "gn:name":"Agakera",
    "gn:population":0,
    "gn:timezone":"Africa/Kigali",
    "iso:country":"RW",
    "wof:name":"Agakera",
    "wof:placetype":"locality"
},
  "geometry": {"coordinates":[29.7612,-2.6461],"type":"Point"}
}