{
  "type": "Feature",
  "properties": {
    "gn:admin1_code":"14",
    "gn:admin2_code":"37.0",
    "gn:admin3_code":"3711.0",
    "gn:admin4_code":"371101.0",
    "gn:asciiname":"Kanyoni",
    "gn:country_code":"RW",
    "gn:dem":1586,
    "gn:feature_class":"P",
    "gn:feature_code":"PPLL",
    "gn:name":"Kanyoni",
    "gn:population":0,
    "gn:timezone":"Africa/Kigali",
    "iso:country":"RW",
    "wof:name":"Kanyoni",
    "wof:placetype":"locality"
},
  "geometry": {"coordinates":[29.2856,-2.2163],"type":"Point"}
}