{
  "type": "Feature",
  "properties": {
    "gn:admin1_code":"11",
    "gn:admin2_code":"53.0",
    "gn:admin3_code":"5313.0",
    "gn:admin4_code":"531302.0",
    "gn:asciiname":"Gihuta",
    "gn:country_code":"RW",
    "gn:dem":1432,
    "gn:feature_class":"P",
    "gn:feature_code":"PPLL",
    "gn:name":"Gihuta",
    "gn:population":0,
    "gn:timezone":"Africa/Kigali",
    "iso:country":"RW",
    "wof:name":"Gihuta",
    "wof:placetype":"locality"
},
  "geometry": {"coordinates":[30.4053,-1.6874],"type":"Point"}
}