{
  "type": "Feature",
  "properties": {
    "gn:admin1_code":"15.0",
    "gn:admin2_code":"25",
    "gn:admin3_code":"2505.0",
    "gn:admin4_code":"250503.0",
    "gn:asciiname":"Uwamarumba",
    "gn:country_code":"RW",
    "gn:dem":1793,
    "gn:feature_class":"P",
    "gn:feature_code":"PPLL",
    "gn:name":"Uwamarumba",
    "gn:population":0,
    "gn:timezone":"Africa/Kigali",
    "iso:country":"RW",
    "wof:name":"Uwamarumba",
    "wof:placetype":"locality"
},
  "geometry": {"coordinates":[29.4847,-2.317],"type":"Point"}
}